Workbook

Sheet Summary
A1: Netflix (NFLX): valuation summary
A2: Values link to the model sheet (green). Switch the discount rate on the WACC tab.
A4: Company | B4: Method | C4: Share price | D4: Discount rate | E4: Bear value | F4: Base value | G4: Bull value | H4: Base vs price | I4: Implied return at price (base case) | J4: Base value (rounded)
A5: Netflix (NFLX) | B5: 10-year DCF | C5: =NFLX!B4 -> 62.52 | D5: =NFLX!B10 -> 0.095 | E5: =NFLX!B75 -> 39.490496 | F5: =NFLX!B76 -> 65.90734 | G5: =NFLX!B77 -> 90.857835 | H5: =F5/C5-1 -> 0.054180102 | I5: =NFLX!B86 -> 0.098412404 | J5: =IF(F5<10,ROUND(F5*4,0)/4,IF(F5<100,ROUND(F5,0),ROUND(F5/5,0)*5)) -> 66
A8: Not a holding. Buy below is the base value, rounded
A9: Buy below (base value, rounded) | C9: =J5 -> 66
A10: Bull value | C10: =G5 -> 90.857835
A11: Bear value | C11: =E5 -> 39.490496

Sheet NFLX
A1: Netflix (NFLX): 10-year scenario DCF
A2: Units: $ billions unless noted. Blue = input, black = formula, green = link, yellow = key lever. Years 6 to 10 fade growth, margin and reinvestment toward each scenario's terminal levels.
A4: Share price ($) | B4: 62.52 | C4: Oct 27, 2026 close (Stock Analysis)
A5: Price date | B5: Oct 27, 2026 close (Stock Analysis) | C5: Text
A6: Shares outstanding (billions) | B6: 4.106 | C6: Market cap $259.11B / price $63.10, Stock Analysis statistics, Oct 27, 2026
A7: Net cash, negative = net debt | B7: -7.1 | C7: Q3 2026 letter: cash $8.2B less gross debt about $15.3B
A8: Other non-operating assets, less outside claims | B8: 0 | C8: None
A9: Tax rate | B9: 0.165 | C9: Analyst assumption (normalized, near the reported effective rate)
A10: Discount rate (WACC), from WACC tab | B10: =WACC!B29 -> 0.095 | C10: Calculated or assumed, per the switch in WACC!B5
A11: Working capital, % of revenue change | B11: 0 | C11: Analyst assumption
A12: Base-year revenue (2026E) | B12: 51.1 | C12: 2026 guide: revenue $51.1B, 31.5% operating margin, about $12.0B FCF (Q3 2026 letter). Reinvestment includes cash content spend above amortization (about 1.1x) plus capex
A13: Selected scenario (1 Bear, 2 Base, 3 Bull) | B13: 2 | C13: Lever
A15: Year | B15: 2027 | C15: 2028 | D15: 2029 | E15: 2030 | F15: 2031 | G15: 2032 | H15: 2033 | I15: 2034 | J15: 2035 | K15: 2036 | L15: Terminal
A16: Discount period (years, mid-year) | B16: 0.5 | C16: =B16+1 -> 1.5 | D16: =C16+1 -> 2.5 | E16: =D16+1 -> 3.5 | F16: =E16+1 -> 4.5 | G16: =F16+1 -> 5.5 | H16: =G16+1 -> 6.5 | I16: =H16+1 -> 7.5 | J16: =I16+1 -> 8.5 | K16: =J16+1 -> 9.5
A17: Fade step (years 6 to 10) | B17: 0 | C17: 0 | D17: 0 | E17: 0 | F17: 0 | G17: 1 | H17: 2 | I17: 3 | J17: 4 | K17: 5
A19: Bear: engagement keeps sliding to YouTube and AI video
A20: Revenue | B20: 54 | C20: 56.5 | D20: 59 | E20: 61 | F20: 63 | G20: =F20*(1+$F21+($L21-$F21)*G$17/5) -> 64.967459 | H20: =G20*(1+$F21+($L21-$F21)*H$17/5) -> 66.895182 | I20: =H20*(1+$F21+($L21-$F21)*I$17/5) -> 68.775924 | J20: =I20*(1+$F21+($L21-$F21)*J$17/5) -> 70.602432 | K20: =J20*(1+$F21+($L21-$F21)*K$17/5) -> 72.367492 | L20: =K20*(1+L21) -> 74.17668
A21: Revenue growth (terminal column = terminal growth, input) | B21: =B20/$B$12-1 -> 0.056751468 | C21: =C20/B20-1 -> 0.046296296 | D21: =D20/C20-1 -> 0.044247788 | E21: =E20/D20-1 -> 0.033898305 | F21: =F20/E20-1 -> 0.032786885 | G21: =G20/F20-1 -> 0.031229508 | H21: =H20/G20-1 -> 0.029672131 | I21: =I20/H20-1 -> 0.028114754 | J21: =J20/I20-1 -> 0.026557377 | K21: =K20/J20-1 -> 0.025 | L21: 0.025
A22: Operating margin | B22: 0.3 | C22: 0.3 | D22: 0.3 | E22: 0.3 | F22: 0.3 | G22: =$F22+($L22-$F22)*G$17/5 -> 0.294 | H22: =$F22+($L22-$F22)*H$17/5 -> 0.288 | I22: =$F22+($L22-$F22)*I$17/5 -> 0.282 | J22: =$F22+($L22-$F22)*J$17/5 -> 0.276 | K22: =$F22+($L22-$F22)*K$17/5 -> 0.27 | L22: 0.27
A23: Operating income | B23: =B20*B22 -> 16.2 | C23: =C20*C22 -> 16.95 | D23: =D20*D22 -> 17.7 | E23: =E20*E22 -> 18.3 | F23: =F20*F22 -> 18.9 | G23: =G20*G22 -> 19.100433 | H23: =H20*H22 -> 19.265812 | I23: =I20*I22 -> 19.39481 | ... L23: =L20*L22 -> 20.027704
A24: NOPAT | B24: =B23*(1-$B$9) -> 13.527 | C24: =C23*(1-$B$9) -> 14.15325 | D24: =D23*(1-$B$9) -> 14.7795 | E24: =E23*(1-$B$9) -> 15.2805 | F24: =F23*(1-$B$9) -> 15.7815 | G24: =G23*(1-$B$9) -> 15.948862 | H24: =H23*(1-$B$9) -> 16.086953 | I24: =I23*(1-$B$9) -> 16.194667 | ... L24: =L23*(1-$B$9) -> 16.723132
A25: Net reinvestment, % of revenue | B25: 0.04 | C25: 0.04 | D25: 0.04 | E25: 0.04 | F25: 0.04 | G25: =$F25+($L25-$F25)*G$17/5 -> 0.039 | H25: =$F25+($L25-$F25)*H$17/5 -> 0.038 | I25: =$F25+($L25-$F25)*I$17/5 -> 0.037 | J25: =$F25+($L25-$F25)*J$17/5 -> 0.036 | K25: =$F25+($L25-$F25)*K$17/5 -> 0.035 | L25: 0.035
A26: Net reinvestment | B26: =B20*B25 -> 2.16 | C26: =C20*C25 -> 2.26 | D26: =D20*D25 -> 2.36 | E26: =E20*E25 -> 2.44 | F26: =F20*F25 -> 2.52 | G26: =G20*G25 -> 2.5337309 | H26: =H20*H25 -> 2.5420169 | I26: =I20*I25 -> 2.5447092 | ... L26: =L20*L25 -> 2.5961838
A27: Change in working capital | B27: =$B$11*(B20-$B$12) -> 0 | C27: =$B$11*(C20-B20) -> 0 | D27: =$B$11*(D20-C20) -> 0 | E27: =$B$11*(E20-D20) -> 0 | F27: =$B$11*(F20-E20) -> 0 | G27: =$B$11*(G20-F20) -> 0 | H27: =$B$11*(H20-G20) -> 0 | I27: =$B$11*(I20-H20) -> 0 | J27: =$B$11*(J20-I20) -> 0 | ... L27: =$B$11*(L20-K20) -> 0
A28: Free cash flow | B28: =B24-B26-B27 -> 11.367 | C28: =C24-C26-C27 -> 11.89325 | D28: =D24-D26-D27 -> 12.4195 | E28: =E24-E26-E27 -> 12.8405 | F28: =F24-F26-F27 -> 13.2615 | G28: =G24-G26-G27 -> 13.415131 | H28: =H24-H26-H27 -> 13.544936 | I28: =I24-I26-I27 -> 13.649958 | ... L28: =L24-L26-L27 -> 14.126949
A29: Discount factor | B29: =1/(1+$B$10)^B$16 -> 0.95563697 | C29: =1/(1+$B$10)^C$16 -> 0.87272782 | D29: =1/(1+$B$10)^D$16 -> 0.79701171 | E29: =1/(1+$B$10)^E$16 -> 0.72786458 | F29: =1/(1+$B$10)^F$16 -> 0.66471651 | G29: =1/(1+$B$10)^G$16 -> 0.60704704 | H29: =1/(1+$B$10)^H$16 -> 0.55438086 | I29: =1/(1+$B$10)^I$16 -> 0.50628389 | ... K29: =1/(1+$B$10)^K$16 -> 0.42224631
A30: PV of free cash flow | B30: =B28*B29 -> 10.862725 | C30: =C28*C29 -> 10.37957 | D30: =D28*D29 -> 9.8984869 | E30: =E28*E29 -> 9.3461451 | F30: =F28*F29 -> 8.815138 | G30: =G28*G29 -> 8.1436153 | H30: =H28*H29 -> 7.5090535 | I30: =I28*I29 -> 6.9107536 | ... K30: =K28*K29 -> 5.8195629
A31: Terminal value | B31: =L28/($B$10-L21) -> 201.81355 | C31: =IF($B$10>L21,"","Discount rate must exceed terminal growth")
A32: PV of terminal value | B32: =B31/(1+$B$10)^$K$16 -> 85.215029
A33: Equity value (PV FCF + PV TV + net cash + other) | B33: =SUM(B30:K30)+B32+$B$7+$B$8 -> 162.14798
A34: Value per share ($) | B34: =B33/$B$6 -> 39.490496
A35: Value vs share price | B35: =B34/$B$4-1 -> -0.36835419
A37: Base: growth slows to about 7%, margins edge up
A38: Revenue | B38: 55.5 | C38: 60 | D38: 64.5 | E38: 69 | F38: 73.5 | G38: =F38*(1+$F39+($L39-$F39)*G$17/5) -> 77.849283 | H38: =G38*(1+$F39+($L39-$F39)*H$17/5) -> 81.985449 | I38: =H38*(1+$F39+($L39-$F39)*I$17/5) -> 85.845894 | J38: =I38*(1+$F39+($L39-$F39)*J$17/5) -> 89.369308 | K38: =J38*(1+$F39+($L39-$F39)*K$17/5) -> 92.497234 | L38: =K38*(1+L39) -> 95.734637
A39: Revenue growth (terminal column = terminal growth, input) | B39: =B38/$B$12-1 -> 0.086105675 | C39: =C38/B38-1 -> 0.081081081 | D39: =D38/C38-1 -> 0.075 | E39: =E38/D38-1 -> 0.069767442 | F39: =F38/E38-1 -> 0.065217391 | G39: =G38/F38-1 -> 0.059173913 | H39: =H38/G38-1 -> 0.053130435 | I39: =I38/H38-1 -> 0.047086957 | J39: =J38/I38-1 -> 0.041043478 | K39: =K38/J38-1 -> 0.035 | L39: 0.035
A40: Operating margin | B40: 0.32 | C40: 0.33 | D40: 0.34 | E40: 0.35 | F40: 0.355 | G40: =$F40+($L40-$F40)*G$17/5 -> 0.35 | H40: =$F40+($L40-$F40)*H$17/5 -> 0.345 | I40: =$F40+($L40-$F40)*I$17/5 -> 0.34 | J40: =$F40+($L40-$F40)*J$17/5 -> 0.335 | K40: =$F40+($L40-$F40)*K$17/5 -> 0.33 | L40: 0.33
A41: Operating income | B41: =B38*B40 -> 17.76 | C41: =C38*C40 -> 19.8 | D41: =D38*D40 -> 21.93 | E41: =E38*E40 -> 24.15 | F41: =F38*F40 -> 26.0925 | G41: =G38*G40 -> 27.247249 | H41: =H38*H40 -> 28.28498 | I41: =I38*I40 -> 29.187604 | ... L41: =L38*L40 -> 31.59243
A42: NOPAT | B42: =B41*(1-$B$9) -> 14.8296 | C42: =C41*(1-$B$9) -> 16.533 | D42: =D41*(1-$B$9) -> 18.31155 | E42: =E41*(1-$B$9) -> 20.16525 | F42: =F41*(1-$B$9) -> 21.787237 | G42: =G41*(1-$B$9) -> 22.751453 | H42: =H41*(1-$B$9) -> 23.617958 | I42: =I41*(1-$B$9) -> 24.371649 | ... L42: =L41*(1-$B$9) -> 26.379679
A43: Net reinvestment, % of revenue | B43: 0.04 | C43: 0.04 | D43: 0.04 | E43: 0.04 | F43: 0.04 | G43: =$F43+($L43-$F43)*G$17/5 -> 0.039 | H43: =$F43+($L43-$F43)*H$17/5 -> 0.038 | I43: =$F43+($L43-$F43)*I$17/5 -> 0.037 | J43: =$F43+($L43-$F43)*J$17/5 -> 0.036 | K43: =$F43+($L43-$F43)*K$17/5 -> 0.035 | L43: 0.035
A44: Net reinvestment | B44: =B38*B43 -> 2.22 | C44: =C38*C43 -> 2.4 | D44: =D38*D43 -> 2.58 | E44: =E38*E43 -> 2.76 | F44: =F38*F43 -> 2.94 | G44: =G38*G43 -> 3.036122 | H44: =H38*H43 -> 3.1154471 | I44: =I38*I43 -> 3.1762981 | ... L44: =L38*L43 -> 3.3507123
A45: Change in working capital | B45: =$B$11*(B38-$B$12) -> 0 | C45: =$B$11*(C38-B38) -> 0 | D45: =$B$11*(D38-C38) -> 0 | E45: =$B$11*(E38-D38) -> 0 | F45: =$B$11*(F38-E38) -> 0 | G45: =$B$11*(G38-F38) -> 0 | H45: =$B$11*(H38-G38) -> 0 | I45: =$B$11*(I38-H38) -> 0 | J45: =$B$11*(J38-I38) -> 0 | ... L45: =$B$11*(L38-K38) -> 0
A46: Free cash flow | B46: =B42-B44-B45 -> 12.6096 | C46: =C42-C44-C45 -> 14.133 | D46: =D42-D44-D45 -> 15.73155 | E46: =E42-E44-E45 -> 17.40525 | F46: =F42-F44-F45 -> 18.847237 | G46: =G42-G44-G45 -> 19.715331 | H46: =H42-H44-H45 -> 20.502511 | I46: =I42-I44-I45 -> 21.195351 | ... L46: =L42-L44-L45 -> 23.028967
A47: Discount factor | B47: =1/(1+$B$10)^B$16 -> 0.95563697 | C47: =1/(1+$B$10)^C$16 -> 0.87272782 | D47: =1/(1+$B$10)^D$16 -> 0.79701171 | E47: =1/(1+$B$10)^E$16 -> 0.72786458 | F47: =1/(1+$B$10)^F$16 -> 0.66471651 | G47: =1/(1+$B$10)^G$16 -> 0.60704704 | H47: =1/(1+$B$10)^H$16 -> 0.55438086 | I47: =1/(1+$B$10)^I$16 -> 0.50628389 | ... K47: =1/(1+$B$10)^K$16 -> 0.42224631
A48: PV of free cash flow | B48: =B46*B47 -> 12.0502 | C48: =C46*C47 -> 12.334262 | D48: =D46*D47 -> 12.53823 | E48: =E46*E47 -> 12.668665 | F48: =F46*F47 -> 12.52807 | G48: =G46*G47 -> 11.968133 | H48: =H46*H47 -> 11.3662 | I48: =I46*I47 -> 10.730865 | ... K48: =K46*K47 -> 9.395069
A49: Terminal value | B49: =L46/($B$10-L39) -> 383.81612 | C49: =IF($B$10>L39,"","Discount rate must exceed terminal growth")
A50: PV of terminal value | B50: =B49/(1+$B$10)^$K$16 -> 162.06494
A51: Equity value (PV FCF + PV TV + net cash + other) | B51: =SUM(B48:K48)+B50+$B$7+$B$8 -> 270.61554
A52: Value per share ($) | B52: =B51/$B$6 -> 65.90734
A53: Value vs share price | B53: =B52/$B$4-1 -> 0.054180102
A55: Bull: ads and pricing compound, margins near 39%
A56: Revenue | B56: 56.5 | C56: 62.5 | D56: 69 | E56: 75.5 | F56: 82 | G56: =F56*(1+$F57+($L57-$F57)*G$17/5) -> 88.303682 | H56: =G56*(1+$F57+($L57-$F57)*H$17/5) -> 94.277923 | I56: =H56*(1+$F57+($L57-$F57)*I$17/5) -> 99.78725 | J56: =I56*(1+$F57+($L57-$F57)*J$17/5) -> 104.69863 | K56: =J56*(1+$F57+($L57-$F57)*K$17/5) -> 108.88658 | L56: =K56*(1+L57) -> 113.24204
A57: Revenue growth (terminal column = terminal growth, input) | B57: =B56/$B$12-1 -> 0.10567515 | C57: =C56/B56-1 -> 0.10619469 | D57: =D56/C56-1 -> 0.104 | E57: =E56/D56-1 -> 0.094202899 | F57: =F56/E56-1 -> 0.086092715 | G57: =G56/F56-1 -> 0.076874172 | H57: =H56/G56-1 -> 0.067655629 | I57: =I56/H56-1 -> 0.058437086 | J57: =J56/I56-1 -> 0.049218543 | K57: =K56/J56-1 -> 0.04 | L57: 0.04
A58: Operating margin | B58: 0.33 | C58: 0.35 | D58: 0.37 | E58: 0.38 | F58: 0.39 | G58: =$F58+($L58-$F58)*G$17/5 -> 0.386 | H58: =$F58+($L58-$F58)*H$17/5 -> 0.382 | I58: =$F58+($L58-$F58)*I$17/5 -> 0.378 | J58: =$F58+($L58-$F58)*J$17/5 -> 0.374 | K58: =$F58+($L58-$F58)*K$17/5 -> 0.37 | L58: 0.37
A59: Operating income | B59: =B56*B58 -> 18.645 | C59: =C56*C58 -> 21.875 | D59: =D56*D58 -> 25.53 | E59: =E56*E58 -> 28.69 | F59: =F56*F58 -> 31.98 | G59: =G56*G58 -> 34.085221 | H59: =H56*H58 -> 36.014167 | I59: =I56*I58 -> 37.719581 | ... L59: =L56*L58 -> 41.899556
A60: NOPAT | B60: =B59*(1-$B$9) -> 15.568575 | C60: =C59*(1-$B$9) -> 18.265625 | D60: =D59*(1-$B$9) -> 21.31755 | E60: =E59*(1-$B$9) -> 23.95615 | F60: =F59*(1-$B$9) -> 26.7033 | G60: =G59*(1-$B$9) -> 28.46116 | H60: =H59*(1-$B$9) -> 30.071829 | I60: =I59*(1-$B$9) -> 31.49585 | ... L60: =L59*(1-$B$9) -> 34.986129
A61: Net reinvestment, % of revenue | B61: 0.04 | C61: 0.04 | D61: 0.04 | E61: 0.04 | F61: 0.04 | G61: =$F61+($L61-$F61)*G$17/5 -> 0.039 | H61: =$F61+($L61-$F61)*H$17/5 -> 0.038 | I61: =$F61+($L61-$F61)*I$17/5 -> 0.037 | J61: =$F61+($L61-$F61)*J$17/5 -> 0.036 | K61: =$F61+($L61-$F61)*K$17/5 -> 0.035 | L61: 0.035
A62: Net reinvestment | B62: =B56*B61 -> 2.26 | C62: =C56*C61 -> 2.5 | D62: =D56*D61 -> 2.76 | E62: =E56*E61 -> 3.02 | F62: =F56*F61 -> 3.28 | G62: =G56*G61 -> 3.4438436 | H62: =H56*H61 -> 3.5825611 | I62: =I56*I61 -> 3.6921283 | ... L62: =L56*L61 -> 3.9634715
A63: Change in working capital | B63: =$B$11*(B56-$B$12) -> 0 | C63: =$B$11*(C56-B56) -> 0 | D63: =$B$11*(D56-C56) -> 0 | E63: =$B$11*(E56-D56) -> 0 | F63: =$B$11*(F56-E56) -> 0 | G63: =$B$11*(G56-F56) -> 0 | H63: =$B$11*(H56-G56) -> 0 | I63: =$B$11*(I56-H56) -> 0 | J63: =$B$11*(J56-I56) -> 0 | ... L63: =$B$11*(L56-K56) -> 0
A64: Free cash flow | B64: =B60-B62-B63 -> 13.308575 | C64: =C60-C62-C63 -> 15.765625 | D64: =D60-D62-D63 -> 18.55755 | E64: =E60-E62-E63 -> 20.93615 | F64: =F60-F62-F63 -> 23.4233 | G64: =G60-G62-G63 -> 25.017316 | H64: =H60-H62-H63 -> 26.489268 | I64: =I60-I62-I63 -> 27.803722 | ... L64: =L60-L62-L63 -> 31.022657
A65: Discount factor | B65: =1/(1+$B$10)^B$16 -> 0.95563697 | C65: =1/(1+$B$10)^C$16 -> 0.87272782 | D65: =1/(1+$B$10)^D$16 -> 0.79701171 | E65: =1/(1+$B$10)^E$16 -> 0.72786458 | F65: =1/(1+$B$10)^F$16 -> 0.66471651 | G65: =1/(1+$B$10)^G$16 -> 0.60704704 | H65: =1/(1+$B$10)^H$16 -> 0.55438086 | I65: =1/(1+$B$10)^I$16 -> 0.50628389 | ... K65: =1/(1+$B$10)^K$16 -> 0.42224631
A66: PV of free cash flow | B66: =B64*B65 -> 12.718166 | C66: =C64*C65 -> 13.7591 | D66: =D64*D65 -> 14.790585 | E66: =E64*E65 -> 15.238682 | F66: =F64*F65 -> 15.569854 | G66: =G64*G65 -> 15.186688 | H66: =H64*H65 -> 14.685143 | I66: =I64*I65 -> 14.076576 | ... K66: =K64*K65 -> 12.595387
A67: Terminal value | B67: =L64/($B$10-L57) -> 564.04832 | C67: =IF($B$10>L57,"","Discount rate must exceed terminal growth")
A68: PV of terminal value | B68: =B67/(1+$B$10)^$K$16 -> 238.16732
A69: Equity value (PV FCF + PV TV + net cash + other) | B69: =SUM(B66:K66)+B68+$B$7+$B$8 -> 373.06227
A70: Value per share ($) | B70: =B69/$B$6 -> 90.857835
A71: Value vs share price | B71: =B70/$B$4-1 -> 0.45326031
A74: Outputs | C74: vs price
A75: Bear value per share | B75: =B34 -> 39.490496 | C75: =B75/$B$4-1 -> -0.36835419
A76: Base value per share | B76: =B52 -> 65.90734 | C76: =B76/$B$4-1 -> 0.054180102
A77: Bull value per share | B77: =B70 -> 90.857835 | C77: =B77/$B$4-1 -> 0.45326031
A78: Selected scenario value per share | B78: =INDEX(B34:B70,1+($B$13-1)*18) -> 65.90734 | C78: =B78/$B$4-1 -> 0.054180102
A79: Share of base value from terminal value | B79: =B50/(SUM(B48:K48)+B50) -> 0.58356454
A81: Base value per share at other discount rates
A82: Discount rate | B82: 0.05 | C82: 0.06 | D82: 0.07 | E82: 0.08 | F82: 0.09 | G82: 0.1 | H82: 0.11 | I82: 0.12 | J82: 0.13 | K82: 0.14
A83: Base value per share | B83: =IF(B82>$L39,(SUMPRODUCT($B46:$K46/(1+B82)^$B$16:$K$16)+$L46/(B82-$L39)/(1+B82)^$K$16+$B$7+$B$8)/$B$6,"n/a") -> 268.13355 | C83: =IF(C82>$L39,(SUMPRODUCT($B46:$K46/(1+C82)^$B$16:$K$16)+$L46/(C82-$L39)/(1+C82)^$K$16+$B$7+$B$8)/$B$6,"n/a") -> 160.27083 | D83: =IF(D82>$L39,(SUMPRODUCT($B46:$K46/(1+D82)^$B$16:$K$16)+$L46/(D82-$L39)/(1+D82)^$K$16+$B$7+$B$8)/$B$6,"n/a") -> 114.04724 | E83: =IF(E82>$L39,(SUMPRODUCT($B46:$K46/(1+E82)^$B$16:$K$16)+$L46/(E82-$L39)/(1+E82)^$K$16+$B$7+$B$8)/$B$6,"n/a") -> 88.370304 | F83: =IF(F82>$L39,(SUMPRODUCT($B46:$K46/(1+F82)^$B$16:$K$16)+$L46/(F82-$L39)/(1+F82)^$K$16+$B$7+$B$8)/$B$6,"n/a") -> 72.032945 | G83: =IF(G82>$L39,(SUMPRODUCT($B46:$K46/(1+G82)^$B$16:$K$16)+$L46/(G82-$L39)/(1+G82)^$K$16+$B$7+$B$8)/$B$6,"n/a") -> 60.72471 | H83: =IF(H82>$L39,(SUMPRODUCT($B46:$K46/(1+H82)^$B$16:$K$16)+$L46/(H82-$L39)/(1+H82)^$K$16+$B$7+$B$8)/$B$6,"n/a") -> 52.43403 | I83: =IF(I82>$L39,(SUMPRODUCT($B46:$K46/(1+I82)^$B$16:$K$16)+$L46/(I82-$L39)/(1+I82)^$K$16+$B$7+$B$8)/$B$6,"n/a") -> 46.095941 | ... K83: =IF(K82>$L39,(SUMPRODUCT($B46:$K46/(1+K82)^$B$16:$K$16)+$L46/(K82-$L39)/(1+K82)^$K$16+$B$7+$B$8)/$B$6,"n/a") -> 37.046116
A84: vs share price | B84: =IFERROR(B83/$B$4-1,"n/a") -> 3.2887645 | C84: =IFERROR(C83/$B$4-1,"n/a") -> 1.5635129 | D84: =IFERROR(D83/$B$4-1,"n/a") -> 0.82417205 | E84: =IFERROR(E83/$B$4-1,"n/a") -> 0.41347256 | F84: =IFERROR(F83/$B$4-1,"n/a") -> 0.15215843 | G84: =IFERROR(G83/$B$4-1,"n/a") -> -0.028715458 | H84: =IFERROR(H83/$B$4-1,"n/a") -> -0.16132389 | I84: =IFERROR(I83/$B$4-1,"n/a") -> -0.26270088 | ... K84: =IFERROR(K83/$B$4-1,"n/a") -> -0.40745177
A86: Implied annual return at today's price, base case | B86: =IFERROR(IF(MATCH($B$4,$B$83:$K$83,-1)=10,"above 14%",INDEX($B$82:$K$82,MATCH($B$4,$B$83:$K$83,-1))+(INDEX($B$83:$K$83,MATCH($B$4,$B$83:$K$83,-1))-$B$4)/(INDEX($B$83:$K$83,MATCH($B$4,$B$83:$K$83,-1))-INDEX($B$83:$K$83,MATCH($B$4,$B$83:$K$83,-1)+1))*(INDEX($B$82:$K$82,MATCH($B$4,$B$83:$K$83,-1)+1)-INDEX($B$82:$K$82,MATCH($B$4,$B$83:$K$83,-1)))),"below 5%") -> 0.098412404 | C86: Discount rate at which base value equals the price (interpolated from the row above)

Sheet WACC
A1: Discount rates: calculated (CAPM) versus assumed
A2: Blue = input, black = formula, green = link. The yellow switches set the rate used on the model sheet.
A5: Rate used in valuations (1 = Calculated, 2 = Assumed) | B5: 2 | C5: Switch. 2 reproduces the doc's figures
A6: Beta used (1 = Raw 5-year, 2 = Blume adjusted) | B6: 2 | C6: Blume adjusted = 0.67 x raw + 0.33
A7: Risk-free rate (10-year Treasury) | B7: 0.0531 | C7: FRED via MacroRadar, Oct 6, 2026 (same as earlier journal models)
A8: Equity risk premium | B8: 0.05 | C8: Analyst assumption
A9: Credit spread over risk-free (pre-tax cost of debt) | B9: 0.012 | C9: Analyst assumption: investment-grade spread
A12: Item | B12: NFLX | C12: Source / note
A13: Raw beta (5-year) | B13: 1.61 | C13: Stock Analysis statistics, Oct 23, 2026
A14: Beta override (blank = none) | C14: Cheniere's 0.06 raw beta reflects its own history, not its risk; 0.80 used instead
A15: Adjusted beta | B15: =0.67*IF(ISNUMBER(B14),B14,B13)+0.33 -> 1.4087 | C15: Blume: 0.67 x raw (or override) + 0.33
A16: Beta used | B16: =IF($B$6=1,IF(ISNUMBER(B14),B14,B13),B15) -> 1.4087 | C16: Per switch in B6
A17: Cost of equity | B17: =$B$7+B16*$B$8 -> 0.123535 | C17: Risk-free + beta x ERP
A18: Pre-tax cost of debt | B18: =$B$7+$B$9 -> 0.0651 | C18: Risk-free + spread
A19: Tax rate | B19: =NFLX!B9 -> 0.165 | C19: Linked from company sheet
A20: After-tax cost of debt | B20: =B18*(1-B19) -> 0.0543585
A21: Market value of equity ($B) | B21: =NFLX!B4*NFLX!B6 -> 256.70712 | C21: Price x shares
A22: Debt ($B) | B22: 15.3 | C22: Stock Analysis, total debt
A23: Equity weight | B23: =B21/(B21+B22) -> 0.94375147
A24: Debt weight | B24: =B22/(B21+B22) -> 0.056248528
A25: Calculated WACC (CAPM) | B25: =B23*B17+B24*B20 -> 0.11964392 | C25: Weighted cost of capital
A26: Assumed WACC | B26: 0.095 | C26: Analyst assumption used in the doc
A27: WACC used | B27: =IF($B$5=1,B25,B26) -> 0.095 | C27: Per switch in B5; feeds each sheet's B10
A28: Check: WACC above every terminal growth rate | B28: =IF(B27>MAX(NFLX!L21,NFLX!L39,NFLX!L57),"OK","WACC must exceed growth") -> OK
A29: Link row read by company sheets | B29: =B27 -> 0.095 | C29: Same as WACC used
