Workbook

Sheet Summary
A1: Celestica (CLS): valuation summary
A2: Values link to the model sheet (green). Switch the discount rate on the WACC tab.
A4: Company | B4: Method | C4: Share price | D4: Discount rate | E4: Bear value | F4: Base value | G4: Bull value | H4: Base vs price | I4: Implied return at price (base case) | J4: Base value (rounded)
A5: Celestica (CLS) | B5: 10-year DCF | C5: =CLS!B4 -> 246.65 | D5: =CLS!B10 -> 0.1022 | E5: =CLS!B75 -> 129.93174 | F5: =CLS!B76 -> 205.81679 | G5: =CLS!B77 -> 330.54089 | H5: =F5/C5-1 -> -0.16555121 | I5: =CLS!B86 -> 0.089558686 | J5: =IF(F5<10,ROUND(F5*4,0)/4,IF(F5<100,ROUND(F5,0),ROUND(F5/5,0)*5)) -> 205
A8: Exit plan on the positions page
A9: Base value (rounded) | C9: 200
A10: Trim above (bull value, rounded) | C10: 315
A11: Exit below (halfway, bear to base) | C11: 160
A12: Thesis-break signal | C12: Sell if a major hyperscaler cuts capex, or if 2027 revenue guidance comes in below 2026. The first position to cut if a contraction starts.

Sheet CLS
A1: Celestica (CLS): 10-year scenario DCF
A2: Units: $ billions unless noted. Blue = input, black = formula, green = link, yellow = key lever. Years 6 to 10 fade growth, margin and reinvestment toward each scenario's terminal levels.
A4: Share price ($) | B4: 246.65 | C4: Oct 26, 2026 close (before results)
A5: Price date | B5: Oct 26, 2026 close (before results) | C5: Text
A6: Shares outstanding (billions) | B6: 0.1261 | C6: 126.1M shares at Sep 30, 2026, after the August offering of 11.1M shares at $310 (Q3 2026 release)
A7: Net cash, negative = net debt | B7: 3.1425 | C7: Q3 2026 release: cash $3,961M less borrowings and leases $819M
A8: Other non-operating assets, less outside claims | B8: 0 | C8: None
A9: Tax rate | B9: 0.21 | C9: Analyst assumption (normalized, near the reported effective rate)
A10: Discount rate (WACC), from WACC tab | B10: =WACC!B29 -> 0.1022 | C10: Calculated or assumed, per the switch in WACC!B5
A11: Working capital, % of revenue change | B11: 0.1 | C11: Analyst assumption
A12: Base-year revenue (2026E) | B12: 21 | C12: 2026 outlook $21.0B (raised from $20.5B, Q3 2026 release). 2027 outlook: $40.0B revenue, 9.0% adjusted operating margin, $21.50 adjusted EPS, $1.5B to $2.0B capex. Margins here are after stock pay, about 0.4 points below adjusted
A13: Selected scenario (1 Bear, 2 Base, 3 Bull) | B13: 2 | C13: Lever
A15: Year | B15: 2027 | C15: 2028 | D15: 2029 | E15: 2030 | F15: 2031 | G15: 2032 | H15: 2033 | I15: 2034 | J15: 2035 | K15: 2036 | L15: Terminal
A16: Discount period (years, mid-year) | B16: 0.5 | C16: =B16+1 -> 1.5 | D16: =C16+1 -> 2.5 | E16: =D16+1 -> 3.5 | F16: =E16+1 -> 4.5 | G16: =F16+1 -> 5.5 | H16: =G16+1 -> 6.5 | I16: =H16+1 -> 7.5 | J16: =I16+1 -> 8.5 | K16: =J16+1 -> 9.5
A17: Fade step (years 6 to 10) | B17: 0 | C17: 0 | D17: 0 | E17: 0 | F17: 0 | G17: 1 | H17: 2 | I17: 3 | J17: 4 | K17: 5
A19: Bear: a large customer pauses, 2027 misses and 2028 falls
A20: Revenue | B20: 33 | C20: 28 | D20: 27 | E20: 29 | F20: 31 | G20: =F20*(1+$F21+($L21-$F21)*G$17/5) -> 32.865345 | H20: =G20*(1+$F21+($L21-$F21)*H$17/5) -> 34.553944 | I20: =H20*(1+$F21+($L21-$F21)*I$17/5) -> 36.025465 | J20: =I20*(1+$F21+($L21-$F21)*J$17/5) -> 37.242877 | K20: =J20*(1+$F21+($L21-$F21)*K$17/5) -> 38.173949 | L20: =K20*(1+L21) -> 39.128298
A21: Revenue growth (terminal column = terminal growth, input) | B21: =B20/$B$12-1 -> 0.57142857 | C21: =C20/B20-1 -> -0.15151515 | D21: =D20/C20-1 -> -0.035714286 | E21: =E20/D20-1 -> 0.074074074 | F21: =F20/E20-1 -> 0.068965517 | G21: =G20/F20-1 -> 0.060172414 | H21: =H20/G20-1 -> 0.05137931 | I21: =I20/H20-1 -> 0.042586207 | J21: =J20/I20-1 -> 0.033793103 | K21: =K20/J20-1 -> 0.025 | L21: 0.025
A22: Operating margin | B22: 0.08 | C22: 0.07 | D22: 0.065 | E22: 0.065 | F22: 0.065 | G22: =$F22+($L22-$F22)*G$17/5 -> 0.064 | H22: =$F22+($L22-$F22)*H$17/5 -> 0.063 | I22: =$F22+($L22-$F22)*I$17/5 -> 0.062 | J22: =$F22+($L22-$F22)*J$17/5 -> 0.061 | K22: =$F22+($L22-$F22)*K$17/5 -> 0.06 | L22: 0.06
A23: Operating income | B23: =B20*B22 -> 2.64 | C23: =C20*C22 -> 1.96 | D23: =D20*D22 -> 1.755 | E23: =E20*E22 -> 1.885 | F23: =F20*F22 -> 2.015 | G23: =G20*G22 -> 2.1033821 | H23: =H20*H22 -> 2.1768984 | I23: =I20*I22 -> 2.2335788 | ... L23: =L20*L22 -> 2.3476979
A24: NOPAT | B24: =B23*(1-$B$9) -> 2.0856 | C24: =C23*(1-$B$9) -> 1.5484 | D24: =D23*(1-$B$9) -> 1.38645 | E24: =E23*(1-$B$9) -> 1.48915 | F24: =F23*(1-$B$9) -> 1.59185 | G24: =G23*(1-$B$9) -> 1.6616718 | H24: =H23*(1-$B$9) -> 1.7197498 | I24: =I23*(1-$B$9) -> 1.7645273 | ... L24: =L23*(1-$B$9) -> 1.8546813
A25: Net reinvestment, % of revenue | B25: 0.035 | C25: 0.02 | D25: 0.012 | E25: 0.012 | F25: 0.012 | G25: =$F25+($L25-$F25)*G$17/5 -> 0.0116 | H25: =$F25+($L25-$F25)*H$17/5 -> 0.0112 | I25: =$F25+($L25-$F25)*I$17/5 -> 0.0108 | J25: =$F25+($L25-$F25)*J$17/5 -> 0.0104 | K25: =$F25+($L25-$F25)*K$17/5 -> 0.01 | L25: 0.01
A26: Net reinvestment | B26: =B20*B25 -> 1.155 | C26: =C20*C25 -> 0.56 | D26: =D20*D25 -> 0.324 | E26: =E20*E25 -> 0.348 | F26: =F20*F25 -> 0.372 | G26: =G20*G25 -> 0.381238 | H26: =H20*H25 -> 0.38700417 | I26: =I20*I25 -> 0.38907502 | ... L26: =L20*L25 -> 0.39128298
A27: Change in working capital | B27: =$B$11*(B20-$B$12) -> 1.2 | C27: =$B$11*(C20-B20) -> -0.5 | D27: =$B$11*(D20-C20) -> -0.1 | E27: =$B$11*(E20-D20) -> 0.2 | F27: =$B$11*(F20-E20) -> 0.2 | G27: =$B$11*(G20-F20) -> 0.18653448 | H27: =$B$11*(H20-G20) -> 0.16885988 | I27: =$B$11*(I20-H20) -> 0.14715214 | J27: =$B$11*(J20-I20) -> 0.12174123 | ... L27: =$B$11*(L20-K20) -> 0.095434873
A28: Free cash flow | B28: =B24-B26-B27 -> -0.2694 | C28: =C24-C26-C27 -> 1.4884 | D28: =D24-D26-D27 -> 1.16245 | E28: =E24-E26-E27 -> 0.94115 | F28: =F24-F26-F27 -> 1.01985 | G28: =G24-G26-G27 -> 1.0938994 | H28: =H24-H26-H27 -> 1.1638857 | I28: =I24-I26-I27 -> 1.2283001 | ... L28: =L24-L26-L27 -> 1.3679635
A29: Discount factor | B29: =1/(1+$B$10)^B$16 -> 0.95251055 | C29: =1/(1+$B$10)^C$16 -> 0.86419031 | D29: =1/(1+$B$10)^D$16 -> 0.78405943 | E29: =1/(1+$B$10)^E$16 -> 0.71135858 | F29: =1/(1+$B$10)^F$16 -> 0.64539882 | G29: =1/(1+$B$10)^G$16 -> 0.58555509 | H29: =1/(1+$B$10)^H$16 -> 0.53126029 | I29: =1/(1+$B$10)^I$16 -> 0.4819999 | ... K29: =1/(1+$B$10)^K$16 -> 0.39675841
A30: PV of free cash flow | B30: =B28*B29 -> -0.25660634 | C30: =C28*C29 -> 1.2862609 | D30: =D28*D29 -> 0.91142989 | E30: =E28*E29 -> 0.66949513 | F30: =F28*F29 -> 0.65820999 | G30: =G28*G29 -> 0.64053834 | H30: =H28*H29 -> 0.61832627 | I30: =I28*I29 -> 0.59204053 | ... K30: =K28*K29 -> 0.52951318
A31: Terminal value | B31: =L28/($B$10-L21) -> 17.719734 | C31: =IF($B$10>L21,"","Discount rate must exceed terminal growth")
A32: PV of terminal value | B32: =B31/(1+$B$10)^$K$16 -> 7.0304534
A33: Equity value (PV FCF + PV TV + net cash + other) | B33: =SUM(B30:K30)+B32+$B$7+$B$8 -> 16.384393
A34: Value per share ($) | B34: =B33/$B$6 -> 129.93174
A35: Value vs share price | B35: =B34/$B$4-1 -> -0.4732141
A37: Base: 2027 lands 8% below the outlook, 2028 grows, 2029 digests
A38: Revenue | B38: 37 | C38: 42 | D38: 40 | E38: 42 | F38: 44 | G38: =F38*(1+$F39+($L39-$F39)*G$17/5) -> 45.94019 | H38: =G38*(1+$F39+($L39-$F39)*H$17/5) -> 47.80405 | I38: =H38*(1+$F39+($L39-$F39)*I$17/5) -> 49.575076 | J38: =I38*(1+$F39+($L39-$F39)*J$17/5) -> 51.237021 | K38: =J38*(1+$F39+($L39-$F39)*K$17/5) -> 52.774132 | L38: =K38*(1+L39) -> 54.357356
A39: Revenue growth (terminal column = terminal growth, input) | B39: =B38/$B$12-1 -> 0.76190476 | C39: =C38/B38-1 -> 0.13513514 | D39: =D38/C38-1 -> -0.047619048 | E39: =E38/D38-1 -> 0.05 | F39: =F38/E38-1 -> 0.047619048 | G39: =G38/F38-1 -> 0.044095238 | H39: =H38/G38-1 -> 0.040571429 | I39: =I38/H38-1 -> 0.037047619 | J39: =J38/I38-1 -> 0.03352381 | K39: =K38/J38-1 -> 0.03 | L39: 0.03
A40: Operating margin | B40: 0.086 | C40: 0.086 | D40: 0.082 | E40: 0.08 | F40: 0.08 | G40: =$F40+($L40-$F40)*G$17/5 -> 0.078 | H40: =$F40+($L40-$F40)*H$17/5 -> 0.076 | I40: =$F40+($L40-$F40)*I$17/5 -> 0.074 | J40: =$F40+($L40-$F40)*J$17/5 -> 0.072 | K40: =$F40+($L40-$F40)*K$17/5 -> 0.07 | L40: 0.07
A41: Operating income | B41: =B38*B40 -> 3.182 | C41: =C38*C40 -> 3.612 | D41: =D38*D40 -> 3.28 | E41: =E38*E40 -> 3.36 | F41: =F38*F40 -> 3.52 | G41: =G38*G40 -> 3.5833349 | H41: =H38*H40 -> 3.6331078 | I41: =I38*I40 -> 3.6685556 | ... L41: =L38*L40 -> 3.8050149
A42: NOPAT | B42: =B41*(1-$B$9) -> 2.51378 | C42: =C41*(1-$B$9) -> 2.85348 | D42: =D41*(1-$B$9) -> 2.5912 | E42: =E41*(1-$B$9) -> 2.6544 | F42: =F41*(1-$B$9) -> 2.7808 | G42: =G41*(1-$B$9) -> 2.8308345 | H42: =H41*(1-$B$9) -> 2.8701551 | I42: =I41*(1-$B$9) -> 2.8981589 | ... L42: =L41*(1-$B$9) -> 3.0059618
A43: Net reinvestment, % of revenue | B43: 0.035 | C43: 0.025 | D43: 0.015 | E43: 0.015 | F43: 0.015 | G43: =$F43+($L43-$F43)*G$17/5 -> 0.014 | H43: =$F43+($L43-$F43)*H$17/5 -> 0.013 | I43: =$F43+($L43-$F43)*I$17/5 -> 0.012 | J43: =$F43+($L43-$F43)*J$17/5 -> 0.011 | K43: =$F43+($L43-$F43)*K$17/5 -> 0.01 | L43: 0.01
A44: Net reinvestment | B44: =B38*B43 -> 1.295 | C44: =C38*C43 -> 1.05 | D44: =D38*D43 -> 0.6 | E44: =E38*E43 -> 0.63 | F44: =F38*F43 -> 0.66 | G44: =G38*G43 -> 0.64316267 | H44: =H38*H43 -> 0.62145265 | I44: =I38*I43 -> 0.59490091 | ... L44: =L38*L43 -> 0.54357356
A45: Change in working capital | B45: =$B$11*(B38-$B$12) -> 1.6 | C45: =$B$11*(C38-B38) -> 0.5 | D45: =$B$11*(D38-C38) -> -0.2 | E45: =$B$11*(E38-D38) -> 0.2 | F45: =$B$11*(F38-E38) -> 0.2 | G45: =$B$11*(G38-F38) -> 0.19401905 | H45: =$B$11*(H38-G38) -> 0.18638592 | I45: =$B$11*(I38-H38) -> 0.17710262 | J45: =$B$11*(J38-I38) -> 0.16619454 | ... L45: =$B$11*(L38-K38) -> 0.1583224
A46: Free cash flow | B46: =B42-B44-B45 -> -0.38122 | C46: =C42-C44-C45 -> 1.30348 | D46: =D42-D44-D45 -> 2.1912 | E46: =E42-E44-E45 -> 1.8244 | F46: =F42-F44-F45 -> 1.9208 | G46: =G42-G44-G45 -> 1.9936528 | H46: =H42-H44-H45 -> 2.0623166 | I46: =I42-I44-I45 -> 2.1261554 | ... L46: =L42-L44-L45 -> 2.3040658
A47: Discount factor | B47: =1/(1+$B$10)^B$16 -> 0.95251055 | C47: =1/(1+$B$10)^C$16 -> 0.86419031 | D47: =1/(1+$B$10)^D$16 -> 0.78405943 | E47: =1/(1+$B$10)^E$16 -> 0.71135858 | F47: =1/(1+$B$10)^F$16 -> 0.64539882 | G47: =1/(1+$B$10)^G$16 -> 0.58555509 | H47: =1/(1+$B$10)^H$16 -> 0.53126029 | I47: =1/(1+$B$10)^I$16 -> 0.4819999 | ... K47: =1/(1+$B$10)^K$16 -> 0.39675841
A48: PV of free cash flow | B48: =B46*B47 -> -0.36311607 | C48: =C46*C47 -> 1.1264548 | D48: =D46*D47 -> 1.718031 | E48: =E46*E47 -> 1.2978026 | F48: =F46*F47 -> 1.2396821 | G48: =G46*G47 -> 1.1673936 | H48: =H46*H47 -> 1.0956269 | I48: =I46*I47 -> 1.0248067 | ... K48: =K46*K47 -> 0.88753154
A49: Terminal value | B49: =L46/($B$10-L39) -> 31.912269 | C49: =IF($B$10>L39,"","Discount rate must exceed terminal growth")
A50: PV of terminal value | B50: =B49/(1+$B$10)^$K$16 -> 12.661461
A51: Equity value (PV FCF + PV TV + net cash + other) | B51: =SUM(B48:K48)+B50+$B$7+$B$8 -> 25.953498
A52: Value per share ($) | B52: =B51/$B$6 -> 205.81679
A53: Value vs share price | B53: =B52/$B$4-1 -> -0.16555121
A55: Bull: the $40B outlook is met and 2028 is meaningfully higher
A56: Revenue | B56: 40 | C56: 50 | D56: 54 | E56: 58 | F56: 62 | G56: =F56*(1+$F57+($L57-$F57)*G$17/5) -> 65.85469 | H56: =G56*(1+$F57+($L57-$F57)*H$17/5) -> 69.501677 | I56: =H56*(1+$F57+($L57-$F57)*I$17/5) -> 72.8785 | J56: =I56*(1+$F57+($L57-$F57)*J$17/5) -> 75.924318 | K56: =J56*(1+$F57+($L57-$F57)*K$17/5) -> 78.58167 | L56: =K56*(1+L57) -> 81.332028
A57: Revenue growth (terminal column = terminal growth, input) | B57: =B56/$B$12-1 -> 0.9047619 | C57: =C56/B56-1 -> 0.25 | D57: =D56/C56-1 -> 0.08 | E57: =E56/D56-1 -> 0.074074074 | F57: =F56/E56-1 -> 0.068965517 | G57: =G56/F56-1 -> 0.062172414 | H57: =H56/G56-1 -> 0.05537931 | I57: =I56/H56-1 -> 0.048586207 | J57: =J56/I56-1 -> 0.041793103 | K57: =K56/J56-1 -> 0.035 | L57: 0.035
A58: Operating margin | B58: 0.088 | C58: 0.09 | D58: 0.09 | E58: 0.09 | F58: 0.088 | G58: =$F58+($L58-$F58)*G$17/5 -> 0.0864 | H58: =$F58+($L58-$F58)*H$17/5 -> 0.0848 | I58: =$F58+($L58-$F58)*I$17/5 -> 0.0832 | J58: =$F58+($L58-$F58)*J$17/5 -> 0.0816 | K58: =$F58+($L58-$F58)*K$17/5 -> 0.08 | L58: 0.08
A59: Operating income | B59: =B56*B58 -> 3.52 | C59: =C56*C58 -> 4.5 | D59: =D56*D58 -> 4.86 | E59: =E56*E58 -> 5.22 | F59: =F56*F58 -> 5.456 | G59: =G56*G58 -> 5.6898452 | H59: =H56*H58 -> 5.8937422 | I59: =I56*I58 -> 6.0634912 | ... L59: =L56*L58 -> 6.5065622
A60: NOPAT | B60: =B59*(1-$B$9) -> 2.7808 | C60: =C59*(1-$B$9) -> 3.555 | D60: =D59*(1-$B$9) -> 3.8394 | E60: =E59*(1-$B$9) -> 4.1238 | F60: =F59*(1-$B$9) -> 4.31024 | G60: =G59*(1-$B$9) -> 4.4949777 | H60: =H59*(1-$B$9) -> 4.6560563 | I60: =I59*(1-$B$9) -> 4.790158 | ... L60: =L59*(1-$B$9) -> 5.1401842
A61: Net reinvestment, % of revenue | B61: 0.04 | C61: 0.03 | D61: 0.02 | E61: 0.015 | F61: 0.015 | G61: =$F61+($L61-$F61)*G$17/5 -> 0.014 | H61: =$F61+($L61-$F61)*H$17/5 -> 0.013 | I61: =$F61+($L61-$F61)*I$17/5 -> 0.012 | J61: =$F61+($L61-$F61)*J$17/5 -> 0.011 | K61: =$F61+($L61-$F61)*K$17/5 -> 0.01 | L61: 0.01
A62: Net reinvestment | B62: =B56*B61 -> 1.6 | C62: =C56*C61 -> 1.5 | D62: =D56*D61 -> 1.08 | E62: =E56*E61 -> 0.87 | F62: =F56*F61 -> 0.93 | G62: =G56*G61 -> 0.92196566 | H62: =H56*H61 -> 0.9035218 | I62: =I56*I61 -> 0.874542 | ... L62: =L56*L61 -> 0.81332028
A63: Change in working capital | B63: =$B$11*(B56-$B$12) -> 1.9 | C63: =$B$11*(C56-B56) -> 1 | D63: =$B$11*(D56-C56) -> 0.4 | E63: =$B$11*(E56-D56) -> 0.4 | F63: =$B$11*(F56-E56) -> 0.4 | G63: =$B$11*(G56-F56) -> 0.38546897 | H63: =$B$11*(H56-G56) -> 0.36469873 | I63: =$B$11*(I56-H56) -> 0.33768229 | J63: =$B$11*(J56-I56) -> 0.30458187 | ... L63: =$B$11*(L56-K56) -> 0.27503584
A64: Free cash flow | B64: =B60-B62-B63 -> -0.7192 | C64: =C60-C62-C63 -> 1.055 | D64: =D60-D62-D63 -> 2.3594 | E64: =E60-E62-E63 -> 2.8538 | F64: =F60-F62-F63 -> 2.98024 | G64: =G60-G62-G63 -> 3.1875431 | H64: =H60-H62-H63 -> 3.3878358 | I64: =I60-I62-I63 -> 3.5779338 | ... L64: =L60-L62-L63 -> 4.051828
A65: Discount factor | B65: =1/(1+$B$10)^B$16 -> 0.95251055 | C65: =1/(1+$B$10)^C$16 -> 0.86419031 | D65: =1/(1+$B$10)^D$16 -> 0.78405943 | E65: =1/(1+$B$10)^E$16 -> 0.71135858 | F65: =1/(1+$B$10)^F$16 -> 0.64539882 | G65: =1/(1+$B$10)^G$16 -> 0.58555509 | H65: =1/(1+$B$10)^H$16 -> 0.53126029 | I65: =1/(1+$B$10)^I$16 -> 0.4819999 | ... K65: =1/(1+$B$10)^K$16 -> 0.39675841
A66: PV of free cash flow | B66: =B64*B65 -> -0.68504559 | C66: =C64*C65 -> 0.91172077 | D66: =D64*D65 -> 1.8499098 | E66: =E64*E65 -> 2.0300751 | F66: =F64*F65 -> 1.9234434 | G66: =G64*G65 -> 1.8664821 | H66: =H64*H65 -> 1.7998226 | I66: =I64*I65 -> 1.7245637 | ... K66: =K64*K65 -> 1.5532337
A67: Terminal value | B67: =L64/($B$10-L57) -> 60.29506 | C67: =IF($B$10>L57,"","Discount rate must exceed terminal growth")
A68: PV of terminal value | B68: =B67/(1+$B$10)^$K$16 -> 23.922572
A69: Equity value (PV FCF + PV TV + net cash + other) | B69: =SUM(B66:K66)+B68+$B$7+$B$8 -> 41.681207
A70: Value per share ($) | B70: =B69/$B$6 -> 330.54089
A71: Value vs share price | B71: =B70/$B$4-1 -> 0.3401212
A74: Outputs | C74: vs price
A75: Bear value per share | B75: =B34 -> 129.93174 | C75: =B75/$B$4-1 -> -0.4732141
A76: Base value per share | B76: =B52 -> 205.81679 | C76: =B76/$B$4-1 -> -0.16555121
A77: Bull value per share | B77: =B70 -> 330.54089 | C77: =B77/$B$4-1 -> 0.3401212
A78: Selected scenario value per share | B78: =INDEX(B34:B70,1+($B$13-1)*18) -> 205.81679 | C78: =B78/$B$4-1 -> -0.16555121
A79: Share of base value from terminal value | B79: =B50/(SUM(B48:K48)+B50) -> 0.5550595
A81: Base value per share at other discount rates
A82: Discount rate | B82: 0.05 | C82: 0.06 | D82: 0.07 | E82: 0.08 | F82: 0.09 | G82: 0.1 | H82: 0.11 | I82: 0.12 | J82: 0.13 | K82: 0.14
A83: Base value per share | B83: =IF(B82>$L39,(SUMPRODUCT($B46:$K46/(1+B82)^$B$16:$K$16)+$L46/(B82-$L39)/(1+B82)^$K$16+$B$7+$B$8)/$B$6,"n/a") -> 704.39451 | C83: =IF(C82>$L39,(SUMPRODUCT($B46:$K46/(1+C82)^$B$16:$K$16)+$L46/(C82-$L39)/(1+C82)^$K$16+$B$7+$B$8)/$B$6,"n/a") -> 474.46434 | D83: =IF(D82>$L39,(SUMPRODUCT($B46:$K46/(1+D82)^$B$16:$K$16)+$L46/(D82-$L39)/(1+D82)^$K$16+$B$7+$B$8)/$B$6,"n/a") -> 359.52096 | E83: =IF(E82>$L39,(SUMPRODUCT($B46:$K46/(1+E82)^$B$16:$K$16)+$L46/(E82-$L39)/(1+E82)^$K$16+$B$7+$B$8)/$B$6,"n/a") -> 290.57266 | F83: =IF(F82>$L39,(SUMPRODUCT($B46:$K46/(1+F82)^$B$16:$K$16)+$L46/(F82-$L39)/(1+F82)^$K$16+$B$7+$B$8)/$B$6,"n/a") -> 244.62214 | G83: =IF(G82>$L39,(SUMPRODUCT($B46:$K46/(1+G82)^$B$16:$K$16)+$L46/(G82-$L39)/(1+G82)^$K$16+$B$7+$B$8)/$B$6,"n/a") -> 211.81337 | H83: =IF(H82>$L39,(SUMPRODUCT($B46:$K46/(1+H82)^$B$16:$K$16)+$L46/(H82-$L39)/(1+H82)^$K$16+$B$7+$B$8)/$B$6,"n/a") -> 187.21829 | I83: =IF(I82>$L39,(SUMPRODUCT($B46:$K46/(1+I82)^$B$16:$K$16)+$L46/(I82-$L39)/(1+I82)^$K$16+$B$7+$B$8)/$B$6,"n/a") -> 168.09906 | ... K83: =IF(K82>$L39,(SUMPRODUCT($B46:$K46/(1+K82)^$B$16:$K$16)+$L46/(K82-$L39)/(1+K82)^$K$16+$B$7+$B$8)/$B$6,"n/a") -> 140.3146
A84: vs share price | B84: =IFERROR(B83/$B$4-1,"n/a") -> 1.8558464 | C84: =IFERROR(C83/$B$4-1,"n/a") -> 0.92363406 | D84: =IFERROR(D83/$B$4-1,"n/a") -> 0.45761589 | E84: =IFERROR(E83/$B$4-1,"n/a") -> 0.17807687 | F84: =IFERROR(F83/$B$4-1,"n/a") -> -0.0082216096 | G84: =IFERROR(G83/$B$4-1,"n/a") -> -0.14123914 | H84: =IFERROR(H83/$B$4-1,"n/a") -> -0.24095566 | I84: =IFERROR(I83/$B$4-1,"n/a") -> -0.31847128 | ... K84: =IFERROR(K83/$B$4-1,"n/a") -> -0.43111859
A86: Implied annual return at today's price, base case | B86: =IFERROR(IF(MATCH($B$4,$B$83:$K$83,-1)=10,"above 14%",INDEX($B$82:$K$82,MATCH($B$4,$B$83:$K$83,-1))+(INDEX($B$83:$K$83,MATCH($B$4,$B$83:$K$83,-1))-$B$4)/(INDEX($B$83:$K$83,MATCH($B$4,$B$83:$K$83,-1))-INDEX($B$83:$K$83,MATCH($B$4,$B$83:$K$83,-1)+1))*(INDEX($B$82:$K$82,MATCH($B$4,$B$83:$K$83,-1)+1)-INDEX($B$82:$K$82,MATCH($B$4,$B$83:$K$83,-1)))),"below 5%") -> 0.089558686 | C86: Discount rate at which base value equals the price (interpolated from the row above)

Sheet WACC
A1: Discount rates: calculated (CAPM) versus assumed
A2: Blue = input, black = formula, green = link. The yellow switches set the rate used on the model sheet.
A5: Rate used in valuations (1 = Calculated, 2 = Assumed) | B5: 2 | C5: Switch. 2 reproduces the doc's figures
A6: Beta used (1 = Raw 5-year, 2 = Blume adjusted) | B6: 2 | C6: Blume adjusted = 0.67 x raw + 0.33
A7: Risk-free rate (10-year Treasury) | B7: 0.0503 | C7: 10-year Treasury yield at the close on 2026-10-28; assumed rates below move with it
A8: Equity risk premium | B8: 0.05 | C8: Analyst assumption
A9: Credit spread over risk-free (pre-tax cost of debt) | B9: 0.012 | C9: Analyst assumption: investment-grade spread
A12: Item | B12: CLS | C12: Source / note
A13: Raw beta (5-year) | B13: 1.32 | C13: Stock Analysis statistics, Oct 23, 2026
A14: Beta override (blank = none) | C14: Cheniere's 0.06 raw beta reflects its own history, not its risk; 0.80 used instead
A15: Adjusted beta | B15: =0.67*IF(ISNUMBER(B14),B14,B13)+0.33 -> 1.2144 | C15: Blume: 0.67 x raw (or override) + 0.33
A16: Beta used | B16: =IF($B$6=1,IF(ISNUMBER(B14),B14,B13),B15) -> 1.2144 | C16: Per switch in B6
A17: Cost of equity | B17: =$B$7+B16*$B$8 -> 0.11102 | C17: Risk-free + beta x ERP
A18: Pre-tax cost of debt | B18: =$B$7+$B$9 -> 0.0623 | C18: Risk-free + spread
A19: Tax rate | B19: =CLS!B9 -> 0.21 | C19: Linked from company sheet
A20: After-tax cost of debt | B20: =B18*(1-B19) -> 0.049217
A21: Market value of equity ($B) | B21: =CLS!B4*CLS!B6 -> 31.102565 | C21: Price x shares
A22: Debt ($B) | B22: 0.8188 | C22: Stock Analysis, total debt
A23: Equity weight | B23: =B21/(B21+B22) -> 0.97434947
A24: Debt weight | B24: =B22/(B21+B22) -> 0.025650532
A25: Calculated WACC (CAPM) | B25: =B23*B17+B24*B20 -> 0.10943472 | C25: Weighted cost of capital
A26: Assumed WACC | B26: 0.1022 | C26: Analyst assumption used in the doc
A27: WACC used | B27: =IF($B$5=1,B25,B26) -> 0.1022 | C27: Per switch in B5; feeds each sheet's B10
A28: Check: WACC above every terminal growth rate | B28: =IF(B27>MAX(CLS!L21,CLS!L39,CLS!L57),"OK","WACC must exceed growth") -> OK
A29: Link row read by company sheets | B29: =B27 -> 0.1022 | C29: Same as WACC used
