Workbook

Sheet Summary
A1: First Solar (FSLR): valuation summary
A2: Values link to the model sheet (green). Switch the discount rate on the WACC tab.
A4: Company | B4: Method | C4: Share price | D4: Discount rate | E4: Bear value | F4: Base value | G4: Bull value | H4: Base vs price | I4: Implied return at price (base case) | J4: Base value (rounded)
A5: First Solar (FSLR) | B5: 10-year DCF | C5: =FSLR!B4 -> 171.57 | D5: =FSLR!B10 -> 0.1022 | E5: =FSLR!B75 -> 73.39468 | F5: =FSLR!B76 -> 128.37795 | G5: =FSLR!B77 -> 193.21628 | H5: =F5/C5-1 -> -0.25174593 | I5: =FSLR!B86 -> 0.075764103 | J5: =IF(F5<10,ROUND(F5*4,0)/4,IF(F5<100,ROUND(F5,0),ROUND(F5/5,0)*5)) -> 130
A8: Exit plan on the positions page
A9: Base value (rounded) | C9: 125
A10: Trim above (bull value, rounded) | C10: 190
A11: Exit below (halfway, bear to base) | C11: 99
A12: Thesis-break signal | C12: Sell if the backlog falls below 35 GW, or if the Section 45X credits change.

Sheet FSLR
A1: First Solar (FSLR): 10-year scenario DCF
A2: Units: $ billions unless noted. Blue = input, black = formula, green = link, yellow = key lever. Years 6 to 10 fade growth, margin and reinvestment toward each scenario's terminal levels.
A4: Share price ($) | B4: 171.57 | C4: Oct 23, 2026 intraday (Yahoo Finance via the site's price feed)
A5: Price date | B5: Oct 23, 2026 | C5: Text
A6: Shares outstanding (billions) | B6: 0.10747 | C6: Stock Analysis statistics, Oct 23, 2026
A7: Net cash, negative = net debt | B7: 1.53 | C7: Stock Analysis statistics, Oct 23, 2026: cash less total debt
A8: Other non-operating assets, less outside claims | B8: 0 | C8: None. Margins include 45X manufacturing credits, which step down from 2030 and end after 2032
A9: Tax rate | B9: 0.12 | C9: Analyst assumption (normalized, near the reported effective rate)
A10: Discount rate (WACC), from WACC tab | B10: =WACC!B29 -> 0.1022 | C10: Calculated or assumed, per the switch in WACC!B5
A11: Working capital, % of revenue change | B11: 0.1 | C11: Analyst assumption
A12: Base-year revenue (2026E) | B12: 5.04 | C12: 2026E consensus $5.04B (Stock Analysis)
A13: Selected scenario (1 Bear, 2 Base, 3 Bull) | B13: 2 | C13: Lever
A15: Year | B15: 2027 | C15: 2028 | D15: 2029 | E15: 2030 | F15: 2031 | G15: 2032 | H15: 2033 | I15: 2034 | J15: 2035 | K15: 2036 | L15: Terminal
A16: Discount period (years, mid-year) | B16: 0.5 | C16: =B16+1 -> 1.5 | D16: =C16+1 -> 2.5 | E16: =D16+1 -> 3.5 | F16: =E16+1 -> 4.5 | G16: =F16+1 -> 5.5 | H16: =G16+1 -> 6.5 | I16: =H16+1 -> 7.5 | J16: =I16+1 -> 8.5 | K16: =J16+1 -> 9.5
A17: Fade step (years 6 to 10) | B17: 0 | C17: 0 | D17: 0 | E17: 0 | F17: 0 | G17: 1 | H17: 2 | I17: 3 | J17: 4 | K17: 5
A19: Bear: module prices fall, policy turns against solar
A20: Revenue | B20: 5 | C20: 5.3 | D20: 5.6 | E20: 5.6 | F20: 5.6 | G20: =F20*(1+$F21+($L21-$F21)*G$17/5) -> 5.6224 | H20: =G20*(1+$F21+($L21-$F21)*H$17/5) -> 5.6673792 | I20: =H20*(1+$F21+($L21-$F21)*I$17/5) -> 5.7353878 | J20: =I20*(1+$F21+($L21-$F21)*J$17/5) -> 5.827154 | K20: =J20*(1+$F21+($L21-$F21)*K$17/5) -> 5.943697 | L20: =K20*(1+L21) -> 6.062571
A21: Revenue growth (terminal column = terminal growth, input) | B21: =B20/$B$12-1 -> -0.0079365079 | C21: =C20/B20-1 -> 0.06 | D21: =D20/C20-1 -> 0.056603774 | E21: =E20/D20-1 -> 0 | F21: =F20/E20-1 -> 0 | G21: =G20/F20-1 -> 0.004 | H21: =H20/G20-1 -> 0.008 | I21: =I20/H20-1 -> 0.012 | J21: =J20/I20-1 -> 0.016 | K21: =K20/J20-1 -> 0.02 | L21: 0.02
A22: Operating margin | B22: 0.28 | C22: 0.27 | D22: 0.27 | E22: 0.2 | F22: 0.15 | G22: =$F22+($L22-$F22)*G$17/5 -> 0.14 | H22: =$F22+($L22-$F22)*H$17/5 -> 0.13 | I22: =$F22+($L22-$F22)*I$17/5 -> 0.12 | J22: =$F22+($L22-$F22)*J$17/5 -> 0.11 | K22: =$F22+($L22-$F22)*K$17/5 -> 0.1 | L22: 0.1
A23: Operating income | B23: =B20*B22 -> 1.4 | C23: =C20*C22 -> 1.431 | D23: =D20*D22 -> 1.512 | E23: =E20*E22 -> 1.12 | F23: =F20*F22 -> 0.84 | G23: =G20*G22 -> 0.787136 | H23: =H20*H22 -> 0.7367593 | I23: =I20*I22 -> 0.68824653 | ... L23: =L20*L22 -> 0.6062571
A24: NOPAT | B24: =B23*(1-$B$9) -> 1.232 | C24: =C23*(1-$B$9) -> 1.25928 | D24: =D23*(1-$B$9) -> 1.33056 | E24: =E23*(1-$B$9) -> 0.9856 | F24: =F23*(1-$B$9) -> 0.7392 | G24: =G23*(1-$B$9) -> 0.69267968 | H24: =H23*(1-$B$9) -> 0.64834818 | I24: =I23*(1-$B$9) -> 0.60565695 | ... L24: =L23*(1-$B$9) -> 0.53350625
A25: Net reinvestment, % of revenue | B25: 0.05 | C25: 0.04 | D25: 0.03 | E25: 0.03 | F25: 0.03 | G25: =$F25+($L25-$F25)*G$17/5 -> 0.03 | H25: =$F25+($L25-$F25)*H$17/5 -> 0.03 | I25: =$F25+($L25-$F25)*I$17/5 -> 0.03 | J25: =$F25+($L25-$F25)*J$17/5 -> 0.03 | K25: =$F25+($L25-$F25)*K$17/5 -> 0.03 | L25: 0.03
A26: Net reinvestment | B26: =B20*B25 -> 0.25 | C26: =C20*C25 -> 0.212 | D26: =D20*D25 -> 0.168 | E26: =E20*E25 -> 0.168 | F26: =F20*F25 -> 0.168 | G26: =G20*G25 -> 0.168672 | H26: =H20*H25 -> 0.17002138 | I26: =I20*I25 -> 0.17206163 | ... L26: =L20*L25 -> 0.18187713
A27: Change in working capital | B27: =$B$11*(B20-$B$12) -> -0.004 | C27: =$B$11*(C20-B20) -> 0.03 | D27: =$B$11*(D20-C20) -> 0.03 | E27: =$B$11*(E20-D20) -> 0 | F27: =$B$11*(F20-E20) -> 0 | G27: =$B$11*(G20-F20) -> 0.00224 | H27: =$B$11*(H20-G20) -> 0.00449792 | I27: =$B$11*(I20-H20) -> 0.006800855 | J27: =$B$11*(J20-I20) -> 0.0091766204 | ... L27: =$B$11*(L20-K20) -> 0.011887394
A28: Free cash flow | B28: =B24-B26-B27 -> 0.986 | C28: =C24-C26-C27 -> 1.01728 | D28: =D24-D26-D27 -> 1.13256 | E28: =E24-E26-E27 -> 0.8176 | F28: =F24-F26-F27 -> 0.5712 | G28: =G24-G26-G27 -> 0.52176768 | H28: =H24-H26-H27 -> 0.47382888 | I28: =I24-I26-I27 -> 0.42679446 | ... L28: =L24-L26-L27 -> 0.33974172
A29: Discount factor | B29: =1/(1+$B$10)^B$16 -> 0.95251055 | C29: =1/(1+$B$10)^C$16 -> 0.86419031 | D29: =1/(1+$B$10)^D$16 -> 0.78405943 | E29: =1/(1+$B$10)^E$16 -> 0.71135858 | F29: =1/(1+$B$10)^F$16 -> 0.64539882 | G29: =1/(1+$B$10)^G$16 -> 0.58555509 | H29: =1/(1+$B$10)^H$16 -> 0.53126029 | I29: =1/(1+$B$10)^I$16 -> 0.4819999 | ... K29: =1/(1+$B$10)^K$16 -> 0.39675841
A30: PV of free cash flow | B30: =B28*B29 -> 0.93917541 | C30: =C28*C29 -> 0.87912351 | D30: =D28*D29 -> 0.88799435 | E30: =E28*E29 -> 0.58160678 | F30: =F28*F29 -> 0.36865181 | G30: =G28*G29 -> 0.30552372 | H30: =H28*H29 -> 0.25172647 | I30: =I28*I29 -> 0.20571489 | ... K30: =K28*K29 -> 0.13215234
A31: Terminal value | B31: =L28/($B$10-L21) -> 4.133111 | C31: =IF($B$10>L21,"","Discount rate must exceed terminal growth")
A32: PV of terminal value | B32: =B31/(1+$B$10)^$K$16 -> 1.6398465
A33: Equity value (PV FCF + PV TV + net cash + other) | B33: =SUM(B30:K30)+B32+$B$7+$B$8 -> 7.8877263
A34: Value per share ($) | B34: =B33/$B$6 -> 73.39468
A35: Value vs share price | B35: =B34/$B$4-1 -> -0.57221729
A37: Base: US capacity fills, credits step down
A38: Revenue | B38: 5.8 | C38: 6.4 | D38: 6.8 | E38: 6.9 | F38: 7 | G38: =F38*(1+$F39+($L39-$F39)*G$17/5) -> 7.1161594 | H38: =G38*(1+$F39+($L39-$F39)*H$17/5) -> 7.2492007 | I38: =H38*(1+$F39+($L39-$F39)*I$17/5) -> 7.399963 | J38: =I38*(1+$F39+($L39-$F39)*J$17/5) -> 7.5694115 | K38: =J38*(1+$F39+($L39-$F39)*K$17/5) -> 7.7586467 | L38: =K38*(1+L39) -> 7.9526129
A39: Revenue growth (terminal column = terminal growth, input) | B39: =B38/$B$12-1 -> 0.15079365 | C39: =C38/B38-1 -> 0.10344828 | D39: =D38/C38-1 -> 0.0625 | E39: =E38/D38-1 -> 0.014705882 | F39: =F38/E38-1 -> 0.014492754 | G39: =G38/F38-1 -> 0.016594203 | H39: =H38/G38-1 -> 0.018695652 | I39: =I38/H38-1 -> 0.020797101 | J39: =J38/I38-1 -> 0.022898551 | K39: =K38/J38-1 -> 0.025 | L39: 0.025
A40: Operating margin | B40: 0.33 | C40: 0.34 | D40: 0.34 | E40: 0.29 | F40: 0.24 | G40: =$F40+($L40-$F40)*G$17/5 -> 0.222 | H40: =$F40+($L40-$F40)*H$17/5 -> 0.204 | I40: =$F40+($L40-$F40)*I$17/5 -> 0.186 | J40: =$F40+($L40-$F40)*J$17/5 -> 0.168 | K40: =$F40+($L40-$F40)*K$17/5 -> 0.15 | L40: 0.15
A41: Operating income | B41: =B38*B40 -> 1.914 | C41: =C38*C40 -> 2.176 | D41: =D38*D40 -> 2.312 | E41: =E38*E40 -> 2.001 | F41: =F38*F40 -> 1.68 | G41: =G38*G40 -> 1.5797874 | H41: =H38*H40 -> 1.4788369 | I41: =I38*I40 -> 1.3763931 | ... L41: =L38*L40 -> 1.1928919
A42: NOPAT | B42: =B41*(1-$B$9) -> 1.68432 | C42: =C41*(1-$B$9) -> 1.91488 | D42: =D41*(1-$B$9) -> 2.03456 | E42: =E41*(1-$B$9) -> 1.76088 | F42: =F41*(1-$B$9) -> 1.4784 | G42: =G41*(1-$B$9) -> 1.3902129 | H42: =H41*(1-$B$9) -> 1.3013765 | I42: =I41*(1-$B$9) -> 1.2112259 | ... L42: =L41*(1-$B$9) -> 1.0497449
A43: Net reinvestment, % of revenue | B43: 0.06 | C43: 0.05 | D43: 0.04 | E43: 0.03 | F43: 0.03 | G43: =$F43+($L43-$F43)*G$17/5 -> 0.03 | H43: =$F43+($L43-$F43)*H$17/5 -> 0.03 | I43: =$F43+($L43-$F43)*I$17/5 -> 0.03 | J43: =$F43+($L43-$F43)*J$17/5 -> 0.03 | K43: =$F43+($L43-$F43)*K$17/5 -> 0.03 | L43: 0.03
A44: Net reinvestment | B44: =B38*B43 -> 0.348 | C44: =C38*C43 -> 0.32 | D44: =D38*D43 -> 0.272 | E44: =E38*E43 -> 0.207 | F44: =F38*F43 -> 0.21 | G44: =G38*G43 -> 0.21348478 | H44: =H38*H43 -> 0.21747602 | I44: =I38*I43 -> 0.22199889 | ... L44: =L38*L43 -> 0.23857839
A45: Change in working capital | B45: =$B$11*(B38-$B$12) -> 0.076 | C45: =$B$11*(C38-B38) -> 0.06 | D45: =$B$11*(D38-C38) -> 0.04 | E45: =$B$11*(E38-D38) -> 0.01 | F45: =$B$11*(F38-E38) -> 0.01 | G45: =$B$11*(G38-F38) -> 0.011615942 | H45: =$B$11*(H38-G38) -> 0.013304124 | I45: =$B$11*(I38-H38) -> 0.015076236 | J45: =$B$11*(J38-I38) -> 0.016944843 | ... L45: =$B$11*(L38-K38) -> 0.019396617
A46: Free cash flow | B46: =B42-B44-B45 -> 1.26032 | C46: =C42-C44-C45 -> 1.53488 | D46: =D42-D44-D45 -> 1.72256 | E46: =E42-E44-E45 -> 1.54388 | F46: =F42-F44-F45 -> 1.2584 | G46: =G42-G44-G45 -> 1.1651122 | H46: =H42-H44-H45 -> 1.0705964 | I46: =I42-I44-I45 -> 0.97415082 | ... L46: =L42-L44-L45 -> 0.7917699
A47: Discount factor | B47: =1/(1+$B$10)^B$16 -> 0.95251055 | C47: =1/(1+$B$10)^C$16 -> 0.86419031 | D47: =1/(1+$B$10)^D$16 -> 0.78405943 | E47: =1/(1+$B$10)^E$16 -> 0.71135858 | F47: =1/(1+$B$10)^F$16 -> 0.64539882 | G47: =1/(1+$B$10)^G$16 -> 0.58555509 | H47: =1/(1+$B$10)^H$16 -> 0.53126029 | I47: =1/(1+$B$10)^I$16 -> 0.4819999 | ... K47: =1/(1+$B$10)^K$16 -> 0.39675841
A48: PV of free cash flow | B48: =B46*B47 -> 1.2004681 | C48: =C46*C47 -> 1.3264284 | D48: =D46*D47 -> 1.3505894 | E48: =E46*E47 -> 1.0982523 | F48: =F46*F47 -> 0.81216988 | G48: =G46*G47 -> 0.68223737 | H48: =H46*H47 -> 0.56876533 | I48: =I46*I47 -> 0.4695406 | ... K48: =K46*K47 -> 0.30647938
A49: Terminal value | B49: =L46/($B$10-L39) -> 10.256087 | C49: =IF($B$10>L39,"","Discount rate must exceed terminal growth")
A50: PV of terminal value | B50: =B49/(1+$B$10)^$K$16 -> 4.0691886
A51: Equity value (PV FCF + PV TV + net cash + other) | B51: =SUM(B48:K48)+B50+$B$7+$B$8 -> 13.796778
A52: Value per share ($) | B52: =B51/$B$6 -> 128.37795
A53: Value vs share price | B53: =B52/$B$4-1 -> -0.25174593
A55: Bull: data center demand, firm US pricing
A56: Revenue | B56: 6.2 | C56: 7.2 | D56: 8 | E56: 8.6 | F56: 9.2 | G56: =F56*(1+$F57+($L57-$F57)*G$17/5) -> 9.7686884 | H56: =G56*(1+$F57+($L57-$F57)*H$17/5) -> 10.294834 | I56: =H56*(1+$F57+($L57-$F57)*I$17/5) -> 10.767439 | J56: =I56*(1+$F57+($L57-$F57)*J$17/5) -> 11.176101 | K56: =J56*(1+$F57+($L57-$F57)*K$17/5) -> 11.511384 | L56: =K56*(1+L57) -> 11.856726
A57: Revenue growth (terminal column = terminal growth, input) | B57: =B56/$B$12-1 -> 0.23015873 | C57: =C56/B56-1 -> 0.16129032 | D57: =D56/C56-1 -> 0.11111111 | E57: =E56/D56-1 -> 0.075 | F57: =F56/E56-1 -> 0.069767442 | G57: =G56/F56-1 -> 0.061813953 | H57: =H56/G56-1 -> 0.053860465 | I57: =I56/H56-1 -> 0.045906977 | J57: =J56/I56-1 -> 0.037953488 | K57: =K56/J56-1 -> 0.03 | L57: 0.03
A58: Operating margin | B58: 0.35 | C58: 0.36 | D58: 0.36 | E58: 0.31 | F58: 0.27 | G58: =$F58+($L58-$F58)*G$17/5 -> 0.252 | H58: =$F58+($L58-$F58)*H$17/5 -> 0.234 | I58: =$F58+($L58-$F58)*I$17/5 -> 0.216 | J58: =$F58+($L58-$F58)*J$17/5 -> 0.198 | K58: =$F58+($L58-$F58)*K$17/5 -> 0.18 | L58: 0.18
A59: Operating income | B59: =B56*B58 -> 2.17 | C59: =C56*C58 -> 2.592 | D59: =D56*D58 -> 2.88 | E59: =E56*E58 -> 2.666 | F59: =F56*F58 -> 2.484 | G59: =G56*G58 -> 2.4617095 | H59: =H56*H58 -> 2.4089913 | I59: =I56*I58 -> 2.3257669 | ... L59: =L56*L58 -> 2.1342106
A60: NOPAT | B60: =B59*(1-$B$9) -> 1.9096 | C60: =C59*(1-$B$9) -> 2.28096 | D60: =D59*(1-$B$9) -> 2.5344 | E60: =E59*(1-$B$9) -> 2.34608 | F60: =F59*(1-$B$9) -> 2.18592 | G60: =G59*(1-$B$9) -> 2.1663043 | H60: =H59*(1-$B$9) -> 2.1199123 | I60: =I59*(1-$B$9) -> 2.0466748 | ... L60: =L59*(1-$B$9) -> 1.8781053
A61: Net reinvestment, % of revenue | B61: 0.07 | C61: 0.06 | D61: 0.05 | E61: 0.04 | F61: 0.03 | G61: =$F61+($L61-$F61)*G$17/5 -> 0.03 | H61: =$F61+($L61-$F61)*H$17/5 -> 0.03 | I61: =$F61+($L61-$F61)*I$17/5 -> 0.03 | J61: =$F61+($L61-$F61)*J$17/5 -> 0.03 | K61: =$F61+($L61-$F61)*K$17/5 -> 0.03 | L61: 0.03
A62: Net reinvestment | B62: =B56*B61 -> 0.434 | C62: =C56*C61 -> 0.432 | D62: =D56*D61 -> 0.4 | E62: =E56*E61 -> 0.344 | F62: =F56*F61 -> 0.276 | G62: =G56*G61 -> 0.29306065 | H62: =H56*H61 -> 0.30884503 | I62: =I56*I61 -> 0.32302318 | ... L62: =L56*L61 -> 0.35570177
A63: Change in working capital | B63: =$B$11*(B56-$B$12) -> 0.116 | C63: =$B$11*(C56-B56) -> 0.1 | D63: =$B$11*(D56-C56) -> 0.08 | E63: =$B$11*(E56-D56) -> 0.06 | F63: =$B$11*(F56-E56) -> 0.06 | G63: =$B$11*(G56-F56) -> 0.056868837 | H63: =$B$11*(H56-G56) -> 0.05261461 | I63: =$B$11*(I56-H56) -> 0.047260473 | J63: =$B$11*(J56-I56) -> 0.040866188 | ... L63: =$B$11*(L56-K56) -> 0.034534152
A64: Free cash flow | B64: =B60-B62-B63 -> 1.3596 | C64: =C60-C62-C63 -> 1.74896 | D64: =D60-D62-D63 -> 2.0544 | E64: =E60-E62-E63 -> 1.94208 | F64: =F60-F62-F63 -> 1.84992 | G64: =G60-G62-G63 -> 1.8163748 | H64: =H60-H62-H63 -> 1.7584527 | I64: =I60-I62-I63 -> 1.6763912 | ... L64: =L60-L62-L63 -> 1.4878694
A65: Discount factor | B65: =1/(1+$B$10)^B$16 -> 0.95251055 | C65: =1/(1+$B$10)^C$16 -> 0.86419031 | D65: =1/(1+$B$10)^D$16 -> 0.78405943 | E65: =1/(1+$B$10)^E$16 -> 0.71135858 | F65: =1/(1+$B$10)^F$16 -> 0.64539882 | G65: =1/(1+$B$10)^G$16 -> 0.58555509 | H65: =1/(1+$B$10)^H$16 -> 0.53126029 | I65: =1/(1+$B$10)^I$16 -> 0.4819999 | ... K65: =1/(1+$B$10)^K$16 -> 0.39675841
A66: PV of free cash flow | B66: =B64*B65 -> 1.2950333 | C66: =C64*C65 -> 1.5114343 | D66: =D64*D65 -> 1.6107717 | E66: =E64*E65 -> 1.3815153 | F66: =F64*F65 -> 1.1939362 | G66: =G64*G65 -> 1.0635875 | H66: =H64*H65 -> 0.93419608 | I66: =I64*I65 -> 0.80802039 | ... K66: =K64*K65 -> 0.57313078
A67: Terminal value | B67: =L64/($B$10-L57) -> 20.60761 | C67: =IF($B$10>L57,"","Discount rate must exceed terminal growth")
A68: PV of terminal value | B68: =B67/(1+$B$10)^$K$16 -> 8.1762424
A69: Equity value (PV FCF + PV TV + net cash + other) | B69: =SUM(B66:K66)+B68+$B$7+$B$8 -> 20.764954
A70: Value per share ($) | B70: =B69/$B$6 -> 193.21628
A71: Value vs share price | B71: =B70/$B$4-1 -> 0.12616589
A74: Outputs | C74: vs price
A75: Bear value per share | B75: =B34 -> 73.39468 | C75: =B75/$B$4-1 -> -0.57221729
A76: Base value per share | B76: =B52 -> 128.37795 | C76: =B76/$B$4-1 -> -0.25174593
A77: Bull value per share | B77: =B70 -> 193.21628 | C77: =B77/$B$4-1 -> 0.12616589
A78: Selected scenario value per share | B78: =INDEX(B34:B70,1+($B$13-1)*18) -> 128.37795 | C78: =B78/$B$4-1 -> -0.25174593
A79: Share of base value from terminal value | B79: =B50/(SUM(B48:K48)+B50) -> 0.33172432
A81: Base value per share at other discount rates
A82: Discount rate | B82: 0.05 | C82: 0.06 | D82: 0.07 | E82: 0.08 | F82: 0.09 | G82: 0.1 | H82: 0.11 | I82: 0.12 | J82: 0.13 | K82: 0.14
A83: Base value per share | B83: =IF(B82>$L39,(SUMPRODUCT($B46:$K46/(1+B82)^$B$16:$K$16)+$L46/(B82-$L39)/(1+B82)^$K$16+$B$7+$B$8)/$B$6,"n/a") -> 291.76959 | C83: =IF(C82>$L39,(SUMPRODUCT($B46:$K46/(1+C82)^$B$16:$K$16)+$L46/(C82-$L39)/(1+C82)^$K$16+$B$7+$B$8)/$B$6,"n/a") -> 223.94659 | D83: =IF(D82>$L39,(SUMPRODUCT($B46:$K46/(1+D82)^$B$16:$K$16)+$L46/(D82-$L39)/(1+D82)^$K$16+$B$7+$B$8)/$B$6,"n/a") -> 185.78141 | E83: =IF(E82>$L39,(SUMPRODUCT($B46:$K46/(1+E82)^$B$16:$K$16)+$L46/(E82-$L39)/(1+E82)^$K$16+$B$7+$B$8)/$B$6,"n/a") -> 161.12638 | F83: =IF(F82>$L39,(SUMPRODUCT($B46:$K46/(1+F82)^$B$16:$K$16)+$L46/(F82-$L39)/(1+F82)^$K$16+$B$7+$B$8)/$B$6,"n/a") -> 143.76872 | G83: =IF(G82>$L39,(SUMPRODUCT($B46:$K46/(1+G82)^$B$16:$K$16)+$L46/(G82-$L39)/(1+G82)^$K$16+$B$7+$B$8)/$B$6,"n/a") -> 130.80747 | H83: =IF(H82>$L39,(SUMPRODUCT($B46:$K46/(1+H82)^$B$16:$K$16)+$L46/(H82-$L39)/(1+H82)^$K$16+$B$7+$B$8)/$B$6,"n/a") -> 120.7055 | I83: =IF(I82>$L39,(SUMPRODUCT($B46:$K46/(1+I82)^$B$16:$K$16)+$L46/(I82-$L39)/(1+I82)^$K$16+$B$7+$B$8)/$B$6,"n/a") -> 112.57179 | ... K83: =IF(K82>$L39,(SUMPRODUCT($B46:$K46/(1+K82)^$B$16:$K$16)+$L46/(K82-$L39)/(1+K82)^$K$16+$B$7+$B$8)/$B$6,"n/a") -> 100.19078
A84: vs share price | B84: =IFERROR(B83/$B$4-1,"n/a") -> 0.70058627 | C84: =IFERROR(C83/$B$4-1,"n/a") -> 0.30527827 | D84: =IFERROR(D83/$B$4-1,"n/a") -> 0.082831573 | E84: =IFERROR(E83/$B$4-1,"n/a") -> -0.06087089 | F84: =IFERROR(F83/$B$4-1,"n/a") -> -0.16204043 | G84: =IFERROR(G83/$B$4-1,"n/a") -> -0.2375854 | H84: =IFERROR(H83/$B$4-1,"n/a") -> -0.29646503 | I84: =IFERROR(I83/$B$4-1,"n/a") -> -0.34387254 | ... K84: =IFERROR(K83/$B$4-1,"n/a") -> -0.41603553
A86: Implied annual return at today's price, base case | B86: =IFERROR(IF(MATCH($B$4,$B$83:$K$83,-1)=10,"above 14%",INDEX($B$82:$K$82,MATCH($B$4,$B$83:$K$83,-1))+(INDEX($B$83:$K$83,MATCH($B$4,$B$83:$K$83,-1))-$B$4)/(INDEX($B$83:$K$83,MATCH($B$4,$B$83:$K$83,-1))-INDEX($B$83:$K$83,MATCH($B$4,$B$83:$K$83,-1)+1))*(INDEX($B$82:$K$82,MATCH($B$4,$B$83:$K$83,-1)+1)-INDEX($B$82:$K$82,MATCH($B$4,$B$83:$K$83,-1)))),"below 5%") -> 0.075764103 | C86: Discount rate at which base value equals the price (interpolated from the row above)

Sheet WACC
A1: Discount rates: calculated (CAPM) versus assumed
A2: Blue = input, black = formula, green = link. The yellow switches set the rate used on the model sheet.
A5: Rate used in valuations (1 = Calculated, 2 = Assumed) | B5: 2 | C5: Switch. 2 reproduces the doc's figures
A6: Beta used (1 = Raw 5-year, 2 = Blume adjusted) | B6: 2 | C6: Blume adjusted = 0.67 x raw + 0.33
A7: Risk-free rate (10-year Treasury) | B7: 0.0503 | C7: 10-year Treasury yield at the close on 2026-10-28; assumed rates below move with it
A8: Equity risk premium | B8: 0.05 | C8: Analyst assumption
A9: Credit spread over risk-free (pre-tax cost of debt) | B9: 0.012 | C9: Analyst assumption: investment-grade spread
A12: Item | B12: FSLR | C12: Source / note
A13: Raw beta (5-year) | B13: 1.79 | C13: Stock Analysis statistics, Oct 23, 2026
A14: Beta override (blank = none) | C14: Cheniere's 0.06 raw beta reflects its own history, not its risk; 0.80 used instead
A15: Adjusted beta | B15: =0.67*IF(ISNUMBER(B14),B14,B13)+0.33 -> 1.5293 | C15: Blume: 0.67 x raw (or override) + 0.33
A16: Beta used | B16: =IF($B$6=1,IF(ISNUMBER(B14),B14,B13),B15) -> 1.5293 | C16: Per switch in B6
A17: Cost of equity | B17: =$B$7+B16*$B$8 -> 0.126765 | C17: Risk-free + beta x ERP
A18: Pre-tax cost of debt | B18: =$B$7+$B$9 -> 0.0623 | C18: Risk-free + spread
A19: Tax rate | B19: =FSLR!B9 -> 0.12 | C19: Linked from company sheet
A20: After-tax cost of debt | B20: =B18*(1-B19) -> 0.054824
A21: Market value of equity ($B) | B21: =FSLR!B4*FSLR!B6 -> 18.438628 | C21: Price x shares
A22: Debt ($B) | B22: 0.194 | C22: Stock Analysis, total debt
A23: Equity weight | B23: =B21/(B21+B22) -> 0.98958816
A24: Debt weight | B24: =B22/(B21+B22) -> 0.010411843
A25: Calculated WACC (CAPM) | B25: =B23*B17+B24*B20 -> 0.12601596 | C25: Weighted cost of capital
A26: Assumed WACC | B26: 0.1022 | C26: Analyst assumption used in the doc
A27: WACC used | B27: =IF($B$5=1,B25,B26) -> 0.1022 | C27: Per switch in B5; feeds each sheet's B10
A28: Check: WACC above every terminal growth rate | B28: =IF(B27>MAX(FSLR!L21,FSLR!L39,FSLR!L57),"OK","WACC must exceed growth") -> OK
A29: Link row read by company sheets | B29: =B27 -> 0.1022 | C29: Same as WACC used
