Workbook

Sheet Summary
A1: Cheniere Energy (LNG): valuation summary
A2: Values link to the model sheet (green). Switch the discount rate on the WACC tab.
A4: Company | B4: Method | C4: Share price | D4: Discount rate | E4: Bear value | F4: Base value | G4: Bull value | H4: Base vs price | I4: Implied return at price (base case) | J4: Base value (rounded)
A5: Cheniere Energy (LNG) | B5: 10-year DCF | C5: =LNG!B4 -> 297.77 | D5: =LNG!B10 -> 0.0722 | E5: =LNG!B75 -> 181.63291 | F5: =LNG!B76 -> 379.86623 | G5: =LNG!B77 -> 532.47953 | H5: =F5/C5-1 -> 0.27570349 | I5: =LNG!B86 -> 0.08192629 | J5: =IF(F5<10,ROUND(F5*4,0)/4,IF(F5<100,ROUND(F5,0),ROUND(F5/5,0)*5)) -> 380
A8: Exit plan on the positions page
A9: Base value (rounded) | C9: 380
A10: Trim above (bull value, rounded) | C10: 530
A11: Exit below (halfway, bear to base) | C11: 280
A12: Thesis-break signal | C12: Sell on a cut to cash flow guidance, or if new long-term contracting stalls as the 2027 to 2028 LNG supply wave arrives.

Sheet LNG
A1: Cheniere Energy (LNG): 10-year scenario DCF
A2: Units: $ billions unless noted. Blue = input, black = formula, green = link, yellow = key lever. Years 6 to 10 fade growth, margin and reinvestment toward each scenario's terminal levels.
A4: Share price ($) | B4: 297.77 | C4: Oct 28, 2026 close (before Q3 results)
A5: Price date | B5: Oct 28, 2026 close (before Q3 results) | C5: Text
A6: Shares outstanding (billions) | B6: 0.2051 | C6: Stock Analysis statistics, Oct 23, 2026
A7: Net cash, negative = net debt | B7: -22.27 | C7: Stock Analysis statistics, Oct 23, 2026: cash less total debt
A8: Other non-operating assets, less outside claims | B8: -15.82 | C8: Less public share of CQP: about 51.4% of CQP market cap $30.77B (Stock Analysis, Oct 16, 2026)
A9: Tax rate | B9: 0.18 | C9: Analyst assumption (normalized, near the reported effective rate)
A10: Discount rate (WACC), from WACC tab | B10: =WACC!B29 -> 0.0722 | C10: Calculated or assumed, per the switch in WACC!B5
A11: Working capital, % of revenue change | B11: 0 | C11: Analyst assumption
A12: Base-year revenue (2026E) | B12: 24.3 | C12: 2026E revenue about $24.3B: $17.77B for nine months plus about $6.5B in Q4 (Q3 2026 release, Oct 29). 2026 EBITDA guidance raised to $8.75B to $9.25B. Margin is the lever
A13: Selected scenario (1 Bear, 2 Base, 3 Bull) | B13: 2 | C13: Lever
A15: Year | B15: 2027 | C15: 2028 | D15: 2029 | E15: 2030 | F15: 2031 | G15: 2032 | H15: 2033 | I15: 2034 | J15: 2035 | K15: 2036 | L15: Terminal
A16: Discount period (years, mid-year) | B16: 0.5 | C16: =B16+1 -> 1.5 | D16: =C16+1 -> 2.5 | E16: =D16+1 -> 3.5 | F16: =E16+1 -> 4.5 | G16: =F16+1 -> 5.5 | H16: =G16+1 -> 6.5 | I16: =H16+1 -> 7.5 | J16: =I16+1 -> 8.5 | K16: =J16+1 -> 9.5
A17: Fade step (years 6 to 10) | B17: 0 | C17: 0 | D17: 0 | E17: 0 | F17: 0 | G17: 1 | H17: 2 | I17: 3 | J17: 4 | K17: 5
A19: Bear: LNG glut from 2027, weaker spot margins
A20: Revenue | B20: 22.5 | C20: 21.5 | D20: 22 | E20: 23 | F20: 24 | G20: =F20*(1+$F21+($L21-$F21)*G$17/5) -> 24.858783 | H20: =G20*(1+$F21+($L21-$F21)*H$17/5) -> 25.55699 | I20: =H20*(1+$F21+($L21-$F21)*I$17/5) -> 26.078131 | J20: =I20*(1+$F21+($L21-$F21)*J$17/5) -> 26.409209 | K20: =J20*(1+$F21+($L21-$F21)*K$17/5) -> 26.541255 | L20: =K20*(1+L21) -> 26.673962
A21: Revenue growth (terminal column = terminal growth, input) | B21: =B20/$B$12-1 -> -0.074074074 | C21: =C20/B20-1 -> -0.044444444 | D21: =D20/C20-1 -> 0.023255814 | E21: =E20/D20-1 -> 0.045454545 | F21: =F20/E20-1 -> 0.043478261 | G21: =G20/F20-1 -> 0.035782609 | H21: =H20/G20-1 -> 0.028086957 | I21: =I20/H20-1 -> 0.020391304 | J21: =J20/I20-1 -> 0.012695652 | K21: =K20/J20-1 -> 0.005 | L21: 0.005
A22: Operating margin | B22: 0.29 | C22: 0.28 | D22: 0.28 | E22: 0.28 | F22: 0.28 | G22: =$F22+($L22-$F22)*G$17/5 -> 0.278 | H22: =$F22+($L22-$F22)*H$17/5 -> 0.276 | I22: =$F22+($L22-$F22)*I$17/5 -> 0.274 | J22: =$F22+($L22-$F22)*J$17/5 -> 0.272 | K22: =$F22+($L22-$F22)*K$17/5 -> 0.27 | L22: 0.27
A23: Operating income | B23: =B20*B22 -> 6.525 | C23: =C20*C22 -> 6.02 | D23: =D20*D22 -> 6.16 | E23: =E20*E22 -> 6.44 | F23: =F20*F22 -> 6.72 | G23: =G20*G22 -> 6.9107416 | H23: =H20*H22 -> 7.0537293 | I23: =I20*I22 -> 7.1454078 | ... L23: =L20*L22 -> 7.2019697
A24: NOPAT | B24: =B23*(1-$B$9) -> 5.3505 | C24: =C23*(1-$B$9) -> 4.9364 | D24: =D23*(1-$B$9) -> 5.0512 | E24: =E23*(1-$B$9) -> 5.2808 | F24: =F23*(1-$B$9) -> 5.5104 | G24: =G23*(1-$B$9) -> 5.6668081 | H24: =H23*(1-$B$9) -> 5.784058 | I24: =I23*(1-$B$9) -> 5.8592344 | ... L24: =L23*(1-$B$9) -> 5.9056151
A25: Net reinvestment, % of revenue | B25: 0.08 | C25: 0.07 | D25: 0.05 | E25: 0.03 | F25: 0.02 | G25: =$F25+($L25-$F25)*G$17/5 -> 0.019 | H25: =$F25+($L25-$F25)*H$17/5 -> 0.018 | I25: =$F25+($L25-$F25)*I$17/5 -> 0.017 | J25: =$F25+($L25-$F25)*J$17/5 -> 0.016 | K25: =$F25+($L25-$F25)*K$17/5 -> 0.015 | L25: 0.015
A26: Net reinvestment | B26: =B20*B25 -> 1.8 | C26: =C20*C25 -> 1.505 | D26: =D20*D25 -> 1.1 | E26: =E20*E25 -> 0.69 | F26: =F20*F25 -> 0.48 | G26: =G20*G25 -> 0.47231687 | H26: =H20*H25 -> 0.46002582 | I26: =I20*I25 -> 0.44332822 | ... L26: =L20*L25 -> 0.40010943
A27: Change in working capital | B27: =$B$11*(B20-$B$12) -> 0 | C27: =$B$11*(C20-B20) -> 0 | D27: =$B$11*(D20-C20) -> 0 | E27: =$B$11*(E20-D20) -> 0 | F27: =$B$11*(F20-E20) -> 0 | G27: =$B$11*(G20-F20) -> 0 | H27: =$B$11*(H20-G20) -> 0 | I27: =$B$11*(I20-H20) -> 0 | J27: =$B$11*(J20-I20) -> 0 | ... L27: =$B$11*(L20-K20) -> 0
A28: Free cash flow | B28: =B24-B26-B27 -> 3.5505 | C28: =C24-C26-C27 -> 3.4314 | D28: =D24-D26-D27 -> 3.9512 | E28: =E24-E26-E27 -> 4.5908 | F28: =F24-F26-F27 -> 5.0304 | G28: =G24-G26-G27 -> 5.1944912 | H28: =H24-H26-H27 -> 5.3240322 | I28: =I24-I26-I27 -> 5.4159061 | ... L28: =L24-L26-L27 -> 5.5055057
A29: Discount factor | B29: =1/(1+$B$10)^B$16 -> 0.96574418 | C29: =1/(1+$B$10)^C$16 -> 0.90071272 | D29: =1/(1+$B$10)^D$16 -> 0.84006036 | E29: =1/(1+$B$10)^E$16 -> 0.78349222 | F29: =1/(1+$B$10)^F$16 -> 0.73073328 | G29: =1/(1+$B$10)^G$16 -> 0.68152703 | H29: =1/(1+$B$10)^H$16 -> 0.63563424 | I29: =1/(1+$B$10)^I$16 -> 0.59283178 | ... K29: =1/(1+$B$10)^K$16 -> 0.51567951
A30: PV of free cash flow | B30: =B28*B29 -> 3.4288747 | C30: =C28*C29 -> 3.0907056 | D30: =D28*D29 -> 3.3192465 | E30: =E28*E29 -> 3.5968561 | F30: =F28*F29 -> 3.6758807 | G30: =G28*G29 -> 3.5401862 | H30: =H28*H29 -> 3.3841371 | I30: =I28*I29 -> 3.2107213 | ... K30: =K28*K29 -> 2.8249517
A31: Terminal value | B31: =L28/($B$10-L21) -> 81.927168 | C31: =IF($B$10>L21,"","Discount rate must exceed terminal growth")
A32: PV of terminal value | B32: =B31/(1+$B$10)^$K$16 -> 42.248162
A33: Equity value (PV FCF + PV TV + net cash + other) | B33: =SUM(B30:K30)+B32+$B$7+$B$8 -> 37.252911
A34: Value per share ($) | B34: =B33/$B$6 -> 181.63291
A35: Value vs share price | B35: =B34/$B$4-1 -> -0.39002279
A37: Base: 2027 near 2026 as spot margins normalize, trains 8 and 9 in 2028
A38: Revenue | B38: 24.6 | C38: 25.8 | D38: 27.2 | E38: 28.6 | F38: 30 | G38: =F38*(1+$F39+($L39-$F39)*G$17/5) -> 31.264825 | H38: =G38*(1+$F39+($L39-$F39)*H$17/5) -> 32.370682 | I38: =H38*(1+$F39+($L39-$F39)*I$17/5) -> 33.295849 | J38: =I38*(1+$F39+($L39-$F39)*J$17/5) -> 34.021373 | K38: =J38*(1+$F39+($L39-$F39)*K$17/5) -> 34.531694 | L38: =K38*(1+L39) -> 35.049669
A39: Revenue growth (terminal column = terminal growth, input) | B39: =B38/$B$12-1 -> 0.012345679 | C39: =C38/B38-1 -> 0.048780488 | D39: =D38/C38-1 -> 0.054263566 | E39: =E38/D38-1 -> 0.051470588 | F39: =F38/E38-1 -> 0.048951049 | G39: =G38/F38-1 -> 0.042160839 | H39: =H38/G38-1 -> 0.035370629 | I39: =I38/H38-1 -> 0.02858042 | J39: =J38/I38-1 -> 0.02179021 | K39: =K38/J38-1 -> 0.015 | L39: 0.015
A40: Operating margin | B40: 0.31 | C40: 0.31 | D40: 0.31 | E40: 0.31 | F40: 0.31 | G40: =$F40+($L40-$F40)*G$17/5 -> 0.306 | H40: =$F40+($L40-$F40)*H$17/5 -> 0.302 | I40: =$F40+($L40-$F40)*I$17/5 -> 0.298 | J40: =$F40+($L40-$F40)*J$17/5 -> 0.294 | K40: =$F40+($L40-$F40)*K$17/5 -> 0.29 | L40: 0.29
A41: Operating income | B41: =B38*B40 -> 7.626 | C41: =C38*C40 -> 7.998 | D41: =D38*D40 -> 8.432 | E41: =E38*E40 -> 8.866 | F41: =F38*F40 -> 9.3 | G41: =G38*G40 -> 9.5670365 | H41: =H38*H40 -> 9.7759459 | I41: =I38*I40 -> 9.9221631 | ... L41: =L38*L40 -> 10.164404
A42: NOPAT | B42: =B41*(1-$B$9) -> 6.25332 | C42: =C41*(1-$B$9) -> 6.55836 | D42: =D41*(1-$B$9) -> 6.91424 | E42: =E41*(1-$B$9) -> 7.27012 | F42: =F41*(1-$B$9) -> 7.626 | G42: =G41*(1-$B$9) -> 7.8449699 | H42: =H41*(1-$B$9) -> 8.0162756 | I42: =I41*(1-$B$9) -> 8.1361738 | ... L42: =L41*(1-$B$9) -> 8.3348113
A43: Net reinvestment, % of revenue | B43: 0.08 | C43: 0.07 | D43: 0.05 | E43: 0.03 | F43: 0.02 | G43: =$F43+($L43-$F43)*G$17/5 -> 0.019 | H43: =$F43+($L43-$F43)*H$17/5 -> 0.018 | I43: =$F43+($L43-$F43)*I$17/5 -> 0.017 | J43: =$F43+($L43-$F43)*J$17/5 -> 0.016 | K43: =$F43+($L43-$F43)*K$17/5 -> 0.015 | L43: 0.015
A44: Net reinvestment | B44: =B38*B43 -> 1.968 | C44: =C38*C43 -> 1.806 | D44: =D38*D43 -> 1.36 | E44: =E38*E43 -> 0.858 | F44: =F38*F43 -> 0.6 | G44: =G38*G43 -> 0.59403168 | H44: =H38*H43 -> 0.58267227 | I44: =I38*I43 -> 0.56602944 | ... L44: =L38*L43 -> 0.52574503
A45: Change in working capital | B45: =$B$11*(B38-$B$12) -> 0 | C45: =$B$11*(C38-B38) -> 0 | D45: =$B$11*(D38-C38) -> 0 | E45: =$B$11*(E38-D38) -> 0 | F45: =$B$11*(F38-E38) -> 0 | G45: =$B$11*(G38-F38) -> 0 | H45: =$B$11*(H38-G38) -> 0 | I45: =$B$11*(I38-H38) -> 0 | J45: =$B$11*(J38-I38) -> 0 | ... L45: =$B$11*(L38-K38) -> 0
A46: Free cash flow | B46: =B42-B44-B45 -> 4.28532 | C46: =C42-C44-C45 -> 4.75236 | D46: =D42-D44-D45 -> 5.55424 | E46: =E42-E44-E45 -> 6.41212 | F46: =F42-F44-F45 -> 7.026 | G46: =G42-G44-G45 -> 7.2509383 | H46: =H42-H44-H45 -> 7.4336033 | I46: =I42-I44-I45 -> 7.5701443 | ... L46: =L42-L44-L45 -> 7.8090662
A47: Discount factor | B47: =1/(1+$B$10)^B$16 -> 0.96574418 | C47: =1/(1+$B$10)^C$16 -> 0.90071272 | D47: =1/(1+$B$10)^D$16 -> 0.84006036 | E47: =1/(1+$B$10)^E$16 -> 0.78349222 | F47: =1/(1+$B$10)^F$16 -> 0.73073328 | G47: =1/(1+$B$10)^G$16 -> 0.68152703 | H47: =1/(1+$B$10)^H$16 -> 0.63563424 | I47: =1/(1+$B$10)^I$16 -> 0.59283178 | ... K47: =1/(1+$B$10)^K$16 -> 0.51567951
A48: PV of free cash flow | B48: =B46*B47 -> 4.1385228 | C48: =C46*C47 -> 4.2805111 | D48: =D46*D47 -> 4.6658969 | E48: =E46*E47 -> 5.0238462 | F48: =F46*F47 -> 5.134132 | G48: =G46*G47 -> 4.9417104 | H48: =H46*H47 -> 4.7250528 | I48: =I46*I47 -> 4.4878221 | ... K48: =K46*K47 -> 3.9674635
A49: Terminal value | B49: =L46/($B$10-L39) -> 136.52214 | C49: =IF($B$10>L39,"","Discount rate must exceed terminal growth")
A50: PV of terminal value | B50: =B49/(1+$B$10)^$K$16 -> 70.401668
A51: Equity value (PV FCF + PV TV + net cash + other) | B51: =SUM(B48:K48)+B50+$B$7+$B$8 -> 77.910563
A52: Value per share ($) | B52: =B51/$B$6 -> 379.86623
A53: Value vs share price | B53: =B52/$B$4-1 -> 0.27570349
A55: Bull: more trains sanctioned at good returns
A56: Revenue | B56: 25.8 | C56: 27.5 | D56: 29.5 | E56: 31.5 | F56: 33.5 | G56: =F56*(1+$F57+($L57-$F57)*G$17/5) -> 35.335587 | H56: =G56*(1+$F57+($L57-$F57)*H$17/5) -> 36.96439 | I56: =H56*(1+$F57+($L57-$F57)*I$17/5) -> 38.34674 | J56: =I56*(1+$F57+($L57-$F57)*J$17/5) -> 39.447231 | K56: =J56*(1+$F57+($L57-$F57)*K$17/5) -> 40.236176 | L56: =K56*(1+L57) -> 41.040899
A57: Revenue growth (terminal column = terminal growth, input) | B57: =B56/$B$12-1 -> 0.061728395 | C57: =C56/B56-1 -> 0.065891473 | D57: =D56/C56-1 -> 0.072727273 | E57: =E56/D56-1 -> 0.06779661 | F57: =F56/E56-1 -> 0.063492063 | G57: =G56/F56-1 -> 0.054793651 | H57: =H56/G56-1 -> 0.046095238 | I57: =I56/H56-1 -> 0.037396825 | J57: =J56/I56-1 -> 0.028698413 | K57: =K56/J56-1 -> 0.02 | L57: 0.02
A58: Operating margin | B58: 0.32 | C58: 0.32 | D58: 0.33 | E58: 0.33 | F58: 0.33 | G58: =$F58+($L58-$F58)*G$17/5 -> 0.326 | H58: =$F58+($L58-$F58)*H$17/5 -> 0.322 | I58: =$F58+($L58-$F58)*I$17/5 -> 0.318 | J58: =$F58+($L58-$F58)*J$17/5 -> 0.314 | K58: =$F58+($L58-$F58)*K$17/5 -> 0.31 | L58: 0.31
A59: Operating income | B59: =B56*B58 -> 8.256 | C59: =C56*C58 -> 8.8 | D59: =D56*D58 -> 9.735 | E59: =E56*E58 -> 10.395 | F59: =F56*F58 -> 11.055 | G59: =G56*G58 -> 11.519401 | H59: =H56*H58 -> 11.902533 | I59: =I56*I58 -> 12.194263 | ... L59: =L56*L58 -> 12.722679
A60: NOPAT | B60: =B59*(1-$B$9) -> 6.76992 | C60: =C59*(1-$B$9) -> 7.216 | D60: =D59*(1-$B$9) -> 7.9827 | E60: =E59*(1-$B$9) -> 8.5239 | F60: =F59*(1-$B$9) -> 9.0651 | G60: =G59*(1-$B$9) -> 9.4459092 | H60: =H59*(1-$B$9) -> 9.7600774 | I60: =I59*(1-$B$9) -> 9.999296 | ... L60: =L59*(1-$B$9) -> 10.432597
A61: Net reinvestment, % of revenue | B61: 0.09 | C61: 0.08 | D61: 0.06 | E61: 0.04 | F61: 0.03 | G61: =$F61+($L61-$F61)*G$17/5 -> 0.028 | H61: =$F61+($L61-$F61)*H$17/5 -> 0.026 | I61: =$F61+($L61-$F61)*I$17/5 -> 0.024 | J61: =$F61+($L61-$F61)*J$17/5 -> 0.022 | K61: =$F61+($L61-$F61)*K$17/5 -> 0.02 | L61: 0.02
A62: Net reinvestment | B62: =B56*B61 -> 2.322 | C62: =C56*C61 -> 2.2 | D62: =D56*D61 -> 1.77 | E62: =E56*E61 -> 1.26 | F62: =F56*F61 -> 1.005 | G62: =G56*G61 -> 0.98939644 | H62: =H56*H61 -> 0.96107413 | I62: =I56*I61 -> 0.92032177 | ... L62: =L56*L61 -> 0.82081798
A63: Change in working capital | B63: =$B$11*(B56-$B$12) -> 0 | C63: =$B$11*(C56-B56) -> 0 | D63: =$B$11*(D56-C56) -> 0 | E63: =$B$11*(E56-D56) -> 0 | F63: =$B$11*(F56-E56) -> 0 | G63: =$B$11*(G56-F56) -> 0 | H63: =$B$11*(H56-G56) -> 0 | I63: =$B$11*(I56-H56) -> 0 | J63: =$B$11*(J56-I56) -> 0 | ... L63: =$B$11*(L56-K56) -> 0
A64: Free cash flow | B64: =B60-B62-B63 -> 4.44792 | C64: =C60-C62-C63 -> 5.016 | D64: =D60-D62-D63 -> 6.2127 | E64: =E60-E62-E63 -> 7.2639 | F64: =F60-F62-F63 -> 8.0601 | G64: =G60-G62-G63 -> 8.4565128 | H64: =H60-H62-H63 -> 8.7990033 | I64: =I60-I62-I63 -> 9.0789743 | ... L64: =L60-L62-L63 -> 9.6117786
A65: Discount factor | B65: =1/(1+$B$10)^B$16 -> 0.96574418 | C65: =1/(1+$B$10)^C$16 -> 0.90071272 | D65: =1/(1+$B$10)^D$16 -> 0.84006036 | E65: =1/(1+$B$10)^E$16 -> 0.78349222 | F65: =1/(1+$B$10)^F$16 -> 0.73073328 | G65: =1/(1+$B$10)^G$16 -> 0.68152703 | H65: =1/(1+$B$10)^H$16 -> 0.63563424 | I65: =1/(1+$B$10)^I$16 -> 0.59283178 | ... K65: =1/(1+$B$10)^K$16 -> 0.51567951
A66: PV of free cash flow | B66: =B64*B65 -> 4.2955528 | C66: =C64*C65 -> 4.517975 | D66: =D64*D65 -> 5.219043 | E66: =E64*E65 -> 5.6912092 | F66: =F64*F65 -> 5.8897833 | G66: =G64*G65 -> 5.763342 | H66: =H64*H65 -> 5.5929477 | I66: =I64*I65 -> 5.3823045 | ... K66: =K64*K65 -> 4.8594091
A67: Terminal value | B67: =L64/($B$10-L57) -> 184.13369 | C67: =IF($B$10>L57,"","Discount rate must exceed terminal growth")
A68: PV of terminal value | B68: =B67/(1+$B$10)^$K$16 -> 94.95397
A69: Equity value (PV FCF + PV TV + net cash + other) | B69: =SUM(B66:K66)+B68+$B$7+$B$8 -> 109.21155
A70: Value per share ($) | B70: =B69/$B$6 -> 532.47953
A71: Value vs share price | B71: =B70/$B$4-1 -> 0.78822422
A74: Outputs | C74: vs price
A75: Bear value per share | B75: =B34 -> 181.63291 | C75: =B75/$B$4-1 -> -0.39002279
A76: Base value per share | B76: =B52 -> 379.86623 | C76: =B76/$B$4-1 -> 0.27570349
A77: Bull value per share | B77: =B70 -> 532.47953 | C77: =B77/$B$4-1 -> 0.78822422
A78: Selected scenario value per share | B78: =INDEX(B34:B70,1+($B$13-1)*18) -> 379.86623 | C78: =B78/$B$4-1 -> 0.27570349
A79: Share of base value from terminal value | B79: =B50/(SUM(B48:K48)+B50) -> 0.60690799
A81: Base value per share at other discount rates
A82: Discount rate | B82: 0.05 | C82: 0.06 | D82: 0.07 | E82: 0.08 | F82: 0.09 | G82: 0.1 | H82: 0.11 | I82: 0.12 | J82: 0.13 | K82: 0.14
A83: Base value per share | B83: =IF(B82>$L39,(SUMPRODUCT($B46:$K46/(1+B82)^$B$16:$K$16)+$L46/(B82-$L39)/(1+B82)^$K$16+$B$7+$B$8)/$B$6,"n/a") -> 745.6584 | C83: =IF(C82>$L39,(SUMPRODUCT($B46:$K46/(1+C82)^$B$16:$K$16)+$L46/(C82-$L39)/(1+C82)^$K$16+$B$7+$B$8)/$B$6,"n/a") -> 536.13202 | D83: =IF(D82>$L39,(SUMPRODUCT($B46:$K46/(1+D82)^$B$16:$K$16)+$L46/(D82-$L39)/(1+D82)^$K$16+$B$7+$B$8)/$B$6,"n/a") -> 402.90977 | E83: =IF(E82>$L39,(SUMPRODUCT($B46:$K46/(1+E82)^$B$16:$K$16)+$L46/(E82-$L39)/(1+E82)^$K$16+$B$7+$B$8)/$B$6,"n/a") -> 310.77088 | F83: =IF(F82>$L39,(SUMPRODUCT($B46:$K46/(1+F82)^$B$16:$K$16)+$L46/(F82-$L39)/(1+F82)^$K$16+$B$7+$B$8)/$B$6,"n/a") -> 243.27906 | G83: =IF(G82>$L39,(SUMPRODUCT($B46:$K46/(1+G82)^$B$16:$K$16)+$L46/(G82-$L39)/(1+G82)^$K$16+$B$7+$B$8)/$B$6,"n/a") -> 191.73281 | H83: =IF(H82>$L39,(SUMPRODUCT($B46:$K46/(1+H82)^$B$16:$K$16)+$L46/(H82-$L39)/(1+H82)^$K$16+$B$7+$B$8)/$B$6,"n/a") -> 151.0945 | I83: =IF(I82>$L39,(SUMPRODUCT($B46:$K46/(1+I82)^$B$16:$K$16)+$L46/(I82-$L39)/(1+I82)^$K$16+$B$7+$B$8)/$B$6,"n/a") -> 118.24565 | ... K83: =IF(K82>$L39,(SUMPRODUCT($B46:$K46/(1+K82)^$B$16:$K$16)+$L46/(K82-$L39)/(1+K82)^$K$16+$B$7+$B$8)/$B$6,"n/a") -> 68.432308
A84: vs share price | B84: =IFERROR(B83/$B$4-1,"n/a") -> 1.5041421 | C84: =IFERROR(C83/$B$4-1,"n/a") -> 0.80049036 | D84: =IFERROR(D83/$B$4-1,"n/a") -> 0.35309055 | E84: =IFERROR(E83/$B$4-1,"n/a") -> 0.04366082 | F84: =IFERROR(F83/$B$4-1,"n/a") -> -0.18299676 | G84: =IFERROR(G83/$B$4-1,"n/a") -> -0.35610436 | H84: =IFERROR(H83/$B$4-1,"n/a") -> -0.49257986 | I84: =IFERROR(I83/$B$4-1,"n/a") -> -0.60289601 | ... K84: =IFERROR(K83/$B$4-1,"n/a") -> -0.77018401
A86: Implied annual return at today's price, base case | B86: =IFERROR(IF(MATCH($B$4,$B$83:$K$83,-1)=10,"above 14%",INDEX($B$82:$K$82,MATCH($B$4,$B$83:$K$83,-1))+(INDEX($B$83:$K$83,MATCH($B$4,$B$83:$K$83,-1))-$B$4)/(INDEX($B$83:$K$83,MATCH($B$4,$B$83:$K$83,-1))-INDEX($B$83:$K$83,MATCH($B$4,$B$83:$K$83,-1)+1))*(INDEX($B$82:$K$82,MATCH($B$4,$B$83:$K$83,-1)+1)-INDEX($B$82:$K$82,MATCH($B$4,$B$83:$K$83,-1)))),"below 5%") -> 0.08192629 | C86: Discount rate at which base value equals the price (interpolated from the row above)

Sheet WACC
A1: Discount rates: calculated (CAPM) versus assumed
A2: Blue = input, black = formula, green = link. The yellow switches set the rate used on the model sheet.
A5: Rate used in valuations (1 = Calculated, 2 = Assumed) | B5: 2 | C5: Switch. 2 reproduces the doc's figures
A6: Beta used (1 = Raw 5-year, 2 = Blume adjusted) | B6: 2 | C6: Blume adjusted = 0.67 x raw + 0.33
A7: Risk-free rate (10-year Treasury) | B7: 0.0503 | C7: 10-year Treasury yield at the close on 2026-10-28; assumed rates below move with it
A8: Equity risk premium | B8: 0.05 | C8: Analyst assumption
A9: Credit spread over risk-free (pre-tax cost of debt) | B9: 0.012 | C9: Analyst assumption: investment-grade spread
A12: Item | B12: LNG | C12: Source / note
A13: Raw beta (5-year) | B13: 0.06 | C13: Stock Analysis statistics, Oct 23, 2026
A14: Beta override (blank = none) | B14: 0.8 | C14: Cheniere's 0.06 raw beta reflects its own history, not its risk; 0.80 used instead
A15: Adjusted beta | B15: =0.67*IF(ISNUMBER(B14),B14,B13)+0.33 -> 0.866 | C15: Blume: 0.67 x raw (or override) + 0.33
A16: Beta used | B16: =IF($B$6=1,IF(ISNUMBER(B14),B14,B13),B15) -> 0.866 | C16: Per switch in B6
A17: Cost of equity | B17: =$B$7+B16*$B$8 -> 0.0936 | C17: Risk-free + beta x ERP
A18: Pre-tax cost of debt | B18: =$B$7+$B$9 -> 0.0623 | C18: Risk-free + spread
A19: Tax rate | B19: =LNG!B9 -> 0.18 | C19: Linked from company sheet
A20: After-tax cost of debt | B20: =B18*(1-B19) -> 0.051086
A21: Market value of equity ($B) | B21: =LNG!B4*LNG!B6 -> 61.072627 | C21: Price x shares
A22: Debt ($B) | B22: 23.93 | C22: Stock Analysis, total debt
A23: Equity weight | B23: =B21/(B21+B22) -> 0.71847929
A24: Debt weight | B24: =B22/(B21+B22) -> 0.28152071
A25: Calculated WACC (CAPM) | B25: =B23*B17+B24*B20 -> 0.081631428 | C25: Weighted cost of capital
A26: Assumed WACC | B26: 0.0722 | C26: Analyst assumption used in the doc
A27: WACC used | B27: =IF($B$5=1,B25,B26) -> 0.0722 | C27: Per switch in B5; feeds each sheet's B10
A28: Check: WACC above every terminal growth rate | B28: =IF(B27>MAX(LNG!L21,LNG!L39,LNG!L57),"OK","WACC must exceed growth") -> OK
A29: Link row read by company sheets | B29: =B27 -> 0.0722 | C29: Same as WACC used
