Workbook

Sheet Summary
A1: ServiceNow (NOW): valuation summary
A2: Values link to the model sheet (green). Switch the discount rate on the WACC tab.
A4: Company | B4: Method | C4: Share price | D4: Discount rate | E4: Bear value | F4: Base value | G4: Bull value | H4: Base vs price | I4: Implied return at price (base case) | J4: Base value (rounded)
A5: ServiceNow (NOW) | B5: 10-year DCF | C5: =NOW!B4 -> 156.84 | D5: =NOW!B10 -> 0.095 | E5: =NOW!B75 -> 58.852825 | F5: =NOW!B76 -> 103.66052 | G5: =NOW!B77 -> 151.93398 | H5: =F5/C5-1 -> -0.33906836 | I5: =NOW!B86 -> 0.077975605 | J5: =IF(F5<10,ROUND(F5*4,0)/4,IF(F5<100,ROUND(F5,0),ROUND(F5/5,0)*5)) -> 105
A8: Exit plan on the positions page
A9: Base value (rounded) | C9: 105
A10: Trim above (bull value, rounded) | C10: 150
A11: Exit below (halfway, bear to base) | C11: 81
A12: Thesis-break signal | C12: Sell if subscription revenue or current remaining performance obligations grow less than 15%.

Sheet NOW
A1: ServiceNow (NOW): 10-year scenario DCF
A2: Units: $ billions unless noted. Blue = input, black = formula, green = link, yellow = key lever. Years 6 to 10 fade growth, margin and reinvestment toward each scenario's terminal levels.
A4: Share price ($) | B4: 156.84 | C4: Oct 23, 2026 intraday (Yahoo Finance via the site's price feed)
A5: Price date | B5: Oct 23, 2026 | C5: Text
A6: Shares outstanding (billions) | B6: 1.03 | C6: Stock Analysis statistics, Oct 23, 2026
A7: Net cash, negative = net debt | B7: -1.75 | C7: Stock Analysis statistics, Oct 23, 2026: cash less total debt
A8: Other non-operating assets, less outside claims | B8: 0 | C8: Long-term investments excluded (conservative)
A9: Tax rate | B9: 0.2 | C9: Analyst assumption (normalized, near the reported effective rate)
A10: Discount rate (WACC), from WACC tab | B10: =WACC!B29 -> 0.095 | C10: Calculated or assumed, per the switch in WACC!B5
A11: Working capital, % of revenue change | B11: -0.05 | C11: Analyst assumption
A12: Base-year revenue (2026E) | B12: 16.22 | C12: 2026E consensus $16.22B (Stock Analysis). Margins are after stock pay (GAAP-like), not the 31.5% non-GAAP figure
A13: Selected scenario (1 Bear, 2 Base, 3 Bull) | B13: 2 | C13: Lever
A15: Year | B15: 2027 | C15: 2028 | D15: 2029 | E15: 2030 | F15: 2031 | G15: 2032 | H15: 2033 | I15: 2034 | J15: 2035 | K15: 2036 | L15: Terminal
A16: Discount period (years, mid-year) | B16: 0.5 | C16: =B16+1 -> 1.5 | D16: =C16+1 -> 2.5 | E16: =D16+1 -> 3.5 | F16: =E16+1 -> 4.5 | G16: =F16+1 -> 5.5 | H16: =G16+1 -> 6.5 | I16: =H16+1 -> 7.5 | J16: =I16+1 -> 8.5 | K16: =J16+1 -> 9.5
A17: Fade step (years 6 to 10) | B17: 0 | C17: 0 | D17: 0 | E17: 0 | F17: 0 | G17: 1 | H17: 2 | I17: 3 | J17: 4 | K17: 5
A19: Bear: AI agents compress seat pricing
A20: Revenue | B20: 18.3 | C20: 20.3 | D20: 22.2 | E20: 24 | F20: 25.7 | G20: =F20*(1+$F21+($L21-$F21)*G$17/5) -> 27.336233 | H20: =G20*(1+$F21+($L21-$F21)*H$17/5) -> 28.880731 | I20: =H20*(1+$F21+($L21-$F21)*I$17/5) -> 30.305513 | J20: =I20*(1+$F21+($L21-$F21)*J$17/5) -> 31.583396 | K20: =J20*(1+$F21+($L21-$F21)*K$17/5) -> 32.688815 | L20: =K20*(1+L21) -> 33.832923
A21: Revenue growth (terminal column = terminal growth, input) | B21: =B20/$B$12-1 -> 0.12823674 | C21: =C20/B20-1 -> 0.10928962 | D21: =D20/C20-1 -> 0.093596059 | E21: =E20/D20-1 -> 0.081081081 | F21: =F20/E20-1 -> 0.070833333 | G21: =G20/F20-1 -> 0.063666667 | H21: =H20/G20-1 -> 0.0565 | I21: =I20/H20-1 -> 0.049333333 | J21: =J20/I20-1 -> 0.042166667 | K21: =K20/J20-1 -> 0.035 | L21: 0.035
A22: Operating margin | B22: 0.17 | C22: 0.18 | D22: 0.19 | E22: 0.2 | F22: 0.21 | G22: =$F22+($L22-$F22)*G$17/5 -> 0.214 | H22: =$F22+($L22-$F22)*H$17/5 -> 0.218 | I22: =$F22+($L22-$F22)*I$17/5 -> 0.222 | J22: =$F22+($L22-$F22)*J$17/5 -> 0.226 | K22: =$F22+($L22-$F22)*K$17/5 -> 0.23 | L22: 0.23
A23: Operating income | B23: =B20*B22 -> 3.111 | C23: =C20*C22 -> 3.654 | D23: =D20*D22 -> 4.218 | E23: =E20*E22 -> 4.8 | F23: =F20*F22 -> 5.397 | G23: =G20*G22 -> 5.8499539 | H23: =H20*H22 -> 6.2959993 | I23: =I20*I22 -> 6.7278239 | ... L23: =L20*L22 -> 7.7815723
A24: NOPAT | B24: =B23*(1-$B$9) -> 2.4888 | C24: =C23*(1-$B$9) -> 2.9232 | D24: =D23*(1-$B$9) -> 3.3744 | E24: =E23*(1-$B$9) -> 3.84 | F24: =F23*(1-$B$9) -> 4.3176 | G24: =G23*(1-$B$9) -> 4.6799631 | H24: =H23*(1-$B$9) -> 5.0367994 | I24: =I23*(1-$B$9) -> 5.3822591 | ... L24: =L23*(1-$B$9) -> 6.2252578
A25: Net reinvestment, % of revenue | B25: 0.03 | C25: 0.03 | D25: 0.03 | E25: 0.03 | F25: 0.03 | G25: =$F25+($L25-$F25)*G$17/5 -> 0.028 | H25: =$F25+($L25-$F25)*H$17/5 -> 0.026 | I25: =$F25+($L25-$F25)*I$17/5 -> 0.024 | J25: =$F25+($L25-$F25)*J$17/5 -> 0.022 | K25: =$F25+($L25-$F25)*K$17/5 -> 0.02 | L25: 0.02
A26: Net reinvestment | B26: =B20*B25 -> 0.549 | C26: =C20*C25 -> 0.609 | D26: =D20*D25 -> 0.666 | E26: =E20*E25 -> 0.72 | F26: =F20*F25 -> 0.771 | G26: =G20*G25 -> 0.76541453 | H26: =H20*H25 -> 0.75089899 | I26: =I20*I25 -> 0.72733232 | ... L26: =L20*L25 -> 0.67665846
A27: Change in working capital | B27: =$B$11*(B20-$B$12) -> -0.104 | C27: =$B$11*(C20-B20) -> -0.1 | D27: =$B$11*(D20-C20) -> -0.095 | E27: =$B$11*(E20-D20) -> -0.09 | F27: =$B$11*(F20-E20) -> -0.085 | G27: =$B$11*(G20-F20) -> -0.081811667 | H27: =$B$11*(H20-G20) -> -0.077224859 | I27: =$B$11*(I20-H20) -> -0.071239135 | J27: =$B$11*(J20-I20) -> -0.063894124 | ... L27: =$B$11*(L20-K20) -> -0.057205425
A28: Free cash flow | B28: =B24-B26-B27 -> 2.0438 | C28: =C24-C26-C27 -> 2.4142 | D28: =D24-D26-D27 -> 2.8034 | E28: =E24-E26-E27 -> 3.21 | F28: =F24-F26-F27 -> 3.6316 | G28: =G24-G26-G27 -> 3.9963603 | H28: =H24-H26-H27 -> 4.3631253 | I28: =I24-I26-I27 -> 4.726166 | ... L28: =L24-L26-L27 -> 5.6058048
A29: Discount factor | B29: =1/(1+$B$10)^B$16 -> 0.95563697 | C29: =1/(1+$B$10)^C$16 -> 0.87272782 | D29: =1/(1+$B$10)^D$16 -> 0.79701171 | E29: =1/(1+$B$10)^E$16 -> 0.72786458 | F29: =1/(1+$B$10)^F$16 -> 0.66471651 | G29: =1/(1+$B$10)^G$16 -> 0.60704704 | H29: =1/(1+$B$10)^H$16 -> 0.55438086 | I29: =1/(1+$B$10)^I$16 -> 0.50628389 | ... K29: =1/(1+$B$10)^K$16 -> 0.42224631
A30: PV of free cash flow | B30: =B28*B29 -> 1.9531308 | C30: =C28*C29 -> 2.1069395 | D30: =D28*D29 -> 2.2343426 | E30: =E28*E29 -> 2.3364453 | F30: =F28*F29 -> 2.4139845 | G30: =G28*G29 -> 2.4259787 | H30: =H28*H29 -> 2.4188331 | I30: =I28*I29 -> 2.3927817 | ... K30: =K28*K29 -> 2.2869859
A31: Terminal value | B31: =L28/($B$10-L21) -> 93.43008 | C31: =IF($B$10>L21,"","Discount rate must exceed terminal growth")
A32: PV of terminal value | B32: =B31/(1+$B$10)^$K$16 -> 39.450507
A33: Equity value (PV FCF + PV TV + net cash + other) | B33: =SUM(B30:K30)+B32+$B$7+$B$8 -> 60.61841
A34: Value per share ($) | B34: =B33/$B$6 -> 58.852825
A35: Value vs share price | B35: =B34/$B$4-1 -> -0.62475883
A37: Base: growth slows from 19% to 11%
A38: Revenue | B38: 19.2 | C38: 22.4 | D38: 25.8 | E38: 29.2 | F38: 32.6 | G38: =F38*(1+$F39+($L39-$F39)*G$17/5) -> 35.897512 | H38: =G38*(1+$F39+($L39-$F39)*H$17/5) -> 38.979781 | I38: =H38*(1+$F39+($L39-$F39)*I$17/5) -> 41.730792 | J38: =I38*(1+$F39+($L39-$F39)*J$17/5) -> 44.037991 | K38: =J38*(1+$F39+($L39-$F39)*K$17/5) -> 45.79951 | L38: =K38*(1+L39) -> 47.631491
A39: Revenue growth (terminal column = terminal growth, input) | B39: =B38/$B$12-1 -> 0.1837238 | C39: =C38/B38-1 -> 0.16666667 | D39: =D38/C38-1 -> 0.15178571 | E39: =E38/D38-1 -> 0.13178295 | F39: =F38/E38-1 -> 0.11643836 | G39: =G38/F38-1 -> 0.10115068 | H39: =H38/G38-1 -> 0.085863014 | I39: =I38/H38-1 -> 0.070575342 | J39: =J38/I38-1 -> 0.055287671 | K39: =K38/J38-1 -> 0.04 | L39: 0.04
A40: Operating margin | B40: 0.19 | C40: 0.21 | D40: 0.23 | E40: 0.245 | F40: 0.26 | G40: =$F40+($L40-$F40)*G$17/5 -> 0.262 | H40: =$F40+($L40-$F40)*H$17/5 -> 0.264 | I40: =$F40+($L40-$F40)*I$17/5 -> 0.266 | J40: =$F40+($L40-$F40)*J$17/5 -> 0.268 | K40: =$F40+($L40-$F40)*K$17/5 -> 0.27 | L40: 0.27
A41: Operating income | B41: =B38*B40 -> 3.648 | C41: =C38*C40 -> 4.704 | D41: =D38*D40 -> 5.934 | E41: =E38*E40 -> 7.154 | F41: =F38*F40 -> 8.476 | G41: =G38*G40 -> 9.4051482 | H41: =H38*H40 -> 10.290662 | I41: =I38*I40 -> 11.100391 | ... L41: =L38*L40 -> 12.860502
A42: NOPAT | B42: =B41*(1-$B$9) -> 2.9184 | C42: =C41*(1-$B$9) -> 3.7632 | D42: =D41*(1-$B$9) -> 4.7472 | E42: =E41*(1-$B$9) -> 5.7232 | F42: =F41*(1-$B$9) -> 6.7808 | G42: =G41*(1-$B$9) -> 7.5241186 | H42: =H41*(1-$B$9) -> 8.2325297 | I42: =I41*(1-$B$9) -> 8.8803126 | ... L42: =L41*(1-$B$9) -> 10.288402
A43: Net reinvestment, % of revenue | B43: 0.03 | C43: 0.03 | D43: 0.03 | E43: 0.03 | F43: 0.03 | G43: =$F43+($L43-$F43)*G$17/5 -> 0.028 | H43: =$F43+($L43-$F43)*H$17/5 -> 0.026 | I43: =$F43+($L43-$F43)*I$17/5 -> 0.024 | J43: =$F43+($L43-$F43)*J$17/5 -> 0.022 | K43: =$F43+($L43-$F43)*K$17/5 -> 0.02 | L43: 0.02
A44: Net reinvestment | B44: =B38*B43 -> 0.576 | C44: =C38*C43 -> 0.672 | D44: =D38*D43 -> 0.774 | E44: =E38*E43 -> 0.876 | F44: =F38*F43 -> 0.978 | G44: =G38*G43 -> 1.0051303 | H44: =H38*H43 -> 1.0134743 | I44: =I38*I43 -> 1.001539 | ... L44: =L38*L43 -> 0.95262981
A45: Change in working capital | B45: =$B$11*(B38-$B$12) -> -0.149 | C45: =$B$11*(C38-B38) -> -0.16 | D45: =$B$11*(D38-C38) -> -0.17 | E45: =$B$11*(E38-D38) -> -0.17 | F45: =$B$11*(F38-E38) -> -0.17 | G45: =$B$11*(G38-F38) -> -0.16487562 | H45: =$B$11*(H38-G38) -> -0.15411343 | I45: =$B$11*(I38-H38) -> -0.13755057 | J45: =$B$11*(J38-I38) -> -0.11535992 | ... L45: =$B$11*(L38-K38) -> -0.091599021
A46: Free cash flow | B46: =B42-B44-B45 -> 2.4914 | C46: =C42-C44-C45 -> 3.2512 | D46: =D42-D44-D45 -> 4.1432 | E46: =E42-E44-E45 -> 5.0172 | F46: =F42-F44-F45 -> 5.9728 | G46: =G42-G44-G45 -> 6.6838639 | H46: =H42-H44-H45 -> 7.3731689 | I46: =I42-I44-I45 -> 8.0163242 | ... L46: =L42-L44-L45 -> 9.4273712
A47: Discount factor | B47: =1/(1+$B$10)^B$16 -> 0.95563697 | C47: =1/(1+$B$10)^C$16 -> 0.87272782 | D47: =1/(1+$B$10)^D$16 -> 0.79701171 | E47: =1/(1+$B$10)^E$16 -> 0.72786458 | F47: =1/(1+$B$10)^F$16 -> 0.66471651 | G47: =1/(1+$B$10)^G$16 -> 0.60704704 | H47: =1/(1+$B$10)^H$16 -> 0.55438086 | I47: =1/(1+$B$10)^I$16 -> 0.50628389 | ... K47: =1/(1+$B$10)^K$16 -> 0.42224631
A48: PV of free cash flow | B48: =B46*B47 -> 2.3808739 | C48: =C46*C47 -> 2.8374127 | D48: =D46*D47 -> 3.3021789 | E48: =E46*E47 -> 3.6518421 | F48: =F46*F47 -> 3.9702188 | G48: =G46*G47 -> 4.0574198 | H48: =H46*H47 -> 4.0875437 | I48: =I46*I47 -> 4.0585358 | ... K48: =K46*K47 -> 3.8275699
A49: Terminal value | B49: =L46/($B$10-L39) -> 171.40675 | C49: =IF($B$10>L39,"","Discount rate must exceed terminal growth")
A50: PV of terminal value | B50: =B49/(1+$B$10)^$K$16 -> 72.375868
A51: Equity value (PV FCF + PV TV + net cash + other) | B51: =SUM(B48:K48)+B50+$B$7+$B$8 -> 106.77033
A52: Value per share ($) | B52: =B51/$B$6 -> 103.66052
A53: Value vs share price | B53: =B52/$B$4-1 -> -0.33906836
A55: Bull: AI agents expand the platform
A56: Revenue | B56: 19.6 | C56: 23.6 | D56: 28 | E56: 32.7 | F56: 37.6 | G56: =F56*(1+$F57+($L57-$F57)*G$17/5) -> 42.445801 | H56: =G56*(1+$F57+($L57-$F57)*H$17/5) -> 47.026053 | I56: =H56*(1+$F57+($L57-$F57)*I$17/5) -> 51.114443 | J56: =I56*(1+$F57+($L57-$F57)*J$17/5) -> 54.486433 | K56: =J56*(1+$F57+($L57-$F57)*K$17/5) -> 56.938323 | L56: =K56*(1+L57) -> 59.500548
A57: Revenue growth (terminal column = terminal growth, input) | B57: =B56/$B$12-1 -> 0.20838471 | C57: =C56/B56-1 -> 0.20408163 | D57: =D56/C56-1 -> 0.18644068 | E57: =E56/D56-1 -> 0.16785714 | F57: =F56/E56-1 -> 0.14984709 | G57: =G56/F56-1 -> 0.12887768 | H57: =H56/G56-1 -> 0.10790826 | I57: =I56/H56-1 -> 0.086938838 | J57: =J56/I56-1 -> 0.065969419 | K57: =K56/J56-1 -> 0.045 | L57: 0.045
A58: Operating margin | B58: 0.2 | C58: 0.23 | D58: 0.25 | E58: 0.27 | F58: 0.28 | G58: =$F58+($L58-$F58)*G$17/5 -> 0.284 | H58: =$F58+($L58-$F58)*H$17/5 -> 0.288 | I58: =$F58+($L58-$F58)*I$17/5 -> 0.292 | J58: =$F58+($L58-$F58)*J$17/5 -> 0.296 | K58: =$F58+($L58-$F58)*K$17/5 -> 0.3 | L58: 0.3
A59: Operating income | B59: =B56*B58 -> 3.92 | C59: =C56*C58 -> 5.428 | D59: =D56*D58 -> 7 | E59: =E56*E58 -> 8.829 | F59: =F56*F58 -> 10.528 | G59: =G56*G58 -> 12.054607 | H59: =H56*H58 -> 13.543503 | I59: =I56*I58 -> 14.925417 | ... L59: =L56*L58 -> 17.850164
A60: NOPAT | B60: =B59*(1-$B$9) -> 3.136 | C60: =C59*(1-$B$9) -> 4.3424 | D60: =D59*(1-$B$9) -> 5.6 | E60: =E59*(1-$B$9) -> 7.0632 | F60: =F59*(1-$B$9) -> 8.4224 | G60: =G59*(1-$B$9) -> 9.6436859 | H60: =H59*(1-$B$9) -> 10.834803 | I60: =I59*(1-$B$9) -> 11.940334 | ... L60: =L59*(1-$B$9) -> 14.280131
A61: Net reinvestment, % of revenue | B61: 0.03 | C61: 0.03 | D61: 0.03 | E61: 0.03 | F61: 0.03 | G61: =$F61+($L61-$F61)*G$17/5 -> 0.028 | H61: =$F61+($L61-$F61)*H$17/5 -> 0.026 | I61: =$F61+($L61-$F61)*I$17/5 -> 0.024 | J61: =$F61+($L61-$F61)*J$17/5 -> 0.022 | K61: =$F61+($L61-$F61)*K$17/5 -> 0.02 | L61: 0.02
A62: Net reinvestment | B62: =B56*B61 -> 0.588 | C62: =C56*C61 -> 0.708 | D62: =D56*D61 -> 0.84 | E62: =E56*E61 -> 0.981 | F62: =F56*F61 -> 1.128 | G62: =G56*G61 -> 1.1884824 | H62: =H56*H61 -> 1.2226774 | I62: =I56*I61 -> 1.2267466 | ... L62: =L56*L61 -> 1.190011
A63: Change in working capital | B63: =$B$11*(B56-$B$12) -> -0.169 | C63: =$B$11*(C56-B56) -> -0.2 | D63: =$B$11*(D56-C56) -> -0.22 | E63: =$B$11*(E56-D56) -> -0.235 | F63: =$B$11*(F56-E56) -> -0.245 | G63: =$B$11*(G56-F56) -> -0.24229003 | H63: =$B$11*(H56-G56) -> -0.22901262 | I63: =$B$11*(I56-H56) -> -0.20441952 | J63: =$B$11*(J56-I56) -> -0.16859951 | ... L63: =$B$11*(L56-K56) -> -0.12811123
A64: Free cash flow | B64: =B60-B62-B63 -> 2.717 | C64: =C60-C62-C63 -> 3.8344 | D64: =D60-D62-D63 -> 4.98 | E64: =E60-E62-E63 -> 6.3172 | F64: =F60-F62-F63 -> 7.5394 | G64: =G60-G62-G63 -> 8.6974935 | H64: =H60-H62-H63 -> 9.8411378 | I64: =I60-I62-I63 -> 10.918007 | ... L64: =L60-L62-L63 -> 13.218232
A65: Discount factor | B65: =1/(1+$B$10)^B$16 -> 0.95563697 | C65: =1/(1+$B$10)^C$16 -> 0.87272782 | D65: =1/(1+$B$10)^D$16 -> 0.79701171 | E65: =1/(1+$B$10)^E$16 -> 0.72786458 | F65: =1/(1+$B$10)^F$16 -> 0.66471651 | G65: =1/(1+$B$10)^G$16 -> 0.60704704 | H65: =1/(1+$B$10)^H$16 -> 0.55438086 | I65: =1/(1+$B$10)^I$16 -> 0.50628389 | ... K65: =1/(1+$B$10)^K$16 -> 0.42224631
A66: PV of free cash flow | B66: =B64*B65 -> 2.5964656 | C66: =C64*C65 -> 3.3463876 | D66: =D64*D65 -> 3.9691183 | E66: =E64*E65 -> 4.5980661 | F66: =F64*F65 -> 5.0115636 | G66: =G64*G65 -> 5.2797877 | H66: =H64*H65 -> 5.4557384 | I66: =I64*I65 -> 5.527611 | ... K66: =K64*K65 -> 5.3410044
A67: Terminal value | B67: =L64/($B$10-L57) -> 264.36463 | C67: =IF($B$10>L57,"","Discount rate must exceed terminal growth")
A68: PV of terminal value | B68: =B67/(1+$B$10)^$K$16 -> 111.62699
A69: Equity value (PV FCF + PV TV + net cash + other) | B69: =SUM(B66:K66)+B68+$B$7+$B$8 -> 156.492
A70: Value per share ($) | B70: =B69/$B$6 -> 151.93398
A71: Value vs share price | B71: =B70/$B$4-1 -> -0.0312804
A74: Outputs | C74: vs price
A75: Bear value per share | B75: =B34 -> 58.852825 | C75: =B75/$B$4-1 -> -0.62475883
A76: Base value per share | B76: =B52 -> 103.66052 | C76: =B76/$B$4-1 -> -0.33906836
A77: Bull value per share | B77: =B70 -> 151.93398 | C77: =B77/$B$4-1 -> -0.0312804
A78: Selected scenario value per share | B78: =INDEX(B34:B70,1+($B$13-1)*18) -> 103.66052 | C78: =B78/$B$4-1 -> -0.33906836
A79: Share of base value from terminal value | B79: =B50/(SUM(B48:K48)+B50) -> 0.66693371
A81: Base value per share at other discount rates
A82: Discount rate | B82: 0.05 | C82: 0.06 | D82: 0.07 | E82: 0.08 | F82: 0.09 | G82: 0.1 | H82: 0.11 | I82: 0.12 | J82: 0.13 | K82: 0.14
A83: Base value per share | B83: =IF(B82>$L39,(SUMPRODUCT($B46:$K46/(1+B82)^$B$16:$K$16)+$L46/(B82-$L39)/(1+B82)^$K$16+$B$7+$B$8)/$B$6,"n/a") -> 618.3126 | C83: =IF(C82>$L39,(SUMPRODUCT($B46:$K46/(1+C82)^$B$16:$K$16)+$L46/(C82-$L39)/(1+C82)^$K$16+$B$7+$B$8)/$B$6,"n/a") -> 303.3313 | D83: =IF(D82>$L39,(SUMPRODUCT($B46:$K46/(1+D82)^$B$16:$K$16)+$L46/(D82-$L39)/(1+D82)^$K$16+$B$7+$B$8)/$B$6,"n/a") -> 198.52762 | E83: =IF(E82>$L39,(SUMPRODUCT($B46:$K46/(1+E82)^$B$16:$K$16)+$L46/(E82-$L39)/(1+E82)^$K$16+$B$7+$B$8)/$B$6,"n/a") -> 146.25871 | F83: =IF(F82>$L39,(SUMPRODUCT($B46:$K46/(1+F82)^$B$16:$K$16)+$L46/(F82-$L39)/(1+F82)^$K$16+$B$7+$B$8)/$B$6,"n/a") -> 114.9966 | G83: =IF(G82>$L39,(SUMPRODUCT($B46:$K46/(1+G82)^$B$16:$K$16)+$L46/(G82-$L39)/(1+G82)^$K$16+$B$7+$B$8)/$B$6,"n/a") -> 94.232448 | H83: =IF(H82>$L39,(SUMPRODUCT($B46:$K46/(1+H82)^$B$16:$K$16)+$L46/(H82-$L39)/(1+H82)^$K$16+$B$7+$B$8)/$B$6,"n/a") -> 79.462821 | I83: =IF(I82>$L39,(SUMPRODUCT($B46:$K46/(1+I82)^$B$16:$K$16)+$L46/(I82-$L39)/(1+I82)^$K$16+$B$7+$B$8)/$B$6,"n/a") -> 68.436298 | ... K83: =IF(K82>$L39,(SUMPRODUCT($B46:$K46/(1+K82)^$B$16:$K$16)+$L46/(K82-$L39)/(1+K82)^$K$16+$B$7+$B$8)/$B$6,"n/a") -> 53.110757
A84: vs share price | B84: =IFERROR(B83/$B$4-1,"n/a") -> 2.9423144 | C84: =IFERROR(C83/$B$4-1,"n/a") -> 0.93401744 | D84: =IFERROR(D83/$B$4-1,"n/a") -> 0.26579713 | E84: =IFERROR(E83/$B$4-1,"n/a") -> -0.067465512 | F84: =IFERROR(F83/$B$4-1,"n/a") -> -0.26679035 | G84: =IFERROR(G83/$B$4-1,"n/a") -> -0.39918103 | H84: =IFERROR(H83/$B$4-1,"n/a") -> -0.49335105 | I84: =IFERROR(I83/$B$4-1,"n/a") -> -0.56365533 | ... K84: =IFERROR(K83/$B$4-1,"n/a") -> -0.66136982
A86: Implied annual return at today's price, base case | B86: =IFERROR(IF(MATCH($B$4,$B$83:$K$83,-1)=10,"above 14%",INDEX($B$82:$K$82,MATCH($B$4,$B$83:$K$83,-1))+(INDEX($B$83:$K$83,MATCH($B$4,$B$83:$K$83,-1))-$B$4)/(INDEX($B$83:$K$83,MATCH($B$4,$B$83:$K$83,-1))-INDEX($B$83:$K$83,MATCH($B$4,$B$83:$K$83,-1)+1))*(INDEX($B$82:$K$82,MATCH($B$4,$B$83:$K$83,-1)+1)-INDEX($B$82:$K$82,MATCH($B$4,$B$83:$K$83,-1)))),"below 5%") -> 0.077975605 | C86: Discount rate at which base value equals the price (interpolated from the row above)

Sheet WACC
A1: Discount rates: calculated (CAPM) versus assumed
A2: Blue = input, black = formula, green = link. The yellow switches set the rate used on the model sheet.
A5: Rate used in valuations (1 = Calculated, 2 = Assumed) | B5: 2 | C5: Switch. 2 reproduces the doc's figures
A6: Beta used (1 = Raw 5-year, 2 = Blume adjusted) | B6: 2 | C6: Blume adjusted = 0.67 x raw + 0.33
A7: Risk-free rate (10-year Treasury) | B7: 0.0531 | C7: FRED via MacroRadar, Oct 6, 2026 (same as earlier journal models)
A8: Equity risk premium | B8: 0.05 | C8: Analyst assumption
A9: Credit spread over risk-free (pre-tax cost of debt) | B9: 0.012 | C9: Analyst assumption: investment-grade spread
A12: Item | B12: NOW | C12: Source / note
A13: Raw beta (5-year) | B13: 0.99 | C13: Stock Analysis statistics, Oct 23, 2026
A14: Beta override (blank = none) | C14: Cheniere's 0.06 raw beta reflects its own history, not its risk; 0.80 used instead
A15: Adjusted beta | B15: =0.67*IF(ISNUMBER(B14),B14,B13)+0.33 -> 0.9933 | C15: Blume: 0.67 x raw (or override) + 0.33
A16: Beta used | B16: =IF($B$6=1,IF(ISNUMBER(B14),B14,B13),B15) -> 0.9933 | C16: Per switch in B6
A17: Cost of equity | B17: =$B$7+B16*$B$8 -> 0.102765 | C17: Risk-free + beta x ERP
A18: Pre-tax cost of debt | B18: =$B$7+$B$9 -> 0.0651 | C18: Risk-free + spread
A19: Tax rate | B19: =NOW!B9 -> 0.2 | C19: Linked from company sheet
A20: After-tax cost of debt | B20: =B18*(1-B19) -> 0.05208
A21: Market value of equity ($B) | B21: =NOW!B4*NOW!B6 -> 161.5452 | C21: Price x shares
A22: Debt ($B) | B22: 8.45 | C22: Stock Analysis, total debt
A23: Equity weight | B23: =B21/(B21+B22) -> 0.95029271
A24: Debt weight | B24: =B22/(B21+B22) -> 0.049707286
A25: Calculated WACC (CAPM) | B25: =B23*B17+B24*B20 -> 0.10024559 | C25: Weighted cost of capital
A26: Assumed WACC | B26: 0.095 | C26: Analyst assumption used in the doc
A27: WACC used | B27: =IF($B$5=1,B25,B26) -> 0.095 | C27: Per switch in B5; feeds each sheet's B10
A28: Check: WACC above every terminal growth rate | B28: =IF(B27>MAX(NOW!L21,NOW!L39,NOW!L57),"OK","WACC must exceed growth") -> OK
A29: Link row read by company sheets | B29: =B27 -> 0.095 | C29: Same as WACC used
