Workbook

Sheet Summary
A1: Nvidia (NVDA): valuation summary
A2: Values link to the model sheet (green). Switch the discount rate on the WACC tab.
A4: Company | B4: Method | C4: Share price | D4: Discount rate | E4: Bear value | F4: Base value | G4: Bull value | H4: Base vs price | I4: Implied return at price (base case) | J4: Base value (rounded)
A5: Nvidia (NVDA) | B5: 10-year DCF | C5: =NVDA!B4 -> 212.28 | D5: =NVDA!B10 -> 0.1072 | E5: =NVDA!B75 -> 97.570758 | F5: =NVDA!B76 -> 171.37658 | G5: =NVDA!B77 -> 244.62145 | H5: =F5/C5-1 -> -0.19268616 | I5: =NVDA!B86 -> 0.092900116 | J5: =IF(F5<10,ROUND(F5*4,0)/4,IF(F5<100,ROUND(F5,0),ROUND(F5/5,0)*5)) -> 170
A8: Exit plan on the positions page
A9: Base value (rounded) | C9: 165
A10: Trim above (bull value, rounded) | C10: 235
A11: Exit below (halfway, bear to base) | C11: 130
A12: Thesis-break signal | C12: Sell if any hyperscaler guides 2027 capex flat or down, or if gross margin falls below 70%.

Sheet NVDA
A1: Nvidia (NVDA): 10-year scenario DCF
A2: Units: $ billions unless noted. Blue = input, black = formula, green = link, yellow = key lever. Years 6 to 10 fade growth, margin and reinvestment toward each scenario's terminal levels.
A4: Share price ($) | B4: 212.28 | C4: Oct 23, 2026 intraday (Yahoo Finance via the site's price feed)
A5: Price date | B5: Oct 23, 2026 | C5: Text
A6: Shares outstanding (billions) | B6: 24.15 | C6: Stock Analysis statistics, Oct 23, 2026
A7: Net cash, negative = net debt | B7: 23.61 | C7: Stock Analysis statistics, Oct 23, 2026: cash less total debt
A8: Other non-operating assets, less outside claims | B8: 0 | C8: None
A9: Tax rate | B9: 0.16 | C9: Analyst assumption (normalized, near the reported effective rate)
A10: Discount rate (WACC), from WACC tab | B10: =WACC!B29 -> 0.1072 | C10: Calculated or assumed, per the switch in WACC!B5
A11: Working capital, % of revenue change | B11: 0.1 | C11: Analyst assumption
A12: Base-year revenue (FY27, Jan 2027) | B12: 411.65 | C12: FY27 (Jan 2027) consensus $411.65B; FY28 consensus $692B (Stock Analysis)
A13: Selected scenario (1 Bear, 2 Base, 3 Bull) | B13: 2 | C13: Lever
A15: Year | B15: FY28 | C15: FY29 | D15: FY30 | E15: FY31 | F15: FY32 | G15: FY33 | H15: FY34 | I15: FY35 | J15: FY36 | K15: FY37 | L15: Terminal
A16: Discount period (years, mid-year) | B16: 0.5 | C16: =B16+1 -> 1.5 | D16: =C16+1 -> 2.5 | E16: =D16+1 -> 3.5 | F16: =E16+1 -> 4.5 | G16: =F16+1 -> 5.5 | H16: =G16+1 -> 6.5 | I16: =H16+1 -> 7.5 | J16: =I16+1 -> 8.5 | K16: =J16+1 -> 9.5
A17: Fade step (years 6 to 10) | B17: 0 | C17: 0 | D17: 0 | E17: 0 | F17: 0 | G17: 1 | H17: 2 | I17: 3 | J17: 4 | K17: 5
A19: Bear: AI capex digestion in FY29 to FY30
A20: Revenue | B20: 560 | C20: 500 | D20: 470 | E20: 520 | F20: 560 | G20: =F20*(1+$F21+($L21-$F21)*G$17/5) -> 597.82154 | H20: =G20*(1+$F21+($L21-$F21)*H$17/5) -> 632.58716 | I20: =H20*(1+$F21+($L21-$F21)*I$17/5) -> 663.43795 | J20: =I20*(1+$F21+($L21-$F21)*J$17/5) -> 689.5672 | K20: =J20*(1+$F21+($L21-$F21)*K$17/5) -> 710.25421 | L20: =K20*(1+L21) -> 731.56184
A21: Revenue growth (terminal column = terminal growth, input) | B21: =B20/$B$12-1 -> 0.36037896 | C21: =C20/B20-1 -> -0.10714286 | D21: =D20/C20-1 -> -0.06 | E21: =E20/D20-1 -> 0.10638298 | F21: =F20/E20-1 -> 0.076923077 | G21: =G20/F20-1 -> 0.067538462 | H21: =H20/G20-1 -> 0.058153846 | I21: =I20/H20-1 -> 0.048769231 | J21: =J20/I20-1 -> 0.039384615 | K21: =K20/J20-1 -> 0.03 | L21: 0.03
A22: Operating margin | B22: 0.6 | C22: 0.52 | D22: 0.48 | E22: 0.48 | F22: 0.47 | G22: =$F22+($L22-$F22)*G$17/5 -> 0.452 | H22: =$F22+($L22-$F22)*H$17/5 -> 0.434 | I22: =$F22+($L22-$F22)*I$17/5 -> 0.416 | J22: =$F22+($L22-$F22)*J$17/5 -> 0.398 | K22: =$F22+($L22-$F22)*K$17/5 -> 0.38 | L22: 0.38
A23: Operating income | B23: =B20*B22 -> 336 | C23: =C20*C22 -> 260 | D23: =D20*D22 -> 225.6 | E23: =E20*E22 -> 249.6 | F23: =F20*F22 -> 263.2 | G23: =G20*G22 -> 270.21534 | H23: =H20*H22 -> 274.54283 | I23: =I20*I22 -> 275.99019 | ... L23: =L20*L22 -> 277.9935
A24: NOPAT | B24: =B23*(1-$B$9) -> 282.24 | C24: =C23*(1-$B$9) -> 218.4 | D24: =D23*(1-$B$9) -> 189.504 | E24: =E23*(1-$B$9) -> 209.664 | F24: =F23*(1-$B$9) -> 221.088 | G24: =G23*(1-$B$9) -> 226.98088 | H24: =H23*(1-$B$9) -> 230.61598 | I24: =I23*(1-$B$9) -> 231.83176 | ... L24: =L23*(1-$B$9) -> 233.51454
A25: Net reinvestment, % of revenue | B25: 0.03 | C25: 0.03 | D25: 0.03 | E25: 0.03 | F25: 0.03 | G25: =$F25+($L25-$F25)*G$17/5 -> 0.03 | H25: =$F25+($L25-$F25)*H$17/5 -> 0.03 | I25: =$F25+($L25-$F25)*I$17/5 -> 0.03 | J25: =$F25+($L25-$F25)*J$17/5 -> 0.03 | K25: =$F25+($L25-$F25)*K$17/5 -> 0.03 | L25: 0.03
A26: Net reinvestment | B26: =B20*B25 -> 16.8 | C26: =C20*C25 -> 15 | D26: =D20*D25 -> 14.1 | E26: =E20*E25 -> 15.6 | F26: =F20*F25 -> 16.8 | G26: =G20*G25 -> 17.934646 | H26: =H20*H25 -> 18.977615 | I26: =I20*I25 -> 19.903138 | ... L26: =L20*L25 -> 21.946855
A27: Change in working capital | B27: =$B$11*(B20-$B$12) -> 14.835 | C27: =$B$11*(C20-B20) -> -6 | D27: =$B$11*(D20-C20) -> -3 | E27: =$B$11*(E20-D20) -> 5 | F27: =$B$11*(F20-E20) -> 4 | G27: =$B$11*(G20-F20) -> 3.7821538 | H27: =$B$11*(H20-G20) -> 3.4765622 | I27: =$B$11*(I20-H20) -> 3.0850789 | J27: =$B$11*(J20-I20) -> 2.6129248 | ... L27: =$B$11*(L20-K20) -> 2.1307626
A28: Free cash flow | B28: =B24-B26-B27 -> 250.605 | C28: =C24-C26-C27 -> 209.4 | D28: =D24-D26-D27 -> 178.404 | E28: =E24-E26-E27 -> 189.064 | F28: =F24-F26-F27 -> 200.288 | G28: =G24-G26-G27 -> 205.26408 | H28: =H24-H26-H27 -> 208.1618 | I28: =I24-I26-I27 -> 208.84354 | ... L28: =L24-L26-L27 -> 209.43692
A29: Discount factor | B29: =1/(1+$B$10)^B$16 -> 0.9503574 | C29: =1/(1+$B$10)^C$16 -> 0.85834303 | D29: =1/(1+$B$10)^D$16 -> 0.77523756 | E29: =1/(1+$B$10)^E$16 -> 0.70017843 | F29: =1/(1+$B$10)^F$16 -> 0.63238659 | G29: =1/(1+$B$10)^G$16 -> 0.57115841 | H29: =1/(1+$B$10)^H$16 -> 0.51585839 | I29: =1/(1+$B$10)^I$16 -> 0.46591256 | ... K29: =1/(1+$B$10)^K$16 -> 0.38006009
A30: PV of free cash flow | B30: =B28*B29 -> 238.16432 | C30: =C28*C29 -> 179.73703 | D30: =D28*D29 -> 138.30548 | E30: =E28*E29 -> 132.37854 | F30: =F28*F29 -> 126.65945 | G30: =G28*G29 -> 117.23831 | H30: =H28*H29 -> 107.38201 | I30: =I28*I29 -> 97.302829 | ... K30: =K28*K29 -> 77.280209
A31: Terminal value | B31: =L28/($B$10-L21) -> 2712.9135 | C31: =IF($B$10>L21,"","Discount rate must exceed terminal growth")
A32: PV of terminal value | B32: =B31/(1+$B$10)^$K$16 -> 1031.0701
A33: Equity value (PV FCF + PV TV + net cash + other) | B33: =SUM(B30:K30)+B32+$B$7+$B$8 -> 2356.3338
A34: Value per share ($) | B34: =B33/$B$6 -> 97.570758
A35: Value vs share price | B35: =B34/$B$4-1 -> -0.54036764
A37: Base: below-consensus growth, margins ease
A38: Revenue | B38: 640 | C38: 720 | D38: 700 | E38: 760 | F38: 820 | G38: =F38*(1+$F39+($L39-$F39)*G$17/5) -> 877.52947 | H38: =G38*(1+$F39+($L39-$F39)*H$17/5) -> 931.38207 | I38: =H38*(1+$F39+($L39-$F39)*I$17/5) -> 980.35316 | J38: =I38*(1+$F39+($L39-$F39)*J$17/5) -> 1023.2823 | K38: =J38*(1+$F39+($L39-$F39)*K$17/5) -> 1059.0972 | L38: =K38*(1+L39) -> 1096.1656
A39: Revenue growth (terminal column = terminal growth, input) | B39: =B38/$B$12-1 -> 0.55471881 | C39: =C38/B38-1 -> 0.125 | D39: =D38/C38-1 -> -0.027777778 | E39: =E38/D38-1 -> 0.085714286 | F39: =F38/E38-1 -> 0.078947368 | G39: =G38/F38-1 -> 0.070157895 | H39: =H38/G38-1 -> 0.061368421 | I39: =I38/H38-1 -> 0.052578947 | J39: =J38/I38-1 -> 0.043789474 | K39: =K38/J38-1 -> 0.035 | L39: 0.035
A40: Operating margin | B40: 0.62 | C40: 0.6 | D40: 0.56 | E40: 0.54 | F40: 0.52 | G40: =$F40+($L40-$F40)*G$17/5 -> 0.508 | H40: =$F40+($L40-$F40)*H$17/5 -> 0.496 | I40: =$F40+($L40-$F40)*I$17/5 -> 0.484 | J40: =$F40+($L40-$F40)*J$17/5 -> 0.472 | K40: =$F40+($L40-$F40)*K$17/5 -> 0.46 | L40: 0.46
A41: Operating income | B41: =B38*B40 -> 396.8 | C41: =C38*C40 -> 432 | D41: =D38*D40 -> 392 | E41: =E38*E40 -> 410.4 | F41: =F38*F40 -> 426.4 | G41: =G38*G40 -> 445.78497 | H41: =H38*H40 -> 461.96551 | I41: =I38*I40 -> 474.49093 | ... L41: =L38*L40 -> 504.23617
A42: NOPAT | B42: =B41*(1-$B$9) -> 333.312 | C42: =C41*(1-$B$9) -> 362.88 | D42: =D41*(1-$B$9) -> 329.28 | E42: =E41*(1-$B$9) -> 344.736 | F42: =F41*(1-$B$9) -> 358.176 | G42: =G41*(1-$B$9) -> 374.45938 | H42: =H41*(1-$B$9) -> 388.05103 | I42: =I41*(1-$B$9) -> 398.57238 | ... L42: =L41*(1-$B$9) -> 423.55838
A43: Net reinvestment, % of revenue | B43: 0.03 | C43: 0.03 | D43: 0.03 | E43: 0.03 | F43: 0.03 | G43: =$F43+($L43-$F43)*G$17/5 -> 0.03 | H43: =$F43+($L43-$F43)*H$17/5 -> 0.03 | I43: =$F43+($L43-$F43)*I$17/5 -> 0.03 | J43: =$F43+($L43-$F43)*J$17/5 -> 0.03 | K43: =$F43+($L43-$F43)*K$17/5 -> 0.03 | L43: 0.03
A44: Net reinvestment | B44: =B38*B43 -> 19.2 | C44: =C38*C43 -> 21.6 | D44: =D38*D43 -> 21 | E44: =E38*E43 -> 22.8 | F44: =F38*F43 -> 24.6 | G44: =G38*G43 -> 26.325884 | H44: =H38*H43 -> 27.941462 | I44: =I38*I43 -> 29.410595 | ... L44: =L38*L43 -> 32.884968
A45: Change in working capital | B45: =$B$11*(B38-$B$12) -> 22.835 | C45: =$B$11*(C38-B38) -> 8 | D45: =$B$11*(D38-C38) -> -2 | E45: =$B$11*(E38-D38) -> 6 | F45: =$B$11*(F38-E38) -> 6 | G45: =$B$11*(G38-F38) -> 5.7529474 | H45: =$B$11*(H38-G38) -> 5.3852598 | I45: =$B$11*(I38-H38) -> 4.8971089 | J45: =$B$11*(J38-I38) -> 4.2929149 | ... L45: =$B$11*(L38-K38) -> 3.7068402
A46: Free cash flow | B46: =B42-B44-B45 -> 291.277 | C46: =C42-C44-C45 -> 333.28 | D46: =D42-D44-D45 -> 310.28 | E46: =E42-E44-E45 -> 315.936 | F46: =F42-F44-F45 -> 327.576 | G46: =G42-G44-G45 -> 342.38055 | H46: =H42-H44-H45 -> 354.7243 | I46: =I42-I44-I45 -> 364.26468 | ... L46: =L42-L44-L45 -> 386.96658
A47: Discount factor | B47: =1/(1+$B$10)^B$16 -> 0.9503574 | C47: =1/(1+$B$10)^C$16 -> 0.85834303 | D47: =1/(1+$B$10)^D$16 -> 0.77523756 | E47: =1/(1+$B$10)^E$16 -> 0.70017843 | F47: =1/(1+$B$10)^F$16 -> 0.63238659 | G47: =1/(1+$B$10)^G$16 -> 0.57115841 | H47: =1/(1+$B$10)^H$16 -> 0.51585839 | I47: =1/(1+$B$10)^I$16 -> 0.46591256 | ... K47: =1/(1+$B$10)^K$16 -> 0.38006009
A48: PV of free cash flow | B48: =B46*B47 -> 276.81725 | C48: =C46*C47 -> 286.06856 | D48: =D46*D47 -> 240.54071 | E48: =E46*E47 -> 221.21157 | F48: =F46*F47 -> 207.15467 | G48: =G46*G47 -> 195.55353 | H48: =H46*H47 -> 182.98751 | I48: =I46*I47 -> 169.71549 | ... K48: =K46*K47 -> 142.09715
A49: Terminal value | B49: =L46/($B$10-L39) -> 5359.6479 | C49: =IF($B$10>L39,"","Discount rate must exceed terminal growth")
A50: PV of terminal value | B50: =B49/(1+$B$10)^$K$16 -> 2036.9883
A51: Equity value (PV FCF + PV TV + net cash + other) | B51: =SUM(B48:K48)+B50+$B$7+$B$8 -> 4138.7444
A52: Value per share ($) | B52: =B51/$B$6 -> 171.37658
A53: Value vs share price | B53: =B52/$B$4-1 -> -0.19268616
A55: Bull: consensus path, share holds
A56: Revenue | B56: 692 | C56: 820 | D56: 880 | E56: 960 | F56: 1040 | G56: =F56*(1+$F57+($L57-$F57)*G$17/5) -> 1117.6533 | H56: =G56*(1+$F57+($L57-$F57)*H$17/5) -> 1191.4185 | I56: =H56*(1+$F57+($L57-$F57)*I$17/5) -> 1259.7264 | J56: =I56*(1+$F57+($L57-$F57)*J$17/5) -> 1321.0331 | K56: =J56*(1+$F57+($L57-$F57)*K$17/5) -> 1373.8745 | L56: =K56*(1+L57) -> 1428.8294
A57: Revenue growth (terminal column = terminal growth, input) | B57: =B56/$B$12-1 -> 0.68103972 | C57: =C56/B56-1 -> 0.1849711 | D57: =D56/C56-1 -> 0.073170732 | E57: =E56/D56-1 -> 0.090909091 | F57: =F56/E56-1 -> 0.083333333 | G57: =G56/F56-1 -> 0.074666667 | H57: =H56/G56-1 -> 0.066 | I57: =I56/H56-1 -> 0.057333333 | J57: =J56/I56-1 -> 0.048666667 | K57: =K56/J56-1 -> 0.04 | L57: 0.04
A58: Operating margin | B58: 0.64 | C58: 0.63 | D58: 0.61 | E58: 0.59 | F58: 0.57 | G58: =$F58+($L58-$F58)*G$17/5 -> 0.556 | H58: =$F58+($L58-$F58)*H$17/5 -> 0.542 | I58: =$F58+($L58-$F58)*I$17/5 -> 0.528 | J58: =$F58+($L58-$F58)*J$17/5 -> 0.514 | K58: =$F58+($L58-$F58)*K$17/5 -> 0.5 | L58: 0.5
A59: Operating income | B59: =B56*B58 -> 442.88 | C59: =C56*C58 -> 516.6 | D59: =D56*D58 -> 536.8 | E59: =E56*E58 -> 566.4 | F59: =F56*F58 -> 592.8 | G59: =G56*G58 -> 621.41525 | H59: =H56*H58 -> 645.7488 | I59: =I56*I58 -> 665.13556 | ... L59: =L56*L58 -> 714.41472
A60: NOPAT | B60: =B59*(1-$B$9) -> 372.0192 | C60: =C59*(1-$B$9) -> 433.944 | D60: =D59*(1-$B$9) -> 450.912 | E60: =E59*(1-$B$9) -> 475.776 | F60: =F59*(1-$B$9) -> 497.952 | G60: =G59*(1-$B$9) -> 521.98881 | H60: =H59*(1-$B$9) -> 542.42899 | I60: =I59*(1-$B$9) -> 558.71387 | ... L60: =L59*(1-$B$9) -> 600.10836
A61: Net reinvestment, % of revenue | B61: 0.03 | C61: 0.03 | D61: 0.03 | E61: 0.03 | F61: 0.03 | G61: =$F61+($L61-$F61)*G$17/5 -> 0.03 | H61: =$F61+($L61-$F61)*H$17/5 -> 0.03 | I61: =$F61+($L61-$F61)*I$17/5 -> 0.03 | J61: =$F61+($L61-$F61)*J$17/5 -> 0.03 | K61: =$F61+($L61-$F61)*K$17/5 -> 0.03 | L61: 0.03
A62: Net reinvestment | B62: =B56*B61 -> 20.76 | C62: =C56*C61 -> 24.6 | D62: =D56*D61 -> 26.4 | E62: =E56*E61 -> 28.8 | F62: =F56*F61 -> 31.2 | G62: =G56*G61 -> 33.5296 | H62: =H56*H61 -> 35.742554 | I62: =I56*I61 -> 37.791793 | ... L62: =L56*L61 -> 42.864883
A63: Change in working capital | B63: =$B$11*(B56-$B$12) -> 28.035 | C63: =$B$11*(C56-B56) -> 12.8 | D63: =$B$11*(D56-C56) -> 6 | E63: =$B$11*(E56-D56) -> 8 | F63: =$B$11*(F56-E56) -> 8 | G63: =$B$11*(G56-F56) -> 7.7653333 | H63: =$B$11*(H56-G56) -> 7.376512 | I63: =$B$11*(I56-H56) -> 6.8307991 | J63: =$B$11*(J56-I56) -> 6.1306687 | ... L63: =$B$11*(L56-K56) -> 5.4954978
A64: Free cash flow | B64: =B60-B62-B63 -> 323.2242 | C64: =C60-C62-C63 -> 396.544 | D64: =D60-D62-D63 -> 418.512 | E64: =E60-E62-E63 -> 438.976 | F64: =F60-F62-F63 -> 458.752 | G64: =G60-G62-G63 -> 480.69388 | H64: =H60-H62-H63 -> 499.30993 | I64: =I60-I62-I63 -> 514.09128 | ... L64: =L60-L62-L63 -> 551.74798
A65: Discount factor | B65: =1/(1+$B$10)^B$16 -> 0.9503574 | C65: =1/(1+$B$10)^C$16 -> 0.85834303 | D65: =1/(1+$B$10)^D$16 -> 0.77523756 | E65: =1/(1+$B$10)^E$16 -> 0.70017843 | F65: =1/(1+$B$10)^F$16 -> 0.63238659 | G65: =1/(1+$B$10)^G$16 -> 0.57115841 | H65: =1/(1+$B$10)^H$16 -> 0.51585839 | I65: =1/(1+$B$10)^I$16 -> 0.46591256 | ... K65: =1/(1+$B$10)^K$16 -> 0.38006009
A66: PV of free cash flow | B66: =B64*B65 -> 307.17851 | C66: =C64*C65 -> 340.37078 | D66: =D64*D65 -> 324.44622 | E66: =E64*E65 -> 307.36153 | F66: =F64*F65 -> 290.10861 | G66: =G64*G65 -> 274.55235 | H66: =H64*H65 -> 257.57322 | I66: =I64*I65 -> 239.52159 | ... K66: =K64*K65 -> 201.6321
A67: Terminal value | B67: =L64/($B$10-L57) -> 8210.5354 | C67: =IF($B$10>L57,"","Discount rate must exceed terminal growth")
A68: PV of terminal value | B68: =B67/(1+$B$10)^$K$16 -> 3120.4968
A69: Equity value (PV FCF + PV TV + net cash + other) | B69: =SUM(B66:K66)+B68+$B$7+$B$8 -> 5907.608
A70: Value per share ($) | B70: =B69/$B$6 -> 244.62145
A71: Value vs share price | B71: =B70/$B$4-1 -> 0.15235278
A74: Outputs | C74: vs price
A75: Bear value per share | B75: =B34 -> 97.570758 | C75: =B75/$B$4-1 -> -0.54036764
A76: Base value per share | B76: =B52 -> 171.37658 | C76: =B76/$B$4-1 -> -0.19268616
A77: Bull value per share | B77: =B70 -> 244.62145 | C77: =B77/$B$4-1 -> 0.15235278
A78: Selected scenario value per share | B78: =INDEX(B34:B70,1+($B$13-1)*18) -> 171.37658 | C78: =B78/$B$4-1 -> -0.19268616
A79: Share of base value from terminal value | B79: =B50/(SUM(B48:K48)+B50) -> 0.4949992
A81: Base value per share at other discount rates
A82: Discount rate | B82: 0.05 | C82: 0.06 | D82: 0.07 | E82: 0.08 | F82: 0.09 | G82: 0.1 | H82: 0.11 | I82: 0.12 | J82: 0.13 | K82: 0.14
A83: Base value per share | B83: =IF(B82>$L39,(SUMPRODUCT($B46:$K46/(1+B82)^$B$16:$K$16)+$L46/(B82-$L39)/(1+B82)^$K$16+$B$7+$B$8)/$B$6,"n/a") -> 782.73921 | C83: =IF(C82>$L39,(SUMPRODUCT($B46:$K46/(1+C82)^$B$16:$K$16)+$L46/(C82-$L39)/(1+C82)^$K$16+$B$7+$B$8)/$B$6,"n/a") -> 474.37141 | D83: =IF(D82>$L39,(SUMPRODUCT($B46:$K46/(1+D82)^$B$16:$K$16)+$L46/(D82-$L39)/(1+D82)^$K$16+$B$7+$B$8)/$B$6,"n/a") -> 342.11179 | E83: =IF(E82>$L39,(SUMPRODUCT($B46:$K46/(1+E82)^$B$16:$K$16)+$L46/(E82-$L39)/(1+E82)^$K$16+$B$7+$B$8)/$B$6,"n/a") -> 268.56113 | F83: =IF(F82>$L39,(SUMPRODUCT($B46:$K46/(1+F82)^$B$16:$K$16)+$L46/(F82-$L39)/(1+F82)^$K$16+$B$7+$B$8)/$B$6,"n/a") -> 221.70097 | G83: =IF(G82>$L39,(SUMPRODUCT($B46:$K46/(1+G82)^$B$16:$K$16)+$L46/(G82-$L39)/(1+G82)^$K$16+$B$7+$B$8)/$B$6,"n/a") -> 189.21616 | H83: =IF(H82>$L39,(SUMPRODUCT($B46:$K46/(1+H82)^$B$16:$K$16)+$L46/(H82-$L39)/(1+H82)^$K$16+$B$7+$B$8)/$B$6,"n/a") -> 165.35934 | I83: =IF(I82>$L39,(SUMPRODUCT($B46:$K46/(1+I82)^$B$16:$K$16)+$L46/(I82-$L39)/(1+I82)^$K$16+$B$7+$B$8)/$B$6,"n/a") -> 147.08757 | ... K83: =IF(K82>$L39,(SUMPRODUCT($B46:$K46/(1+K82)^$B$16:$K$16)+$L46/(K82-$L39)/(1+K82)^$K$16+$B$7+$B$8)/$B$6,"n/a") -> 120.92265
A84: vs share price | B84: =IFERROR(B83/$B$4-1,"n/a") -> 2.6872961 | C84: =IFERROR(C83/$B$4-1,"n/a") -> 1.2346496 | D84: =IFERROR(D83/$B$4-1,"n/a") -> 0.61160632 | E84: =IFERROR(E83/$B$4-1,"n/a") -> 0.26512685 | F84: =IFERROR(F83/$B$4-1,"n/a") -> 0.044379929 | G84: =IFERROR(G83/$B$4-1,"n/a") -> -0.10864819 | H84: =IFERROR(H83/$B$4-1,"n/a") -> -0.22103192 | I84: =IFERROR(I83/$B$4-1,"n/a") -> -0.30710586 | ... K84: =IFERROR(K83/$B$4-1,"n/a") -> -0.43036249
A86: Implied annual return at today's price, base case | B86: =IFERROR(IF(MATCH($B$4,$B$83:$K$83,-1)=10,"above 14%",INDEX($B$82:$K$82,MATCH($B$4,$B$83:$K$83,-1))+(INDEX($B$83:$K$83,MATCH($B$4,$B$83:$K$83,-1))-$B$4)/(INDEX($B$83:$K$83,MATCH($B$4,$B$83:$K$83,-1))-INDEX($B$83:$K$83,MATCH($B$4,$B$83:$K$83,-1)+1))*(INDEX($B$82:$K$82,MATCH($B$4,$B$83:$K$83,-1)+1)-INDEX($B$82:$K$82,MATCH($B$4,$B$83:$K$83,-1)))),"below 5%") -> 0.092900116 | C86: Discount rate at which base value equals the price (interpolated from the row above)

Sheet WACC
A1: Discount rates: calculated (CAPM) versus assumed
A2: Blue = input, black = formula, green = link. The yellow switches set the rate used on the model sheet.
A5: Rate used in valuations (1 = Calculated, 2 = Assumed) | B5: 2 | C5: Switch. 2 reproduces the doc's figures
A6: Beta used (1 = Raw 5-year, 2 = Blume adjusted) | B6: 2 | C6: Blume adjusted = 0.67 x raw + 0.33
A7: Risk-free rate (10-year Treasury) | B7: 0.0503 | C7: 10-year Treasury yield at the close on 2026-10-28; assumed rates below move with it
A8: Equity risk premium | B8: 0.05 | C8: Analyst assumption
A9: Credit spread over risk-free (pre-tax cost of debt) | B9: 0.012 | C9: Analyst assumption: investment-grade spread
A12: Item | B12: NVDA | C12: Source / note
A13: Raw beta (5-year) | B13: 2.22 | C13: Stock Analysis statistics, Oct 23, 2026
A14: Beta override (blank = none) | C14: Cheniere's 0.06 raw beta reflects its own history, not its risk; 0.80 used instead
A15: Adjusted beta | B15: =0.67*IF(ISNUMBER(B14),B14,B13)+0.33 -> 1.8174 | C15: Blume: 0.67 x raw (or override) + 0.33
A16: Beta used | B16: =IF($B$6=1,IF(ISNUMBER(B14),B14,B13),B15) -> 1.8174 | C16: Per switch in B6
A17: Cost of equity | B17: =$B$7+B16*$B$8 -> 0.14117 | C17: Risk-free + beta x ERP
A18: Pre-tax cost of debt | B18: =$B$7+$B$9 -> 0.0623 | C18: Risk-free + spread
A19: Tax rate | B19: =NVDA!B9 -> 0.16 | C19: Linked from company sheet
A20: After-tax cost of debt | B20: =B18*(1-B19) -> 0.052332
A21: Market value of equity ($B) | B21: =NVDA!B4*NVDA!B6 -> 5126.562 | C21: Price x shares
A22: Debt ($B) | B22: 38.86 | C22: Stock Analysis, total debt
A23: Equity weight | B23: =B21/(B21+B22) -> 0.9924769
A24: Debt weight | B24: =B22/(B21+B22) -> 0.0075231027
A25: Calculated WACC (CAPM) | B25: =B23*B17+B24*B20 -> 0.14050166 | C25: Weighted cost of capital
A26: Assumed WACC | B26: 0.1072 | C26: Analyst assumption used in the doc
A27: WACC used | B27: =IF($B$5=1,B25,B26) -> 0.1072 | C27: Per switch in B5; feeds each sheet's B10
A28: Check: WACC above every terminal growth rate | B28: =IF(B27>MAX(NVDA!L21,NVDA!L39,NVDA!L57),"OK","WACC must exceed growth") -> OK
A29: Link row read by company sheets | B29: =B27 -> 0.1072 | C29: Same as WACC used
