Workbook

Sheet Summary
A1: TMC the metals company (TMC): valuation summary
A2: Values link to the model sheet (green). TMC uses its own risk rate on its sheet.
A4: Company | B4: Method | C4: Share price | D4: Discount rate | E4: Bear value | F4: Base value | G4: Bull value | H4: Base vs price | I4: Implied return at price (base case) | J4: Base value (rounded)
A5: TMC the metals company (TMC) | B5: Probability-weighted | C5: =TMC!B4 -> 2.43 | D5: =TMC!B9 -> 0.15 | E5: =TMC!B19 -> 0.19447637 | F5: =TMC!B20 -> 2.2137378 | G5: =TMC!B21 -> 7.9139609 | H5: =F5/C5-1 -> -0.088996784 | I5: n/a | J5: =IF(F5<10,ROUND(F5*4,0)/4,IF(F5<100,ROUND(F5,0),ROUND(F5/5,0)*5)) -> 2.25
A8: Exit plan on the positions page
A9: Base value (rounded) | C9: 2.25
A10: Trim above (bull value, rounded) | C10: 4
A11: Exit below (halfway, bear to base) | C11: 1.5
A12: Thesis-break signal | C12: Sell it all on a permit denial or a ruling that blocks US seabed mining. Keep it under 2% of the portfolio.
A13: Levels follow the rules on the positions page and are reset when the model changes.
A15: Notes
A16: Base value is what the business is worth if the base case plays out and you want to earn the discount rate. Implied return is what the base case earns at today's price.
A17: DCF: five explicit years, then five years fading growth, margin and reinvestment to terminal levels. FCF = operating income x (1 - tax) - net reinvestment - working capital x revenue change. Mid-year discounting from October 2026.
A18: Margins are after stock-based pay. For ServiceNow that is about 19% today, not the 31.5% non-GAAP figure, which is the main reason its value is lower than a multiple of adjusted earnings suggests.
A19: Banks: tangible book plus the present value of returns above the cost of equity (residual income). TMC: probability-weighted, from the company's 2025 study with analyst haircuts.
A20: Discount rates use a 5.31% risk-free rate and a 5% equity risk premium, the same as the earlier journal models. At these rates most quality stocks look fully priced; the implied return column shows by how much.
A21: Price and data dates are on the model sheet. Company data: Stock Analysis, company filings and releases. Research for my own records, not investment advice.

Sheet TMC
A1: TMC the metals company (TMC): probability-weighted scenario value
A2: A DCF does not fit a pre-revenue company waiting on one permit. Each scenario values the NORI-D project from the company's own study, haircut for cost, price and dilution, then weights by probability.
A4: Share price ($) | B4: 2.43 | C4: Oct 23, 2026 intraday (Yahoo Finance via the site's price feed)
A5: Shares outstanding today (billions) | B5: 0.44114 | C5: Stock Analysis statistics, Oct 23, 2026
A6: Cash, $B (no debt) | B6: 0.09866 | C6: Stock Analysis statistics, Oct 23, 2026
A7: NORI-D project NPV, $B (after tax, 8% rate, PFS) | B7: 5.508 | C7: TMC press release, Aug 4, 2025: PFS NPV $5.5B; initial capex $4.9B; first production targeted Q4 2027
A8: Expansion NPV, $B (Initial Assessment, rest of NORI area) | B8: 18.1 | C8: TMC press release, Aug 4, 2025: Initial Assessment NPV $18.1B (combined $23.6B)
A9: Risk discount rate for timing | B9: 0.15 | C9: Analyst assumption: venture-style rate for a project not yet permitted or financed
A11: Scenario | B11: Probability | C11: Share of project NPV realized | D11: Share of expansion NPV realized | E11: Diluted shares (billions) | F11: Years until value is realized | G11: Value per share today | H11: Weighted
A12: Bear: permit denied or stalled for years | B12: 0.4 | C12: 0 | D12: 0 | E12: 0.44114 | F12: 1 | G12: =($B$7*C12+$B$8*D12+$B$6)/E12/(1+$B$9)^F12 -> 0.19447637 | H12: =B12*G12 -> 0.077790547
A13: Base: permit granted, delays, cost overruns, heavy dilution | B13: 0.45 | C13: 0.4 | D13: 0.05 | E13: 1 | F13: 3 | G13: =($B$7*C13+$B$8*D13+$B$6)/E13/(1+$B$9)^F13 -> 2.1085625 | H13: =B13*G13 -> 0.94885313
A14: Bull: permit granted, near schedule, expansion credible | B14: 0.15 | C14: 0.75 | D14: 0.2 | E14: 0.75 | F14: 2 | G14: =($B$7*C14+$B$8*D14+$B$6)/E14/(1+$B$9)^F14 -> 7.9139609 | H14: =B14*G14 -> 1.1870941
A15: Probability-weighted value | B15: =SUM(B12:B14) -> 1 | H15: =SUM(H12:H14) -> 2.2137378
A16: Check: probabilities sum to 100% | B16: =IF(ABS(B15-1)<0.0001,"OK","Probabilities must sum to 100%") -> OK
A18: Outputs | C18: vs price
A19: Bear value per share | B19: =G12 -> 0.19447637 | C19: =B19/$B$4-1 -> -0.91996857
A20: Probability-weighted value per share | B20: =H15 -> 2.2137378 | C20: =B20/$B$4-1 -> -0.088996784
A21: Bull value per share | B21: =G14 -> 7.9139609 | C21: =B21/$B$4-1 -> 2.256774
A23: Permit probability the price implies, holding the other inputs fixed | B23: =(B4-G12)/((B13*G13+B14*G14)/(B13+B14)-G12) -> 0.66425979 | C23: Solves for the combined weight on the two permit scenarios that makes the weighted value equal the price
A25: Notes: the company's study figures are its own and assume its metal price deck; the haircuts are the analyst's. Dilution reflects the roughly $4.9B of capex the project still needs to fund.
