Workbook

Sheet Summary
A1: UnitedHealth (UNH): valuation summary
A2: Values link to the model sheet (green). Switch the discount rate on the WACC tab.
A4: Company | B4: Method | C4: Share price | D4: Discount rate | E4: Bear value | F4: Base value | G4: Bull value | H4: Base vs price | I4: Implied return at price (base case) | J4: Base value (rounded)
A5: UnitedHealth (UNH) | B5: 10-year DCF | C5: =UNH!B4 -> 423.39 | D5: =UNH!B10 -> 0.09 | E5: =UNH!B75 -> 306.35245 | F5: =UNH!B76 -> 474.03446 | G5: =UNH!B77 -> 693.26088 | H5: =F5/C5-1 -> 0.11961656 | I5: =UNH!B86 -> 0.09583158 | J5: =IF(F5<10,ROUND(F5*4,0)/4,IF(F5<100,ROUND(F5,0),ROUND(F5/5,0)*5)) -> 475
A8: Exit plan on the positions page
A9: Base value (rounded) | C9: 475
A10: Trim above (bull value, rounded) | C10: 695
A11: Exit below (halfway, bear to base) | C11: 390
A12: Thesis-break signal | C12: Sell if the medical care ratio goes back above 90% excluding reserve releases, or if 2027 EPS guidance comes in below $22.

Sheet UNH
A1: UnitedHealth (UNH): 10-year scenario DCF
A2: Units: $ billions unless noted. Blue = input, black = formula, green = link, yellow = key lever. Years 6 to 10 fade growth, margin and reinvestment toward each scenario's terminal levels.
A4: Share price ($) | B4: 423.39 | C4: Oct 23, 2026 intraday (Yahoo Finance via the site's price feed)
A5: Price date | B5: Oct 23, 2026 | C5: Text
A6: Shares outstanding (billions) | B6: 0.89759 | C6: Stock Analysis statistics, Oct 23, 2026
A7: Net cash, negative = net debt | B7: -48.49 | C7: Stock Analysis statistics, Oct 23, 2026: cash less total debt
A8: Other non-operating assets, less outside claims | B8: 0 | C8: None
A9: Tax rate | B9: 0.22 | C9: Analyst assumption (normalized, near the reported effective rate)
A10: Discount rate (WACC), from WACC tab | B10: =WACC!B29 -> 0.09 | C10: Calculated or assumed, per the switch in WACC!B5
A11: Working capital, % of revenue change | B11: 0 | C11: Analyst assumption
A12: Base-year revenue (2026E) | B12: 448.7 | C12: 2026E consensus $448.7B (Stock Analysis)
A13: Selected scenario (1 Bear, 2 Base, 3 Bull) | B13: 2 | C13: Lever
A15: Year | B15: 2027 | C15: 2028 | D15: 2029 | E15: 2030 | F15: 2031 | G15: 2032 | H15: 2033 | I15: 2034 | J15: 2035 | K15: 2036 | L15: Terminal
A16: Discount period (years, mid-year) | B16: 0.5 | C16: =B16+1 -> 1.5 | D16: =C16+1 -> 2.5 | E16: =D16+1 -> 3.5 | F16: =E16+1 -> 4.5 | G16: =F16+1 -> 5.5 | H16: =G16+1 -> 6.5 | I16: =H16+1 -> 7.5 | J16: =I16+1 -> 8.5 | K16: =J16+1 -> 9.5
A17: Fade step (years 6 to 10) | B17: 0 | C17: 0 | D17: 0 | E17: 0 | F17: 0 | G17: 1 | H17: 2 | I17: 3 | J17: 4 | K17: 5
A19: Bear: margins stay near trough, policy pressure
A20: Revenue | B20: 455 | C20: 470 | D20: 488 | E20: 506 | F20: 525 | G20: =F20*(1+$F21+($L21-$F21)*G$17/5) -> 543.92075 | H20: =G20*(1+$F21+($L21-$F21)*H$17/5) -> 562.70214 | I20: =H20*(1+$F21+($L21-$F21)*I$17/5) -> 581.28243 | J20: =I20*(1+$F21+($L21-$F21)*J$17/5) -> 599.59857 | K20: =J20*(1+$F21+($L21-$F21)*K$17/5) -> 617.58653 | L20: =K20*(1+L21) -> 636.11413
A21: Revenue growth (terminal column = terminal growth, input) | B21: =B20/$B$12-1 -> 0.014040562 | C21: =C20/B20-1 -> 0.032967033 | D21: =D20/C20-1 -> 0.038297872 | E21: =E20/D20-1 -> 0.036885246 | F21: =F20/E20-1 -> 0.037549407 | G21: =G20/F20-1 -> 0.036039526 | H21: =H20/G20-1 -> 0.034529644 | I21: =I20/H20-1 -> 0.033019763 | J21: =J20/I20-1 -> 0.031509881 | K21: =K20/J20-1 -> 0.03 | L21: 0.03
A22: Operating margin | B22: 0.054 | C22: 0.054 | D22: 0.055 | E22: 0.056 | F22: 0.057 | G22: =$F22+($L22-$F22)*G$17/5 -> 0.0568 | H22: =$F22+($L22-$F22)*H$17/5 -> 0.0566 | I22: =$F22+($L22-$F22)*I$17/5 -> 0.0564 | J22: =$F22+($L22-$F22)*J$17/5 -> 0.0562 | K22: =$F22+($L22-$F22)*K$17/5 -> 0.056 | L22: 0.056
A23: Operating income | B23: =B20*B22 -> 24.57 | C23: =C20*C22 -> 25.38 | D23: =D20*D22 -> 26.84 | E23: =E20*E22 -> 28.336 | F23: =F20*F22 -> 29.925 | G23: =G20*G22 -> 30.894699 | H23: =H20*H22 -> 31.848941 | I23: =I20*I22 -> 32.784329 | ... L23: =L20*L22 -> 35.622391
A24: NOPAT | B24: =B23*(1-$B$9) -> 19.1646 | C24: =C23*(1-$B$9) -> 19.7964 | D24: =D23*(1-$B$9) -> 20.9352 | E24: =E23*(1-$B$9) -> 22.10208 | F24: =F23*(1-$B$9) -> 23.3415 | G24: =G23*(1-$B$9) -> 24.097865 | H24: =H23*(1-$B$9) -> 24.842174 | I24: =I23*(1-$B$9) -> 25.571777 | ... L24: =L23*(1-$B$9) -> 27.785465
A25: Net reinvestment, % of revenue | B25: 0.004 | C25: 0.004 | D25: 0.004 | E25: 0.004 | F25: 0.004 | G25: =$F25+($L25-$F25)*G$17/5 -> 0.004 | H25: =$F25+($L25-$F25)*H$17/5 -> 0.004 | I25: =$F25+($L25-$F25)*I$17/5 -> 0.004 | J25: =$F25+($L25-$F25)*J$17/5 -> 0.004 | K25: =$F25+($L25-$F25)*K$17/5 -> 0.004 | L25: 0.004
A26: Net reinvestment | B26: =B20*B25 -> 1.82 | C26: =C20*C25 -> 1.88 | D26: =D20*D25 -> 1.952 | E26: =E20*E25 -> 2.024 | F26: =F20*F25 -> 2.1 | G26: =G20*G25 -> 2.175683 | H26: =H20*H25 -> 2.2508086 | I26: =I20*I25 -> 2.3251297 | ... L26: =L20*L25 -> 2.5444565
A27: Change in working capital | B27: =$B$11*(B20-$B$12) -> 0 | C27: =$B$11*(C20-B20) -> 0 | D27: =$B$11*(D20-C20) -> 0 | E27: =$B$11*(E20-D20) -> 0 | F27: =$B$11*(F20-E20) -> 0 | G27: =$B$11*(G20-F20) -> 0 | H27: =$B$11*(H20-G20) -> 0 | I27: =$B$11*(I20-H20) -> 0 | J27: =$B$11*(J20-I20) -> 0 | ... L27: =$B$11*(L20-K20) -> 0
A28: Free cash flow | B28: =B24-B26-B27 -> 17.3446 | C28: =C24-C26-C27 -> 17.9164 | D28: =D24-D26-D27 -> 18.9832 | E28: =E24-E26-E27 -> 20.07808 | F28: =F24-F26-F27 -> 21.2415 | G28: =G24-G26-G27 -> 21.922182 | H28: =H24-H26-H27 -> 22.591366 | I28: =I24-I26-I27 -> 23.246647 | ... L28: =L24-L26-L27 -> 25.241009
A29: Discount factor | B29: =1/(1+$B$10)^B$16 -> 0.95782629 | C29: =1/(1+$B$10)^C$16 -> 0.87873971 | D29: =1/(1+$B$10)^D$16 -> 0.80618322 | E29: =1/(1+$B$10)^E$16 -> 0.73961763 | F29: =1/(1+$B$10)^F$16 -> 0.67854829 | G29: =1/(1+$B$10)^G$16 -> 0.62252137 | H29: =1/(1+$B$10)^H$16 -> 0.57112052 | I29: =1/(1+$B$10)^I$16 -> 0.52396378 | ... K29: =1/(1+$B$10)^K$16 -> 0.44100983
A30: PV of free cash flow | B30: =B28*B29 -> 16.613114 | C30: =C28*C29 -> 15.743852 | D30: =D28*D29 -> 15.303937 | E30: =E28*E29 -> 14.850102 | F30: =F28*F29 -> 14.413383 | G30: =G28*G29 -> 13.647027 | H30: =H28*H29 -> 12.902392 | I30: =I28*I29 -> 12.180401 | ... K30: =K28*K29 -> 10.807313
A31: Terminal value | B31: =L28/($B$10-L21) -> 420.68348 | C31: =IF($B$10>L21,"","Discount rate must exceed terminal growth")
A32: PV of terminal value | B32: =B31/(1+$B$10)^$K$16 -> 185.52555
A33: Equity value (PV FCF + PV TV + net cash + other) | B33: =SUM(B30:K30)+B32+$B$7+$B$8 -> 274.9789
A34: Value per share ($) | B34: =B33/$B$6 -> 306.35245
A35: Value vs share price | B35: =B34/$B$4-1 -> -0.27642964
A37: Base: margins repair partway, to about 6.5%
A38: Revenue | B38: 463 | C38: 485 | D38: 510 | E38: 536 | F38: 563 | G38: =F38*(1+$F39+($L39-$F39)*G$17/5) -> 590.19206 | H38: =G38*(1+$F39+($L39-$F39)*H$17/5) -> 617.47303 | I38: =H38*(1+$F39+($L39-$F39)*I$17/5) -> 644.734 | J38: =I38*(1+$F39+($L39-$F39)*J$17/5) -> 671.86094 | K38: =J38*(1+$F39+($L39-$F39)*K$17/5) -> 698.73538 | L38: =K38*(1+L39) -> 726.6848
A39: Revenue growth (terminal column = terminal growth, input) | B39: =B38/$B$12-1 -> 0.031869846 | C39: =C38/B38-1 -> 0.047516199 | D39: =D38/C38-1 -> 0.051546392 | E39: =E38/D38-1 -> 0.050980392 | F39: =F38/E38-1 -> 0.050373134 | G39: =G38/F38-1 -> 0.048298507 | H39: =H38/G38-1 -> 0.046223881 | I39: =I38/H38-1 -> 0.044149254 | J39: =J38/I38-1 -> 0.042074627 | K39: =K38/J38-1 -> 0.04 | L39: 0.04
A40: Operating margin | B40: 0.06 | C40: 0.063 | D40: 0.065 | E40: 0.066 | F40: 0.067 | G40: =$F40+($L40-$F40)*G$17/5 -> 0.0666 | H40: =$F40+($L40-$F40)*H$17/5 -> 0.0662 | I40: =$F40+($L40-$F40)*I$17/5 -> 0.0658 | J40: =$F40+($L40-$F40)*J$17/5 -> 0.0654 | K40: =$F40+($L40-$F40)*K$17/5 -> 0.065 | L40: 0.065
A41: Operating income | B41: =B38*B40 -> 27.78 | C41: =C38*C40 -> 30.555 | D41: =D38*D40 -> 33.15 | E41: =E38*E40 -> 35.376 | F41: =F38*F40 -> 37.721 | G41: =G38*G40 -> 39.306791 | H41: =H38*H40 -> 40.876714 | I41: =I38*I40 -> 42.423497 | ... L41: =L38*L40 -> 47.234512
A42: NOPAT | B42: =B41*(1-$B$9) -> 21.6684 | C42: =C41*(1-$B$9) -> 23.8329 | D42: =D41*(1-$B$9) -> 25.857 | E42: =E41*(1-$B$9) -> 27.59328 | F42: =F41*(1-$B$9) -> 29.42238 | G42: =G41*(1-$B$9) -> 30.659297 | H42: =H41*(1-$B$9) -> 31.883837 | I42: =I41*(1-$B$9) -> 33.090328 | ... L42: =L41*(1-$B$9) -> 36.842919
A43: Net reinvestment, % of revenue | B43: 0.004 | C43: 0.004 | D43: 0.004 | E43: 0.004 | F43: 0.004 | G43: =$F43+($L43-$F43)*G$17/5 -> 0.004 | H43: =$F43+($L43-$F43)*H$17/5 -> 0.004 | I43: =$F43+($L43-$F43)*I$17/5 -> 0.004 | J43: =$F43+($L43-$F43)*J$17/5 -> 0.004 | K43: =$F43+($L43-$F43)*K$17/5 -> 0.004 | L43: 0.004
A44: Net reinvestment | B44: =B38*B43 -> 1.852 | C44: =C38*C43 -> 1.94 | D44: =D38*D43 -> 2.04 | E44: =E38*E43 -> 2.144 | F44: =F38*F43 -> 2.252 | G44: =G38*G43 -> 2.3607682 | H44: =H38*H43 -> 2.4698921 | I44: =I38*I43 -> 2.578936 | ... L44: =L38*L43 -> 2.9067392
A45: Change in working capital | B45: =$B$11*(B38-$B$12) -> 0 | C45: =$B$11*(C38-B38) -> 0 | D45: =$B$11*(D38-C38) -> 0 | E45: =$B$11*(E38-D38) -> 0 | F45: =$B$11*(F38-E38) -> 0 | G45: =$B$11*(G38-F38) -> 0 | H45: =$B$11*(H38-G38) -> 0 | I45: =$B$11*(I38-H38) -> 0 | J45: =$B$11*(J38-I38) -> 0 | ... L45: =$B$11*(L38-K38) -> 0
A46: Free cash flow | B46: =B42-B44-B45 -> 19.8164 | C46: =C42-C44-C45 -> 21.8929 | D46: =D42-D44-D45 -> 23.817 | E46: =E42-E44-E45 -> 25.44928 | F46: =F42-F44-F45 -> 27.17038 | G46: =G42-G44-G45 -> 28.298529 | H46: =H42-H44-H45 -> 29.413945 | I46: =I42-I44-I45 -> 30.511392 | ... L46: =L42-L44-L45 -> 33.93618
A47: Discount factor | B47: =1/(1+$B$10)^B$16 -> 0.95782629 | C47: =1/(1+$B$10)^C$16 -> 0.87873971 | D47: =1/(1+$B$10)^D$16 -> 0.80618322 | E47: =1/(1+$B$10)^E$16 -> 0.73961763 | F47: =1/(1+$B$10)^F$16 -> 0.67854829 | G47: =1/(1+$B$10)^G$16 -> 0.62252137 | H47: =1/(1+$B$10)^H$16 -> 0.57112052 | I47: =1/(1+$B$10)^I$16 -> 0.52396378 | ... K47: =1/(1+$B$10)^K$16 -> 0.44100983
A48: PV of free cash flow | B48: =B46*B47 -> 18.980669 | C48: =C46*C47 -> 19.238161 | D48: =D46*D47 -> 19.200866 | E48: =E46*E47 -> 18.822736 | F48: =F46*F47 -> 18.436415 | G48: =G46*G47 -> 17.616439 | H48: =H46*H47 -> 16.798908 | I48: =I46*I47 -> 15.986864 | ... K48: =K46*K47 -> 14.390566
A49: Terminal value | B49: =L46/($B$10-L39) -> 678.7236 | C49: =IF($B$10>L39,"","Discount rate must exceed terminal growth")
A50: PV of terminal value | B50: =B49/(1+$B$10)^$K$16 -> 299.32378
A51: Equity value (PV FCF + PV TV + net cash + other) | B51: =SUM(B48:K48)+B50+$B$7+$B$8 -> 425.48859
A52: Value per share ($) | B52: =B51/$B$6 -> 474.03446
A53: Value vs share price | B53: =B52/$B$4-1 -> 0.11961656
A55: Bull: margins back to the 8% history
A56: Revenue | B56: 466 | C56: 495 | D56: 528 | E56: 563 | F56: 600 | G56: =F56*(1+$F57+($L57-$F57)*G$17/5) -> 636.94529 | H56: =G56*(1+$F57+($L57-$F57)*H$17/5) -> 673.52609 | I56: =H56*(1+$F57+($L57-$F57)*I$17/5) -> 709.41678 | J56: =I56*(1+$F57+($L57-$F57)*J$17/5) -> 744.28026 | K56: =J56*(1+$F57+($L57-$F57)*K$17/5) -> 777.77288 | L56: =K56*(1+L57) -> 812.77266
A57: Revenue growth (terminal column = terminal growth, input) | B57: =B56/$B$12-1 -> 0.038555828 | C57: =C56/B56-1 -> 0.06223176 | D57: =D56/C56-1 -> 0.066666667 | E57: =E56/D56-1 -> 0.066287879 | F57: =F56/E56-1 -> 0.065719361 | G57: =G56/F56-1 -> 0.061575488 | H57: =H56/G56-1 -> 0.057431616 | I57: =I56/H56-1 -> 0.053287744 | J57: =J56/I56-1 -> 0.049143872 | K57: =K56/J56-1 -> 0.045 | L57: 0.045
A58: Operating margin | B58: 0.062 | C58: 0.068 | D58: 0.074 | E58: 0.078 | F58: 0.08 | G58: =$F58+($L58-$F58)*G$17/5 -> 0.0796 | H58: =$F58+($L58-$F58)*H$17/5 -> 0.0792 | I58: =$F58+($L58-$F58)*I$17/5 -> 0.0788 | J58: =$F58+($L58-$F58)*J$17/5 -> 0.0784 | K58: =$F58+($L58-$F58)*K$17/5 -> 0.078 | L58: 0.078
A59: Operating income | B59: =B56*B58 -> 28.892 | C59: =C56*C58 -> 33.66 | D59: =D56*D58 -> 39.072 | E59: =E56*E58 -> 43.914 | F59: =F56*F58 -> 48 | G59: =G56*G58 -> 50.700845 | H59: =H56*H58 -> 53.343266 | I59: =I56*I58 -> 55.902042 | ... L59: =L56*L58 -> 63.396267
A60: NOPAT | B60: =B59*(1-$B$9) -> 22.53576 | C60: =C59*(1-$B$9) -> 26.2548 | D60: =D59*(1-$B$9) -> 30.47616 | E60: =E59*(1-$B$9) -> 34.25292 | F60: =F59*(1-$B$9) -> 37.44 | G60: =G59*(1-$B$9) -> 39.546659 | H60: =H59*(1-$B$9) -> 41.607748 | I60: =I59*(1-$B$9) -> 43.603593 | ... L60: =L59*(1-$B$9) -> 49.449088
A61: Net reinvestment, % of revenue | B61: 0.004 | C61: 0.004 | D61: 0.004 | E61: 0.004 | F61: 0.004 | G61: =$F61+($L61-$F61)*G$17/5 -> 0.004 | H61: =$F61+($L61-$F61)*H$17/5 -> 0.004 | I61: =$F61+($L61-$F61)*I$17/5 -> 0.004 | J61: =$F61+($L61-$F61)*J$17/5 -> 0.004 | K61: =$F61+($L61-$F61)*K$17/5 -> 0.004 | L61: 0.004
A62: Net reinvestment | B62: =B56*B61 -> 1.864 | C62: =C56*C61 -> 1.98 | D62: =D56*D61 -> 2.112 | E62: =E56*E61 -> 2.252 | F62: =F56*F61 -> 2.4 | G62: =G56*G61 -> 2.5477812 | H62: =H56*H61 -> 2.6941044 | I62: =I56*I61 -> 2.8376671 | ... L62: =L56*L61 -> 3.2510906
A63: Change in working capital | B63: =$B$11*(B56-$B$12) -> 0 | C63: =$B$11*(C56-B56) -> 0 | D63: =$B$11*(D56-C56) -> 0 | E63: =$B$11*(E56-D56) -> 0 | F63: =$B$11*(F56-E56) -> 0 | G63: =$B$11*(G56-F56) -> 0 | H63: =$B$11*(H56-G56) -> 0 | I63: =$B$11*(I56-H56) -> 0 | J63: =$B$11*(J56-I56) -> 0 | ... L63: =$B$11*(L56-K56) -> 0
A64: Free cash flow | B64: =B60-B62-B63 -> 20.67176 | C64: =C60-C62-C63 -> 24.2748 | D64: =D60-D62-D63 -> 28.36416 | E64: =E60-E62-E63 -> 32.00092 | F64: =F60-F62-F63 -> 35.04 | G64: =G60-G62-G63 -> 36.998878 | H64: =H60-H62-H63 -> 38.913643 | I64: =I60-I62-I63 -> 40.765926 | ... L64: =L60-L62-L63 -> 46.197998
A65: Discount factor | B65: =1/(1+$B$10)^B$16 -> 0.95782629 | C65: =1/(1+$B$10)^C$16 -> 0.87873971 | D65: =1/(1+$B$10)^D$16 -> 0.80618322 | E65: =1/(1+$B$10)^E$16 -> 0.73961763 | F65: =1/(1+$B$10)^F$16 -> 0.67854829 | G65: =1/(1+$B$10)^G$16 -> 0.62252137 | H65: =1/(1+$B$10)^H$16 -> 0.57112052 | I65: =1/(1+$B$10)^I$16 -> 0.52396378 | ... K65: =1/(1+$B$10)^K$16 -> 0.44100983
A66: PV of free cash flow | B66: =B64*B65 -> 19.799955 | C66: =C64*C65 -> 21.331231 | D66: =D64*D65 -> 22.86671 | E66: =E64*E65 -> 23.668445 | F66: =F64*F65 -> 23.776332 | G66: =G64*G65 -> 23.032592 | H66: =H64*H65 -> 22.22438 | I66: =I64*I65 -> 21.359868 | ... K66: =K64*K65 -> 19.496432
A67: Terminal value | B67: =L64/($B$10-L57) -> 1026.6222 | C67: =IF($B$10>L57,"","Discount rate must exceed terminal growth")
A68: PV of terminal value | B68: =B67/(1+$B$10)^$K$16 -> 452.75047
A69: Equity value (PV FCF + PV TV + net cash + other) | B69: =SUM(B66:K66)+B68+$B$7+$B$8 -> 622.26403
A70: Value per share ($) | B70: =B69/$B$6 -> 693.26088
A71: Value vs share price | B71: =B70/$B$4-1 -> 0.63740494
A74: Outputs | C74: vs price
A75: Bear value per share | B75: =B34 -> 306.35245 | C75: =B75/$B$4-1 -> -0.27642964
A76: Base value per share | B76: =B52 -> 474.03446 | C76: =B76/$B$4-1 -> 0.11961656
A77: Bull value per share | B77: =B70 -> 693.26088 | C77: =B77/$B$4-1 -> 0.63740494
A78: Selected scenario value per share | B78: =INDEX(B34:B70,1+($B$13-1)*18) -> 474.03446 | C78: =B78/$B$4-1 -> 0.11961656
A79: Share of base value from terminal value | B79: =B50/(SUM(B48:K48)+B50) -> 0.63151329
A81: Base value per share at other discount rates
A82: Discount rate | B82: 0.05 | C82: 0.06 | D82: 0.07 | E82: 0.08 | F82: 0.09 | G82: 0.1 | H82: 0.11 | I82: 0.12 | J82: 0.13 | K82: 0.14
A83: Base value per share | B83: =IF(B82>$L39,(SUMPRODUCT($B46:$K46/(1+B82)^$B$16:$K$16)+$L46/(B82-$L39)/(1+B82)^$K$16+$B$7+$B$8)/$B$6,"n/a") -> 2557.9542 | C83: =IF(C82>$L39,(SUMPRODUCT($B46:$K46/(1+C82)^$B$16:$K$16)+$L46/(C82-$L39)/(1+C82)^$K$16+$B$7+$B$8)/$B$6,"n/a") -> 1255.5401 | D83: =IF(D82>$L39,(SUMPRODUCT($B46:$K46/(1+D82)^$B$16:$K$16)+$L46/(D82-$L39)/(1+D82)^$K$16+$B$7+$B$8)/$B$6,"n/a") -> 821.38413 | E83: =IF(E82>$L39,(SUMPRODUCT($B46:$K46/(1+E82)^$B$16:$K$16)+$L46/(E82-$L39)/(1+E82)^$K$16+$B$7+$B$8)/$B$6,"n/a") -> 604.29507 | F83: =IF(F82>$L39,(SUMPRODUCT($B46:$K46/(1+F82)^$B$16:$K$16)+$L46/(F82-$L39)/(1+F82)^$K$16+$B$7+$B$8)/$B$6,"n/a") -> 474.03446 | G83: =IF(G82>$L39,(SUMPRODUCT($B46:$K46/(1+G82)^$B$16:$K$16)+$L46/(G82-$L39)/(1+G82)^$K$16+$B$7+$B$8)/$B$6,"n/a") -> 387.18929 | H83: =IF(H82>$L39,(SUMPRODUCT($B46:$K46/(1+H82)^$B$16:$K$16)+$L46/(H82-$L39)/(1+H82)^$K$16+$B$7+$B$8)/$B$6,"n/a") -> 325.15386 | I83: =IF(I82>$L39,(SUMPRODUCT($B46:$K46/(1+I82)^$B$16:$K$16)+$L46/(I82-$L39)/(1+I82)^$K$16+$B$7+$B$8)/$B$6,"n/a") -> 278.62519 | ... K83: =IF(K82>$L39,(SUMPRODUCT($B46:$K46/(1+K82)^$B$16:$K$16)+$L46/(K82-$L39)/(1+K82)^$K$16+$B$7+$B$8)/$B$6,"n/a") -> 213.48187
A84: vs share price | B84: =IFERROR(B83/$B$4-1,"n/a") -> 5.0416027 | C84: =IFERROR(C83/$B$4-1,"n/a") -> 1.9654458 | D84: =IFERROR(D83/$B$4-1,"n/a") -> 0.94001778 | E84: =IFERROR(E83/$B$4-1,"n/a") -> 0.42727761 | F84: =IFERROR(F83/$B$4-1,"n/a") -> 0.11961656 | G84: =IFERROR(G83/$B$4-1,"n/a") -> -0.085502043 | H84: =IFERROR(H83/$B$4-1,"n/a") -> -0.23202283 | I84: =IFERROR(I83/$B$4-1,"n/a") -> -0.34191835 | ... K84: =IFERROR(K83/$B$4-1,"n/a") -> -0.49577961
A86: Implied annual return at today's price, base case | B86: =IFERROR(IF(MATCH($B$4,$B$83:$K$83,-1)=10,"above 14%",INDEX($B$82:$K$82,MATCH($B$4,$B$83:$K$83,-1))+(INDEX($B$83:$K$83,MATCH($B$4,$B$83:$K$83,-1))-$B$4)/(INDEX($B$83:$K$83,MATCH($B$4,$B$83:$K$83,-1))-INDEX($B$83:$K$83,MATCH($B$4,$B$83:$K$83,-1)+1))*(INDEX($B$82:$K$82,MATCH($B$4,$B$83:$K$83,-1)+1)-INDEX($B$82:$K$82,MATCH($B$4,$B$83:$K$83,-1)))),"below 5%") -> 0.09583158 | C86: Discount rate at which base value equals the price (interpolated from the row above)

Sheet WACC
A1: Discount rates: calculated (CAPM) versus assumed
A2: Blue = input, black = formula, green = link. The yellow switches set the rate used on the model sheet.
A5: Rate used in valuations (1 = Calculated, 2 = Assumed) | B5: 2 | C5: Switch. 2 reproduces the doc's figures
A6: Beta used (1 = Raw 5-year, 2 = Blume adjusted) | B6: 2 | C6: Blume adjusted = 0.67 x raw + 0.33
A7: Risk-free rate (10-year Treasury) | B7: 0.0531 | C7: FRED via MacroRadar, Oct 6, 2026 (same as earlier journal models)
A8: Equity risk premium | B8: 0.05 | C8: Analyst assumption
A9: Credit spread over risk-free (pre-tax cost of debt) | B9: 0.012 | C9: Analyst assumption: investment-grade spread
A12: Item | B12: UNH | C12: Source / note
A13: Raw beta (5-year) | B13: 0.61 | C13: Stock Analysis statistics, Oct 23, 2026
A14: Beta override (blank = none) | C14: Cheniere's 0.06 raw beta reflects its own history, not its risk; 0.80 used instead
A15: Adjusted beta | B15: =0.67*IF(ISNUMBER(B14),B14,B13)+0.33 -> 0.7387 | C15: Blume: 0.67 x raw (or override) + 0.33
A16: Beta used | B16: =IF($B$6=1,IF(ISNUMBER(B14),B14,B13),B15) -> 0.7387 | C16: Per switch in B6
A17: Cost of equity | B17: =$B$7+B16*$B$8 -> 0.090035 | C17: Risk-free + beta x ERP
A18: Pre-tax cost of debt | B18: =$B$7+$B$9 -> 0.0651 | C18: Risk-free + spread
A19: Tax rate | B19: =UNH!B9 -> 0.22 | C19: Linked from company sheet
A20: After-tax cost of debt | B20: =B18*(1-B19) -> 0.050778
A21: Market value of equity ($B) | B21: =UNH!B4*UNH!B6 -> 380.03063 | C21: Price x shares
A22: Debt ($B) | B22: 74.33 | C22: Stock Analysis, total debt
A23: Equity weight | B23: =B21/(B21+B22) -> 0.83640748
A24: Debt weight | B24: =B22/(B21+B22) -> 0.16359252
A25: Calculated WACC (CAPM) | B25: =B23*B17+B24*B20 -> 0.083612848 | C25: Weighted cost of capital
A26: Assumed WACC | B26: 0.09 | C26: Analyst assumption used in the doc
A27: WACC used | B27: =IF($B$5=1,B25,B26) -> 0.09 | C27: Per switch in B5; feeds each sheet's B10
A28: Check: WACC above every terminal growth rate | B28: =IF(B27>MAX(UNH!L21,UNH!L39,UNH!L57),"OK","WACC must exceed growth") -> OK
A29: Link row read by company sheets | B29: =B27 -> 0.09 | C29: Same as WACC used
