Workbook

Sheet Summary
A1: Current Holdings: scenario values for the 13 stocks (Celestica updated Oct 27, 2026)
A2: Values link to each company sheet (green). Switch the discount rate on the WACC tab. Funds (JCPI, HYBL, VGK, XBI) are excluded.
A4: Company | B4: Method | C4: Share price | D4: Discount rate | E4: Bear value | F4: Base value | G4: Bull value | H4: Base vs price | I4: Implied return at price (base case) | J4: Base target (rounded)
A5: Altria (MO) | B5: 10-year DCF | C5: =MO!B4 -> 74.96 | D5: =MO!B10 -> 0.08 | E5: =MO!B75 -> 41.980663 | F5: =MO!B76 -> 63.115403 | G5: =MO!B77 -> 82.727961 | H5: =F5/C5-1 -> -0.15801224 | I5: =MO!B86 -> 0.067476087 | J5: =IF(F5<10,ROUND(F5*4,0)/4,IF(F5<100,ROUND(F5,0),ROUND(F5/5,0)*5)) -> 63
A6: Coca-Cola (KO) | B6: 10-year DCF | C6: =KO!B4 -> 93.27 | D6: =KO!B10 -> 0.075 | E6: =KO!B75 -> 53.571974 | F6: =KO!B76 -> 71.997025 | G6: =KO!B77 -> 92.33369 | H6: =F6/C6-1 -> -0.2280795 | I6: =KO!B86 -> 0.065520945 | J6: =IF(F6<10,ROUND(F6*4,0)/4,IF(F6<100,ROUND(F6,0),ROUND(F6/5,0)*5)) -> 72
A7: Alphabet (GOOG) | B7: 10-year DCF | C7: =GOOG!B4 -> 320.47 | D7: =GOOG!B10 -> 0.095 | E7: =GOOG!B75 -> 141.94636 | F7: =GOOG!B76 -> 253.24152 | G7: =GOOG!B77 -> 325.68132 | H7: =F7/C7-1 -> -0.20978088 | I7: =GOOG!B86 -> 0.084327818 | J7: =IF(F7<10,ROUND(F7*4,0)/4,IF(F7<100,ROUND(F7,0),ROUND(F7/5,0)*5)) -> 255
A8: UnitedHealth (UNH) | B8: 10-year DCF | C8: =UNH!B4 -> 423.39 | D8: =UNH!B10 -> 0.09 | E8: =UNH!B75 -> 306.35245 | F8: =UNH!B76 -> 474.03446 | G8: =UNH!B77 -> 693.26088 | H8: =F8/C8-1 -> 0.11961656 | I8: =UNH!B86 -> 0.09583158 | J8: =IF(F8<10,ROUND(F8*4,0)/4,IF(F8<100,ROUND(F8,0),ROUND(F8/5,0)*5)) -> 475
A9: Cheniere Energy (LNG) | B9: 10-year DCF | C9: =LNG!B4 -> 297.605 | D9: =LNG!B10 -> 0.075 | E9: =LNG!B75 -> 135.17044 | F9: =LNG!B76 -> 305.06065 | G9: =LNG!B77 -> 441.02468 | H9: =F9/C9-1 -> 0.025052165 | I9: =LNG!B86 -> 0.076268867 | J9: =IF(F9<10,ROUND(F9*4,0)/4,IF(F9<100,ROUND(F9,0),ROUND(F9/5,0)*5)) -> 305
A10: ServiceNow (NOW) | B10: 10-year DCF | C10: =NOW!B4 -> 156.84 | D10: =NOW!B10 -> 0.095 | E10: =NOW!B75 -> 58.852825 | F10: =NOW!B76 -> 103.66052 | G10: =NOW!B77 -> 151.93398 | H10: =F10/C10-1 -> -0.33906836 | I10: =NOW!B86 -> 0.077975605 | J10: =IF(F10<10,ROUND(F10*4,0)/4,IF(F10<100,ROUND(F10,0),ROUND(F10/5,0)*5)) -> 105
A11: Celestica (CLS) | B11: 10-year DCF | C11: =CLS!B4 -> 246.65 | D11: =CLS!B10 -> 0.105 | E11: =CLS!B75 -> 126.07684 | F11: =CLS!B76 -> 198.69445 | G11: =CLS!B77 -> 316.91894 | H11: =F11/C11-1 -> -0.19442752 | I11: =CLS!B86 -> 0.089558686 | J11: =IF(F11<10,ROUND(F11*4,0)/4,IF(F11<100,ROUND(F11,0),ROUND(F11/5,0)*5)) -> 200
A12: Enterprise Products (EPD) | B12: 10-year DCF | C12: =EPD!B4 -> 37.405 | D12: =EPD!B10 -> 0.08 | E12: =EPD!B75 -> 20.134109 | F12: =EPD!B76 -> 34.881406 | G12: =EPD!B77 -> 47.806581 | H12: =F12/C12-1 -> -0.067466758 | I12: =EPD!B86 -> 0.077488214 | J12: =IF(F12<10,ROUND(F12*4,0)/4,IF(F12<100,ROUND(F12,0),ROUND(F12/5,0)*5)) -> 35
A13: Nvidia (NVDA) | B13: 10-year DCF | C13: =NVDA!B4 -> 212.28 | D13: =NVDA!B10 -> 0.11 | E13: =NVDA!B75 -> 94.547961 | F13: =NVDA!B76 -> 165.35934 | G13: =NVDA!B77 -> 235.2016 | H13: =F13/C13-1 -> -0.22103192 | I13: =NVDA!B86 -> 0.092900116 | J13: =IF(F13<10,ROUND(F13*4,0)/4,IF(F13<100,ROUND(F13,0),ROUND(F13/5,0)*5)) -> 165
A14: JPMorgan Chase (JPM) | B14: Residual income | C14: =JPM!B4 -> 332.07 | D14: =JPM!B8 -> 0.1 | E14: =JPM!B53 -> 191.75064 | F14: =JPM!B54 -> 258.747 | G14: =JPM!B55 -> 315.09112 | H14: =F14/C14-1 -> -0.22080585 | I14: =JPM!B65 -> 0.088038318 | J14: =IF(F14<10,ROUND(F14*4,0)/4,IF(F14<100,ROUND(F14,0),ROUND(F14/5,0)*5)) -> 260
A15: Bank of America (BAC) | B15: Residual income | C15: =BAC!B4 -> 50.795 | D15: =BAC!B8 -> 0.105 | E15: =BAC!B53 -> 35.555326 | F15: =BAC!B54 -> 54.44399 | G15: =BAC!B55 -> 63.196153 | H15: =F15/C15-1 -> 0.071837586 | I15: =BAC!B65 -> 0.10944483 | J15: =IF(F15<10,ROUND(F15*4,0)/4,IF(F15<100,ROUND(F15,0),ROUND(F15/5,0)*5)) -> 54
A16: First Solar (FSLR) | B16: 10-year DCF | C16: =FSLR!B4 -> 171.57 | D16: =FSLR!B10 -> 0.105 | E16: =FSLR!B75 -> 72.183385 | F16: =FSLR!B76 -> 125.46518 | G16: =FSLR!B77 -> 187.54415 | H16: =F16/C16-1 -> -0.26872311 | I16: =FSLR!B86 -> 0.075764103 | J16: =IF(F16<10,ROUND(F16*4,0)/4,IF(F16<100,ROUND(F16,0),ROUND(F16/5,0)*5)) -> 125
A17: TMC the metals company (TMC) | B17: Probability-weighted | C17: =TMC!B4 -> 2.43 | D17: =TMC!B9 -> 0.15 | E17: =TMC!B19 -> 0.19447637 | F17: =TMC!B20 -> 2.2137378 | G17: =TMC!B21 -> 7.9139609 | H17: =F17/C17-1 -> -0.088996784 | I17: n/a | J17: =IF(F17<10,ROUND(F17*4,0)/4,IF(F17<100,ROUND(F17,0),ROUND(F17/5,0)*5)) -> 2.25
A19: Notes
A20: Base value is what the business is worth if the base case plays out and you want to earn the discount rate. Implied return is what the base case earns at today's price.
A21: DCF: five explicit years, then five years fading growth, margin and reinvestment to terminal levels. FCF = operating income x (1 - tax) - net reinvestment - working capital x revenue change. Mid-year discounting from October 2026.
A22: Margins are after stock-based pay. For ServiceNow that is about 19% today, not the 31.5% non-GAAP figure, which is the main reason its value is lower than a multiple of adjusted earnings suggests.
A23: Banks: tangible book plus the present value of returns above the cost of equity (residual income). TMC: probability-weighted, from the company's 2025 study with analyst haircuts.
A24: Discount rates use a 5.31% risk-free rate and a 5% equity risk premium, the same as the earlier journal models. At these rates most quality stocks look fully priced; the implied return column shows by how much.
A25: Prices: Oct 23, 2026 intraday, except Celestica (Oct 26 close, model updated for its Q3 results on Oct 27). Company data: Stock Analysis, company filings and releases (see each sheet). Research for my own records, not investment advice.

Sheet WACC
A1: Discount rates: calculated (CAPM) versus assumed
A2: Blue = input, black = formula, green = link. The yellow switches apply to every company. Banks use cost of equity only (lower table). TMC uses its own risk rate on its sheet.
A5: Rate used in valuations (1 = Calculated, 2 = Assumed) | B5: 2 | C5: Switch. 2 reproduces the doc's figures
A6: Beta used (1 = Raw 5-year, 2 = Blume adjusted) | B6: 2 | C6: Blume adjusted = 0.67 x raw + 0.33
A7: Risk-free rate (10-year Treasury) | B7: 0.0531 | C7: FRED via MacroRadar, Oct 6, 2026 (same as earlier journal models)
A8: Equity risk premium | B8: 0.05 | C8: Analyst assumption
A9: Credit spread over risk-free (pre-tax cost of debt) | B9: 0.012 | C9: Analyst assumption: investment-grade spread
A12: Item | B12: MO | C12: KO | D12: GOOG | E12: UNH | F12: LNG | G12: NOW | H12: CLS | I12: EPD | J12: NVDA | K12: FSLR | L12: Source / note
A13: Raw beta (5-year) | B13: 0.46 | C13: 0.32 | D13: 1.21 | E13: 0.61 | F13: 0.06 | G13: 0.99 | H13: 1.32 | I13: 0.49 | J13: 2.22 | K13: 1.79 | L13: Stock Analysis statistics, Oct 23, 2026
A14: Beta override (blank = none) | F14: 0.8 | L14: Cheniere's 0.06 raw beta reflects its own history, not its risk; 0.80 used instead
A15: Adjusted beta | B15: =0.67*IF(ISNUMBER(B14),B14,B13)+0.33 -> 0.6382 | C15: =0.67*IF(ISNUMBER(C14),C14,C13)+0.33 -> 0.5444 | D15: =0.67*IF(ISNUMBER(D14),D14,D13)+0.33 -> 1.1407 | E15: =0.67*IF(ISNUMBER(E14),E14,E13)+0.33 -> 0.7387 | F15: =0.67*IF(ISNUMBER(F14),F14,F13)+0.33 -> 0.866 | G15: =0.67*IF(ISNUMBER(G14),G14,G13)+0.33 -> 0.9933 | H15: =0.67*IF(ISNUMBER(H14),H14,H13)+0.33 -> 1.2144 | I15: =0.67*IF(ISNUMBER(I14),I14,I13)+0.33 -> 0.6583 | ... K15: =0.67*IF(ISNUMBER(K14),K14,K13)+0.33 -> 1.5293 | L15: Blume: 0.67 x raw (or override) + 0.33
A16: Beta used | B16: =IF($B$6=1,IF(ISNUMBER(B14),B14,B13),B15) -> 0.6382 | C16: =IF($B$6=1,IF(ISNUMBER(C14),C14,C13),C15) -> 0.5444 | D16: =IF($B$6=1,IF(ISNUMBER(D14),D14,D13),D15) -> 1.1407 | E16: =IF($B$6=1,IF(ISNUMBER(E14),E14,E13),E15) -> 0.7387 | F16: =IF($B$6=1,IF(ISNUMBER(F14),F14,F13),F15) -> 0.866 | G16: =IF($B$6=1,IF(ISNUMBER(G14),G14,G13),G15) -> 0.9933 | H16: =IF($B$6=1,IF(ISNUMBER(H14),H14,H13),H15) -> 1.2144 | I16: =IF($B$6=1,IF(ISNUMBER(I14),I14,I13),I15) -> 0.6583 | ... K16: =IF($B$6=1,IF(ISNUMBER(K14),K14,K13),K15) -> 1.5293 | L16: Per switch in B6
A17: Cost of equity | B17: =$B$7+B16*$B$8 -> 0.08501 | C17: =$B$7+C16*$B$8 -> 0.08032 | D17: =$B$7+D16*$B$8 -> 0.110135 | E17: =$B$7+E16*$B$8 -> 0.090035 | F17: =$B$7+F16*$B$8 -> 0.0964 | G17: =$B$7+G16*$B$8 -> 0.102765 | H17: =$B$7+H16*$B$8 -> 0.11382 | I17: =$B$7+I16*$B$8 -> 0.086015 | ... K17: =$B$7+K16*$B$8 -> 0.129565 | L17: Risk-free + beta x ERP
A18: Pre-tax cost of debt | B18: =$B$7+$B$9 -> 0.0651 | C18: =$B$7+$B$9 -> 0.0651 | D18: =$B$7+$B$9 -> 0.0651 | E18: =$B$7+$B$9 -> 0.0651 | F18: =$B$7+$B$9 -> 0.0651 | G18: =$B$7+$B$9 -> 0.0651 | H18: =$B$7+$B$9 -> 0.0651 | I18: =$B$7+$B$9 -> 0.0651 | ... K18: =$B$7+$B$9 -> 0.0651 | L18: Risk-free + spread
A19: Tax rate | B19: =MO!B9 -> 0.235 | C19: =KO!B9 -> 0.19 | D19: =GOOG!B9 -> 0.17 | E19: =UNH!B9 -> 0.22 | F19: =LNG!B9 -> 0.18 | G19: =NOW!B9 -> 0.2 | H19: =CLS!B9 -> 0.21 | I19: =EPD!B9 -> 0 | J19: =NVDA!B9 -> 0.16 | K19: =FSLR!B9 -> 0.12 | L19: Linked from company sheet
A20: After-tax cost of debt | B20: =B18*(1-B19) -> 0.0498015 | C20: =C18*(1-C19) -> 0.052731 | D20: =D18*(1-D19) -> 0.054033 | E20: =E18*(1-E19) -> 0.050778 | F20: =F18*(1-F19) -> 0.053382 | G20: =G18*(1-G19) -> 0.05208 | H20: =H18*(1-H19) -> 0.051429 | I20: =I18*(1-I19) -> 0.0651 | ... K20: =K18*(1-K19) -> 0.057288
A21: Market value of equity ($B) | B21: =MO!B4*MO!B6 -> 125.1832 | C21: =KO!B4*KO!B6 -> 401.061 | D21: =GOOG!B4*GOOG!B6 -> 3919.3481 | E21: =UNH!B4*UNH!B6 -> 380.03063 | F21: =LNG!B4*LNG!B6 -> 61.464361 | G21: =NOW!B4*NOW!B6 -> 161.5452 | H21: =CLS!B4*CLS!B6 -> 31.102565 | I21: =EPD!B4*EPD!B6 -> 80.7948 | J21: =NVDA!B4*NVDA!B6 -> 5126.562 | K21: =FSLR!B4*FSLR!B6 -> 18.438628 | L21: Price x shares
A22: Debt ($B) | B22: 24.58 | C22: 44.26 | D22: 120.79 | E22: 74.33 | F22: 27.97 | G22: 8.45 | H22: 0.8188 | I22: 34.21 | J22: 38.86 | K22: 0.194 | L22: Stock Analysis, total debt
A23: Equity weight | B23: =B21/(B21+B22) -> 0.83587423 | C23: =C21/(C21+C22) -> 0.90061102 | D23: =D21/(D21+D22) -> 0.97010251 | E23: =E21/(E21+E22) -> 0.83640748 | F23: =F21/(F21+F22) -> 0.68725667 | G23: =G21/(G21+G22) -> 0.95029271 | H23: =H21/(H21+H22) -> 0.97434947 | I23: =I21/(I21+I22) -> 0.70253416 | ... K23: =K21/(K21+K22) -> 0.98958816
A24: Debt weight | B24: =B22/(B21+B22) -> 0.16412577 | C24: =C22/(C21+C22) -> 0.09938898 | D24: =D22/(D21+D22) -> 0.029897493 | E24: =E22/(E21+E22) -> 0.16359252 | F24: =F22/(F21+F22) -> 0.31274333 | G24: =G22/(G21+G22) -> 0.049707286 | H24: =H22/(H21+H22) -> 0.025650532 | I24: =I22/(I21+I22) -> 0.29746584 | ... K24: =K22/(K21+K22) -> 0.010411843
A25: Calculated WACC (CAPM) | B25: =B23*B17+B24*B20 -> 0.079231378 | C25: =C23*C17+C24*C20 -> 0.077577957 | D25: =D23*D17+D24*D20 -> 0.10845769 | E25: =E23*E17+E24*E20 -> 0.083612848 | F25: =F23*F17+F24*F20 -> 0.082946407 | G25: =G23*G17+G24*G20 -> 0.10024559 | H25: =H23*H17+H24*H20 -> 0.11221964 | I25: =I23*I17+I24*I20 -> 0.079793502 | ... K25: =K23*K17+K24*K20 -> 0.12881246 | L25: Weighted cost of capital
A26: Assumed WACC | B26: 0.08 | C26: 0.075 | D26: 0.095 | E26: 0.09 | F26: 0.075 | G26: 0.095 | H26: 0.105 | I26: 0.08 | J26: 0.11 | K26: 0.105 | L26: Analyst assumption used in the doc
A27: WACC used | B27: =IF($B$5=1,B25,B26) -> 0.08 | C27: =IF($B$5=1,C25,C26) -> 0.075 | D27: =IF($B$5=1,D25,D26) -> 0.095 | E27: =IF($B$5=1,E25,E26) -> 0.09 | F27: =IF($B$5=1,F25,F26) -> 0.075 | G27: =IF($B$5=1,G25,G26) -> 0.095 | H27: =IF($B$5=1,H25,H26) -> 0.105 | I27: =IF($B$5=1,I25,I26) -> 0.08 | ... K27: =IF($B$5=1,K25,K26) -> 0.105 | L27: Per switch in B5; feeds each sheet's B10
A28: Check: WACC above every terminal growth rate | B28: =IF(B27>MAX(MO!L21,MO!L39,MO!L57),"OK","WACC must exceed growth") -> OK | C28: =IF(C27>MAX(KO!L21,KO!L39,KO!L57),"OK","WACC must exceed growth") -> OK | D28: =IF(D27>MAX(GOOG!L21,GOOG!L39,GOOG!L57),"OK","WACC must exceed growth") -> OK | E28: =IF(E27>MAX(UNH!L21,UNH!L39,UNH!L57),"OK","WACC must exceed growth") -> OK | F28: =IF(F27>MAX(LNG!L21,LNG!L39,LNG!L57),"OK","WACC must exceed growth") -> OK | G28: =IF(G27>MAX(NOW!L21,NOW!L39,NOW!L57),"OK","WACC must exceed growth") -> OK | H28: =IF(H27>MAX(CLS!L21,CLS!L39,CLS!L57),"OK","WACC must exceed growth") -> OK | I28: =IF(I27>MAX(EPD!L21,EPD!L39,EPD!L57),"OK","WACC must exceed growth") -> OK | J28: =IF(J27>MAX(NVDA!L21,NVDA!L39,NVDA!L57),"OK","WACC must exceed growth") -> OK | K28: =IF(K27>MAX(FSLR!L21,FSLR!L39,FSLR!L57),"OK","WACC must exceed growth") -> OK
A29: Link row read by company sheets | B29: =B27 -> 0.08 | C29: =C27 -> 0.075 | D29: =D27 -> 0.095 | E29: =E27 -> 0.09 | F29: =F27 -> 0.075 | G29: =G27 -> 0.095 | H29: =H27 -> 0.105 | I29: =I27 -> 0.08 | ... K29: =K27 -> 0.105 | L29: Same as WACC used
A33: Bank cost of equity | B33: JPM | C33: BAC | D33: Source / note
A34: Raw beta (5-year) | B34: 1.02 | C34: 1.21 | D34: Stock Analysis statistics, Oct 23, 2026
A35: Adjusted beta | B35: =0.67*B34+0.33 -> 1.0134 | C35: =0.67*C34+0.33 -> 1.1407 | D35: Blume
A36: Beta used | B36: =IF($B$6=1,B34,B35) -> 1.0134 | C36: =IF($B$6=1,C34,C35) -> 1.1407 | D36: Per switch in B6
A37: Calculated cost of equity (CAPM) | B37: =$B$7+B36*$B$8 -> 0.10377 | C37: =$B$7+C36*$B$8 -> 0.110135 | D37: Risk-free + beta x ERP
A38: Assumed cost of equity | B38: 0.1 | C38: 0.105 | D38: Analyst assumption used in the doc
A39: Cost of equity used | B39: =IF($B$5=1,B37,B38) -> 0.1 | C39: =IF($B$5=1,C37,C38) -> 0.105 | D39: Per switch in B5
A40: Link row read by bank sheets | B40: =B39 -> 0.1 | C40: =C39 -> 0.105

Sheet MO
A1: Altria (MO): 10-year scenario DCF
A2: Units: $ billions unless noted. Blue = input, black = formula, green = link, yellow = key lever. Years 6 to 10 fade growth, margin and reinvestment toward each scenario's terminal levels.
A4: Share price ($) | B4: 74.96 | C4: Oct 23, 2026 intraday (Yahoo Finance via the site's price feed)
A5: Price date | B5: Oct 23, 2026 | C5: Text
A6: Shares outstanding (billions) | B6: 1.67 | C6: Stock Analysis statistics, Oct 23, 2026
A7: Net cash, negative = net debt | B7: -22.21 | C7: Stock Analysis statistics, Oct 23, 2026: cash less total debt
A8: Other non-operating assets, less outside claims | B8: 10.81 | C8: ABI stake: 159.1M shares (Schedule 13D/A, May 2026) x $84.93 (Oct 23, 2026), less 20% for tax on sale
A9: Tax rate | B9: 0.235 | C9: Analyst assumption (normalized, near the reported effective rate)
A10: Discount rate (WACC), from WACC tab | B10: =WACC!B29 -> 0.08 | C10: Calculated or assumed, per the switch in WACC!B5
A11: Working capital, % of revenue change | B11: 0 | C11: Analyst assumption
A12: Base-year revenue (2026E) | B12: 20.6 | C12: 2026E consensus $20.6B (Stock Analysis, revenue net of excise taxes)
A13: Selected scenario (1 Bear, 2 Base, 3 Bull) | B13: 2 | C13: Lever
A15: Year | B15: 2027 | C15: 2028 | D15: 2029 | E15: 2030 | F15: 2031 | G15: 2032 | H15: 2033 | I15: 2034 | J15: 2035 | K15: 2036 | L15: Terminal
A16: Discount period (years, mid-year) | B16: 0.5 | C16: =B16+1 -> 1.5 | D16: =C16+1 -> 2.5 | E16: =D16+1 -> 3.5 | F16: =E16+1 -> 4.5 | G16: =F16+1 -> 5.5 | H16: =G16+1 -> 6.5 | I16: =H16+1 -> 7.5 | J16: =I16+1 -> 8.5 | K16: =J16+1 -> 9.5
A17: Fade step (years 6 to 10) | B17: 0 | C17: 0 | D17: 0 | E17: 0 | F17: 0 | G17: 1 | H17: 2 | I17: 3 | J17: 4 | K17: 5
A19: Bear: volume decline speeds up, pricing power fades
A20: Revenue | B20: 20.2 | C20: 19.6 | D20: 19 | E20: 18.4 | F20: 17.8 | G20: =F20*(1+$F21+($L21-$F21)*G$17/5) -> 17.246652 | H20: =G20*(1+$F21+($L21-$F21)*H$17/5) -> 16.736751 | I20: =H20*(1+$F21+($L21-$F21)*I$17/5) -> 16.267394 | J20: =I20*(1+$F21+($L21-$F21)*J$17/5) -> 15.835955 | K20: =J20*(1+$F21+($L21-$F21)*K$17/5) -> 15.440056 | L20: =K20*(1+L21) -> 15.054055
A21: Revenue growth (terminal column = terminal growth, input) | B21: =B20/$B$12-1 -> -0.019417476 | C21: =C20/B20-1 -> -0.02970297 | D21: =D20/C20-1 -> -0.030612245 | E21: =E20/D20-1 -> -0.031578947 | F21: =F20/E20-1 -> -0.032608696 | G21: =G20/F20-1 -> -0.031086957 | H21: =H20/G20-1 -> -0.029565217 | I21: =I20/H20-1 -> -0.028043478 | J21: =J20/I20-1 -> -0.026521739 | K21: =K20/J20-1 -> -0.025 | L21: -0.025
A22: Operating margin | B22: 0.6 | C22: 0.59 | D22: 0.58 | E22: 0.57 | F22: 0.56 | G22: =$F22+($L22-$F22)*G$17/5 -> 0.554 | H22: =$F22+($L22-$F22)*H$17/5 -> 0.548 | I22: =$F22+($L22-$F22)*I$17/5 -> 0.542 | J22: =$F22+($L22-$F22)*J$17/5 -> 0.536 | K22: =$F22+($L22-$F22)*K$17/5 -> 0.53 | L22: 0.53
A23: Operating income | B23: =B20*B22 -> 12.12 | C23: =C20*C22 -> 11.564 | D23: =D20*D22 -> 11.02 | E23: =E20*E22 -> 10.488 | F23: =F20*F22 -> 9.968 | G23: =G20*G22 -> 9.5546453 | H23: =H20*H22 -> 9.1717396 | I23: =I20*I22 -> 8.8169278 | ... L23: =L20*L22 -> 7.9786489
A24: NOPAT | B24: =B23*(1-$B$9) -> 9.2718 | C24: =C23*(1-$B$9) -> 8.84646 | D24: =D23*(1-$B$9) -> 8.4303 | E24: =E23*(1-$B$9) -> 8.02332 | F24: =F23*(1-$B$9) -> 7.62552 | G24: =G23*(1-$B$9) -> 7.3093037 | H24: =H23*(1-$B$9) -> 7.0163808 | I24: =I23*(1-$B$9) -> 6.7449498 | ... L24: =L23*(1-$B$9) -> 6.1036664
A25: Net reinvestment, % of revenue | B25: 0.005 | C25: 0.005 | D25: 0.005 | E25: 0.005 | F25: 0.005 | G25: =$F25+($L25-$F25)*G$17/5 -> 0.005 | H25: =$F25+($L25-$F25)*H$17/5 -> 0.005 | I25: =$F25+($L25-$F25)*I$17/5 -> 0.005 | J25: =$F25+($L25-$F25)*J$17/5 -> 0.005 | K25: =$F25+($L25-$F25)*K$17/5 -> 0.005 | L25: 0.005
A26: Net reinvestment | B26: =B20*B25 -> 0.101 | C26: =C20*C25 -> 0.098 | D26: =D20*D25 -> 0.095 | E26: =E20*E25 -> 0.092 | F26: =F20*F25 -> 0.089 | G26: =G20*G25 -> 0.086233261 | H26: =H20*H25 -> 0.083683756 | I26: =I20*I25 -> 0.081336972 | ... L26: =L20*L25 -> 0.075270273
A27: Change in working capital | B27: =$B$11*(B20-$B$12) -> 0 | C27: =$B$11*(C20-B20) -> 0 | D27: =$B$11*(D20-C20) -> 0 | E27: =$B$11*(E20-D20) -> 0 | F27: =$B$11*(F20-E20) -> 0 | G27: =$B$11*(G20-F20) -> 0 | H27: =$B$11*(H20-G20) -> 0 | I27: =$B$11*(I20-H20) -> 0 | J27: =$B$11*(J20-I20) -> 0 | ... L27: =$B$11*(L20-K20) -> 0
A28: Free cash flow | B28: =B24-B26-B27 -> 9.1708 | C28: =C24-C26-C27 -> 8.74846 | D28: =D24-D26-D27 -> 8.3353 | E28: =E24-E26-E27 -> 7.93132 | F28: =F24-F26-F27 -> 7.53652 | G28: =G24-G26-G27 -> 7.2230704 | H28: =H24-H26-H27 -> 6.9326971 | I28: =I24-I26-I27 -> 6.6636128 | ... L28: =L24-L26-L27 -> 6.0283962
A29: Discount factor | B29: =1/(1+$B$10)^B$16 -> 0.96225045 | C29: =1/(1+$B$10)^C$16 -> 0.89097264 | D29: =1/(1+$B$10)^D$16 -> 0.82497466 | E29: =1/(1+$B$10)^E$16 -> 0.76386543 | F29: =1/(1+$B$10)^F$16 -> 0.70728281 | G29: =1/(1+$B$10)^G$16 -> 0.65489149 | H29: =1/(1+$B$10)^H$16 -> 0.60638101 | I29: =1/(1+$B$10)^I$16 -> 0.56146389 | ... K29: =1/(1+$B$10)^K$16 -> 0.48136479
A30: PV of free cash flow | B30: =B28*B29 -> 8.8246064 | C30: =C28*C29 -> 7.7946385 | D30: =D28*D29 -> 6.8764113 | E30: =E28*E29 -> 6.0584612 | F30: =F28*F29 -> 5.330451 | G30: =G28*G29 -> 4.7303273 | H30: =H28*H29 -> 4.2038558 | I30: =I28*I29 -> 3.741378 | ... K30: =K28*K29 -> 2.9762643
A31: Terminal value | B31: =L28/($B$10-L21) -> 57.413297 | C31: =IF($B$10>L21,"","Discount rate must exceed terminal growth")
A32: PV of terminal value | B32: =B31/(1+$B$10)^$K$16 -> 27.63674
A33: Equity value (PV FCF + PV TV + net cash + other) | B33: =SUM(B30:K30)+B32+$B$7+$B$8 -> 70.107707
A34: Value per share ($) | B34: =B33/$B$6 -> 41.980663
A35: Value vs share price | B35: =B34/$B$4-1 -> -0.43995914
A37: Base: price offsets volume, flat revenue
A38: Revenue | B38: 20.7 | C38: 20.7 | D38: 20.7 | E38: 20.6 | F38: 20.6 | G38: =F38*(1+$F39+($L39-$F39)*G$17/5) -> 20.5794 | H38: =G38*(1+$F39+($L39-$F39)*H$17/5) -> 20.538241 | I38: =H38*(1+$F39+($L39-$F39)*I$17/5) -> 20.476626 | J38: =I38*(1+$F39+($L39-$F39)*J$17/5) -> 20.39472 | K38: =J38*(1+$F39+($L39-$F39)*K$17/5) -> 20.292746 | L38: =K38*(1+L39) -> 20.191283
A39: Revenue growth (terminal column = terminal growth, input) | B39: =B38/$B$12-1 -> 0.0048543689 | C39: =C38/B38-1 -> 0 | D39: =D38/C38-1 -> 0 | E39: =E38/D38-1 -> -0.0048309179 | F39: =F38/E38-1 -> 0 | G39: =G38/F38-1 -> -0.001 | H39: =H38/G38-1 -> -0.002 | I39: =I38/H38-1 -> -0.003 | J39: =J38/I38-1 -> -0.004 | K39: =K38/J38-1 -> -0.005 | L39: -0.005
A40: Operating margin | B40: 0.61 | C40: 0.61 | D40: 0.61 | E40: 0.61 | F40: 0.61 | G40: =$F40+($L40-$F40)*G$17/5 -> 0.606 | H40: =$F40+($L40-$F40)*H$17/5 -> 0.602 | I40: =$F40+($L40-$F40)*I$17/5 -> 0.598 | J40: =$F40+($L40-$F40)*J$17/5 -> 0.594 | K40: =$F40+($L40-$F40)*K$17/5 -> 0.59 | L40: 0.59
A41: Operating income | B41: =B38*B40 -> 12.627 | C41: =C38*C40 -> 12.627 | D41: =D38*D40 -> 12.627 | E41: =E38*E40 -> 12.566 | F41: =F38*F40 -> 12.566 | G41: =G38*G40 -> 12.471116 | H41: =H38*H40 -> 12.364021 | I41: =I38*I40 -> 12.245023 | ... L41: =L38*L40 -> 11.912857
A42: NOPAT | B42: =B41*(1-$B$9) -> 9.659655 | C42: =C41*(1-$B$9) -> 9.659655 | D42: =D41*(1-$B$9) -> 9.659655 | E42: =E41*(1-$B$9) -> 9.61299 | F42: =F41*(1-$B$9) -> 9.61299 | G42: =G41*(1-$B$9) -> 9.540404 | H42: =H41*(1-$B$9) -> 9.4584762 | I42: =I41*(1-$B$9) -> 9.3674423 | ... L42: =L41*(1-$B$9) -> 9.1133354
A43: Net reinvestment, % of revenue | B43: 0.005 | C43: 0.005 | D43: 0.005 | E43: 0.005 | F43: 0.005 | G43: =$F43+($L43-$F43)*G$17/5 -> 0.005 | H43: =$F43+($L43-$F43)*H$17/5 -> 0.005 | I43: =$F43+($L43-$F43)*I$17/5 -> 0.005 | J43: =$F43+($L43-$F43)*J$17/5 -> 0.005 | K43: =$F43+($L43-$F43)*K$17/5 -> 0.005 | L43: 0.005
A44: Net reinvestment | B44: =B38*B43 -> 0.1035 | C44: =C38*C43 -> 0.1035 | D44: =D38*D43 -> 0.1035 | E44: =E38*E43 -> 0.103 | F44: =F38*F43 -> 0.103 | G44: =G38*G43 -> 0.102897 | H44: =H38*H43 -> 0.10269121 | I44: =I38*I43 -> 0.10238313 | ... L44: =L38*L43 -> 0.10095641
A45: Change in working capital | B45: =$B$11*(B38-$B$12) -> 0 | C45: =$B$11*(C38-B38) -> 0 | D45: =$B$11*(D38-C38) -> 0 | E45: =$B$11*(E38-D38) -> 0 | F45: =$B$11*(F38-E38) -> 0 | G45: =$B$11*(G38-F38) -> 0 | H45: =$B$11*(H38-G38) -> 0 | I45: =$B$11*(I38-H38) -> 0 | J45: =$B$11*(J38-I38) -> 0 | ... L45: =$B$11*(L38-K38) -> 0
A46: Free cash flow | B46: =B42-B44-B45 -> 9.556155 | C46: =C42-C44-C45 -> 9.556155 | D46: =D42-D44-D45 -> 9.556155 | E46: =E42-E44-E45 -> 9.50999 | F46: =F42-F44-F45 -> 9.50999 | G46: =G42-G44-G45 -> 9.437507 | H46: =H42-H44-H45 -> 9.355785 | I46: =I42-I44-I45 -> 9.2650592 | ... L46: =L42-L44-L45 -> 9.012379
A47: Discount factor | B47: =1/(1+$B$10)^B$16 -> 0.96225045 | C47: =1/(1+$B$10)^C$16 -> 0.89097264 | D47: =1/(1+$B$10)^D$16 -> 0.82497466 | E47: =1/(1+$B$10)^E$16 -> 0.76386543 | F47: =1/(1+$B$10)^F$16 -> 0.70728281 | G47: =1/(1+$B$10)^G$16 -> 0.65489149 | H47: =1/(1+$B$10)^H$16 -> 0.60638101 | I47: =1/(1+$B$10)^I$16 -> 0.56146389 | ... K47: =1/(1+$B$10)^K$16 -> 0.48136479
A48: PV of free cash flow | B48: =B46*B47 -> 9.1954144 | C48: =C46*C47 -> 8.5142726 | D48: =D46*D47 -> 7.8835858 | E48: =E46*E47 -> 7.2643526 | F48: =F46*F47 -> 6.7262524 | G48: =G46*G47 -> 6.180543 | H48: =H46*H47 -> 5.6731703 | I48: =I46*I47 -> 5.2019962 | ... K48: =K46*K47 -> 4.3600422
A49: Terminal value | B49: =L46/($B$10-L39) -> 106.02799 | C49: =IF($B$10>L39,"","Discount rate must exceed terminal growth")
A50: PV of terminal value | B50: =B49/(1+$B$10)^$K$16 -> 51.038141
A51: Equity value (PV FCF + PV TV + net cash + other) | B51: =SUM(B48:K48)+B50+$B$7+$B$8 -> 105.40272
A52: Value per share ($) | B52: =B51/$B$6 -> 63.115403
A53: Value vs share price | B53: =B52/$B$4-1 -> -0.15801224
A55: Bull: smoke-free products add growth
A56: Revenue | B56: 20.9 | C56: 21.3 | D56: 21.7 | E56: 22.1 | F56: 22.5 | G56: =F56*(1+$F57+($L57-$F57)*G$17/5) -> 22.870792 | H56: =G56*(1+$F57+($L57-$F57)*H$17/5) -> 23.210646 | I56: =H56*(1+$F57+($L57-$F57)*I$17/5) -> 23.51795 | J56: =I56*(1+$F57+($L57-$F57)*J$17/5) -> 23.791227 | K56: =J56*(1+$F57+($L57-$F57)*K$17/5) -> 24.029139 | L56: =K56*(1+L57) -> 24.26943
A57: Revenue growth (terminal column = terminal growth, input) | B57: =B56/$B$12-1 -> 0.014563107 | C57: =C56/B56-1 -> 0.019138756 | D57: =D56/C56-1 -> 0.018779343 | E57: =E56/D56-1 -> 0.01843318 | F57: =F56/E56-1 -> 0.018099548 | G57: =G56/F56-1 -> 0.016479638 | H57: =H56/G56-1 -> 0.014859729 | I57: =I56/H56-1 -> 0.013239819 | J57: =J56/I56-1 -> 0.01161991 | K57: =K56/J56-1 -> 0.01 | L57: 0.01
A58: Operating margin | B58: 0.615 | C58: 0.62 | D58: 0.62 | E58: 0.62 | F58: 0.62 | G58: =$F58+($L58-$F58)*G$17/5 -> 0.618 | H58: =$F58+($L58-$F58)*H$17/5 -> 0.616 | I58: =$F58+($L58-$F58)*I$17/5 -> 0.614 | J58: =$F58+($L58-$F58)*J$17/5 -> 0.612 | K58: =$F58+($L58-$F58)*K$17/5 -> 0.61 | L58: 0.61
A59: Operating income | B59: =B56*B58 -> 12.8535 | C59: =C56*C58 -> 13.206 | D59: =D56*D58 -> 13.454 | E59: =E56*E58 -> 13.702 | F59: =F56*F58 -> 13.95 | G59: =G56*G58 -> 14.134149 | H59: =H56*H58 -> 14.297758 | I59: =I56*I58 -> 14.440022 | ... L59: =L56*L58 -> 14.804353
A60: NOPAT | B60: =B59*(1-$B$9) -> 9.8329275 | C60: =C59*(1-$B$9) -> 10.10259 | D60: =D59*(1-$B$9) -> 10.29231 | E60: =E59*(1-$B$9) -> 10.48203 | F60: =F59*(1-$B$9) -> 10.67175 | G60: =G59*(1-$B$9) -> 10.812624 | H60: =H59*(1-$B$9) -> 10.937785 | I60: =I59*(1-$B$9) -> 11.046616 | ... L60: =L59*(1-$B$9) -> 11.32533
A61: Net reinvestment, % of revenue | B61: 0.006 | C61: 0.006 | D61: 0.006 | E61: 0.006 | F61: 0.006 | G61: =$F61+($L61-$F61)*G$17/5 -> 0.006 | H61: =$F61+($L61-$F61)*H$17/5 -> 0.006 | I61: =$F61+($L61-$F61)*I$17/5 -> 0.006 | J61: =$F61+($L61-$F61)*J$17/5 -> 0.006 | K61: =$F61+($L61-$F61)*K$17/5 -> 0.006 | L61: 0.006
A62: Net reinvestment | B62: =B56*B61 -> 0.1254 | C62: =C56*C61 -> 0.1278 | D62: =D56*D61 -> 0.1302 | E62: =E56*E61 -> 0.1326 | F62: =F56*F61 -> 0.135 | G62: =G56*G61 -> 0.13722475 | H62: =H56*H61 -> 0.13926387 | I62: =I56*I61 -> 0.1411077 | ... L62: =L56*L61 -> 0.14561658
A63: Change in working capital | B63: =$B$11*(B56-$B$12) -> 0 | C63: =$B$11*(C56-B56) -> 0 | D63: =$B$11*(D56-C56) -> 0 | E63: =$B$11*(E56-D56) -> 0 | F63: =$B$11*(F56-E56) -> 0 | G63: =$B$11*(G56-F56) -> 0 | H63: =$B$11*(H56-G56) -> 0 | I63: =$B$11*(I56-H56) -> 0 | J63: =$B$11*(J56-I56) -> 0 | ... L63: =$B$11*(L56-K56) -> 0
A64: Free cash flow | B64: =B60-B62-B63 -> 9.7075275 | C64: =C60-C62-C63 -> 9.97479 | D64: =D60-D62-D63 -> 10.16211 | E64: =E60-E62-E63 -> 10.34943 | F64: =F60-F62-F63 -> 10.53675 | G64: =G60-G62-G63 -> 10.6754 | H64: =H60-H62-H63 -> 10.798521 | I64: =I60-I62-I63 -> 10.905509 | ... L64: =L60-L62-L63 -> 11.179713
A65: Discount factor | B65: =1/(1+$B$10)^B$16 -> 0.96225045 | C65: =1/(1+$B$10)^C$16 -> 0.89097264 | D65: =1/(1+$B$10)^D$16 -> 0.82497466 | E65: =1/(1+$B$10)^E$16 -> 0.76386543 | F65: =1/(1+$B$10)^F$16 -> 0.70728281 | G65: =1/(1+$B$10)^G$16 -> 0.65489149 | H65: =1/(1+$B$10)^H$16 -> 0.60638101 | I65: =1/(1+$B$10)^I$16 -> 0.56146389 | ... K65: =1/(1+$B$10)^K$16 -> 0.48136479
A66: PV of free cash flow | B66: =B64*B65 -> 9.3410727 | C66: =C64*C65 -> 8.887265 | D66: =D64*D65 -> 8.3834833 | E66: =E64*E65 -> 7.9055718 | F66: =F64*F65 -> 7.4524621 | G66: =G64*G65 -> 6.9912283 | H66: =H64*H65 -> 6.5480179 | I66: =I64*I65 -> 6.1230494 | ... K66: =K64*K65 -> 5.3282379
A67: Terminal value | B67: =L64/($B$10-L57) -> 159.71019 | C67: =IF($B$10>L57,"","Discount rate must exceed terminal growth")
A68: PV of terminal value | B68: =B67/(1+$B$10)^$K$16 -> 76.878862
A69: Equity value (PV FCF + PV TV + net cash + other) | B69: =SUM(B66:K66)+B68+$B$7+$B$8 -> 138.1557
A70: Value per share ($) | B70: =B69/$B$6 -> 82.727961
A71: Value vs share price | B71: =B70/$B$4-1 -> 0.10362809
A74: Outputs | C74: vs price
A75: Bear value per share | B75: =B34 -> 41.980663 | C75: =B75/$B$4-1 -> -0.43995914
A76: Base value per share | B76: =B52 -> 63.115403 | C76: =B76/$B$4-1 -> -0.15801224
A77: Bull value per share | B77: =B70 -> 82.727961 | C77: =B77/$B$4-1 -> 0.10362809
A78: Selected scenario value per share | B78: =INDEX(B34:B70,1+($B$13-1)*18) -> 63.115403 | C78: =B78/$B$4-1 -> -0.15801224
A79: Share of base value from terminal value | B79: =B50/(SUM(B48:K48)+B50) -> 0.4369602
A81: Base value per share at other discount rates
A82: Discount rate | B82: 0.05 | C82: 0.06 | D82: 0.07 | E82: 0.08 | F82: 0.09 | G82: 0.1 | H82: 0.11 | I82: 0.12 | J82: 0.13 | K82: 0.14
A83: Base value per share | B83: =IF(B82>$L39,(SUMPRODUCT($B46:$K46/(1+B82)^$B$16:$K$16)+$L46/(B82-$L39)/(1+B82)^$K$16+$B$7+$B$8)/$B$6,"n/a") -> 99.525283 | C83: =IF(C82>$L39,(SUMPRODUCT($B46:$K46/(1+C82)^$B$16:$K$16)+$L46/(C82-$L39)/(1+C82)^$K$16+$B$7+$B$8)/$B$6,"n/a") -> 83.662099 | D83: =IF(D82>$L39,(SUMPRODUCT($B46:$K46/(1+D82)^$B$16:$K$16)+$L46/(D82-$L39)/(1+D82)^$K$16+$B$7+$B$8)/$B$6,"n/a") -> 72.022187 | E83: =IF(E82>$L39,(SUMPRODUCT($B46:$K46/(1+E82)^$B$16:$K$16)+$L46/(E82-$L39)/(1+E82)^$K$16+$B$7+$B$8)/$B$6,"n/a") -> 63.115403 | F83: =IF(F82>$L39,(SUMPRODUCT($B46:$K46/(1+F82)^$B$16:$K$16)+$L46/(F82-$L39)/(1+F82)^$K$16+$B$7+$B$8)/$B$6,"n/a") -> 56.078995 | G83: =IF(G82>$L39,(SUMPRODUCT($B46:$K46/(1+G82)^$B$16:$K$16)+$L46/(G82-$L39)/(1+G82)^$K$16+$B$7+$B$8)/$B$6,"n/a") -> 50.378854 | H83: =IF(H82>$L39,(SUMPRODUCT($B46:$K46/(1+H82)^$B$16:$K$16)+$L46/(H82-$L39)/(1+H82)^$K$16+$B$7+$B$8)/$B$6,"n/a") -> 45.666621 | I83: =IF(I82>$L39,(SUMPRODUCT($B46:$K46/(1+I82)^$B$16:$K$16)+$L46/(I82-$L39)/(1+I82)^$K$16+$B$7+$B$8)/$B$6,"n/a") -> 41.705397 | ... K83: =IF(K82>$L39,(SUMPRODUCT($B46:$K46/(1+K82)^$B$16:$K$16)+$L46/(K82-$L39)/(1+K82)^$K$16+$B$7+$B$8)/$B$6,"n/a") -> 35.415055
A84: vs share price | B84: =IFERROR(B83/$B$4-1,"n/a") -> 0.32771189 | C84: =IFERROR(C83/$B$4-1,"n/a") -> 0.11608991 | D84: =IFERROR(D83/$B$4-1,"n/a") -> -0.039191736 | E84: =IFERROR(E83/$B$4-1,"n/a") -> -0.15801224 | F84: =IFERROR(F83/$B$4-1,"n/a") -> -0.25188107 | G84: =IFERROR(G83/$B$4-1,"n/a") -> -0.32792351 | H84: =IFERROR(H83/$B$4-1,"n/a") -> -0.3907868 | I84: =IFERROR(I83/$B$4-1,"n/a") -> -0.44363131 | ... K84: =IFERROR(K83/$B$4-1,"n/a") -> -0.52754729
A86: Implied annual return at today's price, base case | B86: =IFERROR(IF(MATCH($B$4,$B$83:$K$83,-1)=10,"above 14%",INDEX($B$82:$K$82,MATCH($B$4,$B$83:$K$83,-1))+(INDEX($B$83:$K$83,MATCH($B$4,$B$83:$K$83,-1))-$B$4)/(INDEX($B$83:$K$83,MATCH($B$4,$B$83:$K$83,-1))-INDEX($B$83:$K$83,MATCH($B$4,$B$83:$K$83,-1)+1))*(INDEX($B$82:$K$82,MATCH($B$4,$B$83:$K$83,-1)+1)-INDEX($B$82:$K$82,MATCH($B$4,$B$83:$K$83,-1)))),"below 5%") -> 0.067476087 | C86: Discount rate at which base value equals the price (interpolated from the row above)

Sheet KO
A1: Coca-Cola (KO): 10-year scenario DCF
A2: Units: $ billions unless noted. Blue = input, black = formula, green = link, yellow = key lever. Years 6 to 10 fade growth, margin and reinvestment toward each scenario's terminal levels.
A4: Share price ($) | B4: 93.27 | C4: Oct 23, 2026 intraday (Yahoo Finance via the site's price feed)
A5: Price date | B5: Oct 23, 2026 | C5: Text
A6: Shares outstanding (billions) | B6: 4.3 | C6: Stock Analysis statistics, Oct 23, 2026
A7: Net cash, negative = net debt | B7: -27.89 | C7: Stock Analysis statistics, Oct 23, 2026: cash less total debt
A8: Other non-operating assets, less outside claims | B8: 20.78 | C8: Equity-method investments (bottlers) at book, $20.78B (10-Q, Jul 3, 2026); fair value likely higher
A9: Tax rate | B9: 0.19 | C9: Analyst assumption (normalized, near the reported effective rate)
A10: Discount rate (WACC), from WACC tab | B10: =WACC!C29 -> 0.075 | C10: Calculated or assumed, per the switch in WACC!B5
A11: Working capital, % of revenue change | B11: 0 | C11: Analyst assumption
A12: Base-year revenue (2026E) | B12: 49.8 | C12: 2026E consensus $49.8B (Stock Analysis)
A13: Selected scenario (1 Bear, 2 Base, 3 Bull) | B13: 2 | C13: Lever
A15: Year | B15: 2027 | C15: 2028 | D15: 2029 | E15: 2030 | F15: 2031 | G15: 2032 | H15: 2033 | I15: 2034 | J15: 2035 | K15: 2036 | L15: Terminal
A16: Discount period (years, mid-year) | B16: 0.5 | C16: =B16+1 -> 1.5 | D16: =C16+1 -> 2.5 | E16: =D16+1 -> 3.5 | F16: =E16+1 -> 4.5 | G16: =F16+1 -> 5.5 | H16: =G16+1 -> 6.5 | I16: =H16+1 -> 7.5 | J16: =I16+1 -> 8.5 | K16: =J16+1 -> 9.5
A17: Fade step (years 6 to 10) | B17: 0 | C17: 0 | D17: 0 | E17: 0 | F17: 0 | G17: 1 | H17: 2 | I17: 3 | J17: 4 | K17: 5
A19: Bear: volumes stall, currency drag
A20: Revenue | B20: 51 | C20: 52.3 | D20: 53.6 | E20: 54.9 | F20: 56.2 | G20: =F20*(1+$F21+($L21-$F21)*G$17/5) -> 57.545627 | H20: =G20*(1+$F21+($L21-$F21)*H$17/5) -> 58.938671 | I20: =H20*(1+$F21+($L21-$F21)*I$17/5) -> 60.381004 | J20: =I20*(1+$F21+($L21-$F21)*J$17/5) -> 61.874582 | K20: =J20*(1+$F21+($L21-$F21)*K$17/5) -> 63.421446 | L20: =K20*(1+L21) -> 65.006983
A21: Revenue growth (terminal column = terminal growth, input) | B21: =B20/$B$12-1 -> 0.024096386 | C21: =C20/B20-1 -> 0.025490196 | D21: =D20/C20-1 -> 0.024856597 | E21: =E20/D20-1 -> 0.024253731 | F21: =F20/E20-1 -> 0.023679417 | G21: =G20/F20-1 -> 0.023943534 | H21: =H20/G20-1 -> 0.02420765 | I21: =I20/H20-1 -> 0.024471767 | J21: =J20/I20-1 -> 0.024735883 | K21: =K20/J20-1 -> 0.025 | L21: 0.025
A22: Operating margin | B22: 0.31 | C22: 0.31 | D22: 0.31 | E22: 0.31 | F22: 0.31 | G22: =$F22+($L22-$F22)*G$17/5 -> 0.308 | H22: =$F22+($L22-$F22)*H$17/5 -> 0.306 | I22: =$F22+($L22-$F22)*I$17/5 -> 0.304 | J22: =$F22+($L22-$F22)*J$17/5 -> 0.302 | K22: =$F22+($L22-$F22)*K$17/5 -> 0.3 | L22: 0.3
A23: Operating income | B23: =B20*B22 -> 15.81 | C23: =C20*C22 -> 16.213 | D23: =D20*D22 -> 16.616 | E23: =E20*E22 -> 17.019 | F23: =F20*F22 -> 17.422 | G23: =G20*G22 -> 17.724053 | H23: =H20*H22 -> 18.035233 | I23: =I20*I22 -> 18.355825 | ... L23: =L20*L22 -> 19.502095
A24: NOPAT | B24: =B23*(1-$B$9) -> 12.8061 | C24: =C23*(1-$B$9) -> 13.13253 | D24: =D23*(1-$B$9) -> 13.45896 | E24: =E23*(1-$B$9) -> 13.78539 | F24: =F23*(1-$B$9) -> 14.11182 | G24: =G23*(1-$B$9) -> 14.356483 | H24: =H23*(1-$B$9) -> 14.608539 | I24: =I23*(1-$B$9) -> 14.868219 | ... L24: =L23*(1-$B$9) -> 15.796697
A25: Net reinvestment, % of revenue | B25: 0.02 | C25: 0.02 | D25: 0.02 | E25: 0.02 | F25: 0.02 | G25: =$F25+($L25-$F25)*G$17/5 -> 0.02 | H25: =$F25+($L25-$F25)*H$17/5 -> 0.02 | I25: =$F25+($L25-$F25)*I$17/5 -> 0.02 | J25: =$F25+($L25-$F25)*J$17/5 -> 0.02 | K25: =$F25+($L25-$F25)*K$17/5 -> 0.02 | L25: 0.02
A26: Net reinvestment | B26: =B20*B25 -> 1.02 | C26: =C20*C25 -> 1.046 | D26: =D20*D25 -> 1.072 | E26: =E20*E25 -> 1.098 | F26: =F20*F25 -> 1.124 | G26: =G20*G25 -> 1.1509125 | H26: =H20*H25 -> 1.1787734 | I26: =I20*I25 -> 1.2076201 | ... L26: =L20*L25 -> 1.3001397
A27: Change in working capital | B27: =$B$11*(B20-$B$12) -> 0 | C27: =$B$11*(C20-B20) -> 0 | D27: =$B$11*(D20-C20) -> 0 | E27: =$B$11*(E20-D20) -> 0 | F27: =$B$11*(F20-E20) -> 0 | G27: =$B$11*(G20-F20) -> 0 | H27: =$B$11*(H20-G20) -> 0 | I27: =$B$11*(I20-H20) -> 0 | J27: =$B$11*(J20-I20) -> 0 | ... L27: =$B$11*(L20-K20) -> 0
A28: Free cash flow | B28: =B24-B26-B27 -> 11.7861 | C28: =C24-C26-C27 -> 12.08653 | D28: =D24-D26-D27 -> 12.38696 | E28: =E24-E26-E27 -> 12.68739 | F28: =F24-F26-F27 -> 12.98782 | G28: =G24-G26-G27 -> 13.20557 | H28: =H24-H26-H27 -> 13.429766 | I28: =I24-I26-I27 -> 13.660598 | ... L28: =L24-L26-L27 -> 14.496557
A29: Discount factor | B29: =1/(1+$B$10)^B$16 -> 0.96448564 | C29: =1/(1+$B$10)^C$16 -> 0.89719595 | D29: =1/(1+$B$10)^D$16 -> 0.83460088 | E29: =1/(1+$B$10)^E$16 -> 0.77637291 | F29: =1/(1+$B$10)^F$16 -> 0.72220736 | G29: =1/(1+$B$10)^G$16 -> 0.6718208 | H29: =1/(1+$B$10)^H$16 -> 0.62494958 | I29: =1/(1+$B$10)^I$16 -> 0.58134845 | ... K29: =1/(1+$B$10)^K$16 -> 0.50305977
A30: PV of free cash flow | B30: =B28*B29 -> 11.367524 | C30: =C28*C29 -> 10.843986 | D30: =D28*D29 -> 10.338168 | E30: =E28*E29 -> 9.8501459 | F30: =F28*F29 -> 9.3798992 | G30: =G28*G29 -> 8.8717769 | H30: =H28*H29 -> 8.3929264 | I30: =I28*I29 -> 7.9415677 | ... K30: =K28*K29 -> 7.1147656
A31: Terminal value | B31: =L28/($B$10-L21) -> 289.93114 | C31: =IF($B$10>L21,"","Discount rate must exceed terminal growth")
A32: PV of terminal value | B32: =B31/(1+$B$10)^$K$16 -> 145.85269
A33: Equity value (PV FCF + PV TV + net cash + other) | B33: =SUM(B30:K30)+B32+$B$7+$B$8 -> 230.35949
A34: Value per share ($) | B34: =B33/$B$6 -> 53.571974
A35: Value vs share price | B35: =B34/$B$4-1 -> -0.42562481
A37: Base: mid-single-digit organic growth
A38: Revenue | B38: 52.3 | C38: 54.9 | D38: 57.6 | E38: 60.3 | F38: 63.1 | G38: =F38*(1+$F39+($L39-$F39)*G$17/5) -> 65.822613 | H38: =G38*(1+$F39+($L39-$F39)*H$17/5) -> 68.446348 | I38: =H38*(1+$F39+($L39-$F39)*I$17/5) -> 70.949691 | J38: =I38*(1+$F39+($L39-$F39)*J$17/5) -> 73.311387 | K38: =J38*(1+$F39+($L39-$F39)*K$17/5) -> 75.510728 | L38: =K38*(1+L39) -> 77.77605
A39: Revenue growth (terminal column = terminal growth, input) | B39: =B38/$B$12-1 -> 0.050200803 | C39: =C38/B38-1 -> 0.049713193 | D39: =D38/C38-1 -> 0.049180328 | E39: =E38/D38-1 -> 0.046875 | F39: =F38/E38-1 -> 0.046434494 | G39: =G38/F38-1 -> 0.043147595 | H39: =H38/G38-1 -> 0.039860697 | I39: =I38/H38-1 -> 0.036573798 | J39: =J38/I38-1 -> 0.033286899 | K39: =K38/J38-1 -> 0.03 | L39: 0.03
A40: Operating margin | B40: 0.32 | C40: 0.325 | D40: 0.33 | E40: 0.33 | F40: 0.33 | G40: =$F40+($L40-$F40)*G$17/5 -> 0.328 | H40: =$F40+($L40-$F40)*H$17/5 -> 0.326 | I40: =$F40+($L40-$F40)*I$17/5 -> 0.324 | J40: =$F40+($L40-$F40)*J$17/5 -> 0.322 | K40: =$F40+($L40-$F40)*K$17/5 -> 0.32 | L40: 0.32
A41: Operating income | B41: =B38*B40 -> 16.736 | C41: =C38*C40 -> 17.8425 | D41: =D38*D40 -> 19.008 | E41: =E38*E40 -> 19.899 | F41: =F38*F40 -> 20.823 | G41: =G38*G40 -> 21.589817 | H41: =H38*H40 -> 22.31351 | I41: =I38*I40 -> 22.9877 | ... L41: =L38*L40 -> 24.888336
A42: NOPAT | B42: =B41*(1-$B$9) -> 13.55616 | C42: =C41*(1-$B$9) -> 14.452425 | D42: =D41*(1-$B$9) -> 15.39648 | E42: =E41*(1-$B$9) -> 16.11819 | F42: =F41*(1-$B$9) -> 16.86663 | G42: =G41*(1-$B$9) -> 17.487752 | H42: =H41*(1-$B$9) -> 18.073943 | I42: =I41*(1-$B$9) -> 18.620037 | ... L42: =L41*(1-$B$9) -> 20.159552
A43: Net reinvestment, % of revenue | B43: 0.02 | C43: 0.02 | D43: 0.02 | E43: 0.02 | F43: 0.02 | G43: =$F43+($L43-$F43)*G$17/5 -> 0.02 | H43: =$F43+($L43-$F43)*H$17/5 -> 0.02 | I43: =$F43+($L43-$F43)*I$17/5 -> 0.02 | J43: =$F43+($L43-$F43)*J$17/5 -> 0.02 | K43: =$F43+($L43-$F43)*K$17/5 -> 0.02 | L43: 0.02
A44: Net reinvestment | B44: =B38*B43 -> 1.046 | C44: =C38*C43 -> 1.098 | D44: =D38*D43 -> 1.152 | E44: =E38*E43 -> 1.206 | F44: =F38*F43 -> 1.262 | G44: =G38*G43 -> 1.3164523 | H44: =H38*H43 -> 1.368927 | I44: =I38*I43 -> 1.4189938 | ... L44: =L38*L43 -> 1.555521
A45: Change in working capital | B45: =$B$11*(B38-$B$12) -> 0 | C45: =$B$11*(C38-B38) -> 0 | D45: =$B$11*(D38-C38) -> 0 | E45: =$B$11*(E38-D38) -> 0 | F45: =$B$11*(F38-E38) -> 0 | G45: =$B$11*(G38-F38) -> 0 | H45: =$B$11*(H38-G38) -> 0 | I45: =$B$11*(I38-H38) -> 0 | J45: =$B$11*(J38-I38) -> 0 | ... L45: =$B$11*(L38-K38) -> 0
A46: Free cash flow | B46: =B42-B44-B45 -> 12.51016 | C46: =C42-C44-C45 -> 13.354425 | D46: =D42-D44-D45 -> 14.24448 | E46: =E42-E44-E45 -> 14.91219 | F46: =F42-F44-F45 -> 15.60463 | G46: =G42-G44-G45 -> 16.1713 | H46: =H42-H44-H45 -> 16.705016 | I46: =I42-I44-I45 -> 17.201043 | ... L46: =L42-L44-L45 -> 18.604031
A47: Discount factor | B47: =1/(1+$B$10)^B$16 -> 0.96448564 | C47: =1/(1+$B$10)^C$16 -> 0.89719595 | D47: =1/(1+$B$10)^D$16 -> 0.83460088 | E47: =1/(1+$B$10)^E$16 -> 0.77637291 | F47: =1/(1+$B$10)^F$16 -> 0.72220736 | G47: =1/(1+$B$10)^G$16 -> 0.6718208 | H47: =1/(1+$B$10)^H$16 -> 0.62494958 | I47: =1/(1+$B$10)^I$16 -> 0.58134845 | ... K47: =1/(1+$B$10)^K$16 -> 0.50305977
A48: PV of free cash flow | B48: =B46*B47 -> 12.06587 | C48: =C46*C47 -> 11.981536 | D48: =D46*D47 -> 11.888456 | E48: =E46*E47 -> 11.57742 | F48: =F46*F47 -> 11.269779 | G48: =G46*G47 -> 10.864215 | H48: =H46*H47 -> 10.439793 | I48: =I46*I47 -> 9.9997998 | ... K48: =K46*K47 -> 9.0863492
A49: Terminal value | B49: =L46/($B$10-L39) -> 413.42291 | C49: =IF($B$10>L39,"","Discount rate must exceed terminal growth")
A50: PV of terminal value | B50: =B49/(1+$B$10)^$K$16 -> 207.97644
A51: Equity value (PV FCF + PV TV + net cash + other) | B51: =SUM(B48:K48)+B50+$B$7+$B$8 -> 309.58721
A52: Value per share ($) | B52: =B51/$B$6 -> 71.997025
A53: Value vs share price | B53: =B52/$B$4-1 -> -0.2280795
A55: Bull: pricing and mix keep compounding
A56: Revenue | B56: 52.8 | C56: 56.2 | D56: 59.8 | E56: 63.6 | F56: 67.6 | G56: =F56*(1+$F57+($L57-$F57)*G$17/5) -> 71.474458 | H56: =G56*(1+$F57+($L57-$F57)*H$17/5) -> 75.17225 | I56: =H56*(1+$F57+($L57-$F57)*I$17/5) -> 78.641993 | J56: =I56*(1+$F57+($L57-$F57)*J$17/5) -> 81.833176 | K56: =J56*(1+$F57+($L57-$F57)*K$17/5) -> 84.697337 | L56: =K56*(1+L57) -> 87.661744
A57: Revenue growth (terminal column = terminal growth, input) | B57: =B56/$B$12-1 -> 0.060240964 | C57: =C56/B56-1 -> 0.064393939 | D57: =D56/C56-1 -> 0.06405694 | E57: =E56/D56-1 -> 0.063545151 | F57: =F56/E56-1 -> 0.062893082 | G57: =G56/F56-1 -> 0.057314465 | H57: =H56/G56-1 -> 0.051735849 | I57: =I56/H56-1 -> 0.046157233 | J57: =J56/I56-1 -> 0.040578616 | K57: =K56/J56-1 -> 0.035 | L57: 0.035
A58: Operating margin | B58: 0.33 | C58: 0.335 | D58: 0.34 | E58: 0.345 | F58: 0.35 | G58: =$F58+($L58-$F58)*G$17/5 -> 0.348 | H58: =$F58+($L58-$F58)*H$17/5 -> 0.346 | I58: =$F58+($L58-$F58)*I$17/5 -> 0.344 | J58: =$F58+($L58-$F58)*J$17/5 -> 0.342 | K58: =$F58+($L58-$F58)*K$17/5 -> 0.34 | L58: 0.34
A59: Operating income | B59: =B56*B58 -> 17.424 | C59: =C56*C58 -> 18.827 | D59: =D56*D58 -> 20.332 | E59: =E56*E58 -> 21.942 | F59: =F56*F58 -> 23.66 | G59: =G56*G58 -> 24.873111 | H59: =H56*H58 -> 26.009598 | I59: =I56*I58 -> 27.052845 | ... L59: =L56*L58 -> 29.804993
A60: NOPAT | B60: =B59*(1-$B$9) -> 14.11344 | C60: =C59*(1-$B$9) -> 15.24987 | D60: =D59*(1-$B$9) -> 16.46892 | E60: =E59*(1-$B$9) -> 17.77302 | F60: =F59*(1-$B$9) -> 19.1646 | G60: =G59*(1-$B$9) -> 20.14722 | H60: =H59*(1-$B$9) -> 21.067775 | I60: =I59*(1-$B$9) -> 21.912805 | ... L60: =L59*(1-$B$9) -> 24.142044
A61: Net reinvestment, % of revenue | B61: 0.02 | C61: 0.02 | D61: 0.02 | E61: 0.02 | F61: 0.02 | G61: =$F61+($L61-$F61)*G$17/5 -> 0.02 | H61: =$F61+($L61-$F61)*H$17/5 -> 0.02 | I61: =$F61+($L61-$F61)*I$17/5 -> 0.02 | J61: =$F61+($L61-$F61)*J$17/5 -> 0.02 | K61: =$F61+($L61-$F61)*K$17/5 -> 0.02 | L61: 0.02
A62: Net reinvestment | B62: =B56*B61 -> 1.056 | C62: =C56*C61 -> 1.124 | D62: =D56*D61 -> 1.196 | E62: =E56*E61 -> 1.272 | F62: =F56*F61 -> 1.352 | G62: =G56*G61 -> 1.4294892 | H62: =H56*H61 -> 1.503445 | I62: =I56*I61 -> 1.5728399 | ... L62: =L56*L61 -> 1.7532349
A63: Change in working capital | B63: =$B$11*(B56-$B$12) -> 0 | C63: =$B$11*(C56-B56) -> 0 | D63: =$B$11*(D56-C56) -> 0 | E63: =$B$11*(E56-D56) -> 0 | F63: =$B$11*(F56-E56) -> 0 | G63: =$B$11*(G56-F56) -> 0 | H63: =$B$11*(H56-G56) -> 0 | I63: =$B$11*(I56-H56) -> 0 | J63: =$B$11*(J56-I56) -> 0 | ... L63: =$B$11*(L56-K56) -> 0
A64: Free cash flow | B64: =B60-B62-B63 -> 13.05744 | C64: =C60-C62-C63 -> 14.12587 | D64: =D60-D62-D63 -> 15.27292 | E64: =E60-E62-E63 -> 16.50102 | F64: =F60-F62-F63 -> 17.8126 | G64: =G60-G62-G63 -> 18.717731 | H64: =H60-H62-H63 -> 19.56433 | I64: =I60-I62-I63 -> 20.339965 | ... L64: =L60-L62-L63 -> 22.388809
A65: Discount factor | B65: =1/(1+$B$10)^B$16 -> 0.96448564 | C65: =1/(1+$B$10)^C$16 -> 0.89719595 | D65: =1/(1+$B$10)^D$16 -> 0.83460088 | E65: =1/(1+$B$10)^E$16 -> 0.77637291 | F65: =1/(1+$B$10)^F$16 -> 0.72220736 | G65: =1/(1+$B$10)^G$16 -> 0.6718208 | H65: =1/(1+$B$10)^H$16 -> 0.62494958 | I65: =1/(1+$B$10)^I$16 -> 0.58134845 | ... K65: =1/(1+$B$10)^K$16 -> 0.50305977
A66: PV of free cash flow | B66: =B64*B65 -> 12.593713 | C66: =C64*C65 -> 12.673673 | D66: =D64*D65 -> 12.746793 | E66: =E64*E65 -> 12.810945 | F66: =F64*F65 -> 12.864391 | G66: =G64*G65 -> 12.574961 | H66: =H64*H65 -> 12.22672 | I66: =I64*I65 -> 11.824607 | ... K66: =K64*K65 -> 10.882038
A67: Terminal value | B67: =L64/($B$10-L57) -> 559.72023 | C67: =IF($B$10>L57,"","Discount rate must exceed terminal growth")
A68: PV of terminal value | B68: =B67/(1+$B$10)^$K$16 -> 281.57273
A69: Equity value (PV FCF + PV TV + net cash + other) | B69: =SUM(B66:K66)+B68+$B$7+$B$8 -> 397.03487
A70: Value per share ($) | B70: =B69/$B$6 -> 92.33369
A71: Value vs share price | B71: =B70/$B$4-1 -> -0.010038706
A74: Outputs | C74: vs price
A75: Bear value per share | B75: =B34 -> 53.571974 | C75: =B75/$B$4-1 -> -0.42562481
A76: Base value per share | B76: =B52 -> 71.997025 | C76: =B76/$B$4-1 -> -0.2280795
A77: Bull value per share | B77: =B70 -> 92.33369 | C77: =B77/$B$4-1 -> -0.010038706
A78: Selected scenario value per share | B78: =INDEX(B34:B70,1+($B$13-1)*18) -> 71.997025 | C78: =B78/$B$4-1 -> -0.2280795
A79: Share of base value from terminal value | B79: =B50/(SUM(B48:K48)+B50) -> 0.65670436
A81: Base value per share at other discount rates
A82: Discount rate | B82: 0.05 | C82: 0.06 | D82: 0.07 | E82: 0.08 | F82: 0.09 | G82: 0.1 | H82: 0.11 | I82: 0.12 | J82: 0.13 | K82: 0.14
A83: Base value per share | B83: =IF(B82>$L39,(SUMPRODUCT($B46:$K46/(1+B82)^$B$16:$K$16)+$L46/(B82-$L39)/(1+B82)^$K$16+$B$7+$B$8)/$B$6,"n/a") -> 162.76023 | C83: =IF(C82>$L39,(SUMPRODUCT($B46:$K46/(1+C82)^$B$16:$K$16)+$L46/(C82-$L39)/(1+C82)^$K$16+$B$7+$B$8)/$B$6,"n/a") -> 108.30323 | D83: =IF(D82>$L39,(SUMPRODUCT($B46:$K46/(1+D82)^$B$16:$K$16)+$L46/(D82-$L39)/(1+D82)^$K$16+$B$7+$B$8)/$B$6,"n/a") -> 81.073778 | E83: =IF(E82>$L39,(SUMPRODUCT($B46:$K46/(1+E82)^$B$16:$K$16)+$L46/(E82-$L39)/(1+E82)^$K$16+$B$7+$B$8)/$B$6,"n/a") -> 64.735483 | F83: =IF(F82>$L39,(SUMPRODUCT($B46:$K46/(1+F82)^$B$16:$K$16)+$L46/(F82-$L39)/(1+F82)^$K$16+$B$7+$B$8)/$B$6,"n/a") -> 53.842871 | G83: =IF(G82>$L39,(SUMPRODUCT($B46:$K46/(1+G82)^$B$16:$K$16)+$L46/(G82-$L39)/(1+G82)^$K$16+$B$7+$B$8)/$B$6,"n/a") -> 46.062154 | H83: =IF(H82>$L39,(SUMPRODUCT($B46:$K46/(1+H82)^$B$16:$K$16)+$L46/(H82-$L39)/(1+H82)^$K$16+$B$7+$B$8)/$B$6,"n/a") -> 40.226427 | I83: =IF(I82>$L39,(SUMPRODUCT($B46:$K46/(1+I82)^$B$16:$K$16)+$L46/(I82-$L39)/(1+I82)^$K$16+$B$7+$B$8)/$B$6,"n/a") -> 35.687402 | ... K83: =IF(K82>$L39,(SUMPRODUCT($B46:$K46/(1+K82)^$B$16:$K$16)+$L46/(K82-$L39)/(1+K82)^$K$16+$B$7+$B$8)/$B$6,"n/a") -> 29.084985
A84: vs share price | B84: =IFERROR(B83/$B$4-1,"n/a") -> 0.74504374 | C84: =IFERROR(C83/$B$4-1,"n/a") -> 0.16117974 | D84: =IFERROR(D83/$B$4-1,"n/a") -> -0.13076254 | E84: =IFERROR(E83/$B$4-1,"n/a") -> -0.30593457 | F84: =IFERROR(F83/$B$4-1,"n/a") -> -0.42272037 | G84: =IFERROR(G83/$B$4-1,"n/a") -> -0.5061418 | H84: =IFERROR(H83/$B$4-1,"n/a") -> -0.56870991 | I84: =IFERROR(I83/$B$4-1,"n/a") -> -0.61737534 | ... K84: =IFERROR(K83/$B$4-1,"n/a") -> -0.68816355
A86: Implied annual return at today's price, base case | B86: =IFERROR(IF(MATCH($B$4,$B$83:$K$83,-1)=10,"above 14%",INDEX($B$82:$K$82,MATCH($B$4,$B$83:$K$83,-1))+(INDEX($B$83:$K$83,MATCH($B$4,$B$83:$K$83,-1))-$B$4)/(INDEX($B$83:$K$83,MATCH($B$4,$B$83:$K$83,-1))-INDEX($B$83:$K$83,MATCH($B$4,$B$83:$K$83,-1)+1))*(INDEX($B$82:$K$82,MATCH($B$4,$B$83:$K$83,-1)+1)-INDEX($B$82:$K$82,MATCH($B$4,$B$83:$K$83,-1)))),"below 5%") -> 0.065520945 | C86: Discount rate at which base value equals the price (interpolated from the row above)

Sheet GOOG
A1: Alphabet (GOOG): 10-year scenario DCF
A2: Units: $ billions unless noted. Blue = input, black = formula, green = link, yellow = key lever. Years 6 to 10 fade growth, margin and reinvestment toward each scenario's terminal levels.
A4: Share price ($) | B4: 320.47 | C4: Oct 23, 2026 intraday (Yahoo Finance via the site's price feed)
A5: Price date | B5: Oct 23, 2026 | C5: Text
A6: Shares outstanding (billions) | B6: 12.23 | C6: Stock Analysis statistics, Oct 23, 2026
A7: Net cash, negative = net debt | B7: 121.68 | C7: Stock Analysis statistics, Oct 23, 2026: cash less total debt
A8: Other non-operating assets, less outside claims | B8: 0 | C8: Private stakes (SpaceX, Anthropic, others) excluded
A9: Tax rate | B9: 0.17 | C9: Analyst assumption (normalized, near the reported effective rate)
A10: Discount rate (WACC), from WACC tab | B10: =WACC!D29 -> 0.095 | C10: Calculated or assumed, per the switch in WACC!B5
A11: Working capital, % of revenue change | B11: 0 | C11: Analyst assumption
A12: Base-year revenue (2026E) | B12: 499.6 | C12: 2026E consensus $499.6B (Stock Analysis)
A13: Selected scenario (1 Bear, 2 Base, 3 Bull) | B13: 2 | C13: Lever
A15: Year | B15: 2027 | C15: 2028 | D15: 2029 | E15: 2030 | F15: 2031 | G15: 2032 | H15: 2033 | I15: 2034 | J15: 2035 | K15: 2036 | L15: Terminal
A16: Discount period (years, mid-year) | B16: 0.5 | C16: =B16+1 -> 1.5 | D16: =C16+1 -> 2.5 | E16: =D16+1 -> 3.5 | F16: =E16+1 -> 4.5 | G16: =F16+1 -> 5.5 | H16: =G16+1 -> 6.5 | I16: =H16+1 -> 7.5 | J16: =I16+1 -> 8.5 | K16: =J16+1 -> 9.5
A17: Fade step (years 6 to 10) | B17: 0 | C17: 0 | D17: 0 | E17: 0 | F17: 0 | G17: 1 | H17: 2 | I17: 3 | J17: 4 | K17: 5
A19: Bear: search share loss, AI capex earns little
A20: Revenue | B20: 565 | C20: 610 | D20: 650 | E20: 690 | F20: 725 | G20: =F20*(1+$F21+($L21-$F21)*G$17/5) -> 759.49529 | H20: =G20*(1+$F21+($L21-$F21)*H$17/5) -> 793.2433 | I20: =H20*(1+$F21+($L21-$F21)*I$17/5) -> 825.9962 | J20: =I20*(1+$F21+($L21-$F21)*J$17/5) -> 857.50376 | K20: =J20*(1+$F21+($L21-$F21)*K$17/5) -> 887.5164 | L20: =K20*(1+L21) -> 918.57947
A21: Revenue growth (terminal column = terminal growth, input) | B21: =B20/$B$12-1 -> 0.13090472 | C21: =C20/B20-1 -> 0.079646018 | D21: =D20/C20-1 -> 0.06557377 | E21: =E20/D20-1 -> 0.061538462 | F21: =F20/E20-1 -> 0.050724638 | G21: =G20/F20-1 -> 0.04757971 | H21: =H20/G20-1 -> 0.044434783 | I21: =I20/H20-1 -> 0.041289855 | J21: =J20/I20-1 -> 0.038144928 | K21: =K20/J20-1 -> 0.035 | L21: 0.035
A22: Operating margin | B22: 0.3 | C22: 0.29 | D22: 0.29 | E22: 0.29 | F22: 0.29 | G22: =$F22+($L22-$F22)*G$17/5 -> 0.286 | H22: =$F22+($L22-$F22)*H$17/5 -> 0.282 | I22: =$F22+($L22-$F22)*I$17/5 -> 0.278 | J22: =$F22+($L22-$F22)*J$17/5 -> 0.274 | K22: =$F22+($L22-$F22)*K$17/5 -> 0.27 | L22: 0.27
A23: Operating income | B23: =B20*B22 -> 169.5 | C23: =C20*C22 -> 176.9 | D23: =D20*D22 -> 188.5 | E23: =E20*E22 -> 200.1 | F23: =F20*F22 -> 210.25 | G23: =G20*G22 -> 217.21565 | H23: =H20*H22 -> 223.69461 | I23: =I20*I22 -> 229.62694 | ... L23: =L20*L22 -> 248.01646
A24: NOPAT | B24: =B23*(1-$B$9) -> 140.685 | C24: =C23*(1-$B$9) -> 146.827 | D24: =D23*(1-$B$9) -> 156.455 | E24: =E23*(1-$B$9) -> 166.083 | F24: =F23*(1-$B$9) -> 174.5075 | G24: =G23*(1-$B$9) -> 180.28899 | H24: =H23*(1-$B$9) -> 185.66653 | I24: =I23*(1-$B$9) -> 190.59036 | ... L24: =L23*(1-$B$9) -> 205.85366
A25: Net reinvestment, % of revenue | B25: 0.24 | C25: 0.19 | D25: 0.14 | E25: 0.11 | F25: 0.09 | G25: =$F25+($L25-$F25)*G$17/5 -> 0.084 | H25: =$F25+($L25-$F25)*H$17/5 -> 0.078 | I25: =$F25+($L25-$F25)*I$17/5 -> 0.072 | J25: =$F25+($L25-$F25)*J$17/5 -> 0.066 | K25: =$F25+($L25-$F25)*K$17/5 -> 0.06 | L25: 0.06
A26: Net reinvestment | B26: =B20*B25 -> 135.6 | C26: =C20*C25 -> 115.9 | D26: =D20*D25 -> 91 | E26: =E20*E25 -> 75.9 | F26: =F20*F25 -> 65.25 | G26: =G20*G25 -> 63.797604 | H26: =H20*H25 -> 61.872977 | I26: =I20*I25 -> 59.471726 | ... L26: =L20*L25 -> 55.114768
A27: Change in working capital | B27: =$B$11*(B20-$B$12) -> 0 | C27: =$B$11*(C20-B20) -> 0 | D27: =$B$11*(D20-C20) -> 0 | E27: =$B$11*(E20-D20) -> 0 | F27: =$B$11*(F20-E20) -> 0 | G27: =$B$11*(G20-F20) -> 0 | H27: =$B$11*(H20-G20) -> 0 | I27: =$B$11*(I20-H20) -> 0 | J27: =$B$11*(J20-I20) -> 0 | ... L27: =$B$11*(L20-K20) -> 0
A28: Free cash flow | B28: =B24-B26-B27 -> 5.085 | C28: =C24-C26-C27 -> 30.927 | D28: =D24-D26-D27 -> 65.455 | E28: =E24-E26-E27 -> 90.183 | F28: =F24-F26-F27 -> 109.2575 | G28: =G24-G26-G27 -> 116.49139 | H28: =H24-H26-H27 -> 123.79355 | I28: =I24-I26-I27 -> 131.11864 | ... L28: =L24-L26-L27 -> 150.73889
A29: Discount factor | B29: =1/(1+$B$10)^B$16 -> 0.95563697 | C29: =1/(1+$B$10)^C$16 -> 0.87272782 | D29: =1/(1+$B$10)^D$16 -> 0.79701171 | E29: =1/(1+$B$10)^E$16 -> 0.72786458 | F29: =1/(1+$B$10)^F$16 -> 0.66471651 | G29: =1/(1+$B$10)^G$16 -> 0.60704704 | H29: =1/(1+$B$10)^H$16 -> 0.55438086 | I29: =1/(1+$B$10)^I$16 -> 0.50628389 | ... K29: =1/(1+$B$10)^K$16 -> 0.42224631
A30: PV of free cash flow | B30: =B28*B29 -> 4.859414 | C30: =C28*C29 -> 26.990853 | D30: =D28*D29 -> 52.168401 | E30: =E28*E29 -> 65.641011 | F30: =F28*F29 -> 72.625264 | G30: =G28*G29 -> 70.715752 | H30: =H28*H29 -> 68.628774 | I30: =I28*I29 -> 66.383253 | ... K30: =K28*K29 -> 61.496562
A31: Terminal value | B31: =L28/($B$10-L21) -> 2512.3148 | C31: =IF($B$10>L21,"","Discount rate must exceed terminal growth")
A32: PV of terminal value | B32: =B31/(1+$B$10)^$K$16 -> 1060.8157
A33: Equity value (PV FCF + PV TV + net cash + other) | B33: =SUM(B30:K30)+B32+$B$7+$B$8 -> 1736.004
A34: Value per share ($) | B34: =B33/$B$6 -> 141.94636
A35: Value vs share price | B35: =B34/$B$4-1 -> -0.55706818
A37: Base: Cloud and Search grow, capex peaks 2027
A38: Revenue | B38: 600 | C38: 690 | D38: 770 | E38: 845 | F38: 915 | G38: =F38*(1+$F39+($L39-$F39)*G$17/5) -> 982.95905 | H38: =G38*(1+$F39+($L39-$F39)*H$17/5) -> 1047.5435 | I38: =H38*(1+$F39+($L39-$F39)*I$17/5) -> 1107.3961 | J38: =I38*(1+$F39+($L39-$F39)*J$17/5) -> 1161.1801 | K38: =J38*(1+$F39+($L39-$F39)*K$17/5) -> 1207.6274 | L38: =K38*(1+L39) -> 1255.9324
A39: Revenue growth (terminal column = terminal growth, input) | B39: =B38/$B$12-1 -> 0.20096077 | C39: =C38/B38-1 -> 0.15 | D39: =D38/C38-1 -> 0.11594203 | E39: =E38/D38-1 -> 0.097402597 | F39: =F38/E38-1 -> 0.082840237 | G39: =G38/F38-1 -> 0.074272189 | H39: =H38/G38-1 -> 0.065704142 | I39: =I38/H38-1 -> 0.057136095 | J39: =J38/I38-1 -> 0.048568047 | K39: =K38/J38-1 -> 0.04 | L39: 0.04
A40: Operating margin | B40: 0.33 | C40: 0.335 | D40: 0.34 | E40: 0.34 | F40: 0.34 | G40: =$F40+($L40-$F40)*G$17/5 -> 0.336 | H40: =$F40+($L40-$F40)*H$17/5 -> 0.332 | I40: =$F40+($L40-$F40)*I$17/5 -> 0.328 | J40: =$F40+($L40-$F40)*J$17/5 -> 0.324 | K40: =$F40+($L40-$F40)*K$17/5 -> 0.32 | L40: 0.32
A41: Operating income | B41: =B38*B40 -> 198 | C41: =C38*C40 -> 231.15 | D41: =D38*D40 -> 261.8 | E41: =E38*E40 -> 287.3 | F41: =F38*F40 -> 311.1 | G41: =G38*G40 -> 330.27424 | H41: =H38*H40 -> 347.78445 | I41: =I38*I40 -> 363.22591 | ... L41: =L38*L40 -> 401.89838
A42: NOPAT | B42: =B41*(1-$B$9) -> 164.34 | C42: =C41*(1-$B$9) -> 191.8545 | D42: =D41*(1-$B$9) -> 217.294 | E42: =E41*(1-$B$9) -> 238.459 | F42: =F41*(1-$B$9) -> 258.213 | G42: =G41*(1-$B$9) -> 274.12762 | H42: =H41*(1-$B$9) -> 288.6611 | I42: =I41*(1-$B$9) -> 301.47751 | ... L42: =L41*(1-$B$9) -> 333.57566
A43: Net reinvestment, % of revenue | B43: 0.22 | C43: 0.17 | D43: 0.13 | E43: 0.1 | F43: 0.08 | G43: =$F43+($L43-$F43)*G$17/5 -> 0.076 | H43: =$F43+($L43-$F43)*H$17/5 -> 0.072 | I43: =$F43+($L43-$F43)*I$17/5 -> 0.068 | J43: =$F43+($L43-$F43)*J$17/5 -> 0.064 | K43: =$F43+($L43-$F43)*K$17/5 -> 0.06 | L43: 0.06
A44: Net reinvestment | B44: =B38*B43 -> 132 | C44: =C38*C43 -> 117.3 | D44: =D38*D43 -> 100.1 | E44: =E38*E43 -> 84.5 | F44: =F38*F43 -> 73.2 | G44: =G38*G43 -> 74.704888 | H44: =H38*H43 -> 75.423134 | I44: =I38*I43 -> 75.302934 | ... L44: =L38*L43 -> 75.355947
A45: Change in working capital | B45: =$B$11*(B38-$B$12) -> 0 | C45: =$B$11*(C38-B38) -> 0 | D45: =$B$11*(D38-C38) -> 0 | E45: =$B$11*(E38-D38) -> 0 | F45: =$B$11*(F38-E38) -> 0 | G45: =$B$11*(G38-F38) -> 0 | H45: =$B$11*(H38-G38) -> 0 | I45: =$B$11*(I38-H38) -> 0 | J45: =$B$11*(J38-I38) -> 0 | ... L45: =$B$11*(L38-K38) -> 0
A46: Free cash flow | B46: =B42-B44-B45 -> 32.34 | C46: =C42-C44-C45 -> 74.5545 | D46: =D42-D44-D45 -> 117.194 | E46: =E42-E44-E45 -> 153.959 | F46: =F42-F44-F45 -> 185.013 | G46: =G42-G44-G45 -> 199.42273 | H46: =H42-H44-H45 -> 213.23796 | I46: =I42-I44-I45 -> 226.17458 | ... L46: =L42-L44-L45 -> 258.21971
A47: Discount factor | B47: =1/(1+$B$10)^B$16 -> 0.95563697 | C47: =1/(1+$B$10)^C$16 -> 0.87272782 | D47: =1/(1+$B$10)^D$16 -> 0.79701171 | E47: =1/(1+$B$10)^E$16 -> 0.72786458 | F47: =1/(1+$B$10)^F$16 -> 0.66471651 | G47: =1/(1+$B$10)^G$16 -> 0.60704704 | H47: =1/(1+$B$10)^H$16 -> 0.55438086 | I47: =1/(1+$B$10)^I$16 -> 0.50628389 | ... K47: =1/(1+$B$10)^K$16 -> 0.42224631
A48: PV of free cash flow | B48: =B46*B47 -> 30.905299 | C48: =C46*C47 -> 65.065786 | D48: =D46*D47 -> 93.40499 | E48: =E46*E47 -> 112.0613 | F48: =F46*F47 -> 122.9812 | G48: =G46*G47 -> 121.05898 | H48: =H46*H47 -> 118.21504 | I48: =I46*I47 -> 114.50854 | ... K48: =K46*K47 -> 104.83877
A49: Terminal value | B49: =L46/($B$10-L39) -> 4694.9038 | C49: =IF($B$10>L39,"","Discount rate must exceed terminal growth")
A50: PV of terminal value | B50: =B49/(1+$B$10)^$K$16 -> 1982.4058
A51: Equity value (PV FCF + PV TV + net cash + other) | B51: =SUM(B48:K48)+B50+$B$7+$B$8 -> 3097.1438
A52: Value per share ($) | B52: =B51/$B$6 -> 253.24152
A53: Value vs share price | B53: =B52/$B$4-1 -> -0.20978088
A55: Bull: Cloud and AI monetization compound
A56: Revenue | B56: 622 | C56: 730 | D56: 840 | E56: 945 | F56: 1040 | G56: =F56*(1+$F57+($L57-$F57)*G$17/5) -> 1131.9602 | H56: =G56*(1+$F57+($L57-$F57)*H$17/5) -> 1218.3485 | I56: =H56*(1+$F57+($L57-$F57)*I$17/5) -> 1296.5807 | J56: =I56*(1+$F57+($L57-$F57)*J$17/5) -> 1364.1401 | K56: =J56*(1+$F57+($L57-$F57)*K$17/5) -> 1418.7057 | L56: =K56*(1+L57) -> 1475.4539
A57: Revenue growth (terminal column = terminal growth, input) | B57: =B56/$B$12-1 -> 0.244996 | C57: =C56/B56-1 -> 0.17363344 | D57: =D56/C56-1 -> 0.15068493 | E57: =E56/D56-1 -> 0.125 | F57: =F56/E56-1 -> 0.1005291 | G57: =G56/F56-1 -> 0.08842328 | H57: =H56/G56-1 -> 0.07631746 | I57: =I56/H56-1 -> 0.06421164 | J57: =J56/I56-1 -> 0.05210582 | K57: =K56/J56-1 -> 0.04 | L57: 0.04
A58: Operating margin | B58: 0.34 | C58: 0.35 | D58: 0.36 | E58: 0.36 | F58: 0.36 | G58: =$F58+($L58-$F58)*G$17/5 -> 0.356 | H58: =$F58+($L58-$F58)*H$17/5 -> 0.352 | I58: =$F58+($L58-$F58)*I$17/5 -> 0.348 | J58: =$F58+($L58-$F58)*J$17/5 -> 0.344 | K58: =$F58+($L58-$F58)*K$17/5 -> 0.34 | L58: 0.34
A59: Operating income | B59: =B56*B58 -> 211.48 | C59: =C56*C58 -> 255.5 | D59: =D56*D58 -> 302.4 | E59: =E56*E58 -> 340.2 | F59: =F56*F58 -> 374.4 | G59: =G56*G58 -> 402.97784 | H59: =H56*H58 -> 428.85869 | I59: =I56*I58 -> 451.21008 | ... L59: =L56*L58 -> 501.65434
A60: NOPAT | B60: =B59*(1-$B$9) -> 175.5284 | C60: =C59*(1-$B$9) -> 212.065 | D60: =D59*(1-$B$9) -> 250.992 | E60: =E59*(1-$B$9) -> 282.366 | F60: =F59*(1-$B$9) -> 310.752 | G60: =G59*(1-$B$9) -> 334.4716 | H60: =H59*(1-$B$9) -> 355.95271 | I60: =I59*(1-$B$9) -> 374.50437 | ... L60: =L59*(1-$B$9) -> 416.3731
A61: Net reinvestment, % of revenue | B61: 0.21 | C61: 0.16 | D61: 0.12 | E61: 0.09 | F61: 0.07 | G61: =$F61+($L61-$F61)*G$17/5 -> 0.067 | H61: =$F61+($L61-$F61)*H$17/5 -> 0.064 | I61: =$F61+($L61-$F61)*I$17/5 -> 0.061 | J61: =$F61+($L61-$F61)*J$17/5 -> 0.058 | K61: =$F61+($L61-$F61)*K$17/5 -> 0.055 | L61: 0.055
A62: Net reinvestment | B62: =B56*B61 -> 130.62 | C62: =C56*C61 -> 116.8 | D62: =D56*D61 -> 100.8 | E62: =E56*E61 -> 85.05 | F62: =F56*F61 -> 72.8 | G62: =G56*G61 -> 75.841334 | H62: =H56*H61 -> 77.974307 | I62: =I56*I61 -> 79.091423 | ... L62: =L56*L61 -> 81.149966
A63: Change in working capital | B63: =$B$11*(B56-$B$12) -> 0 | C63: =$B$11*(C56-B56) -> 0 | D63: =$B$11*(D56-C56) -> 0 | E63: =$B$11*(E56-D56) -> 0 | F63: =$B$11*(F56-E56) -> 0 | G63: =$B$11*(G56-F56) -> 0 | H63: =$B$11*(H56-G56) -> 0 | I63: =$B$11*(I56-H56) -> 0 | J63: =$B$11*(J56-I56) -> 0 | ... L63: =$B$11*(L56-K56) -> 0
A64: Free cash flow | B64: =B60-B62-B63 -> 44.9084 | C64: =C60-C62-C63 -> 95.265 | D64: =D60-D62-D63 -> 150.192 | E64: =E60-E62-E63 -> 197.316 | F64: =F60-F62-F63 -> 237.952 | G64: =G60-G62-G63 -> 258.63027 | H64: =H60-H62-H63 -> 277.9784 | I64: =I60-I62-I63 -> 295.41295 | ... L64: =L60-L62-L63 -> 335.22313
A65: Discount factor | B65: =1/(1+$B$10)^B$16 -> 0.95563697 | C65: =1/(1+$B$10)^C$16 -> 0.87272782 | D65: =1/(1+$B$10)^D$16 -> 0.79701171 | E65: =1/(1+$B$10)^E$16 -> 0.72786458 | F65: =1/(1+$B$10)^F$16 -> 0.66471651 | G65: =1/(1+$B$10)^G$16 -> 0.60704704 | H65: =1/(1+$B$10)^H$16 -> 0.55438086 | I65: =1/(1+$B$10)^I$16 -> 0.50628389 | ... K65: =1/(1+$B$10)^K$16 -> 0.42224631
A66: PV of free cash flow | B66: =B64*B65 -> 42.916127 | C66: =C64*C65 -> 83.140416 | D66: =D64*D65 -> 119.70478 | E66: =E64*E65 -> 143.61933 | F66: =F64*F65 -> 158.17062 | G66: =G64*G65 -> 157.00074 | H66: =H64*H65 -> 154.10591 | I66: =I64*I65 -> 149.56281 | ... K66: =K64*K65 -> 136.10263
A67: Terminal value | B67: =L64/($B$10-L57) -> 6094.9661 | C67: =IF($B$10>L57,"","Discount rate must exceed terminal growth")
A68: PV of terminal value | B68: =B67/(1+$B$10)^$K$16 -> 2573.577
A69: Equity value (PV FCF + PV TV + net cash + other) | B69: =SUM(B66:K66)+B68+$B$7+$B$8 -> 3983.0825
A70: Value per share ($) | B70: =B69/$B$6 -> 325.68132
A71: Value vs share price | B71: =B70/$B$4-1 -> 0.016261483
A74: Outputs | C74: vs price
A75: Bear value per share | B75: =B34 -> 141.94636 | C75: =B75/$B$4-1 -> -0.55706818
A76: Base value per share | B76: =B52 -> 253.24152 | C76: =B76/$B$4-1 -> -0.20978088
A77: Bull value per share | B77: =B70 -> 325.68132 | C77: =B77/$B$4-1 -> 0.016261483
A78: Selected scenario value per share | B78: =INDEX(B34:B70,1+($B$13-1)*18) -> 253.24152 | C78: =B78/$B$4-1 -> -0.20978088
A79: Share of base value from terminal value | B79: =B50/(SUM(B48:K48)+B50) -> 0.66625104
A81: Base value per share at other discount rates
A82: Discount rate | B82: 0.05 | C82: 0.06 | D82: 0.07 | E82: 0.08 | F82: 0.09 | G82: 0.1 | H82: 0.11 | I82: 0.12 | J82: 0.13 | K82: 0.14
A83: Base value per share | B83: =IF(B82>$L39,(SUMPRODUCT($B46:$K46/(1+B82)^$B$16:$K$16)+$L46/(B82-$L39)/(1+B82)^$K$16+$B$7+$B$8)/$B$6,"n/a") -> 1441.2537 | C83: =IF(C82>$L39,(SUMPRODUCT($B46:$K46/(1+C82)^$B$16:$K$16)+$L46/(C82-$L39)/(1+C82)^$K$16+$B$7+$B$8)/$B$6,"n/a") -> 714.45327 | D83: =IF(D82>$L39,(SUMPRODUCT($B46:$K46/(1+D82)^$B$16:$K$16)+$L46/(D82-$L39)/(1+D82)^$K$16+$B$7+$B$8)/$B$6,"n/a") -> 472.50313 | E83: =IF(E82>$L39,(SUMPRODUCT($B46:$K46/(1+E82)^$B$16:$K$16)+$L46/(E82-$L39)/(1+E82)^$K$16+$B$7+$B$8)/$B$6,"n/a") -> 351.75208 | F83: =IF(F82>$L39,(SUMPRODUCT($B46:$K46/(1+F82)^$B$16:$K$16)+$L46/(F82-$L39)/(1+F82)^$K$16+$B$7+$B$8)/$B$6,"n/a") -> 279.47066 | G83: =IF(G82>$L39,(SUMPRODUCT($B46:$K46/(1+G82)^$B$16:$K$16)+$L46/(G82-$L39)/(1+G82)^$K$16+$B$7+$B$8)/$B$6,"n/a") -> 231.41629 | H83: =IF(H82>$L39,(SUMPRODUCT($B46:$K46/(1+H82)^$B$16:$K$16)+$L46/(H82-$L39)/(1+H82)^$K$16+$B$7+$B$8)/$B$6,"n/a") -> 197.19974 | I83: =IF(I82>$L39,(SUMPRODUCT($B46:$K46/(1+I82)^$B$16:$K$16)+$L46/(I82-$L39)/(1+I82)^$K$16+$B$7+$B$8)/$B$6,"n/a") -> 171.62679 | ... K83: =IF(K82>$L39,(SUMPRODUCT($B46:$K46/(1+K82)^$B$16:$K$16)+$L46/(K82-$L39)/(1+K82)^$K$16+$B$7+$B$8)/$B$6,"n/a") -> 136.02449
A84: vs share price | B84: =IFERROR(B83/$B$4-1,"n/a") -> 3.4973123 | C84: =IFERROR(C83/$B$4-1,"n/a") -> 1.2293921 | D84: =IFERROR(D83/$B$4-1,"n/a") -> 0.47440674 | E84: =IFERROR(E83/$B$4-1,"n/a") -> 0.097613135 | F84: =IFERROR(F83/$B$4-1,"n/a") -> -0.12793503 | G84: =IFERROR(G83/$B$4-1,"n/a") -> -0.27788471 | H84: =IFERROR(H83/$B$4-1,"n/a") -> -0.38465459 | I84: =IFERROR(I83/$B$4-1,"n/a") -> -0.46445287 | ... K84: =IFERROR(K83/$B$4-1,"n/a") -> -0.5755469
A86: Implied annual return at today's price, base case | B86: =IFERROR(IF(MATCH($B$4,$B$83:$K$83,-1)=10,"above 14%",INDEX($B$82:$K$82,MATCH($B$4,$B$83:$K$83,-1))+(INDEX($B$83:$K$83,MATCH($B$4,$B$83:$K$83,-1))-$B$4)/(INDEX($B$83:$K$83,MATCH($B$4,$B$83:$K$83,-1))-INDEX($B$83:$K$83,MATCH($B$4,$B$83:$K$83,-1)+1))*(INDEX($B$82:$K$82,MATCH($B$4,$B$83:$K$83,-1)+1)-INDEX($B$82:$K$82,MATCH($B$4,$B$83:$K$83,-1)))),"below 5%") -> 0.084327818 | C86: Discount rate at which base value equals the price (interpolated from the row above)

Sheet UNH
A1: UnitedHealth (UNH): 10-year scenario DCF
A2: Units: $ billions unless noted. Blue = input, black = formula, green = link, yellow = key lever. Years 6 to 10 fade growth, margin and reinvestment toward each scenario's terminal levels.
A4: Share price ($) | B4: 423.39 | C4: Oct 23, 2026 intraday (Yahoo Finance via the site's price feed)
A5: Price date | B5: Oct 23, 2026 | C5: Text
A6: Shares outstanding (billions) | B6: 0.89759 | C6: Stock Analysis statistics, Oct 23, 2026
A7: Net cash, negative = net debt | B7: -48.49 | C7: Stock Analysis statistics, Oct 23, 2026: cash less total debt
A8: Other non-operating assets, less outside claims | B8: 0 | C8: None
A9: Tax rate | B9: 0.22 | C9: Analyst assumption (normalized, near the reported effective rate)
A10: Discount rate (WACC), from WACC tab | B10: =WACC!E29 -> 0.09 | C10: Calculated or assumed, per the switch in WACC!B5
A11: Working capital, % of revenue change | B11: 0 | C11: Analyst assumption
A12: Base-year revenue (2026E) | B12: 448.7 | C12: 2026E consensus $448.7B (Stock Analysis)
A13: Selected scenario (1 Bear, 2 Base, 3 Bull) | B13: 2 | C13: Lever
A15: Year | B15: 2027 | C15: 2028 | D15: 2029 | E15: 2030 | F15: 2031 | G15: 2032 | H15: 2033 | I15: 2034 | J15: 2035 | K15: 2036 | L15: Terminal
A16: Discount period (years, mid-year) | B16: 0.5 | C16: =B16+1 -> 1.5 | D16: =C16+1 -> 2.5 | E16: =D16+1 -> 3.5 | F16: =E16+1 -> 4.5 | G16: =F16+1 -> 5.5 | H16: =G16+1 -> 6.5 | I16: =H16+1 -> 7.5 | J16: =I16+1 -> 8.5 | K16: =J16+1 -> 9.5
A17: Fade step (years 6 to 10) | B17: 0 | C17: 0 | D17: 0 | E17: 0 | F17: 0 | G17: 1 | H17: 2 | I17: 3 | J17: 4 | K17: 5
A19: Bear: margins stay near trough, policy pressure
A20: Revenue | B20: 455 | C20: 470 | D20: 488 | E20: 506 | F20: 525 | G20: =F20*(1+$F21+($L21-$F21)*G$17/5) -> 543.92075 | H20: =G20*(1+$F21+($L21-$F21)*H$17/5) -> 562.70214 | I20: =H20*(1+$F21+($L21-$F21)*I$17/5) -> 581.28243 | J20: =I20*(1+$F21+($L21-$F21)*J$17/5) -> 599.59857 | K20: =J20*(1+$F21+($L21-$F21)*K$17/5) -> 617.58653 | L20: =K20*(1+L21) -> 636.11413
A21: Revenue growth (terminal column = terminal growth, input) | B21: =B20/$B$12-1 -> 0.014040562 | C21: =C20/B20-1 -> 0.032967033 | D21: =D20/C20-1 -> 0.038297872 | E21: =E20/D20-1 -> 0.036885246 | F21: =F20/E20-1 -> 0.037549407 | G21: =G20/F20-1 -> 0.036039526 | H21: =H20/G20-1 -> 0.034529644 | I21: =I20/H20-1 -> 0.033019763 | J21: =J20/I20-1 -> 0.031509881 | K21: =K20/J20-1 -> 0.03 | L21: 0.03
A22: Operating margin | B22: 0.054 | C22: 0.054 | D22: 0.055 | E22: 0.056 | F22: 0.057 | G22: =$F22+($L22-$F22)*G$17/5 -> 0.0568 | H22: =$F22+($L22-$F22)*H$17/5 -> 0.0566 | I22: =$F22+($L22-$F22)*I$17/5 -> 0.0564 | J22: =$F22+($L22-$F22)*J$17/5 -> 0.0562 | K22: =$F22+($L22-$F22)*K$17/5 -> 0.056 | L22: 0.056
A23: Operating income | B23: =B20*B22 -> 24.57 | C23: =C20*C22 -> 25.38 | D23: =D20*D22 -> 26.84 | E23: =E20*E22 -> 28.336 | F23: =F20*F22 -> 29.925 | G23: =G20*G22 -> 30.894699 | H23: =H20*H22 -> 31.848941 | I23: =I20*I22 -> 32.784329 | ... L23: =L20*L22 -> 35.622391
A24: NOPAT | B24: =B23*(1-$B$9) -> 19.1646 | C24: =C23*(1-$B$9) -> 19.7964 | D24: =D23*(1-$B$9) -> 20.9352 | E24: =E23*(1-$B$9) -> 22.10208 | F24: =F23*(1-$B$9) -> 23.3415 | G24: =G23*(1-$B$9) -> 24.097865 | H24: =H23*(1-$B$9) -> 24.842174 | I24: =I23*(1-$B$9) -> 25.571777 | ... L24: =L23*(1-$B$9) -> 27.785465
A25: Net reinvestment, % of revenue | B25: 0.004 | C25: 0.004 | D25: 0.004 | E25: 0.004 | F25: 0.004 | G25: =$F25+($L25-$F25)*G$17/5 -> 0.004 | H25: =$F25+($L25-$F25)*H$17/5 -> 0.004 | I25: =$F25+($L25-$F25)*I$17/5 -> 0.004 | J25: =$F25+($L25-$F25)*J$17/5 -> 0.004 | K25: =$F25+($L25-$F25)*K$17/5 -> 0.004 | L25: 0.004
A26: Net reinvestment | B26: =B20*B25 -> 1.82 | C26: =C20*C25 -> 1.88 | D26: =D20*D25 -> 1.952 | E26: =E20*E25 -> 2.024 | F26: =F20*F25 -> 2.1 | G26: =G20*G25 -> 2.175683 | H26: =H20*H25 -> 2.2508086 | I26: =I20*I25 -> 2.3251297 | ... L26: =L20*L25 -> 2.5444565
A27: Change in working capital | B27: =$B$11*(B20-$B$12) -> 0 | C27: =$B$11*(C20-B20) -> 0 | D27: =$B$11*(D20-C20) -> 0 | E27: =$B$11*(E20-D20) -> 0 | F27: =$B$11*(F20-E20) -> 0 | G27: =$B$11*(G20-F20) -> 0 | H27: =$B$11*(H20-G20) -> 0 | I27: =$B$11*(I20-H20) -> 0 | J27: =$B$11*(J20-I20) -> 0 | ... L27: =$B$11*(L20-K20) -> 0
A28: Free cash flow | B28: =B24-B26-B27 -> 17.3446 | C28: =C24-C26-C27 -> 17.9164 | D28: =D24-D26-D27 -> 18.9832 | E28: =E24-E26-E27 -> 20.07808 | F28: =F24-F26-F27 -> 21.2415 | G28: =G24-G26-G27 -> 21.922182 | H28: =H24-H26-H27 -> 22.591366 | I28: =I24-I26-I27 -> 23.246647 | ... L28: =L24-L26-L27 -> 25.241009
A29: Discount factor | B29: =1/(1+$B$10)^B$16 -> 0.95782629 | C29: =1/(1+$B$10)^C$16 -> 0.87873971 | D29: =1/(1+$B$10)^D$16 -> 0.80618322 | E29: =1/(1+$B$10)^E$16 -> 0.73961763 | F29: =1/(1+$B$10)^F$16 -> 0.67854829 | G29: =1/(1+$B$10)^G$16 -> 0.62252137 | H29: =1/(1+$B$10)^H$16 -> 0.57112052 | I29: =1/(1+$B$10)^I$16 -> 0.52396378 | ... K29: =1/(1+$B$10)^K$16 -> 0.44100983
A30: PV of free cash flow | B30: =B28*B29 -> 16.613114 | C30: =C28*C29 -> 15.743852 | D30: =D28*D29 -> 15.303937 | E30: =E28*E29 -> 14.850102 | F30: =F28*F29 -> 14.413383 | G30: =G28*G29 -> 13.647027 | H30: =H28*H29 -> 12.902392 | I30: =I28*I29 -> 12.180401 | ... K30: =K28*K29 -> 10.807313
A31: Terminal value | B31: =L28/($B$10-L21) -> 420.68348 | C31: =IF($B$10>L21,"","Discount rate must exceed terminal growth")
A32: PV of terminal value | B32: =B31/(1+$B$10)^$K$16 -> 185.52555
A33: Equity value (PV FCF + PV TV + net cash + other) | B33: =SUM(B30:K30)+B32+$B$7+$B$8 -> 274.9789
A34: Value per share ($) | B34: =B33/$B$6 -> 306.35245
A35: Value vs share price | B35: =B34/$B$4-1 -> -0.27642964
A37: Base: margins repair partway, to about 6.5%
A38: Revenue | B38: 463 | C38: 485 | D38: 510 | E38: 536 | F38: 563 | G38: =F38*(1+$F39+($L39-$F39)*G$17/5) -> 590.19206 | H38: =G38*(1+$F39+($L39-$F39)*H$17/5) -> 617.47303 | I38: =H38*(1+$F39+($L39-$F39)*I$17/5) -> 644.734 | J38: =I38*(1+$F39+($L39-$F39)*J$17/5) -> 671.86094 | K38: =J38*(1+$F39+($L39-$F39)*K$17/5) -> 698.73538 | L38: =K38*(1+L39) -> 726.6848
A39: Revenue growth (terminal column = terminal growth, input) | B39: =B38/$B$12-1 -> 0.031869846 | C39: =C38/B38-1 -> 0.047516199 | D39: =D38/C38-1 -> 0.051546392 | E39: =E38/D38-1 -> 0.050980392 | F39: =F38/E38-1 -> 0.050373134 | G39: =G38/F38-1 -> 0.048298507 | H39: =H38/G38-1 -> 0.046223881 | I39: =I38/H38-1 -> 0.044149254 | J39: =J38/I38-1 -> 0.042074627 | K39: =K38/J38-1 -> 0.04 | L39: 0.04
A40: Operating margin | B40: 0.06 | C40: 0.063 | D40: 0.065 | E40: 0.066 | F40: 0.067 | G40: =$F40+($L40-$F40)*G$17/5 -> 0.0666 | H40: =$F40+($L40-$F40)*H$17/5 -> 0.0662 | I40: =$F40+($L40-$F40)*I$17/5 -> 0.0658 | J40: =$F40+($L40-$F40)*J$17/5 -> 0.0654 | K40: =$F40+($L40-$F40)*K$17/5 -> 0.065 | L40: 0.065
A41: Operating income | B41: =B38*B40 -> 27.78 | C41: =C38*C40 -> 30.555 | D41: =D38*D40 -> 33.15 | E41: =E38*E40 -> 35.376 | F41: =F38*F40 -> 37.721 | G41: =G38*G40 -> 39.306791 | H41: =H38*H40 -> 40.876714 | I41: =I38*I40 -> 42.423497 | ... L41: =L38*L40 -> 47.234512
A42: NOPAT | B42: =B41*(1-$B$9) -> 21.6684 | C42: =C41*(1-$B$9) -> 23.8329 | D42: =D41*(1-$B$9) -> 25.857 | E42: =E41*(1-$B$9) -> 27.59328 | F42: =F41*(1-$B$9) -> 29.42238 | G42: =G41*(1-$B$9) -> 30.659297 | H42: =H41*(1-$B$9) -> 31.883837 | I42: =I41*(1-$B$9) -> 33.090328 | ... L42: =L41*(1-$B$9) -> 36.842919
A43: Net reinvestment, % of revenue | B43: 0.004 | C43: 0.004 | D43: 0.004 | E43: 0.004 | F43: 0.004 | G43: =$F43+($L43-$F43)*G$17/5 -> 0.004 | H43: =$F43+($L43-$F43)*H$17/5 -> 0.004 | I43: =$F43+($L43-$F43)*I$17/5 -> 0.004 | J43: =$F43+($L43-$F43)*J$17/5 -> 0.004 | K43: =$F43+($L43-$F43)*K$17/5 -> 0.004 | L43: 0.004
A44: Net reinvestment | B44: =B38*B43 -> 1.852 | C44: =C38*C43 -> 1.94 | D44: =D38*D43 -> 2.04 | E44: =E38*E43 -> 2.144 | F44: =F38*F43 -> 2.252 | G44: =G38*G43 -> 2.3607682 | H44: =H38*H43 -> 2.4698921 | I44: =I38*I43 -> 2.578936 | ... L44: =L38*L43 -> 2.9067392
A45: Change in working capital | B45: =$B$11*(B38-$B$12) -> 0 | C45: =$B$11*(C38-B38) -> 0 | D45: =$B$11*(D38-C38) -> 0 | E45: =$B$11*(E38-D38) -> 0 | F45: =$B$11*(F38-E38) -> 0 | G45: =$B$11*(G38-F38) -> 0 | H45: =$B$11*(H38-G38) -> 0 | I45: =$B$11*(I38-H38) -> 0 | J45: =$B$11*(J38-I38) -> 0 | ... L45: =$B$11*(L38-K38) -> 0
A46: Free cash flow | B46: =B42-B44-B45 -> 19.8164 | C46: =C42-C44-C45 -> 21.8929 | D46: =D42-D44-D45 -> 23.817 | E46: =E42-E44-E45 -> 25.44928 | F46: =F42-F44-F45 -> 27.17038 | G46: =G42-G44-G45 -> 28.298529 | H46: =H42-H44-H45 -> 29.413945 | I46: =I42-I44-I45 -> 30.511392 | ... L46: =L42-L44-L45 -> 33.93618
A47: Discount factor | B47: =1/(1+$B$10)^B$16 -> 0.95782629 | C47: =1/(1+$B$10)^C$16 -> 0.87873971 | D47: =1/(1+$B$10)^D$16 -> 0.80618322 | E47: =1/(1+$B$10)^E$16 -> 0.73961763 | F47: =1/(1+$B$10)^F$16 -> 0.67854829 | G47: =1/(1+$B$10)^G$16 -> 0.62252137 | H47: =1/(1+$B$10)^H$16 -> 0.57112052 | I47: =1/(1+$B$10)^I$16 -> 0.52396378 | ... K47: =1/(1+$B$10)^K$16 -> 0.44100983
A48: PV of free cash flow | B48: =B46*B47 -> 18.980669 | C48: =C46*C47 -> 19.238161 | D48: =D46*D47 -> 19.200866 | E48: =E46*E47 -> 18.822736 | F48: =F46*F47 -> 18.436415 | G48: =G46*G47 -> 17.616439 | H48: =H46*H47 -> 16.798908 | I48: =I46*I47 -> 15.986864 | ... K48: =K46*K47 -> 14.390566
A49: Terminal value | B49: =L46/($B$10-L39) -> 678.7236 | C49: =IF($B$10>L39,"","Discount rate must exceed terminal growth")
A50: PV of terminal value | B50: =B49/(1+$B$10)^$K$16 -> 299.32378
A51: Equity value (PV FCF + PV TV + net cash + other) | B51: =SUM(B48:K48)+B50+$B$7+$B$8 -> 425.48859
A52: Value per share ($) | B52: =B51/$B$6 -> 474.03446
A53: Value vs share price | B53: =B52/$B$4-1 -> 0.11961656
A55: Bull: margins back to the 8% history
A56: Revenue | B56: 466 | C56: 495 | D56: 528 | E56: 563 | F56: 600 | G56: =F56*(1+$F57+($L57-$F57)*G$17/5) -> 636.94529 | H56: =G56*(1+$F57+($L57-$F57)*H$17/5) -> 673.52609 | I56: =H56*(1+$F57+($L57-$F57)*I$17/5) -> 709.41678 | J56: =I56*(1+$F57+($L57-$F57)*J$17/5) -> 744.28026 | K56: =J56*(1+$F57+($L57-$F57)*K$17/5) -> 777.77288 | L56: =K56*(1+L57) -> 812.77266
A57: Revenue growth (terminal column = terminal growth, input) | B57: =B56/$B$12-1 -> 0.038555828 | C57: =C56/B56-1 -> 0.06223176 | D57: =D56/C56-1 -> 0.066666667 | E57: =E56/D56-1 -> 0.066287879 | F57: =F56/E56-1 -> 0.065719361 | G57: =G56/F56-1 -> 0.061575488 | H57: =H56/G56-1 -> 0.057431616 | I57: =I56/H56-1 -> 0.053287744 | J57: =J56/I56-1 -> 0.049143872 | K57: =K56/J56-1 -> 0.045 | L57: 0.045
A58: Operating margin | B58: 0.062 | C58: 0.068 | D58: 0.074 | E58: 0.078 | F58: 0.08 | G58: =$F58+($L58-$F58)*G$17/5 -> 0.0796 | H58: =$F58+($L58-$F58)*H$17/5 -> 0.0792 | I58: =$F58+($L58-$F58)*I$17/5 -> 0.0788 | J58: =$F58+($L58-$F58)*J$17/5 -> 0.0784 | K58: =$F58+($L58-$F58)*K$17/5 -> 0.078 | L58: 0.078
A59: Operating income | B59: =B56*B58 -> 28.892 | C59: =C56*C58 -> 33.66 | D59: =D56*D58 -> 39.072 | E59: =E56*E58 -> 43.914 | F59: =F56*F58 -> 48 | G59: =G56*G58 -> 50.700845 | H59: =H56*H58 -> 53.343266 | I59: =I56*I58 -> 55.902042 | ... L59: =L56*L58 -> 63.396267
A60: NOPAT | B60: =B59*(1-$B$9) -> 22.53576 | C60: =C59*(1-$B$9) -> 26.2548 | D60: =D59*(1-$B$9) -> 30.47616 | E60: =E59*(1-$B$9) -> 34.25292 | F60: =F59*(1-$B$9) -> 37.44 | G60: =G59*(1-$B$9) -> 39.546659 | H60: =H59*(1-$B$9) -> 41.607748 | I60: =I59*(1-$B$9) -> 43.603593 | ... L60: =L59*(1-$B$9) -> 49.449088
A61: Net reinvestment, % of revenue | B61: 0.004 | C61: 0.004 | D61: 0.004 | E61: 0.004 | F61: 0.004 | G61: =$F61+($L61-$F61)*G$17/5 -> 0.004 | H61: =$F61+($L61-$F61)*H$17/5 -> 0.004 | I61: =$F61+($L61-$F61)*I$17/5 -> 0.004 | J61: =$F61+($L61-$F61)*J$17/5 -> 0.004 | K61: =$F61+($L61-$F61)*K$17/5 -> 0.004 | L61: 0.004
A62: Net reinvestment | B62: =B56*B61 -> 1.864 | C62: =C56*C61 -> 1.98 | D62: =D56*D61 -> 2.112 | E62: =E56*E61 -> 2.252 | F62: =F56*F61 -> 2.4 | G62: =G56*G61 -> 2.5477812 | H62: =H56*H61 -> 2.6941044 | I62: =I56*I61 -> 2.8376671 | ... L62: =L56*L61 -> 3.2510906
A63: Change in working capital | B63: =$B$11*(B56-$B$12) -> 0 | C63: =$B$11*(C56-B56) -> 0 | D63: =$B$11*(D56-C56) -> 0 | E63: =$B$11*(E56-D56) -> 0 | F63: =$B$11*(F56-E56) -> 0 | G63: =$B$11*(G56-F56) -> 0 | H63: =$B$11*(H56-G56) -> 0 | I63: =$B$11*(I56-H56) -> 0 | J63: =$B$11*(J56-I56) -> 0 | ... L63: =$B$11*(L56-K56) -> 0
A64: Free cash flow | B64: =B60-B62-B63 -> 20.67176 | C64: =C60-C62-C63 -> 24.2748 | D64: =D60-D62-D63 -> 28.36416 | E64: =E60-E62-E63 -> 32.00092 | F64: =F60-F62-F63 -> 35.04 | G64: =G60-G62-G63 -> 36.998878 | H64: =H60-H62-H63 -> 38.913643 | I64: =I60-I62-I63 -> 40.765926 | ... L64: =L60-L62-L63 -> 46.197998
A65: Discount factor | B65: =1/(1+$B$10)^B$16 -> 0.95782629 | C65: =1/(1+$B$10)^C$16 -> 0.87873971 | D65: =1/(1+$B$10)^D$16 -> 0.80618322 | E65: =1/(1+$B$10)^E$16 -> 0.73961763 | F65: =1/(1+$B$10)^F$16 -> 0.67854829 | G65: =1/(1+$B$10)^G$16 -> 0.62252137 | H65: =1/(1+$B$10)^H$16 -> 0.57112052 | I65: =1/(1+$B$10)^I$16 -> 0.52396378 | ... K65: =1/(1+$B$10)^K$16 -> 0.44100983
A66: PV of free cash flow | B66: =B64*B65 -> 19.799955 | C66: =C64*C65 -> 21.331231 | D66: =D64*D65 -> 22.86671 | E66: =E64*E65 -> 23.668445 | F66: =F64*F65 -> 23.776332 | G66: =G64*G65 -> 23.032592 | H66: =H64*H65 -> 22.22438 | I66: =I64*I65 -> 21.359868 | ... K66: =K64*K65 -> 19.496432
A67: Terminal value | B67: =L64/($B$10-L57) -> 1026.6222 | C67: =IF($B$10>L57,"","Discount rate must exceed terminal growth")
A68: PV of terminal value | B68: =B67/(1+$B$10)^$K$16 -> 452.75047
A69: Equity value (PV FCF + PV TV + net cash + other) | B69: =SUM(B66:K66)+B68+$B$7+$B$8 -> 622.26403
A70: Value per share ($) | B70: =B69/$B$6 -> 693.26088
A71: Value vs share price | B71: =B70/$B$4-1 -> 0.63740494
A74: Outputs | C74: vs price
A75: Bear value per share | B75: =B34 -> 306.35245 | C75: =B75/$B$4-1 -> -0.27642964
A76: Base value per share | B76: =B52 -> 474.03446 | C76: =B76/$B$4-1 -> 0.11961656
A77: Bull value per share | B77: =B70 -> 693.26088 | C77: =B77/$B$4-1 -> 0.63740494
A78: Selected scenario value per share | B78: =INDEX(B34:B70,1+($B$13-1)*18) -> 474.03446 | C78: =B78/$B$4-1 -> 0.11961656
A79: Share of base value from terminal value | B79: =B50/(SUM(B48:K48)+B50) -> 0.63151329
A81: Base value per share at other discount rates
A82: Discount rate | B82: 0.05 | C82: 0.06 | D82: 0.07 | E82: 0.08 | F82: 0.09 | G82: 0.1 | H82: 0.11 | I82: 0.12 | J82: 0.13 | K82: 0.14
A83: Base value per share | B83: =IF(B82>$L39,(SUMPRODUCT($B46:$K46/(1+B82)^$B$16:$K$16)+$L46/(B82-$L39)/(1+B82)^$K$16+$B$7+$B$8)/$B$6,"n/a") -> 2557.9542 | C83: =IF(C82>$L39,(SUMPRODUCT($B46:$K46/(1+C82)^$B$16:$K$16)+$L46/(C82-$L39)/(1+C82)^$K$16+$B$7+$B$8)/$B$6,"n/a") -> 1255.5401 | D83: =IF(D82>$L39,(SUMPRODUCT($B46:$K46/(1+D82)^$B$16:$K$16)+$L46/(D82-$L39)/(1+D82)^$K$16+$B$7+$B$8)/$B$6,"n/a") -> 821.38413 | E83: =IF(E82>$L39,(SUMPRODUCT($B46:$K46/(1+E82)^$B$16:$K$16)+$L46/(E82-$L39)/(1+E82)^$K$16+$B$7+$B$8)/$B$6,"n/a") -> 604.29507 | F83: =IF(F82>$L39,(SUMPRODUCT($B46:$K46/(1+F82)^$B$16:$K$16)+$L46/(F82-$L39)/(1+F82)^$K$16+$B$7+$B$8)/$B$6,"n/a") -> 474.03446 | G83: =IF(G82>$L39,(SUMPRODUCT($B46:$K46/(1+G82)^$B$16:$K$16)+$L46/(G82-$L39)/(1+G82)^$K$16+$B$7+$B$8)/$B$6,"n/a") -> 387.18929 | H83: =IF(H82>$L39,(SUMPRODUCT($B46:$K46/(1+H82)^$B$16:$K$16)+$L46/(H82-$L39)/(1+H82)^$K$16+$B$7+$B$8)/$B$6,"n/a") -> 325.15386 | I83: =IF(I82>$L39,(SUMPRODUCT($B46:$K46/(1+I82)^$B$16:$K$16)+$L46/(I82-$L39)/(1+I82)^$K$16+$B$7+$B$8)/$B$6,"n/a") -> 278.62519 | ... K83: =IF(K82>$L39,(SUMPRODUCT($B46:$K46/(1+K82)^$B$16:$K$16)+$L46/(K82-$L39)/(1+K82)^$K$16+$B$7+$B$8)/$B$6,"n/a") -> 213.48187
A84: vs share price | B84: =IFERROR(B83/$B$4-1,"n/a") -> 5.0416027 | C84: =IFERROR(C83/$B$4-1,"n/a") -> 1.9654458 | D84: =IFERROR(D83/$B$4-1,"n/a") -> 0.94001778 | E84: =IFERROR(E83/$B$4-1,"n/a") -> 0.42727761 | F84: =IFERROR(F83/$B$4-1,"n/a") -> 0.11961656 | G84: =IFERROR(G83/$B$4-1,"n/a") -> -0.085502043 | H84: =IFERROR(H83/$B$4-1,"n/a") -> -0.23202283 | I84: =IFERROR(I83/$B$4-1,"n/a") -> -0.34191835 | ... K84: =IFERROR(K83/$B$4-1,"n/a") -> -0.49577961
A86: Implied annual return at today's price, base case | B86: =IFERROR(IF(MATCH($B$4,$B$83:$K$83,-1)=10,"above 14%",INDEX($B$82:$K$82,MATCH($B$4,$B$83:$K$83,-1))+(INDEX($B$83:$K$83,MATCH($B$4,$B$83:$K$83,-1))-$B$4)/(INDEX($B$83:$K$83,MATCH($B$4,$B$83:$K$83,-1))-INDEX($B$83:$K$83,MATCH($B$4,$B$83:$K$83,-1)+1))*(INDEX($B$82:$K$82,MATCH($B$4,$B$83:$K$83,-1)+1)-INDEX($B$82:$K$82,MATCH($B$4,$B$83:$K$83,-1)))),"below 5%") -> 0.09583158 | C86: Discount rate at which base value equals the price (interpolated from the row above)

Sheet LNG
A1: Cheniere Energy (LNG): 10-year scenario DCF
A2: Units: $ billions unless noted. Blue = input, black = formula, green = link, yellow = key lever. Years 6 to 10 fade growth, margin and reinvestment toward each scenario's terminal levels.
A4: Share price ($) | B4: 297.605 | C4: Oct 23, 2026 intraday (Yahoo Finance via the site's price feed)
A5: Price date | B5: Oct 23, 2026 | C5: Text
A6: Shares outstanding (billions) | B6: 0.20653 | C6: Stock Analysis statistics, Oct 23, 2026
A7: Net cash, negative = net debt | B7: -26.85 | C7: Stock Analysis statistics, Oct 23, 2026: cash less total debt
A8: Other non-operating assets, less outside claims | B8: -15.82 | C8: Less public share of CQP: about 51.4% of CQP market cap $30.77B (Stock Analysis, Oct 16, 2026)
A9: Tax rate | B9: 0.18 | C9: Analyst assumption (normalized, near the reported effective rate)
A10: Discount rate (WACC), from WACC tab | B10: =WACC!F29 -> 0.075 | C10: Calculated or assumed, per the switch in WACC!B5
A11: Working capital, % of revenue change | B11: 0 | C11: Analyst assumption
A12: Base-year revenue (2026E) | B12: 22.6 | C12: 2026E consensus $22.6B (Stock Analysis). Revenue swings with gas prices; margin is the lever
A13: Selected scenario (1 Bear, 2 Base, 3 Bull) | B13: 2 | C13: Lever
A15: Year | B15: 2027 | C15: 2028 | D15: 2029 | E15: 2030 | F15: 2031 | G15: 2032 | H15: 2033 | I15: 2034 | J15: 2035 | K15: 2036 | L15: Terminal
A16: Discount period (years, mid-year) | B16: 0.5 | C16: =B16+1 -> 1.5 | D16: =C16+1 -> 2.5 | E16: =D16+1 -> 3.5 | F16: =E16+1 -> 4.5 | G16: =F16+1 -> 5.5 | H16: =G16+1 -> 6.5 | I16: =H16+1 -> 7.5 | J16: =I16+1 -> 8.5 | K16: =J16+1 -> 9.5
A17: Fade step (years 6 to 10) | B17: 0 | C17: 0 | D17: 0 | E17: 0 | F17: 0 | G17: 1 | H17: 2 | I17: 3 | J17: 4 | K17: 5
A19: Bear: LNG glut from 2027, weaker spot margins
A20: Revenue | B20: 21 | C20: 20.5 | D20: 21.5 | E20: 22.5 | F20: 23.5 | G20: =F20*(1+$F21+($L21-$F21)*G$17/5) -> 24.359056 | H20: =G20*(1+$F21+($L21-$F21)*H$17/5) -> 25.057348 | I20: =H20*(1+$F21+($L21-$F21)*I$17/5) -> 25.577984 | J20: =I20*(1+$F21+($L21-$F21)*J$17/5) -> 25.907656 | K20: =J20*(1+$F21+($L21-$F21)*K$17/5) -> 26.037195 | L20: =K20*(1+L21) -> 26.167381
A21: Revenue growth (terminal column = terminal growth, input) | B21: =B20/$B$12-1 -> -0.07079646 | C21: =C20/B20-1 -> -0.023809524 | D21: =D20/C20-1 -> 0.048780488 | E21: =E20/D20-1 -> 0.046511628 | F21: =F20/E20-1 -> 0.044444444 | G21: =G20/F20-1 -> 0.036555556 | H21: =H20/G20-1 -> 0.028666667 | I21: =I20/H20-1 -> 0.020777778 | J21: =J20/I20-1 -> 0.012888889 | K21: =K20/J20-1 -> 0.005 | L21: 0.005
A22: Operating margin | B22: 0.29 | C22: 0.28 | D22: 0.28 | E22: 0.28 | F22: 0.28 | G22: =$F22+($L22-$F22)*G$17/5 -> 0.278 | H22: =$F22+($L22-$F22)*H$17/5 -> 0.276 | I22: =$F22+($L22-$F22)*I$17/5 -> 0.274 | J22: =$F22+($L22-$F22)*J$17/5 -> 0.272 | K22: =$F22+($L22-$F22)*K$17/5 -> 0.27 | L22: 0.27
A23: Operating income | B23: =B20*B22 -> 6.09 | C23: =C20*C22 -> 5.74 | D23: =D20*D22 -> 6.02 | E23: =E20*E22 -> 6.3 | F23: =F20*F22 -> 6.58 | G23: =G20*G22 -> 6.7718174 | H23: =H20*H22 -> 6.9158282 | I23: =I20*I22 -> 7.0083678 | ... L23: =L20*L22 -> 7.0651927
A24: NOPAT | B24: =B23*(1-$B$9) -> 4.9938 | C24: =C23*(1-$B$9) -> 4.7068 | D24: =D23*(1-$B$9) -> 4.9364 | E24: =E23*(1-$B$9) -> 5.166 | F24: =F23*(1-$B$9) -> 5.3956 | G24: =G23*(1-$B$9) -> 5.5528903 | H24: =H23*(1-$B$9) -> 5.6709791 | I24: =I23*(1-$B$9) -> 5.7468616 | ... L24: =L23*(1-$B$9) -> 5.7934581
A25: Net reinvestment, % of revenue | B25: 0.08 | C25: 0.07 | D25: 0.05 | E25: 0.03 | F25: 0.02 | G25: =$F25+($L25-$F25)*G$17/5 -> 0.019 | H25: =$F25+($L25-$F25)*H$17/5 -> 0.018 | I25: =$F25+($L25-$F25)*I$17/5 -> 0.017 | J25: =$F25+($L25-$F25)*J$17/5 -> 0.016 | K25: =$F25+($L25-$F25)*K$17/5 -> 0.015 | L25: 0.015
A26: Net reinvestment | B26: =B20*B25 -> 1.68 | C26: =C20*C25 -> 1.435 | D26: =D20*D25 -> 1.075 | E26: =E20*E25 -> 0.675 | F26: =F20*F25 -> 0.47 | G26: =G20*G25 -> 0.46282206 | H26: =H20*H25 -> 0.45103227 | I26: =I20*I25 -> 0.43482574 | ... L26: =L20*L25 -> 0.39251071
A27: Change in working capital | B27: =$B$11*(B20-$B$12) -> 0 | C27: =$B$11*(C20-B20) -> 0 | D27: =$B$11*(D20-C20) -> 0 | E27: =$B$11*(E20-D20) -> 0 | F27: =$B$11*(F20-E20) -> 0 | G27: =$B$11*(G20-F20) -> 0 | H27: =$B$11*(H20-G20) -> 0 | I27: =$B$11*(I20-H20) -> 0 | J27: =$B$11*(J20-I20) -> 0 | ... L27: =$B$11*(L20-K20) -> 0
A28: Free cash flow | B28: =B24-B26-B27 -> 3.3138 | C28: =C24-C26-C27 -> 3.2718 | D28: =D24-D26-D27 -> 3.8614 | E28: =E24-E26-E27 -> 4.491 | F28: =F24-F26-F27 -> 4.9256 | G28: =G24-G26-G27 -> 5.0900682 | H28: =H24-H26-H27 -> 5.2199468 | I28: =I24-I26-I27 -> 5.3120358 | ... L28: =L24-L26-L27 -> 5.4009473
A29: Discount factor | B29: =1/(1+$B$10)^B$16 -> 0.96448564 | C29: =1/(1+$B$10)^C$16 -> 0.89719595 | D29: =1/(1+$B$10)^D$16 -> 0.83460088 | E29: =1/(1+$B$10)^E$16 -> 0.77637291 | F29: =1/(1+$B$10)^F$16 -> 0.72220736 | G29: =1/(1+$B$10)^G$16 -> 0.6718208 | H29: =1/(1+$B$10)^H$16 -> 0.62494958 | I29: =1/(1+$B$10)^I$16 -> 0.58134845 | ... K29: =1/(1+$B$10)^K$16 -> 0.50305977
A30: PV of free cash flow | B30: =B28*B29 -> 3.1961125 | C30: =C28*C29 -> 2.9354457 | D30: =D28*D29 -> 3.2227278 | E30: =E28*E29 -> 3.4866908 | F30: =F28*F29 -> 3.5573046 | G30: =G28*G29 -> 3.4196137 | H30: =H28*H29 -> 3.2622036 | I30: =I28*I29 -> 3.0881438 | ... K30: =K28*K29 -> 2.7034819
A31: Terminal value | B31: =L28/($B$10-L21) -> 77.156391 | C31: =IF($B$10>L21,"","Discount rate must exceed terminal growth")
A32: PV of terminal value | B32: =B31/(1+$B$10)^$K$16 -> 38.814276
A33: Equity value (PV FCF + PV TV + net cash + other) | B33: =SUM(B30:K30)+B32+$B$7+$B$8 -> 27.916752
A34: Value per share ($) | B34: =B33/$B$6 -> 135.17044
A35: Value vs share price | B35: =B34/$B$4-1 -> -0.54580587
A37: Base: expansions come online, contracts hold
A38: Revenue | B38: 23.4 | C38: 24.6 | D38: 25.8 | E38: 27.2 | F38: 28.6 | G38: =F38*(1+$F39+($L39-$F39)*G$17/5) -> 29.863447 | H38: =G38*(1+$F39+($L39-$F39)*H$17/5) -> 30.964881 | I38: =H38*(1+$F39+($L39-$F39)*I$17/5) -> 31.881077 | J38: =I38*(1+$F39+($L39-$F39)*J$17/5) -> 32.591838 | K38: =J38*(1+$F39+($L39-$F39)*K$17/5) -> 33.080716 | L38: =K38*(1+L39) -> 33.576926
A39: Revenue growth (terminal column = terminal growth, input) | B39: =B38/$B$12-1 -> 0.03539823 | C39: =C38/B38-1 -> 0.051282051 | D39: =D38/C38-1 -> 0.048780488 | E39: =E38/D38-1 -> 0.054263566 | F39: =F38/E38-1 -> 0.051470588 | G39: =G38/F38-1 -> 0.044176471 | H39: =H38/G38-1 -> 0.036882353 | I39: =I38/H38-1 -> 0.029588235 | J39: =J38/I38-1 -> 0.022294118 | K39: =K38/J38-1 -> 0.015 | L39: 0.015
A40: Operating margin | B40: 0.31 | C40: 0.31 | D40: 0.31 | E40: 0.31 | F40: 0.31 | G40: =$F40+($L40-$F40)*G$17/5 -> 0.306 | H40: =$F40+($L40-$F40)*H$17/5 -> 0.302 | I40: =$F40+($L40-$F40)*I$17/5 -> 0.298 | J40: =$F40+($L40-$F40)*J$17/5 -> 0.294 | K40: =$F40+($L40-$F40)*K$17/5 -> 0.29 | L40: 0.29
A41: Operating income | B41: =B38*B40 -> 7.254 | C41: =C38*C40 -> 7.626 | D41: =D38*D40 -> 7.998 | E41: =E38*E40 -> 8.432 | F41: =F38*F40 -> 8.866 | G41: =G38*G40 -> 9.1382148 | H41: =H38*H40 -> 9.3513941 | I41: =I38*I40 -> 9.5005611 | ... L41: =L38*L40 -> 9.7373086
A42: NOPAT | B42: =B41*(1-$B$9) -> 5.94828 | C42: =C41*(1-$B$9) -> 6.25332 | D42: =D41*(1-$B$9) -> 6.55836 | E42: =E41*(1-$B$9) -> 6.91424 | F42: =F41*(1-$B$9) -> 7.27012 | G42: =G41*(1-$B$9) -> 7.4933361 | H42: =H41*(1-$B$9) -> 7.6681432 | I42: =I41*(1-$B$9) -> 7.7904601 | ... L42: =L41*(1-$B$9) -> 7.9845931
A43: Net reinvestment, % of revenue | B43: 0.08 | C43: 0.07 | D43: 0.05 | E43: 0.03 | F43: 0.02 | G43: =$F43+($L43-$F43)*G$17/5 -> 0.019 | H43: =$F43+($L43-$F43)*H$17/5 -> 0.018 | I43: =$F43+($L43-$F43)*I$17/5 -> 0.017 | J43: =$F43+($L43-$F43)*J$17/5 -> 0.016 | K43: =$F43+($L43-$F43)*K$17/5 -> 0.015 | L43: 0.015
A44: Net reinvestment | B44: =B38*B43 -> 1.872 | C44: =C38*C43 -> 1.722 | D44: =D38*D43 -> 1.29 | E44: =E38*E43 -> 0.816 | F44: =F38*F43 -> 0.572 | G44: =G38*G43 -> 0.56740549 | H44: =H38*H43 -> 0.55736786 | I44: =I38*I43 -> 0.54197832 | ... L44: =L38*L43 -> 0.50365389
A45: Change in working capital | B45: =$B$11*(B38-$B$12) -> 0 | C45: =$B$11*(C38-B38) -> 0 | D45: =$B$11*(D38-C38) -> 0 | E45: =$B$11*(E38-D38) -> 0 | F45: =$B$11*(F38-E38) -> 0 | G45: =$B$11*(G38-F38) -> 0 | H45: =$B$11*(H38-G38) -> 0 | I45: =$B$11*(I38-H38) -> 0 | J45: =$B$11*(J38-I38) -> 0 | ... L45: =$B$11*(L38-K38) -> 0
A46: Free cash flow | B46: =B42-B44-B45 -> 4.07628 | C46: =C42-C44-C45 -> 4.53132 | D46: =D42-D44-D45 -> 5.26836 | E46: =E42-E44-E45 -> 6.09824 | F46: =F42-F44-F45 -> 6.69812 | G46: =G42-G44-G45 -> 6.9259306 | H46: =H42-H44-H45 -> 7.1107753 | I46: =I42-I44-I45 -> 7.2484818 | ... L46: =L42-L44-L45 -> 7.4809392
A47: Discount factor | B47: =1/(1+$B$10)^B$16 -> 0.96448564 | C47: =1/(1+$B$10)^C$16 -> 0.89719595 | D47: =1/(1+$B$10)^D$16 -> 0.83460088 | E47: =1/(1+$B$10)^E$16 -> 0.77637291 | F47: =1/(1+$B$10)^F$16 -> 0.72220736 | G47: =1/(1+$B$10)^G$16 -> 0.6718208 | H47: =1/(1+$B$10)^H$16 -> 0.62494958 | I47: =1/(1+$B$10)^I$16 -> 0.58134845 | ... K47: =1/(1+$B$10)^K$16 -> 0.50305977
A48: PV of free cash flow | B48: =B46*B47 -> 3.9315135 | C48: =C46*C47 -> 4.0654819 | D48: =D46*D47 -> 4.3969779 | E48: =E46*E47 -> 4.7345084 | F48: =F46*F47 -> 4.8374316 | G48: =G46*G47 -> 4.6529843 | H48: =H46*H47 -> 4.4438761 | I48: =I46*I47 -> 4.2138936 | ... K48: =K46*K47 -> 3.7077434
A49: Terminal value | B49: =L46/($B$10-L39) -> 124.68232 | C49: =IF($B$10>L39,"","Discount rate must exceed terminal growth")
A50: PV of terminal value | B50: =B49/(1+$B$10)^$K$16 -> 62.722659
A51: Equity value (PV FCF + PV TV + net cash + other) | B51: =SUM(B48:K48)+B50+$B$7+$B$8 -> 63.004176
A52: Value per share ($) | B52: =B51/$B$6 -> 305.06065
A53: Value vs share price | B53: =B52/$B$4-1 -> 0.025052165
A55: Bull: more trains sanctioned at good returns
A56: Revenue | B56: 24 | C56: 26 | D56: 28 | E56: 30 | F56: 32 | G56: =F56*(1+$F57+($L57-$F57)*G$17/5) -> 33.834667 | H56: =G56*(1+$F57+($L57-$F57)*H$17/5) -> 35.458731 | I56: =H56*(1+$F57+($L57-$F57)*I$17/5) -> 36.829802 | J56: =I56*(1+$F57+($L57-$F57)*J$17/5) -> 37.910142 | K56: =J56*(1+$F57+($L57-$F57)*K$17/5) -> 38.668345 | L56: =K56*(1+L57) -> 39.441712
A57: Revenue growth (terminal column = terminal growth, input) | B57: =B56/$B$12-1 -> 0.061946903 | C57: =C56/B56-1 -> 0.083333333 | D57: =D56/C56-1 -> 0.076923077 | E57: =E56/D56-1 -> 0.071428571 | F57: =F56/E56-1 -> 0.066666667 | G57: =G56/F56-1 -> 0.057333333 | H57: =H56/G56-1 -> 0.048 | I57: =I56/H56-1 -> 0.038666667 | J57: =J56/I56-1 -> 0.029333333 | K57: =K56/J56-1 -> 0.02 | L57: 0.02
A58: Operating margin | B58: 0.32 | C58: 0.32 | D58: 0.33 | E58: 0.33 | F58: 0.33 | G58: =$F58+($L58-$F58)*G$17/5 -> 0.326 | H58: =$F58+($L58-$F58)*H$17/5 -> 0.322 | I58: =$F58+($L58-$F58)*I$17/5 -> 0.318 | J58: =$F58+($L58-$F58)*J$17/5 -> 0.314 | K58: =$F58+($L58-$F58)*K$17/5 -> 0.31 | L58: 0.31
A59: Operating income | B59: =B56*B58 -> 7.68 | C59: =C56*C58 -> 8.32 | D59: =D56*D58 -> 9.24 | E59: =E56*E58 -> 9.9 | F59: =F56*F58 -> 10.56 | G59: =G56*G58 -> 11.030101 | H59: =H56*H58 -> 11.417711 | I59: =I56*I58 -> 11.711877 | ... L59: =L56*L58 -> 12.226931
A60: NOPAT | B60: =B59*(1-$B$9) -> 6.2976 | C60: =C59*(1-$B$9) -> 6.8224 | D60: =D59*(1-$B$9) -> 7.5768 | E60: =E59*(1-$B$9) -> 8.118 | F60: =F59*(1-$B$9) -> 8.6592 | G60: =G59*(1-$B$9) -> 9.0446831 | H60: =H59*(1-$B$9) -> 9.3625232 | I60: =I59*(1-$B$9) -> 9.6037391 | ... L60: =L59*(1-$B$9) -> 10.026083
A61: Net reinvestment, % of revenue | B61: 0.09 | C61: 0.08 | D61: 0.06 | E61: 0.04 | F61: 0.03 | G61: =$F61+($L61-$F61)*G$17/5 -> 0.028 | H61: =$F61+($L61-$F61)*H$17/5 -> 0.026 | I61: =$F61+($L61-$F61)*I$17/5 -> 0.024 | J61: =$F61+($L61-$F61)*J$17/5 -> 0.022 | K61: =$F61+($L61-$F61)*K$17/5 -> 0.02 | L61: 0.02
A62: Net reinvestment | B62: =B56*B61 -> 2.16 | C62: =C56*C61 -> 2.08 | D62: =D56*D61 -> 1.68 | E62: =E56*E61 -> 1.2 | F62: =F56*F61 -> 0.96 | G62: =G56*G61 -> 0.94737067 | H62: =H56*H61 -> 0.921927 | I62: =I56*I61 -> 0.88391524 | ... L62: =L56*L61 -> 0.78883424
A63: Change in working capital | B63: =$B$11*(B56-$B$12) -> 0 | C63: =$B$11*(C56-B56) -> 0 | D63: =$B$11*(D56-C56) -> 0 | E63: =$B$11*(E56-D56) -> 0 | F63: =$B$11*(F56-E56) -> 0 | G63: =$B$11*(G56-F56) -> 0 | H63: =$B$11*(H56-G56) -> 0 | I63: =$B$11*(I56-H56) -> 0 | J63: =$B$11*(J56-I56) -> 0 | ... L63: =$B$11*(L56-K56) -> 0
A64: Free cash flow | B64: =B60-B62-B63 -> 4.1376 | C64: =C60-C62-C63 -> 4.7424 | D64: =D60-D62-D63 -> 5.8968 | E64: =E60-E62-E63 -> 6.918 | F64: =F60-F62-F63 -> 7.6992 | G64: =G60-G62-G63 -> 8.0973124 | H64: =H60-H62-H63 -> 8.4405962 | I64: =I60-I62-I63 -> 8.7198238 | ... L64: =L60-L62-L63 -> 9.237249
A65: Discount factor | B65: =1/(1+$B$10)^B$16 -> 0.96448564 | C65: =1/(1+$B$10)^C$16 -> 0.89719595 | D65: =1/(1+$B$10)^D$16 -> 0.83460088 | E65: =1/(1+$B$10)^E$16 -> 0.77637291 | F65: =1/(1+$B$10)^F$16 -> 0.72220736 | G65: =1/(1+$B$10)^G$16 -> 0.6718208 | H65: =1/(1+$B$10)^H$16 -> 0.62494958 | I65: =1/(1+$B$10)^I$16 -> 0.58134845 | ... K65: =1/(1+$B$10)^K$16 -> 0.50305977
A66: PV of free cash flow | B66: =B64*B65 -> 3.9906558 | C66: =C64*C65 -> 4.2548621 | D66: =D64*D65 -> 4.9214745 | E66: =E64*E65 -> 5.3709478 | F66: =F64*F65 -> 5.5604189 | G66: =G64*G65 -> 5.4399429 | H66: =H64*H65 -> 5.2749471 | I66: =I64*I65 -> 5.0692561 | ... K66: =K64*K65 -> 4.5557729
A67: Terminal value | B67: =L64/($B$10-L57) -> 167.94998 | C67: =IF($B$10>L57,"","Discount rate must exceed terminal growth")
A68: PV of terminal value | B68: =B67/(1+$B$10)^$K$16 -> 84.48888
A69: Equity value (PV FCF + PV TV + net cash + other) | B69: =SUM(B66:K66)+B68+$B$7+$B$8 -> 91.084827
A70: Value per share ($) | B70: =B69/$B$6 -> 441.02468
A71: Value vs share price | B71: =B70/$B$4-1 -> 0.48191286
A74: Outputs | C74: vs price
A75: Bear value per share | B75: =B34 -> 135.17044 | C75: =B75/$B$4-1 -> -0.54580587
A76: Base value per share | B76: =B52 -> 305.06065 | C76: =B76/$B$4-1 -> 0.025052165
A77: Bull value per share | B77: =B70 -> 441.02468 | C77: =B77/$B$4-1 -> 0.48191286
A78: Selected scenario value per share | B78: =INDEX(B34:B70,1+($B$13-1)*18) -> 305.06065 | C78: =B78/$B$4-1 -> 0.025052165
A79: Share of base value from terminal value | B79: =B50/(SUM(B48:K48)+B50) -> 0.59354765
A81: Base value per share at other discount rates
A82: Discount rate | B82: 0.05 | C82: 0.06 | D82: 0.07 | E82: 0.08 | F82: 0.09 | G82: 0.1 | H82: 0.11 | I82: 0.12 | J82: 0.13 | K82: 0.14
A83: Base value per share | B83: =IF(B82>$L39,(SUMPRODUCT($B46:$K46/(1+B82)^$B$16:$K$16)+$L46/(B82-$L39)/(1+B82)^$K$16+$B$7+$B$8)/$B$6,"n/a") -> 678.5648 | C83: =IF(C82>$L39,(SUMPRODUCT($B46:$K46/(1+C82)^$B$16:$K$16)+$L46/(C82-$L39)/(1+C82)^$K$16+$B$7+$B$8)/$B$6,"n/a") -> 479.25759 | D83: =IF(D82>$L39,(SUMPRODUCT($B46:$K46/(1+D82)^$B$16:$K$16)+$L46/(D82-$L39)/(1+D82)^$K$16+$B$7+$B$8)/$B$6,"n/a") -> 352.54102 | E83: =IF(E82>$L39,(SUMPRODUCT($B46:$K46/(1+E82)^$B$16:$K$16)+$L46/(E82-$L39)/(1+E82)^$K$16+$B$7+$B$8)/$B$6,"n/a") -> 264.90793 | F83: =IF(F82>$L39,(SUMPRODUCT($B46:$K46/(1+F82)^$B$16:$K$16)+$L46/(F82-$L39)/(1+F82)^$K$16+$B$7+$B$8)/$B$6,"n/a") -> 200.72175 | G83: =IF(G82>$L39,(SUMPRODUCT($B46:$K46/(1+G82)^$B$16:$K$16)+$L46/(G82-$L39)/(1+G82)^$K$16+$B$7+$B$8)/$B$6,"n/a") -> 151.70438 | H83: =IF(H82>$L39,(SUMPRODUCT($B46:$K46/(1+H82)^$B$16:$K$16)+$L46/(H82-$L39)/(1+H82)^$K$16+$B$7+$B$8)/$B$6,"n/a") -> 113.06335 | I83: =IF(I82>$L39,(SUMPRODUCT($B46:$K46/(1+I82)^$B$16:$K$16)+$L46/(I82-$L39)/(1+I82)^$K$16+$B$7+$B$8)/$B$6,"n/a") -> 81.83195 | ... K83: =IF(K82>$L39,(SUMPRODUCT($B46:$K46/(1+K82)^$B$16:$K$16)+$L46/(K82-$L39)/(1+K82)^$K$16+$B$7+$B$8)/$B$6,"n/a") -> 34.478271
A84: vs share price | B84: =IFERROR(B83/$B$4-1,"n/a") -> 1.2800853 | C84: =IFERROR(C83/$B$4-1,"n/a") -> 0.6103815 | D84: =IFERROR(D83/$B$4-1,"n/a") -> 0.18459374 | E84: =IFERROR(E83/$B$4-1,"n/a") -> -0.10986735 | F84: =IFERROR(F83/$B$4-1,"n/a") -> -0.3255431 | G84: =IFERROR(G83/$B$4-1,"n/a") -> -0.49024921 | H84: =IFERROR(H83/$B$4-1,"n/a") -> -0.62008921 | I84: =IFERROR(I83/$B$4-1,"n/a") -> -0.72503167 | ... K84: =IFERROR(K83/$B$4-1,"n/a") -> -0.88414754
A86: Implied annual return at today's price, base case | B86: =IFERROR(IF(MATCH($B$4,$B$83:$K$83,-1)=10,"above 14%",INDEX($B$82:$K$82,MATCH($B$4,$B$83:$K$83,-1))+(INDEX($B$83:$K$83,MATCH($B$4,$B$83:$K$83,-1))-$B$4)/(INDEX($B$83:$K$83,MATCH($B$4,$B$83:$K$83,-1))-INDEX($B$83:$K$83,MATCH($B$4,$B$83:$K$83,-1)+1))*(INDEX($B$82:$K$82,MATCH($B$4,$B$83:$K$83,-1)+1)-INDEX($B$82:$K$82,MATCH($B$4,$B$83:$K$83,-1)))),"below 5%") -> 0.076268867 | C86: Discount rate at which base value equals the price (interpolated from the row above)

Sheet NOW
A1: ServiceNow (NOW): 10-year scenario DCF
A2: Units: $ billions unless noted. Blue = input, black = formula, green = link, yellow = key lever. Years 6 to 10 fade growth, margin and reinvestment toward each scenario's terminal levels.
A4: Share price ($) | B4: 156.84 | C4: Oct 23, 2026 intraday (Yahoo Finance via the site's price feed)
A5: Price date | B5: Oct 23, 2026 | C5: Text
A6: Shares outstanding (billions) | B6: 1.03 | C6: Stock Analysis statistics, Oct 23, 2026
A7: Net cash, negative = net debt | B7: -1.75 | C7: Stock Analysis statistics, Oct 23, 2026: cash less total debt
A8: Other non-operating assets, less outside claims | B8: 0 | C8: Long-term investments excluded (conservative)
A9: Tax rate | B9: 0.2 | C9: Analyst assumption (normalized, near the reported effective rate)
A10: Discount rate (WACC), from WACC tab | B10: =WACC!G29 -> 0.095 | C10: Calculated or assumed, per the switch in WACC!B5
A11: Working capital, % of revenue change | B11: -0.05 | C11: Analyst assumption
A12: Base-year revenue (2026E) | B12: 16.22 | C12: 2026E consensus $16.22B (Stock Analysis). Margins are after stock pay (GAAP-like), not the 31.5% non-GAAP figure
A13: Selected scenario (1 Bear, 2 Base, 3 Bull) | B13: 2 | C13: Lever
A15: Year | B15: 2027 | C15: 2028 | D15: 2029 | E15: 2030 | F15: 2031 | G15: 2032 | H15: 2033 | I15: 2034 | J15: 2035 | K15: 2036 | L15: Terminal
A16: Discount period (years, mid-year) | B16: 0.5 | C16: =B16+1 -> 1.5 | D16: =C16+1 -> 2.5 | E16: =D16+1 -> 3.5 | F16: =E16+1 -> 4.5 | G16: =F16+1 -> 5.5 | H16: =G16+1 -> 6.5 | I16: =H16+1 -> 7.5 | J16: =I16+1 -> 8.5 | K16: =J16+1 -> 9.5
A17: Fade step (years 6 to 10) | B17: 0 | C17: 0 | D17: 0 | E17: 0 | F17: 0 | G17: 1 | H17: 2 | I17: 3 | J17: 4 | K17: 5
A19: Bear: AI agents compress seat pricing
A20: Revenue | B20: 18.3 | C20: 20.3 | D20: 22.2 | E20: 24 | F20: 25.7 | G20: =F20*(1+$F21+($L21-$F21)*G$17/5) -> 27.336233 | H20: =G20*(1+$F21+($L21-$F21)*H$17/5) -> 28.880731 | I20: =H20*(1+$F21+($L21-$F21)*I$17/5) -> 30.305513 | J20: =I20*(1+$F21+($L21-$F21)*J$17/5) -> 31.583396 | K20: =J20*(1+$F21+($L21-$F21)*K$17/5) -> 32.688815 | L20: =K20*(1+L21) -> 33.832923
A21: Revenue growth (terminal column = terminal growth, input) | B21: =B20/$B$12-1 -> 0.12823674 | C21: =C20/B20-1 -> 0.10928962 | D21: =D20/C20-1 -> 0.093596059 | E21: =E20/D20-1 -> 0.081081081 | F21: =F20/E20-1 -> 0.070833333 | G21: =G20/F20-1 -> 0.063666667 | H21: =H20/G20-1 -> 0.0565 | I21: =I20/H20-1 -> 0.049333333 | J21: =J20/I20-1 -> 0.042166667 | K21: =K20/J20-1 -> 0.035 | L21: 0.035
A22: Operating margin | B22: 0.17 | C22: 0.18 | D22: 0.19 | E22: 0.2 | F22: 0.21 | G22: =$F22+($L22-$F22)*G$17/5 -> 0.214 | H22: =$F22+($L22-$F22)*H$17/5 -> 0.218 | I22: =$F22+($L22-$F22)*I$17/5 -> 0.222 | J22: =$F22+($L22-$F22)*J$17/5 -> 0.226 | K22: =$F22+($L22-$F22)*K$17/5 -> 0.23 | L22: 0.23
A23: Operating income | B23: =B20*B22 -> 3.111 | C23: =C20*C22 -> 3.654 | D23: =D20*D22 -> 4.218 | E23: =E20*E22 -> 4.8 | F23: =F20*F22 -> 5.397 | G23: =G20*G22 -> 5.8499539 | H23: =H20*H22 -> 6.2959993 | I23: =I20*I22 -> 6.7278239 | ... L23: =L20*L22 -> 7.7815723
A24: NOPAT | B24: =B23*(1-$B$9) -> 2.4888 | C24: =C23*(1-$B$9) -> 2.9232 | D24: =D23*(1-$B$9) -> 3.3744 | E24: =E23*(1-$B$9) -> 3.84 | F24: =F23*(1-$B$9) -> 4.3176 | G24: =G23*(1-$B$9) -> 4.6799631 | H24: =H23*(1-$B$9) -> 5.0367994 | I24: =I23*(1-$B$9) -> 5.3822591 | ... L24: =L23*(1-$B$9) -> 6.2252578
A25: Net reinvestment, % of revenue | B25: 0.03 | C25: 0.03 | D25: 0.03 | E25: 0.03 | F25: 0.03 | G25: =$F25+($L25-$F25)*G$17/5 -> 0.028 | H25: =$F25+($L25-$F25)*H$17/5 -> 0.026 | I25: =$F25+($L25-$F25)*I$17/5 -> 0.024 | J25: =$F25+($L25-$F25)*J$17/5 -> 0.022 | K25: =$F25+($L25-$F25)*K$17/5 -> 0.02 | L25: 0.02
A26: Net reinvestment | B26: =B20*B25 -> 0.549 | C26: =C20*C25 -> 0.609 | D26: =D20*D25 -> 0.666 | E26: =E20*E25 -> 0.72 | F26: =F20*F25 -> 0.771 | G26: =G20*G25 -> 0.76541453 | H26: =H20*H25 -> 0.75089899 | I26: =I20*I25 -> 0.72733232 | ... L26: =L20*L25 -> 0.67665846
A27: Change in working capital | B27: =$B$11*(B20-$B$12) -> -0.104 | C27: =$B$11*(C20-B20) -> -0.1 | D27: =$B$11*(D20-C20) -> -0.095 | E27: =$B$11*(E20-D20) -> -0.09 | F27: =$B$11*(F20-E20) -> -0.085 | G27: =$B$11*(G20-F20) -> -0.081811667 | H27: =$B$11*(H20-G20) -> -0.077224859 | I27: =$B$11*(I20-H20) -> -0.071239135 | J27: =$B$11*(J20-I20) -> -0.063894124 | ... L27: =$B$11*(L20-K20) -> -0.057205425
A28: Free cash flow | B28: =B24-B26-B27 -> 2.0438 | C28: =C24-C26-C27 -> 2.4142 | D28: =D24-D26-D27 -> 2.8034 | E28: =E24-E26-E27 -> 3.21 | F28: =F24-F26-F27 -> 3.6316 | G28: =G24-G26-G27 -> 3.9963603 | H28: =H24-H26-H27 -> 4.3631253 | I28: =I24-I26-I27 -> 4.726166 | ... L28: =L24-L26-L27 -> 5.6058048
A29: Discount factor | B29: =1/(1+$B$10)^B$16 -> 0.95563697 | C29: =1/(1+$B$10)^C$16 -> 0.87272782 | D29: =1/(1+$B$10)^D$16 -> 0.79701171 | E29: =1/(1+$B$10)^E$16 -> 0.72786458 | F29: =1/(1+$B$10)^F$16 -> 0.66471651 | G29: =1/(1+$B$10)^G$16 -> 0.60704704 | H29: =1/(1+$B$10)^H$16 -> 0.55438086 | I29: =1/(1+$B$10)^I$16 -> 0.50628389 | ... K29: =1/(1+$B$10)^K$16 -> 0.42224631
A30: PV of free cash flow | B30: =B28*B29 -> 1.9531308 | C30: =C28*C29 -> 2.1069395 | D30: =D28*D29 -> 2.2343426 | E30: =E28*E29 -> 2.3364453 | F30: =F28*F29 -> 2.4139845 | G30: =G28*G29 -> 2.4259787 | H30: =H28*H29 -> 2.4188331 | I30: =I28*I29 -> 2.3927817 | ... K30: =K28*K29 -> 2.2869859
A31: Terminal value | B31: =L28/($B$10-L21) -> 93.43008 | C31: =IF($B$10>L21,"","Discount rate must exceed terminal growth")
A32: PV of terminal value | B32: =B31/(1+$B$10)^$K$16 -> 39.450507
A33: Equity value (PV FCF + PV TV + net cash + other) | B33: =SUM(B30:K30)+B32+$B$7+$B$8 -> 60.61841
A34: Value per share ($) | B34: =B33/$B$6 -> 58.852825
A35: Value vs share price | B35: =B34/$B$4-1 -> -0.62475883
A37: Base: growth slows from 19% to 11%
A38: Revenue | B38: 19.2 | C38: 22.4 | D38: 25.8 | E38: 29.2 | F38: 32.6 | G38: =F38*(1+$F39+($L39-$F39)*G$17/5) -> 35.897512 | H38: =G38*(1+$F39+($L39-$F39)*H$17/5) -> 38.979781 | I38: =H38*(1+$F39+($L39-$F39)*I$17/5) -> 41.730792 | J38: =I38*(1+$F39+($L39-$F39)*J$17/5) -> 44.037991 | K38: =J38*(1+$F39+($L39-$F39)*K$17/5) -> 45.79951 | L38: =K38*(1+L39) -> 47.631491
A39: Revenue growth (terminal column = terminal growth, input) | B39: =B38/$B$12-1 -> 0.1837238 | C39: =C38/B38-1 -> 0.16666667 | D39: =D38/C38-1 -> 0.15178571 | E39: =E38/D38-1 -> 0.13178295 | F39: =F38/E38-1 -> 0.11643836 | G39: =G38/F38-1 -> 0.10115068 | H39: =H38/G38-1 -> 0.085863014 | I39: =I38/H38-1 -> 0.070575342 | J39: =J38/I38-1 -> 0.055287671 | K39: =K38/J38-1 -> 0.04 | L39: 0.04
A40: Operating margin | B40: 0.19 | C40: 0.21 | D40: 0.23 | E40: 0.245 | F40: 0.26 | G40: =$F40+($L40-$F40)*G$17/5 -> 0.262 | H40: =$F40+($L40-$F40)*H$17/5 -> 0.264 | I40: =$F40+($L40-$F40)*I$17/5 -> 0.266 | J40: =$F40+($L40-$F40)*J$17/5 -> 0.268 | K40: =$F40+($L40-$F40)*K$17/5 -> 0.27 | L40: 0.27
A41: Operating income | B41: =B38*B40 -> 3.648 | C41: =C38*C40 -> 4.704 | D41: =D38*D40 -> 5.934 | E41: =E38*E40 -> 7.154 | F41: =F38*F40 -> 8.476 | G41: =G38*G40 -> 9.4051482 | H41: =H38*H40 -> 10.290662 | I41: =I38*I40 -> 11.100391 | ... L41: =L38*L40 -> 12.860502
A42: NOPAT | B42: =B41*(1-$B$9) -> 2.9184 | C42: =C41*(1-$B$9) -> 3.7632 | D42: =D41*(1-$B$9) -> 4.7472 | E42: =E41*(1-$B$9) -> 5.7232 | F42: =F41*(1-$B$9) -> 6.7808 | G42: =G41*(1-$B$9) -> 7.5241186 | H42: =H41*(1-$B$9) -> 8.2325297 | I42: =I41*(1-$B$9) -> 8.8803126 | ... L42: =L41*(1-$B$9) -> 10.288402
A43: Net reinvestment, % of revenue | B43: 0.03 | C43: 0.03 | D43: 0.03 | E43: 0.03 | F43: 0.03 | G43: =$F43+($L43-$F43)*G$17/5 -> 0.028 | H43: =$F43+($L43-$F43)*H$17/5 -> 0.026 | I43: =$F43+($L43-$F43)*I$17/5 -> 0.024 | J43: =$F43+($L43-$F43)*J$17/5 -> 0.022 | K43: =$F43+($L43-$F43)*K$17/5 -> 0.02 | L43: 0.02
A44: Net reinvestment | B44: =B38*B43 -> 0.576 | C44: =C38*C43 -> 0.672 | D44: =D38*D43 -> 0.774 | E44: =E38*E43 -> 0.876 | F44: =F38*F43 -> 0.978 | G44: =G38*G43 -> 1.0051303 | H44: =H38*H43 -> 1.0134743 | I44: =I38*I43 -> 1.001539 | ... L44: =L38*L43 -> 0.95262981
A45: Change in working capital | B45: =$B$11*(B38-$B$12) -> -0.149 | C45: =$B$11*(C38-B38) -> -0.16 | D45: =$B$11*(D38-C38) -> -0.17 | E45: =$B$11*(E38-D38) -> -0.17 | F45: =$B$11*(F38-E38) -> -0.17 | G45: =$B$11*(G38-F38) -> -0.16487562 | H45: =$B$11*(H38-G38) -> -0.15411343 | I45: =$B$11*(I38-H38) -> -0.13755057 | J45: =$B$11*(J38-I38) -> -0.11535992 | ... L45: =$B$11*(L38-K38) -> -0.091599021
A46: Free cash flow | B46: =B42-B44-B45 -> 2.4914 | C46: =C42-C44-C45 -> 3.2512 | D46: =D42-D44-D45 -> 4.1432 | E46: =E42-E44-E45 -> 5.0172 | F46: =F42-F44-F45 -> 5.9728 | G46: =G42-G44-G45 -> 6.6838639 | H46: =H42-H44-H45 -> 7.3731689 | I46: =I42-I44-I45 -> 8.0163242 | ... L46: =L42-L44-L45 -> 9.4273712
A47: Discount factor | B47: =1/(1+$B$10)^B$16 -> 0.95563697 | C47: =1/(1+$B$10)^C$16 -> 0.87272782 | D47: =1/(1+$B$10)^D$16 -> 0.79701171 | E47: =1/(1+$B$10)^E$16 -> 0.72786458 | F47: =1/(1+$B$10)^F$16 -> 0.66471651 | G47: =1/(1+$B$10)^G$16 -> 0.60704704 | H47: =1/(1+$B$10)^H$16 -> 0.55438086 | I47: =1/(1+$B$10)^I$16 -> 0.50628389 | ... K47: =1/(1+$B$10)^K$16 -> 0.42224631
A48: PV of free cash flow | B48: =B46*B47 -> 2.3808739 | C48: =C46*C47 -> 2.8374127 | D48: =D46*D47 -> 3.3021789 | E48: =E46*E47 -> 3.6518421 | F48: =F46*F47 -> 3.9702188 | G48: =G46*G47 -> 4.0574198 | H48: =H46*H47 -> 4.0875437 | I48: =I46*I47 -> 4.0585358 | ... K48: =K46*K47 -> 3.8275699
A49: Terminal value | B49: =L46/($B$10-L39) -> 171.40675 | C49: =IF($B$10>L39,"","Discount rate must exceed terminal growth")
A50: PV of terminal value | B50: =B49/(1+$B$10)^$K$16 -> 72.375868
A51: Equity value (PV FCF + PV TV + net cash + other) | B51: =SUM(B48:K48)+B50+$B$7+$B$8 -> 106.77033
A52: Value per share ($) | B52: =B51/$B$6 -> 103.66052
A53: Value vs share price | B53: =B52/$B$4-1 -> -0.33906836
A55: Bull: AI agents expand the platform
A56: Revenue | B56: 19.6 | C56: 23.6 | D56: 28 | E56: 32.7 | F56: 37.6 | G56: =F56*(1+$F57+($L57-$F57)*G$17/5) -> 42.445801 | H56: =G56*(1+$F57+($L57-$F57)*H$17/5) -> 47.026053 | I56: =H56*(1+$F57+($L57-$F57)*I$17/5) -> 51.114443 | J56: =I56*(1+$F57+($L57-$F57)*J$17/5) -> 54.486433 | K56: =J56*(1+$F57+($L57-$F57)*K$17/5) -> 56.938323 | L56: =K56*(1+L57) -> 59.500548
A57: Revenue growth (terminal column = terminal growth, input) | B57: =B56/$B$12-1 -> 0.20838471 | C57: =C56/B56-1 -> 0.20408163 | D57: =D56/C56-1 -> 0.18644068 | E57: =E56/D56-1 -> 0.16785714 | F57: =F56/E56-1 -> 0.14984709 | G57: =G56/F56-1 -> 0.12887768 | H57: =H56/G56-1 -> 0.10790826 | I57: =I56/H56-1 -> 0.086938838 | J57: =J56/I56-1 -> 0.065969419 | K57: =K56/J56-1 -> 0.045 | L57: 0.045
A58: Operating margin | B58: 0.2 | C58: 0.23 | D58: 0.25 | E58: 0.27 | F58: 0.28 | G58: =$F58+($L58-$F58)*G$17/5 -> 0.284 | H58: =$F58+($L58-$F58)*H$17/5 -> 0.288 | I58: =$F58+($L58-$F58)*I$17/5 -> 0.292 | J58: =$F58+($L58-$F58)*J$17/5 -> 0.296 | K58: =$F58+($L58-$F58)*K$17/5 -> 0.3 | L58: 0.3
A59: Operating income | B59: =B56*B58 -> 3.92 | C59: =C56*C58 -> 5.428 | D59: =D56*D58 -> 7 | E59: =E56*E58 -> 8.829 | F59: =F56*F58 -> 10.528 | G59: =G56*G58 -> 12.054607 | H59: =H56*H58 -> 13.543503 | I59: =I56*I58 -> 14.925417 | ... L59: =L56*L58 -> 17.850164
A60: NOPAT | B60: =B59*(1-$B$9) -> 3.136 | C60: =C59*(1-$B$9) -> 4.3424 | D60: =D59*(1-$B$9) -> 5.6 | E60: =E59*(1-$B$9) -> 7.0632 | F60: =F59*(1-$B$9) -> 8.4224 | G60: =G59*(1-$B$9) -> 9.6436859 | H60: =H59*(1-$B$9) -> 10.834803 | I60: =I59*(1-$B$9) -> 11.940334 | ... L60: =L59*(1-$B$9) -> 14.280131
A61: Net reinvestment, % of revenue | B61: 0.03 | C61: 0.03 | D61: 0.03 | E61: 0.03 | F61: 0.03 | G61: =$F61+($L61-$F61)*G$17/5 -> 0.028 | H61: =$F61+($L61-$F61)*H$17/5 -> 0.026 | I61: =$F61+($L61-$F61)*I$17/5 -> 0.024 | J61: =$F61+($L61-$F61)*J$17/5 -> 0.022 | K61: =$F61+($L61-$F61)*K$17/5 -> 0.02 | L61: 0.02
A62: Net reinvestment | B62: =B56*B61 -> 0.588 | C62: =C56*C61 -> 0.708 | D62: =D56*D61 -> 0.84 | E62: =E56*E61 -> 0.981 | F62: =F56*F61 -> 1.128 | G62: =G56*G61 -> 1.1884824 | H62: =H56*H61 -> 1.2226774 | I62: =I56*I61 -> 1.2267466 | ... L62: =L56*L61 -> 1.190011
A63: Change in working capital | B63: =$B$11*(B56-$B$12) -> -0.169 | C63: =$B$11*(C56-B56) -> -0.2 | D63: =$B$11*(D56-C56) -> -0.22 | E63: =$B$11*(E56-D56) -> -0.235 | F63: =$B$11*(F56-E56) -> -0.245 | G63: =$B$11*(G56-F56) -> -0.24229003 | H63: =$B$11*(H56-G56) -> -0.22901262 | I63: =$B$11*(I56-H56) -> -0.20441952 | J63: =$B$11*(J56-I56) -> -0.16859951 | ... L63: =$B$11*(L56-K56) -> -0.12811123
A64: Free cash flow | B64: =B60-B62-B63 -> 2.717 | C64: =C60-C62-C63 -> 3.8344 | D64: =D60-D62-D63 -> 4.98 | E64: =E60-E62-E63 -> 6.3172 | F64: =F60-F62-F63 -> 7.5394 | G64: =G60-G62-G63 -> 8.6974935 | H64: =H60-H62-H63 -> 9.8411378 | I64: =I60-I62-I63 -> 10.918007 | ... L64: =L60-L62-L63 -> 13.218232
A65: Discount factor | B65: =1/(1+$B$10)^B$16 -> 0.95563697 | C65: =1/(1+$B$10)^C$16 -> 0.87272782 | D65: =1/(1+$B$10)^D$16 -> 0.79701171 | E65: =1/(1+$B$10)^E$16 -> 0.72786458 | F65: =1/(1+$B$10)^F$16 -> 0.66471651 | G65: =1/(1+$B$10)^G$16 -> 0.60704704 | H65: =1/(1+$B$10)^H$16 -> 0.55438086 | I65: =1/(1+$B$10)^I$16 -> 0.50628389 | ... K65: =1/(1+$B$10)^K$16 -> 0.42224631
A66: PV of free cash flow | B66: =B64*B65 -> 2.5964656 | C66: =C64*C65 -> 3.3463876 | D66: =D64*D65 -> 3.9691183 | E66: =E64*E65 -> 4.5980661 | F66: =F64*F65 -> 5.0115636 | G66: =G64*G65 -> 5.2797877 | H66: =H64*H65 -> 5.4557384 | I66: =I64*I65 -> 5.527611 | ... K66: =K64*K65 -> 5.3410044
A67: Terminal value | B67: =L64/($B$10-L57) -> 264.36463 | C67: =IF($B$10>L57,"","Discount rate must exceed terminal growth")
A68: PV of terminal value | B68: =B67/(1+$B$10)^$K$16 -> 111.62699
A69: Equity value (PV FCF + PV TV + net cash + other) | B69: =SUM(B66:K66)+B68+$B$7+$B$8 -> 156.492
A70: Value per share ($) | B70: =B69/$B$6 -> 151.93398
A71: Value vs share price | B71: =B70/$B$4-1 -> -0.0312804
A74: Outputs | C74: vs price
A75: Bear value per share | B75: =B34 -> 58.852825 | C75: =B75/$B$4-1 -> -0.62475883
A76: Base value per share | B76: =B52 -> 103.66052 | C76: =B76/$B$4-1 -> -0.33906836
A77: Bull value per share | B77: =B70 -> 151.93398 | C77: =B77/$B$4-1 -> -0.0312804
A78: Selected scenario value per share | B78: =INDEX(B34:B70,1+($B$13-1)*18) -> 103.66052 | C78: =B78/$B$4-1 -> -0.33906836
A79: Share of base value from terminal value | B79: =B50/(SUM(B48:K48)+B50) -> 0.66693371
A81: Base value per share at other discount rates
A82: Discount rate | B82: 0.05 | C82: 0.06 | D82: 0.07 | E82: 0.08 | F82: 0.09 | G82: 0.1 | H82: 0.11 | I82: 0.12 | J82: 0.13 | K82: 0.14
A83: Base value per share | B83: =IF(B82>$L39,(SUMPRODUCT($B46:$K46/(1+B82)^$B$16:$K$16)+$L46/(B82-$L39)/(1+B82)^$K$16+$B$7+$B$8)/$B$6,"n/a") -> 618.3126 | C83: =IF(C82>$L39,(SUMPRODUCT($B46:$K46/(1+C82)^$B$16:$K$16)+$L46/(C82-$L39)/(1+C82)^$K$16+$B$7+$B$8)/$B$6,"n/a") -> 303.3313 | D83: =IF(D82>$L39,(SUMPRODUCT($B46:$K46/(1+D82)^$B$16:$K$16)+$L46/(D82-$L39)/(1+D82)^$K$16+$B$7+$B$8)/$B$6,"n/a") -> 198.52762 | E83: =IF(E82>$L39,(SUMPRODUCT($B46:$K46/(1+E82)^$B$16:$K$16)+$L46/(E82-$L39)/(1+E82)^$K$16+$B$7+$B$8)/$B$6,"n/a") -> 146.25871 | F83: =IF(F82>$L39,(SUMPRODUCT($B46:$K46/(1+F82)^$B$16:$K$16)+$L46/(F82-$L39)/(1+F82)^$K$16+$B$7+$B$8)/$B$6,"n/a") -> 114.9966 | G83: =IF(G82>$L39,(SUMPRODUCT($B46:$K46/(1+G82)^$B$16:$K$16)+$L46/(G82-$L39)/(1+G82)^$K$16+$B$7+$B$8)/$B$6,"n/a") -> 94.232448 | H83: =IF(H82>$L39,(SUMPRODUCT($B46:$K46/(1+H82)^$B$16:$K$16)+$L46/(H82-$L39)/(1+H82)^$K$16+$B$7+$B$8)/$B$6,"n/a") -> 79.462821 | I83: =IF(I82>$L39,(SUMPRODUCT($B46:$K46/(1+I82)^$B$16:$K$16)+$L46/(I82-$L39)/(1+I82)^$K$16+$B$7+$B$8)/$B$6,"n/a") -> 68.436298 | ... K83: =IF(K82>$L39,(SUMPRODUCT($B46:$K46/(1+K82)^$B$16:$K$16)+$L46/(K82-$L39)/(1+K82)^$K$16+$B$7+$B$8)/$B$6,"n/a") -> 53.110757
A84: vs share price | B84: =IFERROR(B83/$B$4-1,"n/a") -> 2.9423144 | C84: =IFERROR(C83/$B$4-1,"n/a") -> 0.93401744 | D84: =IFERROR(D83/$B$4-1,"n/a") -> 0.26579713 | E84: =IFERROR(E83/$B$4-1,"n/a") -> -0.067465512 | F84: =IFERROR(F83/$B$4-1,"n/a") -> -0.26679035 | G84: =IFERROR(G83/$B$4-1,"n/a") -> -0.39918103 | H84: =IFERROR(H83/$B$4-1,"n/a") -> -0.49335105 | I84: =IFERROR(I83/$B$4-1,"n/a") -> -0.56365533 | ... K84: =IFERROR(K83/$B$4-1,"n/a") -> -0.66136982
A86: Implied annual return at today's price, base case | B86: =IFERROR(IF(MATCH($B$4,$B$83:$K$83,-1)=10,"above 14%",INDEX($B$82:$K$82,MATCH($B$4,$B$83:$K$83,-1))+(INDEX($B$83:$K$83,MATCH($B$4,$B$83:$K$83,-1))-$B$4)/(INDEX($B$83:$K$83,MATCH($B$4,$B$83:$K$83,-1))-INDEX($B$83:$K$83,MATCH($B$4,$B$83:$K$83,-1)+1))*(INDEX($B$82:$K$82,MATCH($B$4,$B$83:$K$83,-1)+1)-INDEX($B$82:$K$82,MATCH($B$4,$B$83:$K$83,-1)))),"below 5%") -> 0.077975605 | C86: Discount rate at which base value equals the price (interpolated from the row above)

Sheet CLS
A1: Celestica (CLS): 10-year scenario DCF
A2: Units: $ billions unless noted. Blue = input, black = formula, green = link, yellow = key lever. Years 6 to 10 fade growth, margin and reinvestment toward each scenario's terminal levels.
A4: Share price ($) | B4: 246.65 | C4: Oct 26, 2026 close (before results)
A5: Price date | B5: Oct 26, 2026 close (before results) | C5: Text
A6: Shares outstanding (billions) | B6: 0.1261 | C6: 126.1M shares at Sep 30, 2026, after the August offering of 11.1M shares at $310 (Q3 2026 release)
A7: Net cash, negative = net debt | B7: 3.1425 | C7: Q3 2026 release: cash $3,961M less borrowings and leases $819M
A8: Other non-operating assets, less outside claims | B8: 0 | C8: None
A9: Tax rate | B9: 0.21 | C9: Analyst assumption (normalized, near the reported effective rate)
A10: Discount rate (WACC), from WACC tab | B10: =WACC!H29 -> 0.105 | C10: Calculated or assumed, per the switch in WACC!B5
A11: Working capital, % of revenue change | B11: 0.1 | C11: Analyst assumption
A12: Base-year revenue (2026E) | B12: 21 | C12: 2026 outlook $21.0B (raised from $20.5B, Q3 2026 release). 2027 outlook: $40.0B revenue, 9.0% adjusted operating margin, $21.50 adjusted EPS, $1.5B to $2.0B capex. Margins here are after stock pay, about 0.4 points below adjusted
A13: Selected scenario (1 Bear, 2 Base, 3 Bull) | B13: 2 | C13: Lever
A15: Year | B15: 2027 | C15: 2028 | D15: 2029 | E15: 2030 | F15: 2031 | G15: 2032 | H15: 2033 | I15: 2034 | J15: 2035 | K15: 2036 | L15: Terminal
A16: Discount period (years, mid-year) | B16: 0.5 | C16: =B16+1 -> 1.5 | D16: =C16+1 -> 2.5 | E16: =D16+1 -> 3.5 | F16: =E16+1 -> 4.5 | G16: =F16+1 -> 5.5 | H16: =G16+1 -> 6.5 | I16: =H16+1 -> 7.5 | J16: =I16+1 -> 8.5 | K16: =J16+1 -> 9.5
A17: Fade step (years 6 to 10) | B17: 0 | C17: 0 | D17: 0 | E17: 0 | F17: 0 | G17: 1 | H17: 2 | I17: 3 | J17: 4 | K17: 5
A19: Bear: a large customer pauses, 2027 misses and 2028 falls
A20: Revenue | B20: 33 | C20: 28 | D20: 27 | E20: 29 | F20: 31 | G20: =F20*(1+$F21+($L21-$F21)*G$17/5) -> 32.865345 | H20: =G20*(1+$F21+($L21-$F21)*H$17/5) -> 34.553944 | I20: =H20*(1+$F21+($L21-$F21)*I$17/5) -> 36.025465 | J20: =I20*(1+$F21+($L21-$F21)*J$17/5) -> 37.242877 | K20: =J20*(1+$F21+($L21-$F21)*K$17/5) -> 38.173949 | L20: =K20*(1+L21) -> 39.128298
A21: Revenue growth (terminal column = terminal growth, input) | B21: =B20/$B$12-1 -> 0.57142857 | C21: =C20/B20-1 -> -0.15151515 | D21: =D20/C20-1 -> -0.035714286 | E21: =E20/D20-1 -> 0.074074074 | F21: =F20/E20-1 -> 0.068965517 | G21: =G20/F20-1 -> 0.060172414 | H21: =H20/G20-1 -> 0.05137931 | I21: =I20/H20-1 -> 0.042586207 | J21: =J20/I20-1 -> 0.033793103 | K21: =K20/J20-1 -> 0.025 | L21: 0.025
A22: Operating margin | B22: 0.08 | C22: 0.07 | D22: 0.065 | E22: 0.065 | F22: 0.065 | G22: =$F22+($L22-$F22)*G$17/5 -> 0.064 | H22: =$F22+($L22-$F22)*H$17/5 -> 0.063 | I22: =$F22+($L22-$F22)*I$17/5 -> 0.062 | J22: =$F22+($L22-$F22)*J$17/5 -> 0.061 | K22: =$F22+($L22-$F22)*K$17/5 -> 0.06 | L22: 0.06
A23: Operating income | B23: =B20*B22 -> 2.64 | C23: =C20*C22 -> 1.96 | D23: =D20*D22 -> 1.755 | E23: =E20*E22 -> 1.885 | F23: =F20*F22 -> 2.015 | G23: =G20*G22 -> 2.1033821 | H23: =H20*H22 -> 2.1768984 | I23: =I20*I22 -> 2.2335788 | ... L23: =L20*L22 -> 2.3476979
A24: NOPAT | B24: =B23*(1-$B$9) -> 2.0856 | C24: =C23*(1-$B$9) -> 1.5484 | D24: =D23*(1-$B$9) -> 1.38645 | E24: =E23*(1-$B$9) -> 1.48915 | F24: =F23*(1-$B$9) -> 1.59185 | G24: =G23*(1-$B$9) -> 1.6616718 | H24: =H23*(1-$B$9) -> 1.7197498 | I24: =I23*(1-$B$9) -> 1.7645273 | ... L24: =L23*(1-$B$9) -> 1.8546813
A25: Net reinvestment, % of revenue | B25: 0.035 | C25: 0.02 | D25: 0.012 | E25: 0.012 | F25: 0.012 | G25: =$F25+($L25-$F25)*G$17/5 -> 0.0116 | H25: =$F25+($L25-$F25)*H$17/5 -> 0.0112 | I25: =$F25+($L25-$F25)*I$17/5 -> 0.0108 | J25: =$F25+($L25-$F25)*J$17/5 -> 0.0104 | K25: =$F25+($L25-$F25)*K$17/5 -> 0.01 | L25: 0.01
A26: Net reinvestment | B26: =B20*B25 -> 1.155 | C26: =C20*C25 -> 0.56 | D26: =D20*D25 -> 0.324 | E26: =E20*E25 -> 0.348 | F26: =F20*F25 -> 0.372 | G26: =G20*G25 -> 0.381238 | H26: =H20*H25 -> 0.38700417 | I26: =I20*I25 -> 0.38907502 | ... L26: =L20*L25 -> 0.39128298
A27: Change in working capital | B27: =$B$11*(B20-$B$12) -> 1.2 | C27: =$B$11*(C20-B20) -> -0.5 | D27: =$B$11*(D20-C20) -> -0.1 | E27: =$B$11*(E20-D20) -> 0.2 | F27: =$B$11*(F20-E20) -> 0.2 | G27: =$B$11*(G20-F20) -> 0.18653448 | H27: =$B$11*(H20-G20) -> 0.16885988 | I27: =$B$11*(I20-H20) -> 0.14715214 | J27: =$B$11*(J20-I20) -> 0.12174123 | ... L27: =$B$11*(L20-K20) -> 0.095434873
A28: Free cash flow | B28: =B24-B26-B27 -> -0.2694 | C28: =C24-C26-C27 -> 1.4884 | D28: =D24-D26-D27 -> 1.16245 | E28: =E24-E26-E27 -> 0.94115 | F28: =F24-F26-F27 -> 1.01985 | G28: =G24-G26-G27 -> 1.0938994 | H28: =H24-H26-H27 -> 1.1638857 | I28: =I24-I26-I27 -> 1.2283001 | ... L28: =L24-L26-L27 -> 1.3679635
A29: Discount factor | B29: =1/(1+$B$10)^B$16 -> 0.95130299 | C29: =1/(1+$B$10)^C$16 -> 0.86090768 | D29: =1/(1+$B$10)^D$16 -> 0.77910197 | E29: =1/(1+$B$10)^E$16 -> 0.70506966 | F29: =1/(1+$B$10)^F$16 -> 0.63807209 | G29: =1/(1+$B$10)^G$16 -> 0.57744081 | H29: =1/(1+$B$10)^H$16 -> 0.52257087 | I29: =1/(1+$B$10)^I$16 -> 0.47291481 | ... K29: =1/(1+$B$10)^K$16 -> 0.38730969
A30: PV of free cash flow | B30: =B28*B29 -> -0.25628103 | C30: =C28*C29 -> 1.281375 | D30: =D28*D29 -> 0.90566709 | E30: =E28*E29 -> 0.66357631 | F30: =F28*F29 -> 0.65073782 | G30: =G28*G29 -> 0.63166212 | H30: =H28*H29 -> 0.60821277 | I30: =I28*I29 -> 0.58088131 | ... K30: =K28*K29 -> 0.51690293
A31: Terminal value | B31: =L28/($B$10-L21) -> 17.099543 | C31: =IF($B$10>L21,"","Discount rate must exceed terminal growth")
A32: PV of terminal value | B32: =B31/(1+$B$10)^$K$16 -> 6.6228188
A33: Equity value (PV FCF + PV TV + net cash + other) | B33: =SUM(B30:K30)+B32+$B$7+$B$8 -> 15.898289
A34: Value per share ($) | B34: =B33/$B$6 -> 126.07684
A35: Value vs share price | B35: =B34/$B$4-1 -> -0.48884314
A37: Base: 2027 lands 8% below the outlook, 2028 grows, 2029 digests
A38: Revenue | B38: 37 | C38: 42 | D38: 40 | E38: 42 | F38: 44 | G38: =F38*(1+$F39+($L39-$F39)*G$17/5) -> 45.94019 | H38: =G38*(1+$F39+($L39-$F39)*H$17/5) -> 47.80405 | I38: =H38*(1+$F39+($L39-$F39)*I$17/5) -> 49.575076 | J38: =I38*(1+$F39+($L39-$F39)*J$17/5) -> 51.237021 | K38: =J38*(1+$F39+($L39-$F39)*K$17/5) -> 52.774132 | L38: =K38*(1+L39) -> 54.357356
A39: Revenue growth (terminal column = terminal growth, input) | B39: =B38/$B$12-1 -> 0.76190476 | C39: =C38/B38-1 -> 0.13513514 | D39: =D38/C38-1 -> -0.047619048 | E39: =E38/D38-1 -> 0.05 | F39: =F38/E38-1 -> 0.047619048 | G39: =G38/F38-1 -> 0.044095238 | H39: =H38/G38-1 -> 0.040571429 | I39: =I38/H38-1 -> 0.037047619 | J39: =J38/I38-1 -> 0.03352381 | K39: =K38/J38-1 -> 0.03 | L39: 0.03
A40: Operating margin | B40: 0.086 | C40: 0.086 | D40: 0.082 | E40: 0.08 | F40: 0.08 | G40: =$F40+($L40-$F40)*G$17/5 -> 0.078 | H40: =$F40+($L40-$F40)*H$17/5 -> 0.076 | I40: =$F40+($L40-$F40)*I$17/5 -> 0.074 | J40: =$F40+($L40-$F40)*J$17/5 -> 0.072 | K40: =$F40+($L40-$F40)*K$17/5 -> 0.07 | L40: 0.07
A41: Operating income | B41: =B38*B40 -> 3.182 | C41: =C38*C40 -> 3.612 | D41: =D38*D40 -> 3.28 | E41: =E38*E40 -> 3.36 | F41: =F38*F40 -> 3.52 | G41: =G38*G40 -> 3.5833349 | H41: =H38*H40 -> 3.6331078 | I41: =I38*I40 -> 3.6685556 | ... L41: =L38*L40 -> 3.8050149
A42: NOPAT | B42: =B41*(1-$B$9) -> 2.51378 | C42: =C41*(1-$B$9) -> 2.85348 | D42: =D41*(1-$B$9) -> 2.5912 | E42: =E41*(1-$B$9) -> 2.6544 | F42: =F41*(1-$B$9) -> 2.7808 | G42: =G41*(1-$B$9) -> 2.8308345 | H42: =H41*(1-$B$9) -> 2.8701551 | I42: =I41*(1-$B$9) -> 2.8981589 | ... L42: =L41*(1-$B$9) -> 3.0059618
A43: Net reinvestment, % of revenue | B43: 0.035 | C43: 0.025 | D43: 0.015 | E43: 0.015 | F43: 0.015 | G43: =$F43+($L43-$F43)*G$17/5 -> 0.014 | H43: =$F43+($L43-$F43)*H$17/5 -> 0.013 | I43: =$F43+($L43-$F43)*I$17/5 -> 0.012 | J43: =$F43+($L43-$F43)*J$17/5 -> 0.011 | K43: =$F43+($L43-$F43)*K$17/5 -> 0.01 | L43: 0.01
A44: Net reinvestment | B44: =B38*B43 -> 1.295 | C44: =C38*C43 -> 1.05 | D44: =D38*D43 -> 0.6 | E44: =E38*E43 -> 0.63 | F44: =F38*F43 -> 0.66 | G44: =G38*G43 -> 0.64316267 | H44: =H38*H43 -> 0.62145265 | I44: =I38*I43 -> 0.59490091 | ... L44: =L38*L43 -> 0.54357356
A45: Change in working capital | B45: =$B$11*(B38-$B$12) -> 1.6 | C45: =$B$11*(C38-B38) -> 0.5 | D45: =$B$11*(D38-C38) -> -0.2 | E45: =$B$11*(E38-D38) -> 0.2 | F45: =$B$11*(F38-E38) -> 0.2 | G45: =$B$11*(G38-F38) -> 0.19401905 | H45: =$B$11*(H38-G38) -> 0.18638592 | I45: =$B$11*(I38-H38) -> 0.17710262 | J45: =$B$11*(J38-I38) -> 0.16619454 | ... L45: =$B$11*(L38-K38) -> 0.1583224
A46: Free cash flow | B46: =B42-B44-B45 -> -0.38122 | C46: =C42-C44-C45 -> 1.30348 | D46: =D42-D44-D45 -> 2.1912 | E46: =E42-E44-E45 -> 1.8244 | F46: =F42-F44-F45 -> 1.9208 | G46: =G42-G44-G45 -> 1.9936528 | H46: =H42-H44-H45 -> 2.0623166 | I46: =I42-I44-I45 -> 2.1261554 | ... L46: =L42-L44-L45 -> 2.3040658
A47: Discount factor | B47: =1/(1+$B$10)^B$16 -> 0.95130299 | C47: =1/(1+$B$10)^C$16 -> 0.86090768 | D47: =1/(1+$B$10)^D$16 -> 0.77910197 | E47: =1/(1+$B$10)^E$16 -> 0.70506966 | F47: =1/(1+$B$10)^F$16 -> 0.63807209 | G47: =1/(1+$B$10)^G$16 -> 0.57744081 | H47: =1/(1+$B$10)^H$16 -> 0.52257087 | I47: =1/(1+$B$10)^I$16 -> 0.47291481 | ... K47: =1/(1+$B$10)^K$16 -> 0.38730969
A48: PV of free cash flow | B48: =B46*B47 -> -0.36265573 | C48: =C46*C47 -> 1.1221759 | D48: =D46*D47 -> 1.7071682 | E48: =E46*E47 -> 1.2863291 | F48: =F46*F47 -> 1.2256089 | G48: =G46*G47 -> 1.1512165 | H48: =H46*H47 -> 1.0777066 | I48: =I46*I47 -> 1.0054904 | ... K48: =K46*K47 -> 0.86639516
A49: Terminal value | B49: =L46/($B$10-L39) -> 30.720878 | C49: =IF($B$10>L39,"","Discount rate must exceed terminal growth")
A50: PV of terminal value | B50: =B49/(1+$B$10)^$K$16 -> 11.898493
A51: Equity value (PV FCF + PV TV + net cash + other) | B51: =SUM(B48:K48)+B50+$B$7+$B$8 -> 25.05537
A52: Value per share ($) | B52: =B51/$B$6 -> 198.69445
A53: Value vs share price | B53: =B52/$B$4-1 -> -0.19442752
A55: Bull: the $40B outlook is met and 2028 is meaningfully higher
A56: Revenue | B56: 40 | C56: 50 | D56: 54 | E56: 58 | F56: 62 | G56: =F56*(1+$F57+($L57-$F57)*G$17/5) -> 65.85469 | H56: =G56*(1+$F57+($L57-$F57)*H$17/5) -> 69.501677 | I56: =H56*(1+$F57+($L57-$F57)*I$17/5) -> 72.8785 | J56: =I56*(1+$F57+($L57-$F57)*J$17/5) -> 75.924318 | K56: =J56*(1+$F57+($L57-$F57)*K$17/5) -> 78.58167 | L56: =K56*(1+L57) -> 81.332028
A57: Revenue growth (terminal column = terminal growth, input) | B57: =B56/$B$12-1 -> 0.9047619 | C57: =C56/B56-1 -> 0.25 | D57: =D56/C56-1 -> 0.08 | E57: =E56/D56-1 -> 0.074074074 | F57: =F56/E56-1 -> 0.068965517 | G57: =G56/F56-1 -> 0.062172414 | H57: =H56/G56-1 -> 0.05537931 | I57: =I56/H56-1 -> 0.048586207 | J57: =J56/I56-1 -> 0.041793103 | K57: =K56/J56-1 -> 0.035 | L57: 0.035
A58: Operating margin | B58: 0.088 | C58: 0.09 | D58: 0.09 | E58: 0.09 | F58: 0.088 | G58: =$F58+($L58-$F58)*G$17/5 -> 0.0864 | H58: =$F58+($L58-$F58)*H$17/5 -> 0.0848 | I58: =$F58+($L58-$F58)*I$17/5 -> 0.0832 | J58: =$F58+($L58-$F58)*J$17/5 -> 0.0816 | K58: =$F58+($L58-$F58)*K$17/5 -> 0.08 | L58: 0.08
A59: Operating income | B59: =B56*B58 -> 3.52 | C59: =C56*C58 -> 4.5 | D59: =D56*D58 -> 4.86 | E59: =E56*E58 -> 5.22 | F59: =F56*F58 -> 5.456 | G59: =G56*G58 -> 5.6898452 | H59: =H56*H58 -> 5.8937422 | I59: =I56*I58 -> 6.0634912 | ... L59: =L56*L58 -> 6.5065622
A60: NOPAT | B60: =B59*(1-$B$9) -> 2.7808 | C60: =C59*(1-$B$9) -> 3.555 | D60: =D59*(1-$B$9) -> 3.8394 | E60: =E59*(1-$B$9) -> 4.1238 | F60: =F59*(1-$B$9) -> 4.31024 | G60: =G59*(1-$B$9) -> 4.4949777 | H60: =H59*(1-$B$9) -> 4.6560563 | I60: =I59*(1-$B$9) -> 4.790158 | ... L60: =L59*(1-$B$9) -> 5.1401842
A61: Net reinvestment, % of revenue | B61: 0.04 | C61: 0.03 | D61: 0.02 | E61: 0.015 | F61: 0.015 | G61: =$F61+($L61-$F61)*G$17/5 -> 0.014 | H61: =$F61+($L61-$F61)*H$17/5 -> 0.013 | I61: =$F61+($L61-$F61)*I$17/5 -> 0.012 | J61: =$F61+($L61-$F61)*J$17/5 -> 0.011 | K61: =$F61+($L61-$F61)*K$17/5 -> 0.01 | L61: 0.01
A62: Net reinvestment | B62: =B56*B61 -> 1.6 | C62: =C56*C61 -> 1.5 | D62: =D56*D61 -> 1.08 | E62: =E56*E61 -> 0.87 | F62: =F56*F61 -> 0.93 | G62: =G56*G61 -> 0.92196566 | H62: =H56*H61 -> 0.9035218 | I62: =I56*I61 -> 0.874542 | ... L62: =L56*L61 -> 0.81332028
A63: Change in working capital | B63: =$B$11*(B56-$B$12) -> 1.9 | C63: =$B$11*(C56-B56) -> 1 | D63: =$B$11*(D56-C56) -> 0.4 | E63: =$B$11*(E56-D56) -> 0.4 | F63: =$B$11*(F56-E56) -> 0.4 | G63: =$B$11*(G56-F56) -> 0.38546897 | H63: =$B$11*(H56-G56) -> 0.36469873 | I63: =$B$11*(I56-H56) -> 0.33768229 | J63: =$B$11*(J56-I56) -> 0.30458187 | ... L63: =$B$11*(L56-K56) -> 0.27503584
A64: Free cash flow | B64: =B60-B62-B63 -> -0.7192 | C64: =C60-C62-C63 -> 1.055 | D64: =D60-D62-D63 -> 2.3594 | E64: =E60-E62-E63 -> 2.8538 | F64: =F60-F62-F63 -> 2.98024 | G64: =G60-G62-G63 -> 3.1875431 | H64: =H60-H62-H63 -> 3.3878358 | I64: =I60-I62-I63 -> 3.5779338 | ... L64: =L60-L62-L63 -> 4.051828
A65: Discount factor | B65: =1/(1+$B$10)^B$16 -> 0.95130299 | C65: =1/(1+$B$10)^C$16 -> 0.86090768 | D65: =1/(1+$B$10)^D$16 -> 0.77910197 | E65: =1/(1+$B$10)^E$16 -> 0.70506966 | F65: =1/(1+$B$10)^F$16 -> 0.63807209 | G65: =1/(1+$B$10)^G$16 -> 0.57744081 | H65: =1/(1+$B$10)^H$16 -> 0.52257087 | I65: =1/(1+$B$10)^I$16 -> 0.47291481 | ... K65: =1/(1+$B$10)^K$16 -> 0.38730969
A66: PV of free cash flow | B66: =B64*B65 -> -0.68417711 | C66: =C64*C65 -> 0.9082576 | D66: =D64*D65 -> 1.8382132 | E66: =E64*E65 -> 2.0121278 | F66: =F64*F65 -> 1.901608 | G66: =G64*G65 -> 1.8406174 | H66: =H64*H65 -> 1.7703843 | I66: =I64*I65 -> 1.6920579 | ... K66: =K64*K65 -> 1.5162437
A67: Terminal value | B67: =L64/($B$10-L57) -> 57.883258 | C67: =IF($B$10>L57,"","Discount rate must exceed terminal growth")
A68: PV of terminal value | B68: =B67/(1+$B$10)^$K$16 -> 22.418746
A69: Equity value (PV FCF + PV TV + net cash + other) | B69: =SUM(B66:K66)+B68+$B$7+$B$8 -> 39.963478
A70: Value per share ($) | B70: =B69/$B$6 -> 316.91894
A71: Value vs share price | B71: =B70/$B$4-1 -> 0.28489331
A74: Outputs | C74: vs price
A75: Bear value per share | B75: =B34 -> 126.07684 | C75: =B75/$B$4-1 -> -0.48884314
A76: Base value per share | B76: =B52 -> 198.69445 | C76: =B76/$B$4-1 -> -0.19442752
A77: Bull value per share | B77: =B70 -> 316.91894 | C77: =B77/$B$4-1 -> 0.28489331
A78: Selected scenario value per share | B78: =INDEX(B34:B70,1+($B$13-1)*18) -> 198.69445 | C78: =B78/$B$4-1 -> -0.19442752
A79: Share of base value from terminal value | B79: =B50/(SUM(B48:K48)+B50) -> 0.5429911
A81: Base value per share at other discount rates
A82: Discount rate | B82: 0.05 | C82: 0.06 | D82: 0.07 | E82: 0.08 | F82: 0.09 | G82: 0.1 | H82: 0.11 | I82: 0.12 | J82: 0.13 | K82: 0.14
A83: Base value per share | B83: =IF(B82>$L39,(SUMPRODUCT($B46:$K46/(1+B82)^$B$16:$K$16)+$L46/(B82-$L39)/(1+B82)^$K$16+$B$7+$B$8)/$B$6,"n/a") -> 704.39451 | C83: =IF(C82>$L39,(SUMPRODUCT($B46:$K46/(1+C82)^$B$16:$K$16)+$L46/(C82-$L39)/(1+C82)^$K$16+$B$7+$B$8)/$B$6,"n/a") -> 474.46434 | D83: =IF(D82>$L39,(SUMPRODUCT($B46:$K46/(1+D82)^$B$16:$K$16)+$L46/(D82-$L39)/(1+D82)^$K$16+$B$7+$B$8)/$B$6,"n/a") -> 359.52096 | E83: =IF(E82>$L39,(SUMPRODUCT($B46:$K46/(1+E82)^$B$16:$K$16)+$L46/(E82-$L39)/(1+E82)^$K$16+$B$7+$B$8)/$B$6,"n/a") -> 290.57266 | F83: =IF(F82>$L39,(SUMPRODUCT($B46:$K46/(1+F82)^$B$16:$K$16)+$L46/(F82-$L39)/(1+F82)^$K$16+$B$7+$B$8)/$B$6,"n/a") -> 244.62214 | G83: =IF(G82>$L39,(SUMPRODUCT($B46:$K46/(1+G82)^$B$16:$K$16)+$L46/(G82-$L39)/(1+G82)^$K$16+$B$7+$B$8)/$B$6,"n/a") -> 211.81337 | H83: =IF(H82>$L39,(SUMPRODUCT($B46:$K46/(1+H82)^$B$16:$K$16)+$L46/(H82-$L39)/(1+H82)^$K$16+$B$7+$B$8)/$B$6,"n/a") -> 187.21829 | I83: =IF(I82>$L39,(SUMPRODUCT($B46:$K46/(1+I82)^$B$16:$K$16)+$L46/(I82-$L39)/(1+I82)^$K$16+$B$7+$B$8)/$B$6,"n/a") -> 168.09906 | ... K83: =IF(K82>$L39,(SUMPRODUCT($B46:$K46/(1+K82)^$B$16:$K$16)+$L46/(K82-$L39)/(1+K82)^$K$16+$B$7+$B$8)/$B$6,"n/a") -> 140.3146
A84: vs share price | B84: =IFERROR(B83/$B$4-1,"n/a") -> 1.8558464 | C84: =IFERROR(C83/$B$4-1,"n/a") -> 0.92363406 | D84: =IFERROR(D83/$B$4-1,"n/a") -> 0.45761589 | E84: =IFERROR(E83/$B$4-1,"n/a") -> 0.17807687 | F84: =IFERROR(F83/$B$4-1,"n/a") -> -0.0082216096 | G84: =IFERROR(G83/$B$4-1,"n/a") -> -0.14123914 | H84: =IFERROR(H83/$B$4-1,"n/a") -> -0.24095566 | I84: =IFERROR(I83/$B$4-1,"n/a") -> -0.31847128 | ... K84: =IFERROR(K83/$B$4-1,"n/a") -> -0.43111859
A86: Implied annual return at today's price, base case | B86: =IFERROR(IF(MATCH($B$4,$B$83:$K$83,-1)=10,"above 14%",INDEX($B$82:$K$82,MATCH($B$4,$B$83:$K$83,-1))+(INDEX($B$83:$K$83,MATCH($B$4,$B$83:$K$83,-1))-$B$4)/(INDEX($B$83:$K$83,MATCH($B$4,$B$83:$K$83,-1))-INDEX($B$83:$K$83,MATCH($B$4,$B$83:$K$83,-1)+1))*(INDEX($B$82:$K$82,MATCH($B$4,$B$83:$K$83,-1)+1)-INDEX($B$82:$K$82,MATCH($B$4,$B$83:$K$83,-1)))),"below 5%") -> 0.089558686 | C86: Discount rate at which base value equals the price (interpolated from the row above)

Sheet EPD
A1: Enterprise Products (EPD): 10-year scenario DCF
A2: Units: $ billions unless noted. Blue = input, black = formula, green = link, yellow = key lever. Years 6 to 10 fade growth, margin and reinvestment toward each scenario's terminal levels.
A4: Share price ($) | B4: 37.405 | C4: Oct 23, 2026 intraday (Yahoo Finance via the site's price feed)
A5: Price date | B5: Oct 23, 2026 | C5: Text
A6: Shares outstanding (billions) | B6: 2.16 | C6: Stock Analysis statistics, Oct 23, 2026
A7: Net cash, negative = net debt | B7: -33.96 | C7: Stock Analysis statistics, Oct 23, 2026: cash less total debt
A8: Other non-operating assets, less outside claims | B8: 0 | C8: None. Partnership: no entity tax, so the discount rate is set without a tax shield
A9: Tax rate | B9: 0 | C9: Analyst assumption (normalized, near the reported effective rate)
A10: Discount rate (WACC), from WACC tab | B10: =WACC!I29 -> 0.08 | C10: Calculated or assumed, per the switch in WACC!B5
A11: Working capital, % of revenue change | B11: 0 | C11: Analyst assumption
A12: Base-year revenue (2026E) | B12: 58.5 | C12: TTM revenue $58.47B (Stock Analysis). Revenue swings with commodity prices
A13: Selected scenario (1 Bear, 2 Base, 3 Bull) | B13: 2 | C13: Lever
A15: Year | B15: 2027 | C15: 2028 | D15: 2029 | E15: 2030 | F15: 2031 | G15: 2032 | H15: 2033 | I15: 2034 | J15: 2035 | K15: 2036 | L15: Terminal
A16: Discount period (years, mid-year) | B16: 0.5 | C16: =B16+1 -> 1.5 | D16: =C16+1 -> 2.5 | E16: =D16+1 -> 3.5 | F16: =E16+1 -> 4.5 | G16: =F16+1 -> 5.5 | H16: =G16+1 -> 6.5 | I16: =H16+1 -> 7.5 | J16: =I16+1 -> 8.5 | K16: =J16+1 -> 9.5
A17: Fade step (years 6 to 10) | B17: 0 | C17: 0 | D17: 0 | E17: 0 | F17: 0 | G17: 1 | H17: 2 | I17: 3 | J17: 4 | K17: 5
A19: Bear: volumes flat, spreads tighten
A20: Revenue | B20: 57 | C20: 57 | D20: 57.5 | E20: 58 | F20: 58.5 | G20: =F20*(1+$F21+($L21-$F21)*G$17/5) -> 59.020448 | H20: =G20*(1+$F21+($L21-$F21)*H$17/5) -> 59.561808 | I20: =H20*(1+$F21+($L21-$F21)*I$17/5) -> 60.124565 | J20: =I20*(1+$F21+($L21-$F21)*J$17/5) -> 60.709224 | K20: =J20*(1+$F21+($L21-$F21)*K$17/5) -> 61.316316 | L20: =K20*(1+L21) -> 61.92948
A21: Revenue growth (terminal column = terminal growth, input) | B21: =B20/$B$12-1 -> -0.025641026 | C21: =C20/B20-1 -> 0 | D21: =D20/C20-1 -> 0.0087719298 | E21: =E20/D20-1 -> 0.0086956522 | F21: =F20/E20-1 -> 0.0086206897 | G21: =G20/F20-1 -> 0.0088965517 | H21: =H20/G20-1 -> 0.0091724138 | I21: =I20/H20-1 -> 0.0094482759 | J21: =J20/I20-1 -> 0.0097241379 | K21: =K20/J20-1 -> 0.01 | L21: 0.01
A22: Operating margin | B22: 0.12 | C22: 0.12 | D22: 0.12 | E22: 0.12 | F22: 0.12 | G22: =$F22+($L22-$F22)*G$17/5 -> 0.119 | H22: =$F22+($L22-$F22)*H$17/5 -> 0.118 | I22: =$F22+($L22-$F22)*I$17/5 -> 0.117 | J22: =$F22+($L22-$F22)*J$17/5 -> 0.116 | K22: =$F22+($L22-$F22)*K$17/5 -> 0.115 | L22: 0.115
A23: Operating income | B23: =B20*B22 -> 6.84 | C23: =C20*C22 -> 6.84 | D23: =D20*D22 -> 6.9 | E23: =E20*E22 -> 6.96 | F23: =F20*F22 -> 7.02 | G23: =G20*G22 -> 7.0234333 | H23: =H20*H22 -> 7.0282934 | I23: =I20*I22 -> 7.0345741 | ... L23: =L20*L22 -> 7.1218902
A24: NOPAT | B24: =B23*(1-$B$9) -> 6.84 | C24: =C23*(1-$B$9) -> 6.84 | D24: =D23*(1-$B$9) -> 6.9 | E24: =E23*(1-$B$9) -> 6.96 | F24: =F23*(1-$B$9) -> 7.02 | G24: =G23*(1-$B$9) -> 7.0234333 | H24: =H23*(1-$B$9) -> 7.0282934 | I24: =I23*(1-$B$9) -> 7.0345741 | ... L24: =L23*(1-$B$9) -> 7.1218902
A25: Net reinvestment, % of revenue | B25: 0.05 | C25: 0.04 | D25: 0.03 | E25: 0.025 | F25: 0.02 | G25: =$F25+($L25-$F25)*G$17/5 -> 0.02 | H25: =$F25+($L25-$F25)*H$17/5 -> 0.02 | I25: =$F25+($L25-$F25)*I$17/5 -> 0.02 | J25: =$F25+($L25-$F25)*J$17/5 -> 0.02 | K25: =$F25+($L25-$F25)*K$17/5 -> 0.02 | L25: 0.02
A26: Net reinvestment | B26: =B20*B25 -> 2.85 | C26: =C20*C25 -> 2.28 | D26: =D20*D25 -> 1.725 | E26: =E20*E25 -> 1.45 | F26: =F20*F25 -> 1.17 | G26: =G20*G25 -> 1.180409 | H26: =H20*H25 -> 1.1912362 | I26: =I20*I25 -> 1.2024913 | ... L26: =L20*L25 -> 1.2385896
A27: Change in working capital | B27: =$B$11*(B20-$B$12) -> 0 | C27: =$B$11*(C20-B20) -> 0 | D27: =$B$11*(D20-C20) -> 0 | E27: =$B$11*(E20-D20) -> 0 | F27: =$B$11*(F20-E20) -> 0 | G27: =$B$11*(G20-F20) -> 0 | H27: =$B$11*(H20-G20) -> 0 | I27: =$B$11*(I20-H20) -> 0 | J27: =$B$11*(J20-I20) -> 0 | ... L27: =$B$11*(L20-K20) -> 0
A28: Free cash flow | B28: =B24-B26-B27 -> 3.99 | C28: =C24-C26-C27 -> 4.56 | D28: =D24-D26-D27 -> 5.175 | E28: =E24-E26-E27 -> 5.51 | F28: =F24-F26-F27 -> 5.85 | G28: =G24-G26-G27 -> 5.8430244 | H28: =H24-H26-H27 -> 5.8370572 | I28: =I24-I26-I27 -> 5.8320828 | ... L28: =L24-L26-L27 -> 5.8833006
A29: Discount factor | B29: =1/(1+$B$10)^B$16 -> 0.96225045 | C29: =1/(1+$B$10)^C$16 -> 0.89097264 | D29: =1/(1+$B$10)^D$16 -> 0.82497466 | E29: =1/(1+$B$10)^E$16 -> 0.76386543 | F29: =1/(1+$B$10)^F$16 -> 0.70728281 | G29: =1/(1+$B$10)^G$16 -> 0.65489149 | H29: =1/(1+$B$10)^H$16 -> 0.60638101 | I29: =1/(1+$B$10)^I$16 -> 0.56146389 | ... K29: =1/(1+$B$10)^K$16 -> 0.48136479
A30: PV of free cash flow | B30: =B28*B29 -> 3.8393793 | C30: =C28*C29 -> 4.0628352 | D30: =D28*D29 -> 4.2692439 | E30: =E28*E29 -> 4.2088985 | F30: =F28*F29 -> 4.1376044 | G30: =G28*G29 -> 3.8265469 | H30: =H28*H29 -> 3.5394806 | I30: =I28*I29 -> 3.2745039 | ... K30: =K28*K29 -> 2.803974
A31: Terminal value | B31: =L28/($B$10-L21) -> 84.047151 | C31: =IF($B$10>L21,"","Discount rate must exceed terminal growth")
A32: PV of terminal value | B32: =B31/(1+$B$10)^$K$16 -> 40.457339
A33: Equity value (PV FCF + PV TV + net cash + other) | B33: =SUM(B30:K30)+B32+$B$7+$B$8 -> 43.489676
A34: Value per share ($) | B34: =B33/$B$6 -> 20.134109
A35: Value vs share price | B35: =B34/$B$4-1 -> -0.46172679
A37: Base: Permian volumes grow, capex normalizes
A38: Revenue | B38: 60 | C38: 61.5 | D38: 63 | E38: 64.5 | F38: 66 | G38: =F38*(1+$F39+($L39-$F39)*G$17/5) -> 67.491907 | H38: =G38*(1+$F39+($L39-$F39)*H$17/5) -> 68.97359 | I38: =H38*(1+$F39+($L39-$F39)*I$17/5) -> 70.442888 | J38: =I38*(1+$F39+($L39-$F39)*J$17/5) -> 71.897615 | K38: =J38*(1+$F39+($L39-$F39)*K$17/5) -> 73.335567 | L38: =K38*(1+L39) -> 74.802279
A39: Revenue growth (terminal column = terminal growth, input) | B39: =B38/$B$12-1 -> 0.025641026 | C39: =C38/B38-1 -> 0.025 | D39: =D38/C38-1 -> 0.024390244 | E39: =E38/D38-1 -> 0.023809524 | F39: =F38/E38-1 -> 0.023255814 | G39: =G38/F38-1 -> 0.022604651 | H39: =H38/G38-1 -> 0.021953488 | I39: =I38/H38-1 -> 0.021302326 | J39: =J38/I38-1 -> 0.020651163 | K39: =K38/J38-1 -> 0.02 | L39: 0.02
A40: Operating margin | B40: 0.13 | C40: 0.13 | D40: 0.13 | E40: 0.13 | F40: 0.13 | G40: =$F40+($L40-$F40)*G$17/5 -> 0.129 | H40: =$F40+($L40-$F40)*H$17/5 -> 0.128 | I40: =$F40+($L40-$F40)*I$17/5 -> 0.127 | J40: =$F40+($L40-$F40)*J$17/5 -> 0.126 | K40: =$F40+($L40-$F40)*K$17/5 -> 0.125 | L40: 0.125
A41: Operating income | B41: =B38*B40 -> 7.8 | C41: =C38*C40 -> 7.995 | D41: =D38*D40 -> 8.19 | E41: =E38*E40 -> 8.385 | F41: =F38*F40 -> 8.58 | G41: =G38*G40 -> 8.706456 | H41: =H38*H40 -> 8.8286195 | I41: =I38*I40 -> 8.9462467 | ... L41: =L38*L40 -> 9.3502849
A42: NOPAT | B42: =B41*(1-$B$9) -> 7.8 | C42: =C41*(1-$B$9) -> 7.995 | D42: =D41*(1-$B$9) -> 8.19 | E42: =E41*(1-$B$9) -> 8.385 | F42: =F41*(1-$B$9) -> 8.58 | G42: =G41*(1-$B$9) -> 8.706456 | H42: =H41*(1-$B$9) -> 8.8286195 | I42: =I41*(1-$B$9) -> 8.9462467 | ... L42: =L41*(1-$B$9) -> 9.3502849
A43: Net reinvestment, % of revenue | B43: 0.05 | C43: 0.04 | D43: 0.03 | E43: 0.025 | F43: 0.02 | G43: =$F43+($L43-$F43)*G$17/5 -> 0.02 | H43: =$F43+($L43-$F43)*H$17/5 -> 0.02 | I43: =$F43+($L43-$F43)*I$17/5 -> 0.02 | J43: =$F43+($L43-$F43)*J$17/5 -> 0.02 | K43: =$F43+($L43-$F43)*K$17/5 -> 0.02 | L43: 0.02
A44: Net reinvestment | B44: =B38*B43 -> 3 | C44: =C38*C43 -> 2.46 | D44: =D38*D43 -> 1.89 | E44: =E38*E43 -> 1.6125 | F44: =F38*F43 -> 1.32 | G44: =G38*G43 -> 1.3498381 | H44: =H38*H43 -> 1.3794718 | I44: =I38*I43 -> 1.4088578 | ... L44: =L38*L43 -> 1.4960456
A45: Change in working capital | B45: =$B$11*(B38-$B$12) -> 0 | C45: =$B$11*(C38-B38) -> 0 | D45: =$B$11*(D38-C38) -> 0 | E45: =$B$11*(E38-D38) -> 0 | F45: =$B$11*(F38-E38) -> 0 | G45: =$B$11*(G38-F38) -> 0 | H45: =$B$11*(H38-G38) -> 0 | I45: =$B$11*(I38-H38) -> 0 | J45: =$B$11*(J38-I38) -> 0 | ... L45: =$B$11*(L38-K38) -> 0
A46: Free cash flow | B46: =B42-B44-B45 -> 4.8 | C46: =C42-C44-C45 -> 5.535 | D46: =D42-D44-D45 -> 6.3 | E46: =E42-E44-E45 -> 6.7725 | F46: =F42-F44-F45 -> 7.26 | G46: =G42-G44-G45 -> 7.3566179 | H46: =H42-H44-H45 -> 7.4491477 | I46: =I42-I44-I45 -> 7.537389 | ... L46: =L42-L44-L45 -> 7.8542393
A47: Discount factor | B47: =1/(1+$B$10)^B$16 -> 0.96225045 | C47: =1/(1+$B$10)^C$16 -> 0.89097264 | D47: =1/(1+$B$10)^D$16 -> 0.82497466 | E47: =1/(1+$B$10)^E$16 -> 0.76386543 | F47: =1/(1+$B$10)^F$16 -> 0.70728281 | G47: =1/(1+$B$10)^G$16 -> 0.65489149 | H47: =1/(1+$B$10)^H$16 -> 0.60638101 | I47: =1/(1+$B$10)^I$16 -> 0.56146389 | ... K47: =1/(1+$B$10)^K$16 -> 0.48136479
A48: PV of free cash flow | B48: =B46*B47 -> 4.6188022 | C48: =C46*C47 -> 4.9315335 | D48: =D46*D47 -> 5.1973404 | E48: =E46*E47 -> 5.1732786 | F48: =F46*F47 -> 5.1348732 | G48: =G46*G47 -> 4.8177864 | H48: =H46*H47 -> 4.5170217 | I48: =I46*I47 -> 4.2319718 | ... K48: =K46*K47 -> 3.7066218
A49: Terminal value | B49: =L46/($B$10-L39) -> 130.90399 | C49: =IF($B$10>L39,"","Discount rate must exceed terminal growth")
A50: PV of terminal value | B50: =B49/(1+$B$10)^$K$16 -> 63.012571
A51: Equity value (PV FCF + PV TV + net cash + other) | B51: =SUM(B48:K48)+B50+$B$7+$B$8 -> 75.343837
A52: Value per share ($) | B52: =B51/$B$6 -> 34.881406
A53: Value vs share price | B53: =B52/$B$4-1 -> -0.067466758
A55: Bull: export capacity fills at high spreads
A56: Revenue | B56: 61.5 | C56: 64.5 | D56: 67.5 | E56: 70.5 | F56: 73.5 | G56: =F56*(1+$F57+($L57-$F57)*G$17/5) -> 76.369628 | H56: =G56*(1+$F57+($L57-$F57)*H$17/5) -> 79.083187 | I56: =H56*(1+$F57+($L57-$F57)*I$17/5) -> 81.615531 | J56: =I56*(1+$F57+($L57-$F57)*J$17/5) -> 83.942442 | K56: =J56*(1+$F57+($L57-$F57)*K$17/5) -> 86.041003 | L56: =K56*(1+L57) -> 88.192028
A57: Revenue growth (terminal column = terminal growth, input) | B57: =B56/$B$12-1 -> 0.051282051 | C57: =C56/B56-1 -> 0.048780488 | D57: =D56/C56-1 -> 0.046511628 | E57: =E56/D56-1 -> 0.044444444 | F57: =F56/E56-1 -> 0.042553191 | G57: =G56/F56-1 -> 0.039042553 | H57: =H56/G56-1 -> 0.035531915 | I57: =I56/H56-1 -> 0.032021277 | J57: =J56/I56-1 -> 0.028510638 | K57: =K56/J56-1 -> 0.025 | L57: 0.025
A58: Operating margin | B58: 0.135 | C58: 0.135 | D58: 0.135 | E58: 0.135 | F58: 0.135 | G58: =$F58+($L58-$F58)*G$17/5 -> 0.134 | H58: =$F58+($L58-$F58)*H$17/5 -> 0.133 | I58: =$F58+($L58-$F58)*I$17/5 -> 0.132 | J58: =$F58+($L58-$F58)*J$17/5 -> 0.131 | K58: =$F58+($L58-$F58)*K$17/5 -> 0.13 | L58: 0.13
A59: Operating income | B59: =B56*B58 -> 8.3025 | C59: =C56*C58 -> 8.7075 | D59: =D56*D58 -> 9.1125 | E59: =E56*E58 -> 9.5175 | F59: =F56*F58 -> 9.9225 | G59: =G56*G58 -> 10.23353 | H59: =H56*H58 -> 10.518064 | I59: =I56*I58 -> 10.77325 | ... L59: =L56*L58 -> 11.464964
A60: NOPAT | B60: =B59*(1-$B$9) -> 8.3025 | C60: =C59*(1-$B$9) -> 8.7075 | D60: =D59*(1-$B$9) -> 9.1125 | E60: =E59*(1-$B$9) -> 9.5175 | F60: =F59*(1-$B$9) -> 9.9225 | G60: =G59*(1-$B$9) -> 10.23353 | H60: =H59*(1-$B$9) -> 10.518064 | I60: =I59*(1-$B$9) -> 10.77325 | ... L60: =L59*(1-$B$9) -> 11.464964
A61: Net reinvestment, % of revenue | B61: 0.05 | C61: 0.045 | D61: 0.035 | E61: 0.03 | F61: 0.025 | G61: =$F61+($L61-$F61)*G$17/5 -> 0.024 | H61: =$F61+($L61-$F61)*H$17/5 -> 0.023 | I61: =$F61+($L61-$F61)*I$17/5 -> 0.022 | J61: =$F61+($L61-$F61)*J$17/5 -> 0.021 | K61: =$F61+($L61-$F61)*K$17/5 -> 0.02 | L61: 0.02
A62: Net reinvestment | B62: =B56*B61 -> 3.075 | C62: =C56*C61 -> 2.9025 | D62: =D56*D61 -> 2.3625 | E62: =E56*E61 -> 2.115 | F62: =F56*F61 -> 1.8375 | G62: =G56*G61 -> 1.8328711 | H62: =H56*H61 -> 1.8189133 | I62: =I56*I61 -> 1.7955417 | ... L62: =L56*L61 -> 1.7638406
A63: Change in working capital | B63: =$B$11*(B56-$B$12) -> 0 | C63: =$B$11*(C56-B56) -> 0 | D63: =$B$11*(D56-C56) -> 0 | E63: =$B$11*(E56-D56) -> 0 | F63: =$B$11*(F56-E56) -> 0 | G63: =$B$11*(G56-F56) -> 0 | H63: =$B$11*(H56-G56) -> 0 | I63: =$B$11*(I56-H56) -> 0 | J63: =$B$11*(J56-I56) -> 0 | ... L63: =$B$11*(L56-K56) -> 0
A64: Free cash flow | B64: =B60-B62-B63 -> 5.2275 | C64: =C60-C62-C63 -> 5.805 | D64: =D60-D62-D63 -> 6.75 | E64: =E60-E62-E63 -> 7.4025 | F64: =F60-F62-F63 -> 8.085 | G64: =G60-G62-G63 -> 8.400659 | H64: =H60-H62-H63 -> 8.6991505 | I64: =I60-I62-I63 -> 8.9777085 | ... L64: =L60-L62-L63 -> 9.7011231
A65: Discount factor | B65: =1/(1+$B$10)^B$16 -> 0.96225045 | C65: =1/(1+$B$10)^C$16 -> 0.89097264 | D65: =1/(1+$B$10)^D$16 -> 0.82497466 | E65: =1/(1+$B$10)^E$16 -> 0.76386543 | F65: =1/(1+$B$10)^F$16 -> 0.70728281 | G65: =1/(1+$B$10)^G$16 -> 0.65489149 | H65: =1/(1+$B$10)^H$16 -> 0.60638101 | I65: =1/(1+$B$10)^I$16 -> 0.56146389 | ... K65: =1/(1+$B$10)^K$16 -> 0.48136479
A66: PV of free cash flow | B66: =B64*B65 -> 5.0301642 | C66: =C64*C65 -> 5.1720962 | D66: =D64*D65 -> 5.568579 | E66: =E64*E65 -> 5.6545138 | F66: =F64*F65 -> 5.7183815 | G66: =G64*G65 -> 5.5015201 | H66: =H64*H65 -> 5.2749997 | I66: =I64*I65 -> 5.0406592 | ... K66: =K64*K65 -> 4.5558821
A67: Terminal value | B67: =L64/($B$10-L57) -> 176.38406 | C67: =IF($B$10>L57,"","Discount rate must exceed terminal growth")
A68: PV of terminal value | B68: =B67/(1+$B$10)^$K$16 -> 84.905075
A69: Equity value (PV FCF + PV TV + net cash + other) | B69: =SUM(B66:K66)+B68+$B$7+$B$8 -> 103.26221
A70: Value per share ($) | B70: =B69/$B$6 -> 47.806581
A71: Value vs share price | B71: =B70/$B$4-1 -> 0.27807996
A74: Outputs | C74: vs price
A75: Bear value per share | B75: =B34 -> 20.134109 | C75: =B75/$B$4-1 -> -0.46172679
A76: Base value per share | B76: =B52 -> 34.881406 | C76: =B76/$B$4-1 -> -0.067466758
A77: Bull value per share | B77: =B70 -> 47.806581 | C77: =B77/$B$4-1 -> 0.27807996
A78: Selected scenario value per share | B78: =INDEX(B34:B70,1+($B$13-1)*18) -> 34.881406 | C78: =B78/$B$4-1 -> -0.067466758
A79: Share of base value from terminal value | B79: =B50/(SUM(B48:K48)+B50) -> 0.57649002
A81: Base value per share at other discount rates
A82: Discount rate | B82: 0.05 | C82: 0.06 | D82: 0.07 | E82: 0.08 | F82: 0.09 | G82: 0.1 | H82: 0.11 | I82: 0.12 | J82: 0.13 | K82: 0.14
A83: Base value per share | B83: =IF(B82>$L39,(SUMPRODUCT($B46:$K46/(1+B82)^$B$16:$K$16)+$L46/(B82-$L39)/(1+B82)^$K$16+$B$7+$B$8)/$B$6,"n/a") -> 85.109045 | C83: =IF(C82>$L39,(SUMPRODUCT($B46:$K46/(1+C82)^$B$16:$K$16)+$L46/(C82-$L39)/(1+C82)^$K$16+$B$7+$B$8)/$B$6,"n/a") -> 59.997246 | D83: =IF(D82>$L39,(SUMPRODUCT($B46:$K46/(1+D82)^$B$16:$K$16)+$L46/(D82-$L39)/(1+D82)^$K$16+$B$7+$B$8)/$B$6,"n/a") -> 44.928419 | E83: =IF(E82>$L39,(SUMPRODUCT($B46:$K46/(1+E82)^$B$16:$K$16)+$L46/(E82-$L39)/(1+E82)^$K$16+$B$7+$B$8)/$B$6,"n/a") -> 34.881406 | F83: =IF(F82>$L39,(SUMPRODUCT($B46:$K46/(1+F82)^$B$16:$K$16)+$L46/(F82-$L39)/(1+F82)^$K$16+$B$7+$B$8)/$B$6,"n/a") -> 27.704249 | G83: =IF(G82>$L39,(SUMPRODUCT($B46:$K46/(1+G82)^$B$16:$K$16)+$L46/(G82-$L39)/(1+G82)^$K$16+$B$7+$B$8)/$B$6,"n/a") -> 22.320942 | H83: =IF(H82>$L39,(SUMPRODUCT($B46:$K46/(1+H82)^$B$16:$K$16)+$L46/(H82-$L39)/(1+H82)^$K$16+$B$7+$B$8)/$B$6,"n/a") -> 18.133681 | I83: =IF(I82>$L39,(SUMPRODUCT($B46:$K46/(1+I82)^$B$16:$K$16)+$L46/(I82-$L39)/(1+I82)^$K$16+$B$7+$B$8)/$B$6,"n/a") -> 14.783768 | ... K83: =IF(K82>$L39,(SUMPRODUCT($B46:$K46/(1+K82)^$B$16:$K$16)+$L46/(K82-$L39)/(1+K82)^$K$16+$B$7+$B$8)/$B$6,"n/a") -> 9.7589648
A84: vs share price | B84: =IFERROR(B83/$B$4-1,"n/a") -> 1.2753387 | C84: =IFERROR(C83/$B$4-1,"n/a") -> 0.60399001 | D84: =IFERROR(D83/$B$4-1,"n/a") -> 0.20113404 | E84: =IFERROR(E83/$B$4-1,"n/a") -> -0.067466758 | F84: =IFERROR(F83/$B$4-1,"n/a") -> -0.2593437 | G84: =IFERROR(G83/$B$4-1,"n/a") -> -0.40326316 | H84: =IFERROR(H83/$B$4-1,"n/a") -> -0.51520704 | I84: =IFERROR(I83/$B$4-1,"n/a") -> -0.60476491 | ... K84: =IFERROR(K83/$B$4-1,"n/a") -> -0.73909999
A86: Implied annual return at today's price, base case | B86: =IFERROR(IF(MATCH($B$4,$B$83:$K$83,-1)=10,"above 14%",INDEX($B$82:$K$82,MATCH($B$4,$B$83:$K$83,-1))+(INDEX($B$83:$K$83,MATCH($B$4,$B$83:$K$83,-1))-$B$4)/(INDEX($B$83:$K$83,MATCH($B$4,$B$83:$K$83,-1))-INDEX($B$83:$K$83,MATCH($B$4,$B$83:$K$83,-1)+1))*(INDEX($B$82:$K$82,MATCH($B$4,$B$83:$K$83,-1)+1)-INDEX($B$82:$K$82,MATCH($B$4,$B$83:$K$83,-1)))),"below 5%") -> 0.077488214 | C86: Discount rate at which base value equals the price (interpolated from the row above)

Sheet NVDA
A1: Nvidia (NVDA): 10-year scenario DCF
A2: Units: $ billions unless noted. Blue = input, black = formula, green = link, yellow = key lever. Years 6 to 10 fade growth, margin and reinvestment toward each scenario's terminal levels.
A4: Share price ($) | B4: 212.28 | C4: Oct 23, 2026 intraday (Yahoo Finance via the site's price feed)
A5: Price date | B5: Oct 23, 2026 | C5: Text
A6: Shares outstanding (billions) | B6: 24.15 | C6: Stock Analysis statistics, Oct 23, 2026
A7: Net cash, negative = net debt | B7: 23.61 | C7: Stock Analysis statistics, Oct 23, 2026: cash less total debt
A8: Other non-operating assets, less outside claims | B8: 0 | C8: None
A9: Tax rate | B9: 0.16 | C9: Analyst assumption (normalized, near the reported effective rate)
A10: Discount rate (WACC), from WACC tab | B10: =WACC!J29 -> 0.11 | C10: Calculated or assumed, per the switch in WACC!B5
A11: Working capital, % of revenue change | B11: 0.1 | C11: Analyst assumption
A12: Base-year revenue (FY27, Jan 2027) | B12: 411.65 | C12: FY27 (Jan 2027) consensus $411.65B; FY28 consensus $692B (Stock Analysis)
A13: Selected scenario (1 Bear, 2 Base, 3 Bull) | B13: 2 | C13: Lever
A15: Year | B15: FY28 | C15: FY29 | D15: FY30 | E15: FY31 | F15: FY32 | G15: FY33 | H15: FY34 | I15: FY35 | J15: FY36 | K15: FY37 | L15: Terminal
A16: Discount period (years, mid-year) | B16: 0.5 | C16: =B16+1 -> 1.5 | D16: =C16+1 -> 2.5 | E16: =D16+1 -> 3.5 | F16: =E16+1 -> 4.5 | G16: =F16+1 -> 5.5 | H16: =G16+1 -> 6.5 | I16: =H16+1 -> 7.5 | J16: =I16+1 -> 8.5 | K16: =J16+1 -> 9.5
A17: Fade step (years 6 to 10) | B17: 0 | C17: 0 | D17: 0 | E17: 0 | F17: 0 | G17: 1 | H17: 2 | I17: 3 | J17: 4 | K17: 5
A19: Bear: AI capex digestion in FY29 to FY30
A20: Revenue | B20: 560 | C20: 500 | D20: 470 | E20: 520 | F20: 560 | G20: =F20*(1+$F21+($L21-$F21)*G$17/5) -> 597.82154 | H20: =G20*(1+$F21+($L21-$F21)*H$17/5) -> 632.58716 | I20: =H20*(1+$F21+($L21-$F21)*I$17/5) -> 663.43795 | J20: =I20*(1+$F21+($L21-$F21)*J$17/5) -> 689.5672 | K20: =J20*(1+$F21+($L21-$F21)*K$17/5) -> 710.25421 | L20: =K20*(1+L21) -> 731.56184
A21: Revenue growth (terminal column = terminal growth, input) | B21: =B20/$B$12-1 -> 0.36037896 | C21: =C20/B20-1 -> -0.10714286 | D21: =D20/C20-1 -> -0.06 | E21: =E20/D20-1 -> 0.10638298 | F21: =F20/E20-1 -> 0.076923077 | G21: =G20/F20-1 -> 0.067538462 | H21: =H20/G20-1 -> 0.058153846 | I21: =I20/H20-1 -> 0.048769231 | J21: =J20/I20-1 -> 0.039384615 | K21: =K20/J20-1 -> 0.03 | L21: 0.03
A22: Operating margin | B22: 0.6 | C22: 0.52 | D22: 0.48 | E22: 0.48 | F22: 0.47 | G22: =$F22+($L22-$F22)*G$17/5 -> 0.452 | H22: =$F22+($L22-$F22)*H$17/5 -> 0.434 | I22: =$F22+($L22-$F22)*I$17/5 -> 0.416 | J22: =$F22+($L22-$F22)*J$17/5 -> 0.398 | K22: =$F22+($L22-$F22)*K$17/5 -> 0.38 | L22: 0.38
A23: Operating income | B23: =B20*B22 -> 336 | C23: =C20*C22 -> 260 | D23: =D20*D22 -> 225.6 | E23: =E20*E22 -> 249.6 | F23: =F20*F22 -> 263.2 | G23: =G20*G22 -> 270.21534 | H23: =H20*H22 -> 274.54283 | I23: =I20*I22 -> 275.99019 | ... L23: =L20*L22 -> 277.9935
A24: NOPAT | B24: =B23*(1-$B$9) -> 282.24 | C24: =C23*(1-$B$9) -> 218.4 | D24: =D23*(1-$B$9) -> 189.504 | E24: =E23*(1-$B$9) -> 209.664 | F24: =F23*(1-$B$9) -> 221.088 | G24: =G23*(1-$B$9) -> 226.98088 | H24: =H23*(1-$B$9) -> 230.61598 | I24: =I23*(1-$B$9) -> 231.83176 | ... L24: =L23*(1-$B$9) -> 233.51454
A25: Net reinvestment, % of revenue | B25: 0.03 | C25: 0.03 | D25: 0.03 | E25: 0.03 | F25: 0.03 | G25: =$F25+($L25-$F25)*G$17/5 -> 0.03 | H25: =$F25+($L25-$F25)*H$17/5 -> 0.03 | I25: =$F25+($L25-$F25)*I$17/5 -> 0.03 | J25: =$F25+($L25-$F25)*J$17/5 -> 0.03 | K25: =$F25+($L25-$F25)*K$17/5 -> 0.03 | L25: 0.03
A26: Net reinvestment | B26: =B20*B25 -> 16.8 | C26: =C20*C25 -> 15 | D26: =D20*D25 -> 14.1 | E26: =E20*E25 -> 15.6 | F26: =F20*F25 -> 16.8 | G26: =G20*G25 -> 17.934646 | H26: =H20*H25 -> 18.977615 | I26: =I20*I25 -> 19.903138 | ... L26: =L20*L25 -> 21.946855
A27: Change in working capital | B27: =$B$11*(B20-$B$12) -> 14.835 | C27: =$B$11*(C20-B20) -> -6 | D27: =$B$11*(D20-C20) -> -3 | E27: =$B$11*(E20-D20) -> 5 | F27: =$B$11*(F20-E20) -> 4 | G27: =$B$11*(G20-F20) -> 3.7821538 | H27: =$B$11*(H20-G20) -> 3.4765622 | I27: =$B$11*(I20-H20) -> 3.0850789 | J27: =$B$11*(J20-I20) -> 2.6129248 | ... L27: =$B$11*(L20-K20) -> 2.1307626
A28: Free cash flow | B28: =B24-B26-B27 -> 250.605 | C28: =C24-C26-C27 -> 209.4 | D28: =D24-D26-D27 -> 178.404 | E28: =E24-E26-E27 -> 189.064 | F28: =F24-F26-F27 -> 200.288 | G28: =G24-G26-G27 -> 205.26408 | H28: =H24-H26-H27 -> 208.1618 | I28: =I24-I26-I27 -> 208.84354 | ... L28: =L24-L26-L27 -> 209.43692
A29: Discount factor | B29: =1/(1+$B$10)^B$16 -> 0.949158 | C29: =1/(1+$B$10)^C$16 -> 0.85509729 | D29: =1/(1+$B$10)^D$16 -> 0.77035792 | E29: =1/(1+$B$10)^E$16 -> 0.69401615 | F29: =1/(1+$B$10)^F$16 -> 0.62523977 | G29: =1/(1+$B$10)^G$16 -> 0.56327907 | H29: =1/(1+$B$10)^H$16 -> 0.50745862 | I29: =1/(1+$B$10)^I$16 -> 0.45716993 | ... K29: =1/(1+$B$10)^K$16 -> 0.37104937
A30: PV of free cash flow | B30: =B28*B29 -> 237.86374 | C30: =C28*C29 -> 179.05737 | D30: =D28*D29 -> 137.43493 | E30: =E28*E29 -> 131.21347 | F30: =F28*F29 -> 125.22802 | G30: =G28*G29 -> 115.62096 | H30: =H28*H29 -> 105.6335 | I30: =I28*I29 -> 95.476987 | ... K30: =K28*K29 -> 75.447998
A31: Terminal value | B31: =L28/($B$10-L21) -> 2617.9615 | C31: =IF($B$10>L21,"","Discount rate must exceed terminal growth")
A32: PV of terminal value | B32: =B31/(1+$B$10)^$K$16 -> 971.39298
A33: Equity value (PV FCF + PV TV + net cash + other) | B33: =SUM(B30:K30)+B32+$B$7+$B$8 -> 2283.3332
A34: Value per share ($) | B34: =B33/$B$6 -> 94.547961
A35: Value vs share price | B35: =B34/$B$4-1 -> -0.55460731
A37: Base: below-consensus growth, margins ease
A38: Revenue | B38: 640 | C38: 720 | D38: 700 | E38: 760 | F38: 820 | G38: =F38*(1+$F39+($L39-$F39)*G$17/5) -> 877.52947 | H38: =G38*(1+$F39+($L39-$F39)*H$17/5) -> 931.38207 | I38: =H38*(1+$F39+($L39-$F39)*I$17/5) -> 980.35316 | J38: =I38*(1+$F39+($L39-$F39)*J$17/5) -> 1023.2823 | K38: =J38*(1+$F39+($L39-$F39)*K$17/5) -> 1059.0972 | L38: =K38*(1+L39) -> 1096.1656
A39: Revenue growth (terminal column = terminal growth, input) | B39: =B38/$B$12-1 -> 0.55471881 | C39: =C38/B38-1 -> 0.125 | D39: =D38/C38-1 -> -0.027777778 | E39: =E38/D38-1 -> 0.085714286 | F39: =F38/E38-1 -> 0.078947368 | G39: =G38/F38-1 -> 0.070157895 | H39: =H38/G38-1 -> 0.061368421 | I39: =I38/H38-1 -> 0.052578947 | J39: =J38/I38-1 -> 0.043789474 | K39: =K38/J38-1 -> 0.035 | L39: 0.035
A40: Operating margin | B40: 0.62 | C40: 0.6 | D40: 0.56 | E40: 0.54 | F40: 0.52 | G40: =$F40+($L40-$F40)*G$17/5 -> 0.508 | H40: =$F40+($L40-$F40)*H$17/5 -> 0.496 | I40: =$F40+($L40-$F40)*I$17/5 -> 0.484 | J40: =$F40+($L40-$F40)*J$17/5 -> 0.472 | K40: =$F40+($L40-$F40)*K$17/5 -> 0.46 | L40: 0.46
A41: Operating income | B41: =B38*B40 -> 396.8 | C41: =C38*C40 -> 432 | D41: =D38*D40 -> 392 | E41: =E38*E40 -> 410.4 | F41: =F38*F40 -> 426.4 | G41: =G38*G40 -> 445.78497 | H41: =H38*H40 -> 461.96551 | I41: =I38*I40 -> 474.49093 | ... L41: =L38*L40 -> 504.23617
A42: NOPAT | B42: =B41*(1-$B$9) -> 333.312 | C42: =C41*(1-$B$9) -> 362.88 | D42: =D41*(1-$B$9) -> 329.28 | E42: =E41*(1-$B$9) -> 344.736 | F42: =F41*(1-$B$9) -> 358.176 | G42: =G41*(1-$B$9) -> 374.45938 | H42: =H41*(1-$B$9) -> 388.05103 | I42: =I41*(1-$B$9) -> 398.57238 | ... L42: =L41*(1-$B$9) -> 423.55838
A43: Net reinvestment, % of revenue | B43: 0.03 | C43: 0.03 | D43: 0.03 | E43: 0.03 | F43: 0.03 | G43: =$F43+($L43-$F43)*G$17/5 -> 0.03 | H43: =$F43+($L43-$F43)*H$17/5 -> 0.03 | I43: =$F43+($L43-$F43)*I$17/5 -> 0.03 | J43: =$F43+($L43-$F43)*J$17/5 -> 0.03 | K43: =$F43+($L43-$F43)*K$17/5 -> 0.03 | L43: 0.03
A44: Net reinvestment | B44: =B38*B43 -> 19.2 | C44: =C38*C43 -> 21.6 | D44: =D38*D43 -> 21 | E44: =E38*E43 -> 22.8 | F44: =F38*F43 -> 24.6 | G44: =G38*G43 -> 26.325884 | H44: =H38*H43 -> 27.941462 | I44: =I38*I43 -> 29.410595 | ... L44: =L38*L43 -> 32.884968
A45: Change in working capital | B45: =$B$11*(B38-$B$12) -> 22.835 | C45: =$B$11*(C38-B38) -> 8 | D45: =$B$11*(D38-C38) -> -2 | E45: =$B$11*(E38-D38) -> 6 | F45: =$B$11*(F38-E38) -> 6 | G45: =$B$11*(G38-F38) -> 5.7529474 | H45: =$B$11*(H38-G38) -> 5.3852598 | I45: =$B$11*(I38-H38) -> 4.8971089 | J45: =$B$11*(J38-I38) -> 4.2929149 | ... L45: =$B$11*(L38-K38) -> 3.7068402
A46: Free cash flow | B46: =B42-B44-B45 -> 291.277 | C46: =C42-C44-C45 -> 333.28 | D46: =D42-D44-D45 -> 310.28 | E46: =E42-E44-E45 -> 315.936 | F46: =F42-F44-F45 -> 327.576 | G46: =G42-G44-G45 -> 342.38055 | H46: =H42-H44-H45 -> 354.7243 | I46: =I42-I44-I45 -> 364.26468 | ... L46: =L42-L44-L45 -> 386.96658
A47: Discount factor | B47: =1/(1+$B$10)^B$16 -> 0.949158 | C47: =1/(1+$B$10)^C$16 -> 0.85509729 | D47: =1/(1+$B$10)^D$16 -> 0.77035792 | E47: =1/(1+$B$10)^E$16 -> 0.69401615 | F47: =1/(1+$B$10)^F$16 -> 0.62523977 | G47: =1/(1+$B$10)^G$16 -> 0.56327907 | H47: =1/(1+$B$10)^H$16 -> 0.50745862 | I47: =1/(1+$B$10)^I$16 -> 0.45716993 | ... K47: =1/(1+$B$10)^K$16 -> 0.37104937
A48: PV of free cash flow | B48: =B46*B47 -> 276.46789 | C48: =C46*C47 -> 284.98683 | D48: =D46*D47 -> 239.02666 | E48: =E46*E47 -> 219.26469 | F48: =F46*F47 -> 204.81354 | G48: =G46*G47 -> 192.8558 | H48: =H46*H47 -> 180.00791 | I48: =I46*I47 -> 166.53086 | ... K48: =K46*K47 -> 138.72822
A49: Terminal value | B49: =L46/($B$10-L39) -> 5159.5544 | C49: =IF($B$10>L39,"","Discount rate must exceed terminal growth")
A50: PV of terminal value | B50: =B49/(1+$B$10)^$K$16 -> 1914.4494
A51: Equity value (PV FCF + PV TV + net cash + other) | B51: =SUM(B48:K48)+B50+$B$7+$B$8 -> 3993.4281
A52: Value per share ($) | B52: =B51/$B$6 -> 165.35934
A53: Value vs share price | B53: =B52/$B$4-1 -> -0.22103192
A55: Bull: consensus path, share holds
A56: Revenue | B56: 692 | C56: 820 | D56: 880 | E56: 960 | F56: 1040 | G56: =F56*(1+$F57+($L57-$F57)*G$17/5) -> 1117.6533 | H56: =G56*(1+$F57+($L57-$F57)*H$17/5) -> 1191.4185 | I56: =H56*(1+$F57+($L57-$F57)*I$17/5) -> 1259.7264 | J56: =I56*(1+$F57+($L57-$F57)*J$17/5) -> 1321.0331 | K56: =J56*(1+$F57+($L57-$F57)*K$17/5) -> 1373.8745 | L56: =K56*(1+L57) -> 1428.8294
A57: Revenue growth (terminal column = terminal growth, input) | B57: =B56/$B$12-1 -> 0.68103972 | C57: =C56/B56-1 -> 0.1849711 | D57: =D56/C56-1 -> 0.073170732 | E57: =E56/D56-1 -> 0.090909091 | F57: =F56/E56-1 -> 0.083333333 | G57: =G56/F56-1 -> 0.074666667 | H57: =H56/G56-1 -> 0.066 | I57: =I56/H56-1 -> 0.057333333 | J57: =J56/I56-1 -> 0.048666667 | K57: =K56/J56-1 -> 0.04 | L57: 0.04
A58: Operating margin | B58: 0.64 | C58: 0.63 | D58: 0.61 | E58: 0.59 | F58: 0.57 | G58: =$F58+($L58-$F58)*G$17/5 -> 0.556 | H58: =$F58+($L58-$F58)*H$17/5 -> 0.542 | I58: =$F58+($L58-$F58)*I$17/5 -> 0.528 | J58: =$F58+($L58-$F58)*J$17/5 -> 0.514 | K58: =$F58+($L58-$F58)*K$17/5 -> 0.5 | L58: 0.5
A59: Operating income | B59: =B56*B58 -> 442.88 | C59: =C56*C58 -> 516.6 | D59: =D56*D58 -> 536.8 | E59: =E56*E58 -> 566.4 | F59: =F56*F58 -> 592.8 | G59: =G56*G58 -> 621.41525 | H59: =H56*H58 -> 645.7488 | I59: =I56*I58 -> 665.13556 | ... L59: =L56*L58 -> 714.41472
A60: NOPAT | B60: =B59*(1-$B$9) -> 372.0192 | C60: =C59*(1-$B$9) -> 433.944 | D60: =D59*(1-$B$9) -> 450.912 | E60: =E59*(1-$B$9) -> 475.776 | F60: =F59*(1-$B$9) -> 497.952 | G60: =G59*(1-$B$9) -> 521.98881 | H60: =H59*(1-$B$9) -> 542.42899 | I60: =I59*(1-$B$9) -> 558.71387 | ... L60: =L59*(1-$B$9) -> 600.10836
A61: Net reinvestment, % of revenue | B61: 0.03 | C61: 0.03 | D61: 0.03 | E61: 0.03 | F61: 0.03 | G61: =$F61+($L61-$F61)*G$17/5 -> 0.03 | H61: =$F61+($L61-$F61)*H$17/5 -> 0.03 | I61: =$F61+($L61-$F61)*I$17/5 -> 0.03 | J61: =$F61+($L61-$F61)*J$17/5 -> 0.03 | K61: =$F61+($L61-$F61)*K$17/5 -> 0.03 | L61: 0.03
A62: Net reinvestment | B62: =B56*B61 -> 20.76 | C62: =C56*C61 -> 24.6 | D62: =D56*D61 -> 26.4 | E62: =E56*E61 -> 28.8 | F62: =F56*F61 -> 31.2 | G62: =G56*G61 -> 33.5296 | H62: =H56*H61 -> 35.742554 | I62: =I56*I61 -> 37.791793 | ... L62: =L56*L61 -> 42.864883
A63: Change in working capital | B63: =$B$11*(B56-$B$12) -> 28.035 | C63: =$B$11*(C56-B56) -> 12.8 | D63: =$B$11*(D56-C56) -> 6 | E63: =$B$11*(E56-D56) -> 8 | F63: =$B$11*(F56-E56) -> 8 | G63: =$B$11*(G56-F56) -> 7.7653333 | H63: =$B$11*(H56-G56) -> 7.376512 | I63: =$B$11*(I56-H56) -> 6.8307991 | J63: =$B$11*(J56-I56) -> 6.1306687 | ... L63: =$B$11*(L56-K56) -> 5.4954978
A64: Free cash flow | B64: =B60-B62-B63 -> 323.2242 | C64: =C60-C62-C63 -> 396.544 | D64: =D60-D62-D63 -> 418.512 | E64: =E60-E62-E63 -> 438.976 | F64: =F60-F62-F63 -> 458.752 | G64: =G60-G62-G63 -> 480.69388 | H64: =H60-H62-H63 -> 499.30993 | I64: =I60-I62-I63 -> 514.09128 | ... L64: =L60-L62-L63 -> 551.74798
A65: Discount factor | B65: =1/(1+$B$10)^B$16 -> 0.949158 | C65: =1/(1+$B$10)^C$16 -> 0.85509729 | D65: =1/(1+$B$10)^D$16 -> 0.77035792 | E65: =1/(1+$B$10)^E$16 -> 0.69401615 | F65: =1/(1+$B$10)^F$16 -> 0.62523977 | G65: =1/(1+$B$10)^G$16 -> 0.56327907 | H65: =1/(1+$B$10)^H$16 -> 0.50745862 | I65: =1/(1+$B$10)^I$16 -> 0.45716993 | ... K65: =1/(1+$B$10)^K$16 -> 0.37104937
A66: PV of free cash flow | B66: =B64*B65 -> 306.79083 | C66: =C64*C65 -> 339.0837 | D66: =D64*D65 -> 322.40403 | E66: =E64*E65 -> 304.65643 | F66: =F64*F65 -> 286.83 | G66: =G64*G65 -> 270.7648 | H66: =H64*H65 -> 253.37913 | I66: =I64*I65 -> 235.02708 | ... K66: =K64*K65 -> 196.85168
A67: Terminal value | B67: =L64/($B$10-L57) -> 7882.114 | C67: =IF($B$10>L57,"","Discount rate must exceed terminal growth")
A68: PV of terminal value | B68: =B67/(1+$B$10)^$K$16 -> 2924.6535
A69: Equity value (PV FCF + PV TV + net cash + other) | B69: =SUM(B66:K66)+B68+$B$7+$B$8 -> 5680.1186
A70: Value per share ($) | B70: =B69/$B$6 -> 235.2016
A71: Value vs share price | B71: =B70/$B$4-1 -> 0.10797812
A74: Outputs | C74: vs price
A75: Bear value per share | B75: =B34 -> 94.547961 | C75: =B75/$B$4-1 -> -0.55460731
A76: Base value per share | B76: =B52 -> 165.35934 | C76: =B76/$B$4-1 -> -0.22103192
A77: Bull value per share | B77: =B70 -> 235.2016 | C77: =B77/$B$4-1 -> 0.10797812
A78: Selected scenario value per share | B78: =INDEX(B34:B70,1+($B$13-1)*18) -> 165.35934 | C78: =B78/$B$4-1 -> -0.22103192
A79: Share of base value from terminal value | B79: =B50/(SUM(B48:K48)+B50) -> 0.48225116
A81: Base value per share at other discount rates
A82: Discount rate | B82: 0.05 | C82: 0.06 | D82: 0.07 | E82: 0.08 | F82: 0.09 | G82: 0.1 | H82: 0.11 | I82: 0.12 | J82: 0.13 | K82: 0.14
A83: Base value per share | B83: =IF(B82>$L39,(SUMPRODUCT($B46:$K46/(1+B82)^$B$16:$K$16)+$L46/(B82-$L39)/(1+B82)^$K$16+$B$7+$B$8)/$B$6,"n/a") -> 782.73921 | C83: =IF(C82>$L39,(SUMPRODUCT($B46:$K46/(1+C82)^$B$16:$K$16)+$L46/(C82-$L39)/(1+C82)^$K$16+$B$7+$B$8)/$B$6,"n/a") -> 474.37141 | D83: =IF(D82>$L39,(SUMPRODUCT($B46:$K46/(1+D82)^$B$16:$K$16)+$L46/(D82-$L39)/(1+D82)^$K$16+$B$7+$B$8)/$B$6,"n/a") -> 342.11179 | E83: =IF(E82>$L39,(SUMPRODUCT($B46:$K46/(1+E82)^$B$16:$K$16)+$L46/(E82-$L39)/(1+E82)^$K$16+$B$7+$B$8)/$B$6,"n/a") -> 268.56113 | F83: =IF(F82>$L39,(SUMPRODUCT($B46:$K46/(1+F82)^$B$16:$K$16)+$L46/(F82-$L39)/(1+F82)^$K$16+$B$7+$B$8)/$B$6,"n/a") -> 221.70097 | G83: =IF(G82>$L39,(SUMPRODUCT($B46:$K46/(1+G82)^$B$16:$K$16)+$L46/(G82-$L39)/(1+G82)^$K$16+$B$7+$B$8)/$B$6,"n/a") -> 189.21616 | H83: =IF(H82>$L39,(SUMPRODUCT($B46:$K46/(1+H82)^$B$16:$K$16)+$L46/(H82-$L39)/(1+H82)^$K$16+$B$7+$B$8)/$B$6,"n/a") -> 165.35934 | I83: =IF(I82>$L39,(SUMPRODUCT($B46:$K46/(1+I82)^$B$16:$K$16)+$L46/(I82-$L39)/(1+I82)^$K$16+$B$7+$B$8)/$B$6,"n/a") -> 147.08757 | ... K83: =IF(K82>$L39,(SUMPRODUCT($B46:$K46/(1+K82)^$B$16:$K$16)+$L46/(K82-$L39)/(1+K82)^$K$16+$B$7+$B$8)/$B$6,"n/a") -> 120.92265
A84: vs share price | B84: =IFERROR(B83/$B$4-1,"n/a") -> 2.6872961 | C84: =IFERROR(C83/$B$4-1,"n/a") -> 1.2346496 | D84: =IFERROR(D83/$B$4-1,"n/a") -> 0.61160632 | E84: =IFERROR(E83/$B$4-1,"n/a") -> 0.26512685 | F84: =IFERROR(F83/$B$4-1,"n/a") -> 0.044379929 | G84: =IFERROR(G83/$B$4-1,"n/a") -> -0.10864819 | H84: =IFERROR(H83/$B$4-1,"n/a") -> -0.22103192 | I84: =IFERROR(I83/$B$4-1,"n/a") -> -0.30710586 | ... K84: =IFERROR(K83/$B$4-1,"n/a") -> -0.43036249
A86: Implied annual return at today's price, base case | B86: =IFERROR(IF(MATCH($B$4,$B$83:$K$83,-1)=10,"above 14%",INDEX($B$82:$K$82,MATCH($B$4,$B$83:$K$83,-1))+(INDEX($B$83:$K$83,MATCH($B$4,$B$83:$K$83,-1))-$B$4)/(INDEX($B$83:$K$83,MATCH($B$4,$B$83:$K$83,-1))-INDEX($B$83:$K$83,MATCH($B$4,$B$83:$K$83,-1)+1))*(INDEX($B$82:$K$82,MATCH($B$4,$B$83:$K$83,-1)+1)-INDEX($B$82:$K$82,MATCH($B$4,$B$83:$K$83,-1)))),"below 5%") -> 0.092900116 | C86: Discount rate at which base value equals the price (interpolated from the row above)

Sheet FSLR
A1: First Solar (FSLR): 10-year scenario DCF
A2: Units: $ billions unless noted. Blue = input, black = formula, green = link, yellow = key lever. Years 6 to 10 fade growth, margin and reinvestment toward each scenario's terminal levels.
A4: Share price ($) | B4: 171.57 | C4: Oct 23, 2026 intraday (Yahoo Finance via the site's price feed)
A5: Price date | B5: Oct 23, 2026 | C5: Text
A6: Shares outstanding (billions) | B6: 0.10747 | C6: Stock Analysis statistics, Oct 23, 2026
A7: Net cash, negative = net debt | B7: 1.53 | C7: Stock Analysis statistics, Oct 23, 2026: cash less total debt
A8: Other non-operating assets, less outside claims | B8: 0 | C8: None. Margins include 45X manufacturing credits, which step down from 2030 and end after 2032
A9: Tax rate | B9: 0.12 | C9: Analyst assumption (normalized, near the reported effective rate)
A10: Discount rate (WACC), from WACC tab | B10: =WACC!K29 -> 0.105 | C10: Calculated or assumed, per the switch in WACC!B5
A11: Working capital, % of revenue change | B11: 0.1 | C11: Analyst assumption
A12: Base-year revenue (2026E) | B12: 5.04 | C12: 2026E consensus $5.04B (Stock Analysis)
A13: Selected scenario (1 Bear, 2 Base, 3 Bull) | B13: 2 | C13: Lever
A15: Year | B15: 2027 | C15: 2028 | D15: 2029 | E15: 2030 | F15: 2031 | G15: 2032 | H15: 2033 | I15: 2034 | J15: 2035 | K15: 2036 | L15: Terminal
A16: Discount period (years, mid-year) | B16: 0.5 | C16: =B16+1 -> 1.5 | D16: =C16+1 -> 2.5 | E16: =D16+1 -> 3.5 | F16: =E16+1 -> 4.5 | G16: =F16+1 -> 5.5 | H16: =G16+1 -> 6.5 | I16: =H16+1 -> 7.5 | J16: =I16+1 -> 8.5 | K16: =J16+1 -> 9.5
A17: Fade step (years 6 to 10) | B17: 0 | C17: 0 | D17: 0 | E17: 0 | F17: 0 | G17: 1 | H17: 2 | I17: 3 | J17: 4 | K17: 5
A19: Bear: module prices fall, policy turns against solar
A20: Revenue | B20: 5 | C20: 5.3 | D20: 5.6 | E20: 5.6 | F20: 5.6 | G20: =F20*(1+$F21+($L21-$F21)*G$17/5) -> 5.6224 | H20: =G20*(1+$F21+($L21-$F21)*H$17/5) -> 5.6673792 | I20: =H20*(1+$F21+($L21-$F21)*I$17/5) -> 5.7353878 | J20: =I20*(1+$F21+($L21-$F21)*J$17/5) -> 5.827154 | K20: =J20*(1+$F21+($L21-$F21)*K$17/5) -> 5.943697 | L20: =K20*(1+L21) -> 6.062571
A21: Revenue growth (terminal column = terminal growth, input) | B21: =B20/$B$12-1 -> -0.0079365079 | C21: =C20/B20-1 -> 0.06 | D21: =D20/C20-1 -> 0.056603774 | E21: =E20/D20-1 -> 0 | F21: =F20/E20-1 -> 0 | G21: =G20/F20-1 -> 0.004 | H21: =H20/G20-1 -> 0.008 | I21: =I20/H20-1 -> 0.012 | J21: =J20/I20-1 -> 0.016 | K21: =K20/J20-1 -> 0.02 | L21: 0.02
A22: Operating margin | B22: 0.28 | C22: 0.27 | D22: 0.27 | E22: 0.2 | F22: 0.15 | G22: =$F22+($L22-$F22)*G$17/5 -> 0.14 | H22: =$F22+($L22-$F22)*H$17/5 -> 0.13 | I22: =$F22+($L22-$F22)*I$17/5 -> 0.12 | J22: =$F22+($L22-$F22)*J$17/5 -> 0.11 | K22: =$F22+($L22-$F22)*K$17/5 -> 0.1 | L22: 0.1
A23: Operating income | B23: =B20*B22 -> 1.4 | C23: =C20*C22 -> 1.431 | D23: =D20*D22 -> 1.512 | E23: =E20*E22 -> 1.12 | F23: =F20*F22 -> 0.84 | G23: =G20*G22 -> 0.787136 | H23: =H20*H22 -> 0.7367593 | I23: =I20*I22 -> 0.68824653 | ... L23: =L20*L22 -> 0.6062571
A24: NOPAT | B24: =B23*(1-$B$9) -> 1.232 | C24: =C23*(1-$B$9) -> 1.25928 | D24: =D23*(1-$B$9) -> 1.33056 | E24: =E23*(1-$B$9) -> 0.9856 | F24: =F23*(1-$B$9) -> 0.7392 | G24: =G23*(1-$B$9) -> 0.69267968 | H24: =H23*(1-$B$9) -> 0.64834818 | I24: =I23*(1-$B$9) -> 0.60565695 | ... L24: =L23*(1-$B$9) -> 0.53350625
A25: Net reinvestment, % of revenue | B25: 0.05 | C25: 0.04 | D25: 0.03 | E25: 0.03 | F25: 0.03 | G25: =$F25+($L25-$F25)*G$17/5 -> 0.03 | H25: =$F25+($L25-$F25)*H$17/5 -> 0.03 | I25: =$F25+($L25-$F25)*I$17/5 -> 0.03 | J25: =$F25+($L25-$F25)*J$17/5 -> 0.03 | K25: =$F25+($L25-$F25)*K$17/5 -> 0.03 | L25: 0.03
A26: Net reinvestment | B26: =B20*B25 -> 0.25 | C26: =C20*C25 -> 0.212 | D26: =D20*D25 -> 0.168 | E26: =E20*E25 -> 0.168 | F26: =F20*F25 -> 0.168 | G26: =G20*G25 -> 0.168672 | H26: =H20*H25 -> 0.17002138 | I26: =I20*I25 -> 0.17206163 | ... L26: =L20*L25 -> 0.18187713
A27: Change in working capital | B27: =$B$11*(B20-$B$12) -> -0.004 | C27: =$B$11*(C20-B20) -> 0.03 | D27: =$B$11*(D20-C20) -> 0.03 | E27: =$B$11*(E20-D20) -> 0 | F27: =$B$11*(F20-E20) -> 0 | G27: =$B$11*(G20-F20) -> 0.00224 | H27: =$B$11*(H20-G20) -> 0.00449792 | I27: =$B$11*(I20-H20) -> 0.006800855 | J27: =$B$11*(J20-I20) -> 0.0091766204 | ... L27: =$B$11*(L20-K20) -> 0.011887394
A28: Free cash flow | B28: =B24-B26-B27 -> 0.986 | C28: =C24-C26-C27 -> 1.01728 | D28: =D24-D26-D27 -> 1.13256 | E28: =E24-E26-E27 -> 0.8176 | F28: =F24-F26-F27 -> 0.5712 | G28: =G24-G26-G27 -> 0.52176768 | H28: =H24-H26-H27 -> 0.47382888 | I28: =I24-I26-I27 -> 0.42679446 | ... L28: =L24-L26-L27 -> 0.33974172
A29: Discount factor | B29: =1/(1+$B$10)^B$16 -> 0.95130299 | C29: =1/(1+$B$10)^C$16 -> 0.86090768 | D29: =1/(1+$B$10)^D$16 -> 0.77910197 | E29: =1/(1+$B$10)^E$16 -> 0.70506966 | F29: =1/(1+$B$10)^F$16 -> 0.63807209 | G29: =1/(1+$B$10)^G$16 -> 0.57744081 | H29: =1/(1+$B$10)^H$16 -> 0.52257087 | I29: =1/(1+$B$10)^I$16 -> 0.47291481 | ... K29: =1/(1+$B$10)^K$16 -> 0.38730969
A30: PV of free cash flow | B30: =B28*B29 -> 0.93798475 | C30: =C28*C29 -> 0.87578417 | D30: =D28*D29 -> 0.88237973 | E30: =E28*E29 -> 0.57646495 | F30: =F28*F29 -> 0.36446678 | G30: =G28*G29 -> 0.30128995 | H30: =H28*H29 -> 0.24760917 | I30: =I28*I29 -> 0.20183742 | ... K30: =K28*K29 -> 0.12900516
A31: Terminal value | B31: =L28/($B$10-L21) -> 3.9969614 | C31: =IF($B$10>L21,"","Discount rate must exceed terminal growth")
A32: PV of terminal value | B32: =B31/(1+$B$10)^$K$16 -> 1.5480619
A33: Equity value (PV FCF + PV TV + net cash + other) | B33: =SUM(B30:K30)+B32+$B$7+$B$8 -> 7.7575484
A34: Value per share ($) | B34: =B33/$B$6 -> 72.183385
A35: Value vs share price | B35: =B34/$B$4-1 -> -0.57927735
A37: Base: US capacity fills, credits step down
A38: Revenue | B38: 5.8 | C38: 6.4 | D38: 6.8 | E38: 6.9 | F38: 7 | G38: =F38*(1+$F39+($L39-$F39)*G$17/5) -> 7.1161594 | H38: =G38*(1+$F39+($L39-$F39)*H$17/5) -> 7.2492007 | I38: =H38*(1+$F39+($L39-$F39)*I$17/5) -> 7.399963 | J38: =I38*(1+$F39+($L39-$F39)*J$17/5) -> 7.5694115 | K38: =J38*(1+$F39+($L39-$F39)*K$17/5) -> 7.7586467 | L38: =K38*(1+L39) -> 7.9526129
A39: Revenue growth (terminal column = terminal growth, input) | B39: =B38/$B$12-1 -> 0.15079365 | C39: =C38/B38-1 -> 0.10344828 | D39: =D38/C38-1 -> 0.0625 | E39: =E38/D38-1 -> 0.014705882 | F39: =F38/E38-1 -> 0.014492754 | G39: =G38/F38-1 -> 0.016594203 | H39: =H38/G38-1 -> 0.018695652 | I39: =I38/H38-1 -> 0.020797101 | J39: =J38/I38-1 -> 0.022898551 | K39: =K38/J38-1 -> 0.025 | L39: 0.025
A40: Operating margin | B40: 0.33 | C40: 0.34 | D40: 0.34 | E40: 0.29 | F40: 0.24 | G40: =$F40+($L40-$F40)*G$17/5 -> 0.222 | H40: =$F40+($L40-$F40)*H$17/5 -> 0.204 | I40: =$F40+($L40-$F40)*I$17/5 -> 0.186 | J40: =$F40+($L40-$F40)*J$17/5 -> 0.168 | K40: =$F40+($L40-$F40)*K$17/5 -> 0.15 | L40: 0.15
A41: Operating income | B41: =B38*B40 -> 1.914 | C41: =C38*C40 -> 2.176 | D41: =D38*D40 -> 2.312 | E41: =E38*E40 -> 2.001 | F41: =F38*F40 -> 1.68 | G41: =G38*G40 -> 1.5797874 | H41: =H38*H40 -> 1.4788369 | I41: =I38*I40 -> 1.3763931 | ... L41: =L38*L40 -> 1.1928919
A42: NOPAT | B42: =B41*(1-$B$9) -> 1.68432 | C42: =C41*(1-$B$9) -> 1.91488 | D42: =D41*(1-$B$9) -> 2.03456 | E42: =E41*(1-$B$9) -> 1.76088 | F42: =F41*(1-$B$9) -> 1.4784 | G42: =G41*(1-$B$9) -> 1.3902129 | H42: =H41*(1-$B$9) -> 1.3013765 | I42: =I41*(1-$B$9) -> 1.2112259 | ... L42: =L41*(1-$B$9) -> 1.0497449
A43: Net reinvestment, % of revenue | B43: 0.06 | C43: 0.05 | D43: 0.04 | E43: 0.03 | F43: 0.03 | G43: =$F43+($L43-$F43)*G$17/5 -> 0.03 | H43: =$F43+($L43-$F43)*H$17/5 -> 0.03 | I43: =$F43+($L43-$F43)*I$17/5 -> 0.03 | J43: =$F43+($L43-$F43)*J$17/5 -> 0.03 | K43: =$F43+($L43-$F43)*K$17/5 -> 0.03 | L43: 0.03
A44: Net reinvestment | B44: =B38*B43 -> 0.348 | C44: =C38*C43 -> 0.32 | D44: =D38*D43 -> 0.272 | E44: =E38*E43 -> 0.207 | F44: =F38*F43 -> 0.21 | G44: =G38*G43 -> 0.21348478 | H44: =H38*H43 -> 0.21747602 | I44: =I38*I43 -> 0.22199889 | ... L44: =L38*L43 -> 0.23857839
A45: Change in working capital | B45: =$B$11*(B38-$B$12) -> 0.076 | C45: =$B$11*(C38-B38) -> 0.06 | D45: =$B$11*(D38-C38) -> 0.04 | E45: =$B$11*(E38-D38) -> 0.01 | F45: =$B$11*(F38-E38) -> 0.01 | G45: =$B$11*(G38-F38) -> 0.011615942 | H45: =$B$11*(H38-G38) -> 0.013304124 | I45: =$B$11*(I38-H38) -> 0.015076236 | J45: =$B$11*(J38-I38) -> 0.016944843 | ... L45: =$B$11*(L38-K38) -> 0.019396617
A46: Free cash flow | B46: =B42-B44-B45 -> 1.26032 | C46: =C42-C44-C45 -> 1.53488 | D46: =D42-D44-D45 -> 1.72256 | E46: =E42-E44-E45 -> 1.54388 | F46: =F42-F44-F45 -> 1.2584 | G46: =G42-G44-G45 -> 1.1651122 | H46: =H42-H44-H45 -> 1.0705964 | I46: =I42-I44-I45 -> 0.97415082 | ... L46: =L42-L44-L45 -> 0.7917699
A47: Discount factor | B47: =1/(1+$B$10)^B$16 -> 0.95130299 | C47: =1/(1+$B$10)^C$16 -> 0.86090768 | D47: =1/(1+$B$10)^D$16 -> 0.77910197 | E47: =1/(1+$B$10)^E$16 -> 0.70506966 | F47: =1/(1+$B$10)^F$16 -> 0.63807209 | G47: =1/(1+$B$10)^G$16 -> 0.57744081 | H47: =1/(1+$B$10)^H$16 -> 0.52257087 | I47: =1/(1+$B$10)^I$16 -> 0.47291481 | ... K47: =1/(1+$B$10)^K$16 -> 0.38730969
A48: PV of free cash flow | B48: =B46*B47 -> 1.1989462 | C48: =C46*C47 -> 1.32139 | D48: =D46*D47 -> 1.3420499 | E48: =E46*E47 -> 1.0885429 | F48: =F46*F47 -> 0.80294992 | G48: =G46*G47 -> 0.67278332 | H48: =H46*H47 -> 0.55946247 | I48: =I46*I47 -> 0.46069035 | ... K48: =K46*K47 -> 0.29918064
A49: Terminal value | B49: =L46/($B$10-L39) -> 9.8971237 | C49: =IF($B$10>L39,"","Discount rate must exceed terminal growth")
A50: PV of terminal value | B50: =B49/(1+$B$10)^$K$16 -> 3.8332519
A51: Equity value (PV FCF + PV TV + net cash + other) | B51: =SUM(B48:K48)+B50+$B$7+$B$8 -> 13.483742
A52: Value per share ($) | B52: =B51/$B$6 -> 125.46518
A53: Value vs share price | B53: =B52/$B$4-1 -> -0.26872311
A55: Bull: data center demand, firm US pricing
A56: Revenue | B56: 6.2 | C56: 7.2 | D56: 8 | E56: 8.6 | F56: 9.2 | G56: =F56*(1+$F57+($L57-$F57)*G$17/5) -> 9.7686884 | H56: =G56*(1+$F57+($L57-$F57)*H$17/5) -> 10.294834 | I56: =H56*(1+$F57+($L57-$F57)*I$17/5) -> 10.767439 | J56: =I56*(1+$F57+($L57-$F57)*J$17/5) -> 11.176101 | K56: =J56*(1+$F57+($L57-$F57)*K$17/5) -> 11.511384 | L56: =K56*(1+L57) -> 11.856726
A57: Revenue growth (terminal column = terminal growth, input) | B57: =B56/$B$12-1 -> 0.23015873 | C57: =C56/B56-1 -> 0.16129032 | D57: =D56/C56-1 -> 0.11111111 | E57: =E56/D56-1 -> 0.075 | F57: =F56/E56-1 -> 0.069767442 | G57: =G56/F56-1 -> 0.061813953 | H57: =H56/G56-1 -> 0.053860465 | I57: =I56/H56-1 -> 0.045906977 | J57: =J56/I56-1 -> 0.037953488 | K57: =K56/J56-1 -> 0.03 | L57: 0.03
A58: Operating margin | B58: 0.35 | C58: 0.36 | D58: 0.36 | E58: 0.31 | F58: 0.27 | G58: =$F58+($L58-$F58)*G$17/5 -> 0.252 | H58: =$F58+($L58-$F58)*H$17/5 -> 0.234 | I58: =$F58+($L58-$F58)*I$17/5 -> 0.216 | J58: =$F58+($L58-$F58)*J$17/5 -> 0.198 | K58: =$F58+($L58-$F58)*K$17/5 -> 0.18 | L58: 0.18
A59: Operating income | B59: =B56*B58 -> 2.17 | C59: =C56*C58 -> 2.592 | D59: =D56*D58 -> 2.88 | E59: =E56*E58 -> 2.666 | F59: =F56*F58 -> 2.484 | G59: =G56*G58 -> 2.4617095 | H59: =H56*H58 -> 2.4089913 | I59: =I56*I58 -> 2.3257669 | ... L59: =L56*L58 -> 2.1342106
A60: NOPAT | B60: =B59*(1-$B$9) -> 1.9096 | C60: =C59*(1-$B$9) -> 2.28096 | D60: =D59*(1-$B$9) -> 2.5344 | E60: =E59*(1-$B$9) -> 2.34608 | F60: =F59*(1-$B$9) -> 2.18592 | G60: =G59*(1-$B$9) -> 2.1663043 | H60: =H59*(1-$B$9) -> 2.1199123 | I60: =I59*(1-$B$9) -> 2.0466748 | ... L60: =L59*(1-$B$9) -> 1.8781053
A61: Net reinvestment, % of revenue | B61: 0.07 | C61: 0.06 | D61: 0.05 | E61: 0.04 | F61: 0.03 | G61: =$F61+($L61-$F61)*G$17/5 -> 0.03 | H61: =$F61+($L61-$F61)*H$17/5 -> 0.03 | I61: =$F61+($L61-$F61)*I$17/5 -> 0.03 | J61: =$F61+($L61-$F61)*J$17/5 -> 0.03 | K61: =$F61+($L61-$F61)*K$17/5 -> 0.03 | L61: 0.03
A62: Net reinvestment | B62: =B56*B61 -> 0.434 | C62: =C56*C61 -> 0.432 | D62: =D56*D61 -> 0.4 | E62: =E56*E61 -> 0.344 | F62: =F56*F61 -> 0.276 | G62: =G56*G61 -> 0.29306065 | H62: =H56*H61 -> 0.30884503 | I62: =I56*I61 -> 0.32302318 | ... L62: =L56*L61 -> 0.35570177
A63: Change in working capital | B63: =$B$11*(B56-$B$12) -> 0.116 | C63: =$B$11*(C56-B56) -> 0.1 | D63: =$B$11*(D56-C56) -> 0.08 | E63: =$B$11*(E56-D56) -> 0.06 | F63: =$B$11*(F56-E56) -> 0.06 | G63: =$B$11*(G56-F56) -> 0.056868837 | H63: =$B$11*(H56-G56) -> 0.05261461 | I63: =$B$11*(I56-H56) -> 0.047260473 | J63: =$B$11*(J56-I56) -> 0.040866188 | ... L63: =$B$11*(L56-K56) -> 0.034534152
A64: Free cash flow | B64: =B60-B62-B63 -> 1.3596 | C64: =C60-C62-C63 -> 1.74896 | D64: =D60-D62-D63 -> 2.0544 | E64: =E60-E62-E63 -> 1.94208 | F64: =F60-F62-F63 -> 1.84992 | G64: =G60-G62-G63 -> 1.8163748 | H64: =H60-H62-H63 -> 1.7584527 | I64: =I60-I62-I63 -> 1.6763912 | ... L64: =L60-L62-L63 -> 1.4878694
A65: Discount factor | B65: =1/(1+$B$10)^B$16 -> 0.95130299 | C65: =1/(1+$B$10)^C$16 -> 0.86090768 | D65: =1/(1+$B$10)^D$16 -> 0.77910197 | E65: =1/(1+$B$10)^E$16 -> 0.70506966 | F65: =1/(1+$B$10)^F$16 -> 0.63807209 | G65: =1/(1+$B$10)^G$16 -> 0.57744081 | H65: =1/(1+$B$10)^H$16 -> 0.52257087 | I65: =1/(1+$B$10)^I$16 -> 0.47291481 | ... K65: =1/(1+$B$10)^K$16 -> 0.38730969
A66: PV of free cash flow | B66: =B64*B65 -> 1.2933915 | C66: =C64*C65 -> 1.5056931 | D66: =D64*D65 -> 1.6005871 | E66: =E64*E65 -> 1.3693017 | F66: =F64*F65 -> 1.1803823 | G66: =G64*G65 -> 1.048849 | H66: =H64*H65 -> 0.91891613 | I66: =I64*I65 -> 0.79279022 | ... K66: =K64*K65 -> 0.55948178
A67: Terminal value | B67: =L64/($B$10-L57) -> 19.838259 | C67: =IF($B$10>L57,"","Discount rate must exceed terminal growth")
A68: PV of terminal value | B68: =B67/(1+$B$10)^$K$16 -> 7.6835498
A69: Equity value (PV FCF + PV TV + net cash + other) | B69: =SUM(B66:K66)+B68+$B$7+$B$8 -> 20.15537
A70: Value per share ($) | B70: =B69/$B$6 -> 187.54415
A71: Value vs share price | B71: =B70/$B$4-1 -> 0.093105719
A74: Outputs | C74: vs price
A75: Bear value per share | B75: =B34 -> 72.183385 | C75: =B75/$B$4-1 -> -0.57927735
A76: Base value per share | B76: =B52 -> 125.46518 | C76: =B76/$B$4-1 -> -0.26872311
A77: Bull value per share | B77: =B70 -> 187.54415 | C77: =B77/$B$4-1 -> 0.093105719
A78: Selected scenario value per share | B78: =INDEX(B34:B70,1+($B$13-1)*18) -> 125.46518 | C78: =B78/$B$4-1 -> -0.26872311
A79: Share of base value from terminal value | B79: =B50/(SUM(B48:K48)+B50) -> 0.32067379
A81: Base value per share at other discount rates
A82: Discount rate | B82: 0.05 | C82: 0.06 | D82: 0.07 | E82: 0.08 | F82: 0.09 | G82: 0.1 | H82: 0.11 | I82: 0.12 | J82: 0.13 | K82: 0.14
A83: Base value per share | B83: =IF(B82>$L39,(SUMPRODUCT($B46:$K46/(1+B82)^$B$16:$K$16)+$L46/(B82-$L39)/(1+B82)^$K$16+$B$7+$B$8)/$B$6,"n/a") -> 291.76959 | C83: =IF(C82>$L39,(SUMPRODUCT($B46:$K46/(1+C82)^$B$16:$K$16)+$L46/(C82-$L39)/(1+C82)^$K$16+$B$7+$B$8)/$B$6,"n/a") -> 223.94659 | D83: =IF(D82>$L39,(SUMPRODUCT($B46:$K46/(1+D82)^$B$16:$K$16)+$L46/(D82-$L39)/(1+D82)^$K$16+$B$7+$B$8)/$B$6,"n/a") -> 185.78141 | E83: =IF(E82>$L39,(SUMPRODUCT($B46:$K46/(1+E82)^$B$16:$K$16)+$L46/(E82-$L39)/(1+E82)^$K$16+$B$7+$B$8)/$B$6,"n/a") -> 161.12638 | F83: =IF(F82>$L39,(SUMPRODUCT($B46:$K46/(1+F82)^$B$16:$K$16)+$L46/(F82-$L39)/(1+F82)^$K$16+$B$7+$B$8)/$B$6,"n/a") -> 143.76872 | G83: =IF(G82>$L39,(SUMPRODUCT($B46:$K46/(1+G82)^$B$16:$K$16)+$L46/(G82-$L39)/(1+G82)^$K$16+$B$7+$B$8)/$B$6,"n/a") -> 130.80747 | H83: =IF(H82>$L39,(SUMPRODUCT($B46:$K46/(1+H82)^$B$16:$K$16)+$L46/(H82-$L39)/(1+H82)^$K$16+$B$7+$B$8)/$B$6,"n/a") -> 120.7055 | I83: =IF(I82>$L39,(SUMPRODUCT($B46:$K46/(1+I82)^$B$16:$K$16)+$L46/(I82-$L39)/(1+I82)^$K$16+$B$7+$B$8)/$B$6,"n/a") -> 112.57179 | ... K83: =IF(K82>$L39,(SUMPRODUCT($B46:$K46/(1+K82)^$B$16:$K$16)+$L46/(K82-$L39)/(1+K82)^$K$16+$B$7+$B$8)/$B$6,"n/a") -> 100.19078
A84: vs share price | B84: =IFERROR(B83/$B$4-1,"n/a") -> 0.70058627 | C84: =IFERROR(C83/$B$4-1,"n/a") -> 0.30527827 | D84: =IFERROR(D83/$B$4-1,"n/a") -> 0.082831573 | E84: =IFERROR(E83/$B$4-1,"n/a") -> -0.06087089 | F84: =IFERROR(F83/$B$4-1,"n/a") -> -0.16204043 | G84: =IFERROR(G83/$B$4-1,"n/a") -> -0.2375854 | H84: =IFERROR(H83/$B$4-1,"n/a") -> -0.29646503 | I84: =IFERROR(I83/$B$4-1,"n/a") -> -0.34387254 | ... K84: =IFERROR(K83/$B$4-1,"n/a") -> -0.41603553
A86: Implied annual return at today's price, base case | B86: =IFERROR(IF(MATCH($B$4,$B$83:$K$83,-1)=10,"above 14%",INDEX($B$82:$K$82,MATCH($B$4,$B$83:$K$83,-1))+(INDEX($B$83:$K$83,MATCH($B$4,$B$83:$K$83,-1))-$B$4)/(INDEX($B$83:$K$83,MATCH($B$4,$B$83:$K$83,-1))-INDEX($B$83:$K$83,MATCH($B$4,$B$83:$K$83,-1)+1))*(INDEX($B$82:$K$82,MATCH($B$4,$B$83:$K$83,-1)+1)-INDEX($B$82:$K$82,MATCH($B$4,$B$83:$K$83,-1)))),"below 5%") -> 0.075764103 | C86: Discount rate at which base value equals the price (interpolated from the row above)

Sheet JPM
A1: JPMorgan Chase (JPM): residual income valuation
A2: Per-share values. A bank is worth its tangible book plus the present value of future returns above its cost of equity. Years 6 to 10 fade ROTCE to the terminal level.
A4: Share price ($) | B4: 332.07 | C4: Oct 23, 2026 intraday (Yahoo Finance via the site's price feed)
A5: Price date | B5: Oct 23, 2026 | C5: Text
A6: Tangible book value per share, today ($) | B6: 109.96 | C6: Price / P/TBV 3.02 (Stock Analysis, Oct 23, 2026); BVPS $132.30
A7: Payout ratio (dividends plus buybacks) | B7: 0.6 | C7: Analyst assumption
A8: Cost of equity, from WACC tab | B8: =WACC!B40 -> 0.1 | C8: Calculated or assumed, per the switch in WACC!B5
A9: Selected scenario (1 Bear, 2 Base, 3 Bull) | B9: 2 | C9: Lever
A11: Year | B11: 2027 | C11: 2028 | D11: 2029 | E11: 2030 | F11: 2031 | G11: 2032 | H11: 2033 | I11: 2034 | J11: 2035 | K11: 2036 | L11: Terminal
A12: Discount period (years) | B12: 1 | C12: 2 | D12: 3 | E12: 4 | F12: 5 | G12: 6 | H12: 7 | I12: 8 | J12: 9 | K12: 10
A13: Fade step (years 6 to 10) | B13: 0 | C13: 0 | D13: 0 | E13: 0 | F13: 0 | G13: 1 | H13: 2 | I13: 3 | J13: 4 | K13: 5
A15: Bear: credit cycle in 2027 to 2028
A16: Return on tangible equity (ROTCE) | B16: 0.17 | C16: 0.13 | D16: 0.12 | E16: 0.14 | F16: 0.15 | G16: =$F16+($L16-$F16)*G$13/5 -> 0.148 | H16: =$F16+($L16-$F16)*H$13/5 -> 0.146 | I16: =$F16+($L16-$F16)*I$13/5 -> 0.144 | J16: =$F16+($L16-$F16)*J$13/5 -> 0.142 | K16: =$F16+($L16-$F16)*K$13/5 -> 0.14 | L16: 0.14
A17: Tangible book, start of year | B17: =$B$6 -> 109.96 | C17: =B17+B19 -> 117.43728 | D17: =C17+C19 -> 123.54402 | E17: =D17+D19 -> 129.47413 | F17: =E17+E19 -> 136.72468 | G17: =F17+F19 -> 144.92816 | H17: =G17+G19 -> 153.50791 | I17: =H17+H19 -> 162.47277 | J17: =I17+I19 -> 171.8312 | ... L17: =K17+K19 -> 191.76033
A18: Earnings | B18: =B16*B17 -> 18.6932 | C18: =C16*C17 -> 15.266846 | D18: =D16*D17 -> 14.825282 | E18: =E16*E17 -> 18.126378 | F18: =F16*F17 -> 20.508702 | G18: =G16*G17 -> 21.449368 | H18: =H16*H17 -> 22.412155 | I18: =I16*I17 -> 23.396079 | ... K18: =K16*K17 -> 25.42277
A19: Retained earnings | B19: =B18*(1-$B$7) -> 7.47728 | C19: =C18*(1-$B$7) -> 6.1067386 | D19: =D18*(1-$B$7) -> 5.9301129 | E19: =E18*(1-$B$7) -> 7.2505514 | F19: =F18*(1-$B$7) -> 8.203481 | G19: =G18*(1-$B$7) -> 8.5797473 | H19: =H18*(1-$B$7) -> 8.964862 | I19: =I18*(1-$B$7) -> 9.3584317 | ... K19: =K18*(1-$B$7) -> 10.169108
A20: Residual income (ROTCE less cost of equity) x book | B20: =(B16-$B$8)*B17 -> 7.6972 | C20: =(C16-$B$8)*C17 -> 3.5231184 | D20: =(D16-$B$8)*D17 -> 2.4708804 | E20: =(E16-$B$8)*E17 -> 5.1789653 | F20: =(F16-$B$8)*F17 -> 6.8362341 | G20: =(G16-$B$8)*G17 -> 6.9565519 | H20: =(H16-$B$8)*H17 -> 7.0613639 | I20: =(I16-$B$8)*I17 -> 7.148802 | ... L20: =(L16-$B$8)*L17 -> 7.670413
A21: Discount factor | B21: =1/(1+$B$8)^B$12 -> 0.90909091 | C21: =1/(1+$B$8)^C$12 -> 0.82644628 | D21: =1/(1+$B$8)^D$12 -> 0.7513148 | E21: =1/(1+$B$8)^E$12 -> 0.68301346 | F21: =1/(1+$B$8)^F$12 -> 0.62092132 | G21: =1/(1+$B$8)^G$12 -> 0.56447393 | H21: =1/(1+$B$8)^H$12 -> 0.51315812 | I21: =1/(1+$B$8)^I$12 -> 0.46650738 | ... K21: =1/(1+$B$8)^K$12 -> 0.38554329
A22: PV of residual income | B22: =B20*B21 -> 6.9974545 | C22: =C20*C21 -> 2.9116681 | D22: =D20*D21 -> 1.856409 | E22: =E20*E21 -> 3.537303 | F22: =F20*F21 -> 4.2447635 | G22: =G20*G21 -> 3.9267922 | H22: =H20*H21 -> 3.6235962 | I22: =I20*I21 -> 3.3349689 | ... K22: =K20*K21 -> 2.800451
A23: Terminal growth (input) | B23: 0.035
A24: PV of terminal residual income | B24: =L20/($B$8-B23)/(1+$B$8)^$K$12 -> 45.496558
A25: Value per share (book + PV residual income) | B25: =$B$6+SUM(B22:K22)+B24 -> 191.75064
A26: Value vs share price | B26: =B25/$B$4-1 -> -0.42255958
A27: Base: ROTCE eases from 20% to 16%
A28: Return on tangible equity (ROTCE) | B28: 0.2 | C28: 0.19 | D28: 0.18 | E28: 0.17 | F28: 0.17 | G28: =$F28+($L28-$F28)*G$13/5 -> 0.168 | H28: =$F28+($L28-$F28)*H$13/5 -> 0.166 | I28: =$F28+($L28-$F28)*I$13/5 -> 0.164 | J28: =$F28+($L28-$F28)*J$13/5 -> 0.162 | K28: =$F28+($L28-$F28)*K$13/5 -> 0.16 | L28: 0.16
A29: Tangible book, start of year | B29: =$B$6 -> 109.96 | C29: =B29+B31 -> 118.7568 | D29: =C29+C31 -> 127.78232 | E29: =D29+D31 -> 136.98264 | F29: =E29+E31 -> 146.29746 | G29: =F29+F31 -> 156.24569 | H29: =G29+G31 -> 166.7454 | I29: =H29+H31 -> 177.8173 | J29: =I29+I31 -> 189.48211 | ... L29: =K29+K31 -> 214.67323
A30: Earnings | B30: =B28*B29 -> 21.992 | C30: =C28*C29 -> 22.563792 | D30: =D28*D29 -> 23.000817 | E30: =E28*E29 -> 23.287049 | F30: =F28*F29 -> 24.870569 | G30: =G28*G29 -> 26.249276 | H30: =H28*H29 -> 27.679737 | I30: =I28*I29 -> 29.162037 | ... K30: =K28*K29 -> 32.281688
A31: Retained earnings | B31: =B30*(1-$B$7) -> 8.7968 | C31: =C30*(1-$B$7) -> 9.0255168 | D31: =D30*(1-$B$7) -> 9.2003268 | E31: =E30*(1-$B$7) -> 9.3148198 | F31: =F30*(1-$B$7) -> 9.9482275 | G31: =G30*(1-$B$7) -> 10.49971 | H31: =H30*(1-$B$7) -> 11.071895 | I31: =I30*(1-$B$7) -> 11.664815 | ... K31: =K30*(1-$B$7) -> 12.912675
A32: Residual income (ROTCE less cost of equity) x book | B32: =(B28-$B$8)*B29 -> 10.996 | C32: =(C28-$B$8)*C29 -> 10.688112 | D32: =(D28-$B$8)*D29 -> 10.222585 | E32: =(E28-$B$8)*E29 -> 9.5887851 | F32: =(F28-$B$8)*F29 -> 10.240822 | G32: =(G28-$B$8)*G29 -> 10.624707 | H32: =(H28-$B$8)*H29 -> 11.005196 | I32: =(I28-$B$8)*I29 -> 11.380307 | ... L32: =(L28-$B$8)*L29 -> 12.880394
A33: Discount factor | B33: =1/(1+$B$8)^B$12 -> 0.90909091 | C33: =1/(1+$B$8)^C$12 -> 0.82644628 | D33: =1/(1+$B$8)^D$12 -> 0.7513148 | E33: =1/(1+$B$8)^E$12 -> 0.68301346 | F33: =1/(1+$B$8)^F$12 -> 0.62092132 | G33: =1/(1+$B$8)^G$12 -> 0.56447393 | H33: =1/(1+$B$8)^H$12 -> 0.51315812 | I33: =1/(1+$B$8)^I$12 -> 0.46650738 | ... K33: =1/(1+$B$8)^K$12 -> 0.38554329
A34: PV of residual income | B34: =B32*B33 -> 9.9963636 | C34: =C32*C33 -> 8.8331504 | D34: =D32*D33 -> 7.6803797 | E34: =E32*E33 -> 6.5492692 | F34: =F32*F33 -> 6.358745 | G34: =G32*G33 -> 5.9973701 | H34: =H32*H33 -> 5.6474059 | I34: =I32*I33 -> 5.3089972 | ... K34: =K32*K33 -> 4.6672456
A35: Terminal growth (input) | B35: 0.04
A36: PV of terminal residual income | B36: =L32/($B$8-B35)/(1+$B$8)^$K$12 -> 82.765822
A37: Value per share (book + PV residual income) | B37: =$B$6+SUM(B34:K34)+B36 -> 258.747
A38: Value vs share price | B38: =B37/$B$4-1 -> -0.22080585
A39: Bull: ROTCE stays near 20%
A40: Return on tangible equity (ROTCE) | B40: 0.21 | C40: 0.21 | D40: 0.2 | E40: 0.2 | F40: 0.19 | G40: =$F40+($L40-$F40)*G$13/5 -> 0.188 | H40: =$F40+($L40-$F40)*H$13/5 -> 0.186 | I40: =$F40+($L40-$F40)*I$13/5 -> 0.184 | J40: =$F40+($L40-$F40)*J$13/5 -> 0.182 | K40: =$F40+($L40-$F40)*K$13/5 -> 0.18 | L40: 0.18
A41: Tangible book, start of year | B41: =$B$6 -> 109.96 | C41: =B41+B43 -> 119.19664 | D41: =C41+C43 -> 129.20916 | E41: =D41+D43 -> 139.54589 | F41: =E41+E43 -> 150.70956 | G41: =F41+F43 -> 162.16349 | H41: =G41+G43 -> 174.35818 | I41: =H41+H43 -> 187.33043 | J41: =I41+I43 -> 201.11795 | ... L41: =K41+K43 -> 231.29401
A42: Earnings | B42: =B40*B41 -> 23.0916 | C42: =C40*C41 -> 25.031294 | D42: =D40*D41 -> 25.841832 | E42: =E40*E41 -> 27.909178 | F42: =F40*F41 -> 28.634817 | G42: =G40*G41 -> 30.486736 | H42: =H40*H41 -> 32.430622 | I42: =I40*I41 -> 34.468799 | ... K42: =K40*K41 -> 38.836681
A43: Retained earnings | B43: =B42*(1-$B$7) -> 9.23664 | C43: =C42*(1-$B$7) -> 10.012518 | D43: =D42*(1-$B$7) -> 10.336733 | E43: =E42*(1-$B$7) -> 11.163671 | F43: =F42*(1-$B$7) -> 11.453927 | G43: =G42*(1-$B$7) -> 12.194694 | H43: =H42*(1-$B$7) -> 12.972249 | I43: =I42*(1-$B$7) -> 13.78752 | ... K43: =K42*(1-$B$7) -> 15.534672
A44: Residual income (ROTCE less cost of equity) x book | B44: =(B40-$B$8)*B41 -> 12.0956 | C44: =(C40-$B$8)*C41 -> 13.11163 | D44: =(D40-$B$8)*D41 -> 12.920916 | E44: =(E40-$B$8)*E41 -> 13.954589 | F44: =(F40-$B$8)*F41 -> 13.563861 | G44: =(G40-$B$8)*G41 -> 14.270387 | H44: =(H40-$B$8)*H41 -> 14.994804 | I44: =(I40-$B$8)*I41 -> 15.735756 | ... L44: =(L40-$B$8)*L41 -> 18.503521
A45: Discount factor | B45: =1/(1+$B$8)^B$12 -> 0.90909091 | C45: =1/(1+$B$8)^C$12 -> 0.82644628 | D45: =1/(1+$B$8)^D$12 -> 0.7513148 | E45: =1/(1+$B$8)^E$12 -> 0.68301346 | F45: =1/(1+$B$8)^F$12 -> 0.62092132 | G45: =1/(1+$B$8)^G$12 -> 0.56447393 | H45: =1/(1+$B$8)^H$12 -> 0.51315812 | I45: =1/(1+$B$8)^I$12 -> 0.46650738 | ... K45: =1/(1+$B$8)^K$12 -> 0.38554329
A46: PV of residual income | B46: =B44*B45 -> 10.996 | C46: =C44*C45 -> 10.836058 | D46: =D44*D45 -> 9.7076753 | E46: =E44*E45 -> 9.5311721 | F46: =F44*F45 -> 8.4220902 | G46: =G44*G45 -> 8.0552614 | H46: =H44*H45 -> 7.6947053 | I46: =I44*I45 -> 7.3408464 | ... K46: =K44*K45 -> 6.6547652
A47: Terminal growth (input) | B47: 0.04
A48: PV of terminal residual income | B48: =L44/($B$8-B47)/(1+$B$8)^$K$12 -> 118.89847
A49: Value per share (book + PV residual income) | B49: =$B$6+SUM(B46:K46)+B48 -> 315.09112
A50: Value vs share price | B50: =B49/$B$4-1 -> -0.051130411
A52: Outputs | C52: vs price
A53: Bear value per share | B53: =B25 -> 191.75064 | C53: =B53/$B$4-1 -> -0.42255958
A54: Base value per share | B54: =B37 -> 258.747 | C54: =B54/$B$4-1 -> -0.22080585
A55: Bull value per share | B55: =B49 -> 315.09112 | C55: =B55/$B$4-1 -> -0.051130411
A56: Selected scenario value per share | B56: =INDEX(B25:B49,1+($B$9-1)*12) -> 258.747 | C56: =B56/$B$4-1 -> -0.22080585
A57: Base value as a multiple of tangible book | B57: =B54/$B$6 -> 2.3531011
A58: Price as a multiple of tangible book | B58: =B4/B6 -> 3.0199163
A60: Base value per share at other costs of equity
A61: Cost of equity | B61: 0.05 | C61: 0.06 | D61: 0.07 | E61: 0.08 | F61: 0.09 | G61: 0.1 | H61: 0.11 | I61: 0.12 | J61: 0.13 | K61: 0.14
A62: Base value per share | B62: =IF(B$61>$B$35,$B$6+SUMPRODUCT(($B$28:$K$28-B$61)*$B$29:$K$29/(1+B$61)^$B$12:$K$12)+($L$28-B$61)*$L$29/(B$61-$B$35)/(1+B$61)^$K$12,"n/a") -> 1700.6051 | C62: =IF(C$61>$B$35,$B$6+SUMPRODUCT(($B$28:$K$28-C$61)*$B$29:$K$29/(1+C$61)^$B$12:$K$12)+($L$28-C$61)*$L$29/(C$61-$B$35)/(1+C$61)^$K$12,"n/a") -> 832.37998 | D62: =IF(D$61>$B$35,$B$6+SUMPRODUCT(($B$28:$K$28-D$61)*$B$29:$K$29/(1+D$61)^$B$12:$K$12)+($L$28-D$61)*$L$29/(D$61-$B$35)/(1+D$61)^$K$12,"n/a") -> 544.12171 | E62: =IF(E$61>$B$35,$B$6+SUMPRODUCT(($B$28:$K$28-E$61)*$B$29:$K$29/(1+E$61)^$B$12:$K$12)+($L$28-E$61)*$L$29/(E$61-$B$35)/(1+E$61)^$K$12,"n/a") -> 400.7652 | F62: =IF(F$61>$B$35,$B$6+SUMPRODUCT(($B$28:$K$28-F$61)*$B$29:$K$29/(1+F$61)^$B$12:$K$12)+($L$28-F$61)*$L$29/(F$61-$B$35)/(1+F$61)^$K$12,"n/a") -> 315.30553 | G62: =IF(G$61>$B$35,$B$6+SUMPRODUCT(($B$28:$K$28-G$61)*$B$29:$K$29/(1+G$61)^$B$12:$K$12)+($L$28-G$61)*$L$29/(G$61-$B$35)/(1+G$61)^$K$12,"n/a") -> 258.747 | H62: =IF(H$61>$B$35,$B$6+SUMPRODUCT(($B$28:$K$28-H$61)*$B$29:$K$29/(1+H$61)^$B$12:$K$12)+($L$28-H$61)*$L$29/(H$61-$B$35)/(1+H$61)^$K$12,"n/a") -> 218.66737 | I62: =IF(I$61>$B$35,$B$6+SUMPRODUCT(($B$28:$K$28-I$61)*$B$29:$K$29/(1+I$61)^$B$12:$K$12)+($L$28-I$61)*$L$29/(I$61-$B$35)/(1+I$61)^$K$12,"n/a") -> 188.85896 | ... K62: =IF(K$61>$B$35,$B$6+SUMPRODUCT(($B$28:$K$28-K$61)*$B$29:$K$29/(1+K$61)^$B$12:$K$12)+($L$28-K$61)*$L$29/(K$61-$B$35)/(1+K$61)^$K$12,"n/a") -> 147.65241
A63: vs share price | B63: =IFERROR(B62/$B$4-1,"n/a") -> 4.1212247 | C63: =IFERROR(C62/$B$4-1,"n/a") -> 1.5066401 | D63: =IFERROR(D62/$B$4-1,"n/a") -> 0.63857534 | E63: =IFERROR(E62/$B$4-1,"n/a") -> 0.20686963 | F63: =IFERROR(F62/$B$4-1,"n/a") -> -0.050484752 | G63: =IFERROR(G62/$B$4-1,"n/a") -> -0.22080585 | H63: =IFERROR(H62/$B$4-1,"n/a") -> -0.34150219 | I63: =IFERROR(I62/$B$4-1,"n/a") -> -0.43126762 | ... K63: =IFERROR(K62/$B$4-1,"n/a") -> -0.55535759
A65: Implied annual return at today's price, base case | B65: =IFERROR(IF(MATCH($B$4,$B$62:$K$62,-1)=10,"above 14%",INDEX($B$61:$K$61,MATCH($B$4,$B$62:$K$62,-1))+(INDEX($B$62:$K$62,MATCH($B$4,$B$62:$K$62,-1))-$B$4)/(INDEX($B$62:$K$62,MATCH($B$4,$B$62:$K$62,-1))-INDEX($B$62:$K$62,MATCH($B$4,$B$62:$K$62,-1)+1))*(INDEX($B$61:$K$61,MATCH($B$4,$B$62:$K$62,-1)+1)-INDEX($B$61:$K$61,MATCH($B$4,$B$62:$K$62,-1)))),"below 5%") -> 0.088038318 | C65: Cost of equity at which base value equals the price (interpolated)
A66: Note: the rate sensitivity holds book value growth fixed at the base-case path, so it isolates the discount rate.

Sheet BAC
A1: Bank of America (BAC): residual income valuation
A2: Per-share values. A bank is worth its tangible book plus the present value of future returns above its cost of equity. Years 6 to 10 fade ROTCE to the terminal level.
A4: Share price ($) | B4: 50.795 | C4: Oct 23, 2026 intraday (Yahoo Finance via the site's price feed)
A5: Price date | B5: Oct 23, 2026 | C5: Text
A6: Tangible book value per share, today ($) | B6: 29.14 | C6: Stock Analysis, Oct 23, 2026; BVPS $39.26
A7: Payout ratio (dividends plus buybacks) | B7: 0.65 | C7: Analyst assumption
A8: Cost of equity, from WACC tab | B8: =WACC!C40 -> 0.105 | C8: Calculated or assumed, per the switch in WACC!B5
A9: Selected scenario (1 Bear, 2 Base, 3 Bull) | B9: 2 | C9: Lever
A11: Year | B11: 2027 | C11: 2028 | D11: 2029 | E11: 2030 | F11: 2031 | G11: 2032 | H11: 2033 | I11: 2034 | J11: 2035 | K11: 2036 | L11: Terminal
A12: Discount period (years) | B12: 1 | C12: 2 | D12: 3 | E12: 4 | F12: 5 | G12: 6 | H12: 7 | I12: 8 | J12: 9 | K12: 10
A13: Fade step (years 6 to 10) | B13: 0 | C13: 0 | D13: 0 | E13: 0 | F13: 0 | G13: 1 | H13: 2 | I13: 3 | J13: 4 | K13: 5
A15: Bear: credit cycle, rate cuts squeeze NII
A16: Return on tangible equity (ROTCE) | B16: 0.13 | C16: 0.1 | D16: 0.1 | E16: 0.12 | F16: 0.13 | G16: =$F16+($L16-$F16)*G$13/5 -> 0.128 | H16: =$F16+($L16-$F16)*H$13/5 -> 0.126 | I16: =$F16+($L16-$F16)*I$13/5 -> 0.124 | J16: =$F16+($L16-$F16)*J$13/5 -> 0.122 | K16: =$F16+($L16-$F16)*K$13/5 -> 0.12 | L16: 0.12
A17: Tangible book, start of year | B17: =$B$6 -> 29.14 | C17: =B17+B19 -> 30.46587 | D17: =C17+C19 -> 31.532175 | E17: =D17+D19 -> 32.635802 | F17: =E17+E19 -> 34.006505 | G17: =F17+F19 -> 35.553801 | H17: =G17+G19 -> 37.146612 | I17: =H17+H19 -> 38.784777 | J17: =I17+I19 -> 40.468036 | ... L17: =K17+K19 -> 43.968255
A18: Earnings | B18: =B16*B17 -> 3.7882 | C18: =C16*C17 -> 3.046587 | D18: =D16*D17 -> 3.1532175 | E18: =E16*E17 -> 3.9162962 | F18: =F16*F17 -> 4.4208457 | G18: =G16*G17 -> 4.5508866 | H18: =H16*H17 -> 4.6804731 | I18: =I16*I17 -> 4.8093124 | ... K18: =K16*K17 -> 5.0635226
A19: Retained earnings | B19: =B18*(1-$B$7) -> 1.32587 | C19: =C18*(1-$B$7) -> 1.0663054 | D19: =D18*(1-$B$7) -> 1.1036261 | E19: =E18*(1-$B$7) -> 1.3707037 | F19: =F18*(1-$B$7) -> 1.547296 | G19: =G18*(1-$B$7) -> 1.5928103 | H19: =H18*(1-$B$7) -> 1.6381656 | I19: =I18*(1-$B$7) -> 1.6832593 | ... K19: =K18*(1-$B$7) -> 1.7722329
A20: Residual income (ROTCE less cost of equity) x book | B20: =(B16-$B$8)*B17 -> 0.7285 | C20: =(C16-$B$8)*C17 -> -0.15232935 | D20: =(D16-$B$8)*D17 -> -0.15766088 | E20: =(E16-$B$8)*E17 -> 0.48953702 | F20: =(F16-$B$8)*F17 -> 0.85016263 | G20: =(G16-$B$8)*G17 -> 0.81773743 | H20: =(H16-$B$8)*H17 -> 0.78007884 | I20: =(I16-$B$8)*I17 -> 0.73691077 | ... L20: =(L16-$B$8)*L17 -> 0.65952382
A21: Discount factor | B21: =1/(1+$B$8)^B$12 -> 0.90497738 | C21: =1/(1+$B$8)^C$12 -> 0.81898405 | D21: =1/(1+$B$8)^D$12 -> 0.74116204 | E21: =1/(1+$B$8)^E$12 -> 0.67073487 | F21: =1/(1+$B$8)^F$12 -> 0.60699989 | G21: =1/(1+$B$8)^G$12 -> 0.54932116 | H21: =1/(1+$B$8)^H$12 -> 0.49712323 | I21: =1/(1+$B$8)^I$12 -> 0.44988527 | ... K21: =1/(1+$B$8)^K$12 -> 0.36844886
A22: PV of residual income | B22: =B20*B21 -> 0.65927602 | C22: =C20*C21 -> -0.12475531 | D22: =D20*D21 -> -0.11685226 | E22: =E20*E21 -> 0.32834955 | F22: =F20*F21 -> 0.51604862 | G22: =G20*G21 -> 0.44920048 | H22: =H20*H21 -> 0.38779531 | I22: =I20*I21 -> 0.3315253 | ... K22: =K20*K21 -> 0.23320614
A23: Terminal growth (input) | B23: 0.035
A24: PV of terminal residual income | B24: =L20/($B$8-B23)/(1+$B$8)^$K$12 -> 3.47144
A25: Value per share (book + PV residual income) | B25: =$B$6+SUM(B22:K22)+B24 -> 35.555326
A26: Value vs share price | B26: =B25/$B$4-1 -> -0.30002312
A27: Base: ROTCE reaches the 16% target
A28: Return on tangible equity (ROTCE) | B28: 0.15 | C28: 0.155 | D28: 0.16 | E28: 0.16 | F28: 0.16 | G28: =$F28+($L28-$F28)*G$13/5 -> 0.159 | H28: =$F28+($L28-$F28)*H$13/5 -> 0.158 | I28: =$F28+($L28-$F28)*I$13/5 -> 0.157 | J28: =$F28+($L28-$F28)*J$13/5 -> 0.156 | K28: =$F28+($L28-$F28)*K$13/5 -> 0.155 | L28: 0.155
A29: Tangible book, start of year | B29: =$B$6 -> 29.14 | C29: =B29+B31 -> 30.66985 | D29: =C29+C31 -> 32.333689 | E29: =D29+D31 -> 34.144376 | F29: =E29+E31 -> 36.056461 | G29: =F29+F31 -> 38.075623 | H29: =G29+G31 -> 40.194531 | I29: =H29+H31 -> 42.417289 | J29: =I29+I31 -> 44.748119 | ... L29: =K29+K31 -> 49.751498
A30: Earnings | B30: =B28*B29 -> 4.371 | C30: =C28*C29 -> 4.7538267 | D30: =D28*D29 -> 5.1733903 | E30: =E28*E29 -> 5.4631002 | F30: =F28*F29 -> 5.7690338 | G30: =G28*G29 -> 6.054024 | H30: =H28*H29 -> 6.3507359 | I30: =I28*I29 -> 6.6595143 | ... K30: =K28*K29 -> 7.3146618
A31: Retained earnings | B31: =B30*(1-$B$7) -> 1.52985 | C31: =C30*(1-$B$7) -> 1.6638394 | D31: =D30*(1-$B$7) -> 1.8106866 | E31: =E30*(1-$B$7) -> 1.9120851 | F31: =F30*(1-$B$7) -> 2.0191618 | G31: =G30*(1-$B$7) -> 2.1189084 | H31: =H30*(1-$B$7) -> 2.2227576 | I31: =I30*(1-$B$7) -> 2.33083 | ... K31: =K30*(1-$B$7) -> 2.5601316
A32: Residual income (ROTCE less cost of equity) x book | B32: =(B28-$B$8)*B29 -> 1.3113 | C32: =(C28-$B$8)*C29 -> 1.5334925 | D32: =(D28-$B$8)*D29 -> 1.7783529 | E32: =(E28-$B$8)*E29 -> 1.8779407 | F32: =(F28-$B$8)*F29 -> 1.9831054 | G32: =(G28-$B$8)*G29 -> 2.0560836 | H32: =(H28-$B$8)*H29 -> 2.1303102 | I32: =(I28-$B$8)*I29 -> 2.205699 | ... L32: =(L28-$B$8)*L29 -> 2.4875749
A33: Discount factor | B33: =1/(1+$B$8)^B$12 -> 0.90497738 | C33: =1/(1+$B$8)^C$12 -> 0.81898405 | D33: =1/(1+$B$8)^D$12 -> 0.74116204 | E33: =1/(1+$B$8)^E$12 -> 0.67073487 | F33: =1/(1+$B$8)^F$12 -> 0.60699989 | G33: =1/(1+$B$8)^G$12 -> 0.54932116 | H33: =1/(1+$B$8)^H$12 -> 0.49712323 | I33: =1/(1+$B$8)^I$12 -> 0.44988527 | ... K33: =1/(1+$B$8)^K$12 -> 0.36844886
A34: PV of residual income | B34: =B32*B33 -> 1.1866968 | C34: =C32*C33 -> 1.2559059 | D34: =D32*D33 -> 1.3180477 | E34: =E32*E33 -> 1.2596003 | F34: =F32*F33 -> 1.2037447 | G34: =G32*G33 -> 1.1294503 | H34: =H32*H33 -> 1.0590267 | I34: =I32*I33 -> 0.9923115 | ... K34: =K32*K33 -> 0.86938026
A35: Terminal growth (input) | B35: 0.04
A36: PV of terminal residual income | B36: =L32/($B$8-B35)/(1+$B$8)^$K$12 -> 14.100679
A37: Value per share (book + PV residual income) | B37: =$B$6+SUM(B34:K34)+B36 -> 54.44399
A38: Value vs share price | B38: =B37/$B$4-1 -> 0.071837586
A39: Bull: ROTCE climbs to 18%
A40: Return on tangible equity (ROTCE) | B40: 0.155 | C40: 0.165 | D40: 0.175 | E40: 0.18 | F40: 0.18 | G40: =$F40+($L40-$F40)*G$13/5 -> 0.178 | H40: =$F40+($L40-$F40)*H$13/5 -> 0.176 | I40: =$F40+($L40-$F40)*I$13/5 -> 0.174 | J40: =$F40+($L40-$F40)*J$13/5 -> 0.172 | K40: =$F40+($L40-$F40)*K$13/5 -> 0.17 | L40: 0.17
A41: Tangible book, start of year | B41: =$B$6 -> 29.14 | C41: =B41+B43 -> 30.720845 | D41: =C41+C43 -> 32.494974 | E41: =D41+D43 -> 34.485291 | F41: =E41+E43 -> 36.657864 | G41: =F41+F43 -> 38.96731 | H41: =G41+G43 -> 41.394973 | I41: =H41+H43 -> 43.944903 | J41: =I41+I43 -> 46.621148 | ... L41: =K41+K43 -> 52.368692
A42: Earnings | B42: =B40*B41 -> 4.5167 | C42: =C40*C41 -> 5.0689394 | D42: =D40*D41 -> 5.6866204 | E42: =E40*E41 -> 6.2073524 | F42: =F40*F41 -> 6.5984156 | G42: =G40*G41 -> 6.9361811 | H42: =H40*H41 -> 7.2855153 | I42: =I40*I41 -> 7.6464132 | ... K42: =K40*K41 -> 8.402716
A43: Retained earnings | B43: =B42*(1-$B$7) -> 1.580845 | C43: =C42*(1-$B$7) -> 1.7741288 | D43: =D42*(1-$B$7) -> 1.9903171 | E43: =E42*(1-$B$7) -> 2.1725733 | F43: =F42*(1-$B$7) -> 2.3094454 | G43: =G42*(1-$B$7) -> 2.4276634 | H43: =H42*(1-$B$7) -> 2.5499303 | I43: =I42*(1-$B$7) -> 2.6762446 | ... K43: =K42*(1-$B$7) -> 2.9409506
A44: Residual income (ROTCE less cost of equity) x book | B44: =(B40-$B$8)*B41 -> 1.457 | C44: =(C40-$B$8)*C41 -> 1.8432507 | D44: =(D40-$B$8)*D41 -> 2.2746482 | E44: =(E40-$B$8)*E41 -> 2.5863968 | F44: =(F40-$B$8)*F41 -> 2.7493398 | G44: =(G40-$B$8)*G41 -> 2.8446136 | H44: =(H40-$B$8)*H41 -> 2.9390431 | I44: =(I40-$B$8)*I41 -> 3.0321983 | ... L44: =(L40-$B$8)*L41 -> 3.403965
