Workbook

Sheet Summary
A1: Healthcare: scenario values for four candidates
A2: Values link to each company sheet (green). Switch the discount rate on the WACC tab. Same framework and discount-rate inputs as the current holdings workbook.
A4: Company | B4: Sector | C4: Share price | D4: Discount rate | E4: Bear value | F4: Base value | G4: Bull value | H4: Base vs price | I4: Implied return at price (base case) | J4: Buy below (base value, rounded)
A5: Abbott Laboratories (ABT) | B5: Healthcare | C5: =ABT!B4 -> 103.7 | D5: =ABT!B10 -> 0.08 | E5: =ABT!B75 -> 91.378797 | F5: =ABT!B76 -> 131.63733 | G5: =ABT!B77 -> 183.33535 | H5: =F5/C5-1 -> 0.26940534 | I5: =ABT!B86 -> 0.090600005 | J5: =IF(F5<100,ROUND(F5,0),ROUND(F5/5,0)*5) -> 130
A6: Medtronic (MDT) | B6: Healthcare | C6: =MDT!B4 -> 95.41 | D6: =MDT!B10 -> 0.08 | E6: =MDT!B75 -> 86.830946 | F6: =MDT!B76 -> 118.40131 | G6: =MDT!B77 -> 155.45631 | H6: =F6/C6-1 -> 0.24097384 | I6: =MDT!B86 -> 0.09054539 | J6: =IF(F6<100,ROUND(F6,0),ROUND(F6/5,0)*5) -> 120
A7: Merck (MRK) | B7: Healthcare | C7: =MRK!B4 -> 144.45 | D7: =MRK!B10 -> 0.08 | E7: =MRK!B75 -> 61.660411 | F7: =MRK!B76 -> 97.506469 | G7: =MRK!B77 -> 137.75206 | H7: =F7/C7-1 -> -0.32498118 | I7: =MRK!B86 -> 0.064102216 | J7: =IF(F7<100,ROUND(F7,0),ROUND(F7/5,0)*5) -> 98
A8: Becton Dickinson (BDX) | B8: Healthcare | C8: =BDX!B4 -> 198.91 | D8: =BDX!B10 -> 0.08 | E8: =BDX!B75 -> 169.03206 | F8: =BDX!B76 -> 233.04879 | G8: =BDX!B77 -> 302.47563 | H8: =F8/C8-1 -> 0.17162932 | I8: =BDX!B86 -> 0.08707639 | J8: =IF(F8<100,ROUND(F8,0),ROUND(F8/5,0)*5) -> 235

Sheet WACC
A1: Discount rates: calculated (CAPM) versus assumed
A2: Blue = input, black = formula, green = link. The yellow switches apply to every company. Same risk-free rate and premium as the holdings workbook.
A5: Rate used in valuations (1 = Calculated, 2 = Assumed) | B5: 2 | C5: Switch. 2 reproduces the published figures
A6: Beta used (1 = Raw 5-year, 2 = Blume adjusted) | B6: 2 | C6: Blume adjusted = 0.67 x raw + 0.33
A7: Risk-free rate (10-year Treasury) | B7: 0.0531 | C7: FRED via MacroRadar, Oct 6, 2026 (same as the holdings workbook)
A8: Equity risk premium | B8: 0.05 | C8: Analyst assumption
A9: Credit spread over risk-free (pre-tax cost of debt) | B9: 0.012 | C9: Analyst assumption: investment-grade spread
A12: Item | B12: ABT | C12: MDT | D12: MRK | E12: BDX | F12: Source / note
A13: Raw beta (5-year) | B13: 0.58 | C13: 0.57 | D13: 0.22 | E13: 0.28 | F13: Stock Analysis statistics, Oct 23 to 26, 2026
A14: Beta override (blank = none) | F14: None used
A15: Adjusted beta | B15: =0.67*IF(ISNUMBER(B14),B14,B13)+0.33 -> 0.7186 | C15: =0.67*IF(ISNUMBER(C14),C14,C13)+0.33 -> 0.7119 | D15: =0.67*IF(ISNUMBER(D14),D14,D13)+0.33 -> 0.4774 | E15: =0.67*IF(ISNUMBER(E14),E14,E13)+0.33 -> 0.5176 | F15: Blume: 0.67 x raw (or override) + 0.33
A16: Beta used | B16: =IF($B$6=1,IF(ISNUMBER(B14),B14,B13),B15) -> 0.7186 | C16: =IF($B$6=1,IF(ISNUMBER(C14),C14,C13),C15) -> 0.7119 | D16: =IF($B$6=1,IF(ISNUMBER(D14),D14,D13),D15) -> 0.4774 | E16: =IF($B$6=1,IF(ISNUMBER(E14),E14,E13),E15) -> 0.5176 | F16: Per switch in B6
A17: Cost of equity | B17: =$B$7+B16*$B$8 -> 0.08903 | C17: =$B$7+C16*$B$8 -> 0.088695 | D17: =$B$7+D16*$B$8 -> 0.07697 | E17: =$B$7+E16*$B$8 -> 0.07898 | F17: Risk-free + beta x ERP
A18: Pre-tax cost of debt | B18: =$B$7+$B$9 -> 0.0651 | C18: =$B$7+$B$9 -> 0.0651 | D18: =$B$7+$B$9 -> 0.0651 | E18: =$B$7+$B$9 -> 0.0651 | F18: Risk-free + spread
A19: Tax rate | B19: =ABT!B9 -> 0.15 | C19: =MDT!B9 -> 0.165 | D19: =MRK!B9 -> 0.15 | E19: =BDX!B9 -> 0.14 | F19: Linked from each company sheet
A20: After-tax cost of debt | B20: =B18*(1-B19) -> 0.055335 | C20: =C18*(1-C19) -> 0.0543585 | D20: =D18*(1-D19) -> 0.055335 | E20: =E18*(1-E19) -> 0.055986
A21: Market value of equity ($B) | B21: =ABT!B4*ABT!B6 -> 179.44248 | C21: =MDT!B4*MDT!B6 -> 116.79138 | D21: =MRK!B4*MRK!B6 -> 356.38704 | E21: =BDX!B4*BDX!B6 -> 54.181095 | F21: Price x shares
A22: Debt ($B) | B22: 32.72 | C22: 28.15 | D22: 53.91 | E22: 16.81 | F22: Stock Analysis, total debt
A23: Equity weight | B23: =B21/(B21+B22) -> 0.84577857 | C23: =C21/(C21+C22) -> 0.80578355 | D23: =D21/(D21+D22) -> 0.86860739 | E23: =E21/(E21+E22) -> 0.76320974
A24: Debt weight | B24: =B22/(B21+B22) -> 0.15422143 | C24: =C22/(C21+C22) -> 0.19421645 | D24: =D22/(D21+D22) -> 0.13139261 | E24: =E22/(E21+E22) -> 0.23679026
A25: Calculated WACC (CAPM) | B25: =B23*B17+B24*B20 -> 0.083833509 | C25: =C23*C17+C24*C20 -> 0.082026287 | D25: =D23*D17+D24*D20 -> 0.074127321 | E25: =E23*E17+E24*E20 -> 0.073535245 | F25: Weighted cost of capital
A26: Assumed WACC | B26: 0.08 | C26: 0.08 | D26: 0.08 | E26: 0.08 | F26: Analyst assumption
A27: WACC used | B27: =IF($B$5=1,B25,B26) -> 0.08 | C27: =IF($B$5=1,C25,C26) -> 0.08 | D27: =IF($B$5=1,D25,D26) -> 0.08 | E27: =IF($B$5=1,E25,E26) -> 0.08 | F27: Per switch in B5
A28: Check: WACC above every terminal growth rate | B28: =IF(B27>MAX(ABT!L21,ABT!L39,ABT!L57),"OK","WACC must exceed growth") -> OK | C28: =IF(C27>MAX(MDT!L21,MDT!L39,MDT!L57),"OK","WACC must exceed growth") -> OK | D28: =IF(D27>MAX(MRK!L21,MRK!L39,MRK!L57),"OK","WACC must exceed growth") -> OK | E28: =IF(E27>MAX(BDX!L21,BDX!L39,BDX!L57),"OK","WACC must exceed growth") -> OK
A29: Link row read by company sheets | B29: =B27 -> 0.08 | C29: =C27 -> 0.08 | D29: =D27 -> 0.08 | E29: =E27 -> 0.08 | F29: Same as WACC used

Sheet ABT
A1: Abbott Laboratories (ABT): 10-year scenario DCF
A2: Units: $ billions unless noted. Blue = input, black = formula, green = link, yellow = key lever. Years 6 to 10 fade growth, margin and reinvestment toward each scenario's terminal levels.
A4: Share price ($) | B4: 103.7 | C4: Stock Analysis, Oct 23, 2026 close
A5: Price date | B5: Oct 23, 2026 close | C5: Text
A6: Shares outstanding (billions) | B6: 1.7304 | C6: Stock Analysis statistics, Oct 23 to 26, 2026 (market cap / price)
A7: Net cash, negative = net debt | B7: -27.12 | C7: Stock Analysis statistics, Oct 23 to 26, 2026: cash less total debt
A8: Other non-operating assets, less outside claims | B8: 0 | C8: None
A9: Tax rate | B9: 0.15 | C9: Analyst assumption, near the adjusted effective rate
A10: Discount rate (WACC), from WACC tab | B10: =WACC!B29 -> 0.08 | C10: Calculated or assumed, per the switch in WACC!B5
A11: Working capital, % of revenue change | B11: 0.15 | C11: Analyst assumption
A12: Base-year revenue (2026E) | B12: 50.2 | C12: 2026E consensus $50.20B incl. Exact Sciences (Stock Analysis forecast). Margins are adjusted operating margins, after stock pay
A13: Selected scenario (1 Bear, 2 Base, 3 Bull) | B13: 2 | C13: Lever
A15: Year | B15: 2027 | C15: 2028 | D15: 2029 | E15: 2030 | F15: 2031 | G15: 2032 | H15: 2033 | I15: 2034 | J15: 2035 | K15: 2036 | L15: Terminal
A16: Discount period (years, mid-year) | B16: 0.5 | C16: =B16+1 -> 1.5 | D16: =C16+1 -> 2.5 | E16: =D16+1 -> 3.5 | F16: =E16+1 -> 4.5 | G16: =F16+1 -> 5.5 | H16: =G16+1 -> 6.5 | I16: =H16+1 -> 7.5 | J16: =I16+1 -> 8.5 | K16: =J16+1 -> 9.5
A17: Fade step (years 6 to 10) | B17: 0 | C17: 0 | D17: 0 | E17: 0 | F17: 0 | G17: 1 | H17: 2 | I17: 3 | J17: 4 | K17: 5
A19: Bear: CGM pricing pressure, Libre recall costs share
A20: Revenue | B20: 52 | C20: 54 | D20: 56 | E20: 58 | F20: 60 | G20: =F20*(1+$F21+($L21-$F21)*G$17/5) -> 62.015172 | H20: =G20*(1+$F21+($L21-$F21)*H$17/5) -> 64.042427 | I20: =H20*(1+$F21+($L21-$F21)*I$17/5) -> 66.078535 | J20: =I20*(1+$F21+($L21-$F21)*J$17/5) -> 68.120133 | K20: =J20*(1+$F21+($L21-$F21)*K$17/5) -> 70.163737 | L20: =K20*(1+L21) -> 72.26865
A21: Revenue growth (terminal column = terminal growth, input) | B21: =B20/$B$12-1 -> 0.035856574 | C21: =C20/B20-1 -> 0.038461538 | D21: =D20/C20-1 -> 0.037037037 | E21: =E20/D20-1 -> 0.035714286 | F21: =F20/E20-1 -> 0.034482759 | G21: =G20/F20-1 -> 0.033586207 | H21: =H20/G20-1 -> 0.032689655 | I21: =I20/H20-1 -> 0.031793103 | J21: =J20/I20-1 -> 0.030896552 | K21: =K20/J20-1 -> 0.03 | L21: 0.03
A22: Operating margin | B22: 0.235 | C22: 0.235 | D22: 0.24 | E22: 0.24 | F22: 0.24 | G22: =$F22+($L22-$F22)*G$17/5 -> 0.238 | H22: =$F22+($L22-$F22)*H$17/5 -> 0.236 | I22: =$F22+($L22-$F22)*I$17/5 -> 0.234 | J22: =$F22+($L22-$F22)*J$17/5 -> 0.232 | K22: =$F22+($L22-$F22)*K$17/5 -> 0.23 | L22: 0.23
A23: Operating income | B23: =B20*B22 -> 12.22 | C23: =C20*C22 -> 12.69 | D23: =D20*D22 -> 13.44 | E23: =E20*E22 -> 13.92 | F23: =F20*F22 -> 14.4 | G23: =G20*G22 -> 14.759611 | H23: =H20*H22 -> 15.114013 | I23: =I20*I22 -> 15.462377 | ... L23: =L20*L22 -> 16.621789
A24: NOPAT | B24: =B23*(1-$B$9) -> 10.387 | C24: =C23*(1-$B$9) -> 10.7865 | D24: =D23*(1-$B$9) -> 11.424 | E24: =E23*(1-$B$9) -> 11.832 | F24: =F23*(1-$B$9) -> 12.24 | G24: =G23*(1-$B$9) -> 12.545669 | H24: =H23*(1-$B$9) -> 12.846911 | I24: =I23*(1-$B$9) -> 13.143021 | ... L24: =L23*(1-$B$9) -> 14.128521
A25: Net reinvestment, % of revenue | B25: 0.03 | C25: 0.03 | D25: 0.03 | E25: 0.03 | F25: 0.03 | G25: =$F25+($L25-$F25)*G$17/5 -> 0.029 | H25: =$F25+($L25-$F25)*H$17/5 -> 0.028 | I25: =$F25+($L25-$F25)*I$17/5 -> 0.027 | J25: =$F25+($L25-$F25)*J$17/5 -> 0.026 | K25: =$F25+($L25-$F25)*K$17/5 -> 0.025 | L25: 0.025
A26: Net reinvestment | B26: =B20*B25 -> 1.56 | C26: =C20*C25 -> 1.62 | D26: =D20*D25 -> 1.68 | E26: =E20*E25 -> 1.74 | F26: =F20*F25 -> 1.8 | G26: =G20*G25 -> 1.79844 | H26: =H20*H25 -> 1.793188 | I26: =I20*I25 -> 1.7841204 | ... L26: =L20*L25 -> 1.8067162
A27: Change in working capital | B27: =$B$11*(B20-$B$12) -> 0.27 | C27: =$B$11*(C20-B20) -> 0.3 | D27: =$B$11*(D20-C20) -> 0.3 | E27: =$B$11*(E20-D20) -> 0.3 | F27: =$B$11*(F20-E20) -> 0.3 | G27: =$B$11*(G20-F20) -> 0.30227586 | H27: =$B$11*(H20-G20) -> 0.30408819 | I27: =$B$11*(I20-H20) -> 0.30541613 | J27: =$B$11*(J20-I20) -> 0.30623983 | ... L27: =$B$11*(L20-K20) -> 0.31573682
A28: Free cash flow | B28: =B24-B26-B27 -> 8.557 | C28: =C24-C26-C27 -> 8.8665 | D28: =D24-D26-D27 -> 9.444 | E28: =E24-E26-E27 -> 9.792 | F28: =F24-F26-F27 -> 10.14 | G28: =G24-G26-G27 -> 10.444954 | H28: =H24-H26-H27 -> 10.749635 | I28: =I24-I26-I27 -> 11.053484 | ... L28: =L24-L26-L27 -> 12.006068
A29: Discount factor | B29: =1/(1+$B$10)^B$16 -> 0.96225045 | C29: =1/(1+$B$10)^C$16 -> 0.89097264 | D29: =1/(1+$B$10)^D$16 -> 0.82497466 | E29: =1/(1+$B$10)^E$16 -> 0.76386543 | F29: =1/(1+$B$10)^F$16 -> 0.70728281 | G29: =1/(1+$B$10)^G$16 -> 0.65489149 | H29: =1/(1+$B$10)^H$16 -> 0.60638101 | I29: =1/(1+$B$10)^I$16 -> 0.56146389 | ... K29: =1/(1+$B$10)^K$16 -> 0.48136479
A30: PV of free cash flow | B30: =B28*B29 -> 8.2339771 | C30: =C28*C29 -> 7.8998089 | D30: =D28*D29 -> 7.7910607 | E30: =E28*E29 -> 7.4797703 | F30: =F28*F29 -> 7.1718476 | G30: =G28*G29 -> 6.8403111 | H30: =H28*H29 -> 6.5183743 | I30: =I28*I29 -> 6.2061322 | ... K30: =K28*K29 -> 5.6109693
A31: Terminal value | B31: =L28/($B$10-L21) -> 240.12136 | C31: =IF($B$10>L21,"","Discount rate must exceed terminal growth")
A32: PV of terminal value | B32: =B31/(1+$B$10)^$K$16 -> 115.58597
A33: Equity value (PV FCF + PV TV + net cash + other) | B33: =SUM(B30:K30)+B32+$B$7+$B$8 -> 158.12187
A34: Value per share ($) | B34: =B33/$B$6 -> 91.378797
A35: Value vs share price | B35: =B34/$B$4-1 -> -0.11881584
A37: Base: about 6.5% growth, slow margin expansion
A38: Revenue | B38: 53.5 | C38: 57 | D38: 60.7 | E38: 64.6 | F38: 68.8 | G38: =F38*(1+$F39+($L39-$F39)*G$17/5) -> 72.860052 | H38: =G38*(1+$F39+($L39-$F39)*H$17/5) -> 76.722311 | I38: =H38*(1+$F39+($L39-$F39)*I$17/5) -> 80.328735 | J38: =I38*(1+$F39+($L39-$F39)*J$17/5) -> 83.622462 | K38: =J38*(1+$F39+($L39-$F39)*K$17/5) -> 86.549248 | L38: =K38*(1+L39) -> 89.578472
A39: Revenue growth (terminal column = terminal growth, input) | B39: =B38/$B$12-1 -> 0.065737052 | C39: =C38/B38-1 -> 0.065420561 | D39: =D38/C38-1 -> 0.064912281 | E39: =E38/D38-1 -> 0.064250412 | F39: =F38/E38-1 -> 0.06501548 | G39: =G38/F38-1 -> 0.059012384 | H39: =H38/G38-1 -> 0.053009288 | I39: =I38/H38-1 -> 0.047006192 | J39: =J38/I38-1 -> 0.041003096 | K39: =K38/J38-1 -> 0.035 | L39: 0.035
A40: Operating margin | B40: 0.245 | C40: 0.248 | D40: 0.252 | E40: 0.256 | F40: 0.26 | G40: =$F40+($L40-$F40)*G$17/5 -> 0.257 | H40: =$F40+($L40-$F40)*H$17/5 -> 0.254 | I40: =$F40+($L40-$F40)*I$17/5 -> 0.251 | J40: =$F40+($L40-$F40)*J$17/5 -> 0.248 | K40: =$F40+($L40-$F40)*K$17/5 -> 0.245 | L40: 0.245
A41: Operating income | B41: =B38*B40 -> 13.1075 | C41: =C38*C40 -> 14.136 | D41: =D38*D40 -> 15.2964 | E41: =E38*E40 -> 16.5376 | F41: =F38*F40 -> 17.888 | G41: =G38*G40 -> 18.725033 | H41: =H38*H40 -> 19.487467 | I41: =I38*I40 -> 20.162513 | ... L41: =L38*L40 -> 21.946726
A42: NOPAT | B42: =B41*(1-$B$9) -> 11.141375 | C42: =C41*(1-$B$9) -> 12.0156 | D42: =D41*(1-$B$9) -> 13.00194 | E42: =E41*(1-$B$9) -> 14.05696 | F42: =F41*(1-$B$9) -> 15.2048 | G42: =G41*(1-$B$9) -> 15.916278 | H42: =H41*(1-$B$9) -> 16.564347 | I42: =I41*(1-$B$9) -> 17.138136 | ... L42: =L41*(1-$B$9) -> 18.654717
A43: Net reinvestment, % of revenue | B43: 0.03 | C43: 0.03 | D43: 0.03 | E43: 0.03 | F43: 0.03 | G43: =$F43+($L43-$F43)*G$17/5 -> 0.029 | H43: =$F43+($L43-$F43)*H$17/5 -> 0.028 | I43: =$F43+($L43-$F43)*I$17/5 -> 0.027 | J43: =$F43+($L43-$F43)*J$17/5 -> 0.026 | K43: =$F43+($L43-$F43)*K$17/5 -> 0.025 | L43: 0.025
A44: Net reinvestment | B44: =B38*B43 -> 1.605 | C44: =C38*C43 -> 1.71 | D44: =D38*D43 -> 1.821 | E44: =E38*E43 -> 1.938 | F44: =F38*F43 -> 2.064 | G44: =G38*G43 -> 2.1129415 | H44: =H38*H43 -> 2.1482247 | I44: =I38*I43 -> 2.1688759 | ... L44: =L38*L43 -> 2.2394618
A45: Change in working capital | B45: =$B$11*(B38-$B$12) -> 0.495 | C45: =$B$11*(C38-B38) -> 0.525 | D45: =$B$11*(D38-C38) -> 0.555 | E45: =$B$11*(E38-D38) -> 0.585 | F45: =$B$11*(F38-E38) -> 0.63 | G45: =$B$11*(G38-F38) -> 0.6090078 | H45: =$B$11*(H38-G38) -> 0.57933892 | I45: =$B$11*(I38-H38) -> 0.54096356 | J45: =$B$11*(J38-I38) -> 0.49405903 | ... L45: =$B$11*(L38-K38) -> 0.45438355
A46: Free cash flow | B46: =B42-B44-B45 -> 9.041375 | C46: =C42-C44-C45 -> 9.7806 | D46: =D42-D44-D45 -> 10.62594 | E46: =E42-E44-E45 -> 11.53396 | F46: =F42-F44-F45 -> 12.5108 | G46: =G42-G44-G45 -> 13.194329 | H46: =H42-H44-H45 -> 13.836783 | I46: =I42-I44-I45 -> 14.428296 | ... L46: =L42-L44-L45 -> 15.960871
A47: Discount factor | B47: =1/(1+$B$10)^B$16 -> 0.96225045 | C47: =1/(1+$B$10)^C$16 -> 0.89097264 | D47: =1/(1+$B$10)^D$16 -> 0.82497466 | E47: =1/(1+$B$10)^E$16 -> 0.76386543 | F47: =1/(1+$B$10)^F$16 -> 0.70728281 | G47: =1/(1+$B$10)^G$16 -> 0.65489149 | H47: =1/(1+$B$10)^H$16 -> 0.60638101 | I47: =1/(1+$B$10)^I$16 -> 0.56146389 | ... K47: =1/(1+$B$10)^K$16 -> 0.48136479
A48: PV of free cash flow | B48: =B46*B47 -> 8.7000672 | C48: =C46*C47 -> 8.714247 | D48: =D46*D47 -> 8.7661313 | E48: =E46*E47 -> 8.8103933 | F48: =F46*F47 -> 8.8486737 | G48: =G46*G47 -> 8.6408538 | H48: =H46*H47 -> 8.3903626 | I48: =I46*I47 -> 8.1009674 | ... K48: =K46*K47 -> 7.4231899
A49: Terminal value | B49: =L46/($B$10-L39) -> 354.68603 | C49: =IF($B$10>L39,"","Discount rate must exceed terminal growth")
A50: PV of terminal value | B50: =B49/(1+$B$10)^$K$16 -> 170.73337
A51: Equity value (PV FCF + PV TV + net cash + other) | B51: =SUM(B48:K48)+B50+$B$7+$B$8 -> 227.78524
A52: Value per share ($) | B52: =B51/$B$6 -> 131.63733
A53: Value vs share price | B53: =B52/$B$4-1 -> 0.26940534
A55: Bull: CGM and Exact Sciences compound
A56: Revenue | B56: 54.2 | C56: 58.8 | D56: 63.8 | E56: 69.2 | F56: 74.9 | G56: =F56*(1+$F57+($L57-$F57)*G$17/5) -> 80.434807 | H56: =G56*(1+$F57+($L57-$F57)*H$17/5) -> 85.69701 | I56: =H56*(1+$F57+($L57-$F57)*I$17/5) -> 90.577281 | J56: =I56*(1+$F57+($L57-$F57)*J$17/5) -> 94.967924 | K56: =J56*(1+$F57+($L57-$F57)*K$17/5) -> 98.76664 | L56: =K56*(1+L57) -> 102.71731
A57: Revenue growth (terminal column = terminal growth, input) | B57: =B56/$B$12-1 -> 0.079681275 | C57: =C56/B56-1 -> 0.084870849 | D57: =D56/C56-1 -> 0.085034014 | E57: =E56/D56-1 -> 0.084639498 | F57: =F56/E56-1 -> 0.082369942 | G57: =G56/F56-1 -> 0.073895954 | H57: =H56/G56-1 -> 0.065421965 | I57: =I56/H56-1 -> 0.056947977 | J57: =J56/I56-1 -> 0.048473988 | K57: =K56/J56-1 -> 0.04 | L57: 0.04
A58: Operating margin | B58: 0.25 | C58: 0.26 | D58: 0.27 | E58: 0.275 | F58: 0.28 | G58: =$F58+($L58-$F58)*G$17/5 -> 0.278 | H58: =$F58+($L58-$F58)*H$17/5 -> 0.276 | I58: =$F58+($L58-$F58)*I$17/5 -> 0.274 | J58: =$F58+($L58-$F58)*J$17/5 -> 0.272 | K58: =$F58+($L58-$F58)*K$17/5 -> 0.27 | L58: 0.27
A59: Operating income | B59: =B56*B58 -> 13.55 | C59: =C56*C58 -> 15.288 | D59: =D56*D58 -> 17.226 | E59: =E56*E58 -> 19.03 | F59: =F56*F58 -> 20.972 | G59: =G56*G58 -> 22.360876 | H59: =H56*H58 -> 23.652375 | I59: =I56*I58 -> 24.818175 | ... L59: =L56*L58 -> 27.733673
A60: NOPAT | B60: =B59*(1-$B$9) -> 11.5175 | C60: =C59*(1-$B$9) -> 12.9948 | D60: =D59*(1-$B$9) -> 14.6421 | E60: =E59*(1-$B$9) -> 16.1755 | F60: =F59*(1-$B$9) -> 17.8262 | G60: =G59*(1-$B$9) -> 19.006745 | H60: =H59*(1-$B$9) -> 20.104519 | I60: =I59*(1-$B$9) -> 21.095449 | ... L60: =L59*(1-$B$9) -> 23.573622
A61: Net reinvestment, % of revenue | B61: 0.03 | C61: 0.03 | D61: 0.03 | E61: 0.03 | F61: 0.03 | G61: =$F61+($L61-$F61)*G$17/5 -> 0.029 | H61: =$F61+($L61-$F61)*H$17/5 -> 0.028 | I61: =$F61+($L61-$F61)*I$17/5 -> 0.027 | J61: =$F61+($L61-$F61)*J$17/5 -> 0.026 | K61: =$F61+($L61-$F61)*K$17/5 -> 0.025 | L61: 0.025
A62: Net reinvestment | B62: =B56*B61 -> 1.626 | C62: =C56*C61 -> 1.764 | D62: =D56*D61 -> 1.914 | E62: =E56*E61 -> 2.076 | F62: =F56*F61 -> 2.247 | G62: =G56*G61 -> 2.3326094 | H62: =H56*H61 -> 2.3995163 | I62: =I56*I61 -> 2.4455866 | ... L62: =L56*L61 -> 2.5679327
A63: Change in working capital | B63: =$B$11*(B56-$B$12) -> 0.6 | C63: =$B$11*(C56-B56) -> 0.69 | D63: =$B$11*(D56-C56) -> 0.75 | E63: =$B$11*(E56-D56) -> 0.81 | F63: =$B$11*(F56-E56) -> 0.855 | G63: =$B$11*(G56-F56) -> 0.83022104 | H63: =$B$11*(H56-G56) -> 0.78933047 | I63: =$B$11*(I56-H56) -> 0.7320407 | J63: =$B$11*(J56-I56) -> 0.65859631 | ... L63: =$B$11*(L56-K56) -> 0.59259984
A64: Free cash flow | B64: =B60-B62-B63 -> 9.2915 | C64: =C60-C62-C63 -> 10.5408 | D64: =D60-D62-D63 -> 11.9781 | E64: =E60-E62-E63 -> 13.2895 | F64: =F60-F62-F63 -> 14.7242 | G64: =G60-G62-G63 -> 15.843914 | H64: =H60-H62-H63 -> 16.915672 | I64: =I60-I62-I63 -> 17.917822 | ... L64: =L60-L62-L63 -> 20.413089
A65: Discount factor | B65: =1/(1+$B$10)^B$16 -> 0.96225045 | C65: =1/(1+$B$10)^C$16 -> 0.89097264 | D65: =1/(1+$B$10)^D$16 -> 0.82497466 | E65: =1/(1+$B$10)^E$16 -> 0.76386543 | F65: =1/(1+$B$10)^F$16 -> 0.70728281 | G65: =1/(1+$B$10)^G$16 -> 0.65489149 | H65: =1/(1+$B$10)^H$16 -> 0.60638101 | I65: =1/(1+$B$10)^I$16 -> 0.56146389 | ... K65: =1/(1+$B$10)^K$16 -> 0.48136479
A66: PV of free cash flow | B66: =B64*B65 -> 8.94075 | C66: =C64*C65 -> 9.3915644 | D66: =D64*D65 -> 9.881629 | E66: =E64*E65 -> 10.15139 | F66: =F64*F65 -> 10.414173 | G66: =G64*G65 -> 10.376045 | H66: =H64*H65 -> 10.257342 | I66: =I64*I65 -> 10.06021 | ... K66: =K64*K65 -> 9.4482139
A67: Terminal value | B67: =L64/($B$10-L57) -> 510.32723 | C67: =IF($B$10>L57,"","Discount rate must exceed terminal growth")
A68: PV of terminal value | B68: =B67/(1+$B$10)^$K$16 -> 245.65356
A69: Equity value (PV FCF + PV TV + net cash + other) | B69: =SUM(B66:K66)+B68+$B$7+$B$8 -> 317.24349
A70: Value per share ($) | B70: =B69/$B$6 -> 183.33535
A71: Value vs share price | B71: =B70/$B$4-1 -> 0.76793975
A74: Outputs | C74: vs price
A75: Bear value per share | B75: =B34 -> 91.378797 | C75: =B75/$B$4-1 -> -0.11881584
A76: Base value per share | B76: =B52 -> 131.63733 | C76: =B76/$B$4-1 -> 0.26940534
A77: Bull value per share | B77: =B70 -> 183.33535 | C77: =B77/$B$4-1 -> 0.76793975
A78: Selected scenario value per share | B78: =INDEX(B34:B70,1+($B$13-1)*18) -> 131.63733 | C78: =B78/$B$4-1 -> 0.26940534
A79: Share of base value from terminal value | B79: =B50/(SUM(B48:K48)+B50) -> 0.66979151
A81: Base value per share at other discount rates
A82: Discount rate | B82: 0.05 | C82: 0.06 | D82: 0.07 | E82: 0.08 | F82: 0.09 | G82: 0.1 | H82: 0.11 | I82: 0.12 | J82: 0.13 | K82: 0.14
A83: Base value per share | B83: =IF(B82>$L39,(SUMPRODUCT($B46:$K46/(1+B82)^$B$16:$K$16)+$L46/(B82-$L39)/(1+B82)^$K$16+$B$7+$B$8)/$B$6,"n/a") -> 427.12262 | C83: =IF(C82>$L39,(SUMPRODUCT($B46:$K46/(1+C82)^$B$16:$K$16)+$L46/(C82-$L39)/(1+C82)^$K$16+$B$7+$B$8)/$B$6,"n/a") -> 249.78682 | D83: =IF(D82>$L39,(SUMPRODUCT($B46:$K46/(1+D82)^$B$16:$K$16)+$L46/(D82-$L39)/(1+D82)^$K$16+$B$7+$B$8)/$B$6,"n/a") -> 173.81825 | E83: =IF(E82>$L39,(SUMPRODUCT($B46:$K46/(1+E82)^$B$16:$K$16)+$L46/(E82-$L39)/(1+E82)^$K$16+$B$7+$B$8)/$B$6,"n/a") -> 131.63733 | F83: =IF(F82>$L39,(SUMPRODUCT($B46:$K46/(1+F82)^$B$16:$K$16)+$L46/(F82-$L39)/(1+F82)^$K$16+$B$7+$B$8)/$B$6,"n/a") -> 104.81335 | G83: =IF(G82>$L39,(SUMPRODUCT($B46:$K46/(1+G82)^$B$16:$K$16)+$L46/(G82-$L39)/(1+G82)^$K$16+$B$7+$B$8)/$B$6,"n/a") -> 86.257623 | H83: =IF(H82>$L39,(SUMPRODUCT($B46:$K46/(1+H82)^$B$16:$K$16)+$L46/(H82-$L39)/(1+H82)^$K$16+$B$7+$B$8)/$B$6,"n/a") -> 72.662139 | I83: =IF(I82>$L39,(SUMPRODUCT($B46:$K46/(1+I82)^$B$16:$K$16)+$L46/(I82-$L39)/(1+I82)^$K$16+$B$7+$B$8)/$B$6,"n/a") -> 62.275642 | ... K83: =IF(K82>$L39,(SUMPRODUCT($B46:$K46/(1+K82)^$B$16:$K$16)+$L46/(K82-$L39)/(1+K82)^$K$16+$B$7+$B$8)/$B$6,"n/a") -> 47.460448
A84: vs share price | B84: =IFERROR(B83/$B$4-1,"n/a") -> 3.1188295 | C84: =IFERROR(C83/$B$4-1,"n/a") -> 1.4087446 | D84: =IFERROR(D83/$B$4-1,"n/a") -> 0.6761644 | E84: =IFERROR(E83/$B$4-1,"n/a") -> 0.26940534 | F84: =IFERROR(F83/$B$4-1,"n/a") -> 0.010736283 | G84: =IFERROR(G83/$B$4-1,"n/a") -> -0.16820036 | H84: =IFERROR(H83/$B$4-1,"n/a") -> -0.29930435 | I84: =IFERROR(I83/$B$4-1,"n/a") -> -0.39946343 | ... K84: =IFERROR(K83/$B$4-1,"n/a") -> -0.54232933
A86: Implied annual return at today's price, base case | B86: =IFERROR(IF(MATCH($B$4,$B$83:$K$83,-1)=10,"above 14%",INDEX($B$82:$K$82,MATCH($B$4,$B$83:$K$83,-1))+(INDEX($B$83:$K$83,MATCH($B$4,$B$83:$K$83,-1))-$B$4)/(INDEX($B$83:$K$83,MATCH($B$4,$B$83:$K$83,-1))-INDEX($B$83:$K$83,MATCH($B$4,$B$83:$K$83,-1)+1))*(INDEX($B$82:$K$82,MATCH($B$4,$B$83:$K$83,-1)+1)-INDEX($B$82:$K$82,MATCH($B$4,$B$83:$K$83,-1)))),"below 5%") -> 0.090600005 | C86: Discount rate at which base value equals the price (interpolated from the row above)

Sheet MDT
A1: Medtronic (MDT): 10-year scenario DCF
A2: Units: $ billions unless noted. Blue = input, black = formula, green = link, yellow = key lever. Years 6 to 10 fade growth, margin and reinvestment toward each scenario's terminal levels.
A4: Share price ($) | B4: 95.41 | C4: Stock Analysis, Oct 23, 2026 close
A5: Price date | B5: Oct 23, 2026 close | C5: Text
A6: Shares outstanding (billions) | B6: 1.2241 | C6: Stock Analysis statistics, Oct 23 to 26, 2026 (market cap / price)
A7: Net cash, negative = net debt | B7: -19.17 | C7: Stock Analysis statistics, Oct 23 to 26, 2026: cash less total debt
A8: Other non-operating assets, less outside claims | B8: 0 | C8: None
A9: Tax rate | B9: 0.165 | C9: Analyst assumption, near the adjusted effective rate
A10: Discount rate (WACC), from WACC tab | B10: =WACC!C29 -> 0.08 | C10: Calculated or assumed, per the switch in WACC!B5
A11: Working capital, % of revenue change | B11: 0.1 | C11: Analyst assumption
A12: Base-year revenue (FY27, ends Apr 2027) | B12: 38.97 | C12: FY27 consensus $38.97B (Stock Analysis); FY27 guide: 7.25% to 7.75% organic growth incl. a 53rd week. Diabetes kept in (separation is value-neutral here)
A13: Selected scenario (1 Bear, 2 Base, 3 Bull) | B13: 2 | C13: Lever
A15: Year | B15: FY28 | C15: FY29 | D15: FY30 | E15: FY31 | F15: FY32 | G15: FY33 | H15: FY34 | I15: FY35 | J15: FY36 | K15: FY37 | L15: Terminal
A16: Discount period (years, mid-year) | B16: 0.5 | C16: =B16+1 -> 1.5 | D16: =C16+1 -> 2.5 | E16: =D16+1 -> 3.5 | F16: =E16+1 -> 4.5 | G16: =F16+1 -> 5.5 | H16: =G16+1 -> 6.5 | I16: =H16+1 -> 7.5 | J16: =I16+1 -> 8.5 | K16: =J16+1 -> 9.5
A17: Fade step (years 6 to 10) | B17: 0 | C17: 0 | D17: 0 | E17: 0 | F17: 0 | G17: 1 | H17: 2 | I17: 3 | J17: 4 | K17: 5
A19: Bear: procedure growth slows to about 2.5%
A20: Revenue | B20: 39.8 | C20: 40.8 | D20: 41.8 | E20: 42.9 | F20: 44 | G20: =F20*(1+$F21+($L21-$F21)*G$17/5) -> 45.122564 | H20: =G20*(1+$F21+($L21-$F21)*H$17/5) -> 46.267983 | I20: =H20*(1+$F21+($L21-$F21)*I$17/5) -> 47.436546 | J20: =I20*(1+$F21+($L21-$F21)*J$17/5) -> 48.628541 | K20: =J20*(1+$F21+($L21-$F21)*K$17/5) -> 49.844255 | L20: =K20*(1+L21) -> 51.090361
A21: Revenue growth (terminal column = terminal growth, input) | B21: =B20/$B$12-1 -> 0.021298435 | C21: =C20/B20-1 -> 0.025125628 | D21: =D20/C20-1 -> 0.024509804 | E21: =E20/D20-1 -> 0.026315789 | F21: =F20/E20-1 -> 0.025641026 | G21: =G20/F20-1 -> 0.025512821 | H21: =H20/G20-1 -> 0.025384615 | I21: =I20/H20-1 -> 0.02525641 | J21: =J20/I20-1 -> 0.025128205 | K21: =K20/J20-1 -> 0.025 | L21: 0.025
A22: Operating margin | B22: 0.235 | C22: 0.235 | D22: 0.235 | E22: 0.235 | F22: 0.235 | G22: =$F22+($L22-$F22)*G$17/5 -> 0.233 | H22: =$F22+($L22-$F22)*H$17/5 -> 0.231 | I22: =$F22+($L22-$F22)*I$17/5 -> 0.229 | J22: =$F22+($L22-$F22)*J$17/5 -> 0.227 | K22: =$F22+($L22-$F22)*K$17/5 -> 0.225 | L22: 0.225
A23: Operating income | B23: =B20*B22 -> 9.353 | C23: =C20*C22 -> 9.588 | D23: =D20*D22 -> 9.823 | E23: =E20*E22 -> 10.0815 | F23: =F20*F22 -> 10.34 | G23: =G20*G22 -> 10.513557 | H23: =H20*H22 -> 10.687904 | I23: =I20*I22 -> 10.862969 | ... L23: =L20*L22 -> 11.495331
A24: NOPAT | B24: =B23*(1-$B$9) -> 7.809755 | C24: =C23*(1-$B$9) -> 8.00598 | D24: =D23*(1-$B$9) -> 8.202205 | E24: =E23*(1-$B$9) -> 8.4180525 | F24: =F23*(1-$B$9) -> 8.6339 | G24: =G23*(1-$B$9) -> 8.7788205 | H24: =H23*(1-$B$9) -> 8.9243999 | I24: =I23*(1-$B$9) -> 9.0705792 | ... L24: =L23*(1-$B$9) -> 9.5986016
A25: Net reinvestment, % of revenue | B25: 0.025 | C25: 0.025 | D25: 0.025 | E25: 0.025 | F25: 0.025 | G25: =$F25+($L25-$F25)*G$17/5 -> 0.024 | H25: =$F25+($L25-$F25)*H$17/5 -> 0.023 | I25: =$F25+($L25-$F25)*I$17/5 -> 0.022 | J25: =$F25+($L25-$F25)*J$17/5 -> 0.021 | K25: =$F25+($L25-$F25)*K$17/5 -> 0.02 | L25: 0.02
A26: Net reinvestment | B26: =B20*B25 -> 0.995 | C26: =C20*C25 -> 1.02 | D26: =D20*D25 -> 1.045 | E26: =E20*E25 -> 1.0725 | F26: =F20*F25 -> 1.1 | G26: =G20*G25 -> 1.0829415 | H26: =H20*H25 -> 1.0641636 | I26: =I20*I25 -> 1.043604 | ... L26: =L20*L25 -> 1.0218072
A27: Change in working capital | B27: =$B$11*(B20-$B$12) -> 0.083 | C27: =$B$11*(C20-B20) -> 0.1 | D27: =$B$11*(D20-C20) -> 0.1 | E27: =$B$11*(E20-D20) -> 0.11 | F27: =$B$11*(F20-E20) -> 0.11 | G27: =$B$11*(G20-F20) -> 0.11225641 | H27: =$B$11*(H20-G20) -> 0.11454189 | I27: =$B$11*(I20-H20) -> 0.11685632 | J27: =$B$11*(J20-I20) -> 0.11919953 | ... L27: =$B$11*(L20-K20) -> 0.12461064
A28: Free cash flow | B28: =B24-B26-B27 -> 6.731755 | C28: =C24-C26-C27 -> 6.88598 | D28: =D24-D26-D27 -> 7.057205 | E28: =E24-E26-E27 -> 7.2355525 | F28: =F24-F26-F27 -> 7.4239 | G28: =G24-G26-G27 -> 7.5836225 | H28: =H24-H26-H27 -> 7.7456944 | I28: =I24-I26-I27 -> 7.9101188 | ... L28: =L24-L26-L27 -> 8.4521838
A29: Discount factor | B29: =1/(1+$B$10)^B$16 -> 0.96225045 | C29: =1/(1+$B$10)^C$16 -> 0.89097264 | D29: =1/(1+$B$10)^D$16 -> 0.82497466 | E29: =1/(1+$B$10)^E$16 -> 0.76386543 | F29: =1/(1+$B$10)^F$16 -> 0.70728281 | G29: =1/(1+$B$10)^G$16 -> 0.65489149 | H29: =1/(1+$B$10)^H$16 -> 0.60638101 | I29: =1/(1+$B$10)^I$16 -> 0.56146389 | ... K29: =1/(1+$B$10)^K$16 -> 0.48136479
A30: PV of free cash flow | B30: =B28*B29 -> 6.4776343 | C30: =C28*C29 -> 6.1352198 | D30: =D28*D29 -> 5.8220153 | E30: =E28*E29 -> 5.5269884 | F30: =F28*F29 -> 5.2507968 | G30: =G28*G29 -> 4.9664498 | H30: =H28*H29 -> 4.696842 | I30: =I28*I29 -> 4.4412461 | ... K30: =K28*K29 -> 3.9693499
A31: Terminal value | B31: =L28/($B$10-L21) -> 153.67607 | C31: =IF($B$10>L21,"","Discount rate must exceed terminal growth")
A32: PV of terminal value | B32: =B31/(1+$B$10)^$K$16 -> 73.974249
A33: Equity value (PV FCF + PV TV + net cash + other) | B33: =SUM(B30:K30)+B32+$B$7+$B$8 -> 106.28976
A34: Value per share ($) | B34: =B33/$B$6 -> 86.830946
A35: Value vs share price | B35: =B34/$B$4-1 -> -0.089917769
A37: Base: consensus FY28, then about 4.5%
A38: Revenue | B38: 40.4 | C38: 42.2 | D38: 44.1 | E38: 46.1 | F38: 48.2 | G38: =F38*(1+$F39+($L39-$F39)*G$17/5) -> 50.245729 | H38: =G38*(1+$F39+($L39-$F39)*H$17/5) -> 52.221989 | I38: =H38*(1+$F39+($L39-$F39)*I$17/5) -> 54.113535 | J38: =I38*(1+$F39+($L39-$F39)*J$17/5) -> 55.905268 | K38: =J38*(1+$F39+($L39-$F39)*K$17/5) -> 57.582426 | L38: =K38*(1+L39) -> 59.309899
A39: Revenue growth (terminal column = terminal growth, input) | B39: =B38/$B$12-1 -> 0.036694894 | C39: =C38/B38-1 -> 0.044554455 | D39: =D38/C38-1 -> 0.045023697 | E39: =E38/D38-1 -> 0.045351474 | F39: =F38/E38-1 -> 0.045553145 | G39: =G38/F38-1 -> 0.042442516 | H39: =H38/G38-1 -> 0.039331887 | I39: =I38/H38-1 -> 0.036221258 | J39: =J38/I38-1 -> 0.033110629 | K39: =K38/J38-1 -> 0.03 | L39: 0.03
A40: Operating margin | B40: 0.245 | C40: 0.248 | D40: 0.25 | E40: 0.252 | F40: 0.255 | G40: =$F40+($L40-$F40)*G$17/5 -> 0.253 | H40: =$F40+($L40-$F40)*H$17/5 -> 0.251 | I40: =$F40+($L40-$F40)*I$17/5 -> 0.249 | J40: =$F40+($L40-$F40)*J$17/5 -> 0.247 | K40: =$F40+($L40-$F40)*K$17/5 -> 0.245 | L40: 0.245
A41: Operating income | B41: =B38*B40 -> 9.898 | C41: =C38*C40 -> 10.4656 | D41: =D38*D40 -> 11.025 | E41: =E38*E40 -> 11.6172 | F41: =F38*F40 -> 12.291 | G41: =G38*G40 -> 12.71217 | H41: =H38*H40 -> 13.107719 | I41: =I38*I40 -> 13.47427 | ... L41: =L38*L40 -> 14.530925
A42: NOPAT | B42: =B41*(1-$B$9) -> 8.26483 | C42: =C41*(1-$B$9) -> 8.738776 | D42: =D41*(1-$B$9) -> 9.205875 | E42: =E41*(1-$B$9) -> 9.700362 | F42: =F41*(1-$B$9) -> 10.262985 | G42: =G41*(1-$B$9) -> 10.614662 | H42: =H41*(1-$B$9) -> 10.944945 | I42: =I41*(1-$B$9) -> 11.251016 | ... L42: =L41*(1-$B$9) -> 12.133323
A43: Net reinvestment, % of revenue | B43: 0.025 | C43: 0.025 | D43: 0.025 | E43: 0.025 | F43: 0.025 | G43: =$F43+($L43-$F43)*G$17/5 -> 0.024 | H43: =$F43+($L43-$F43)*H$17/5 -> 0.023 | I43: =$F43+($L43-$F43)*I$17/5 -> 0.022 | J43: =$F43+($L43-$F43)*J$17/5 -> 0.021 | K43: =$F43+($L43-$F43)*K$17/5 -> 0.02 | L43: 0.02
A44: Net reinvestment | B44: =B38*B43 -> 1.01 | C44: =C38*C43 -> 1.055 | D44: =D38*D43 -> 1.1025 | E44: =E38*E43 -> 1.1525 | F44: =F38*F43 -> 1.205 | G44: =G38*G43 -> 1.2058975 | H44: =H38*H43 -> 1.2011057 | I44: =I38*I43 -> 1.1904978 | ... L44: =L38*L43 -> 1.186198
A45: Change in working capital | B45: =$B$11*(B38-$B$12) -> 0.143 | C45: =$B$11*(C38-B38) -> 0.18 | D45: =$B$11*(D38-C38) -> 0.19 | E45: =$B$11*(E38-D38) -> 0.2 | F45: =$B$11*(F38-E38) -> 0.21 | G45: =$B$11*(G38-F38) -> 0.20457293 | H45: =$B$11*(H38-G38) -> 0.19762594 | I45: =$B$11*(I38-H38) -> 0.18915461 | J45: =$B$11*(J38-I38) -> 0.17917332 | ... L45: =$B$11*(L38-K38) -> 0.17274728
A46: Free cash flow | B46: =B42-B44-B45 -> 7.11183 | C46: =C42-C44-C45 -> 7.503776 | D46: =D42-D44-D45 -> 7.913375 | E46: =E42-E44-E45 -> 8.347862 | F46: =F42-F44-F45 -> 8.847985 | G46: =G42-G44-G45 -> 9.2041911 | H46: =H42-H44-H45 -> 9.5462138 | I46: =I42-I44-I45 -> 9.8713632 | ... L46: =L42-L44-L45 -> 10.774377
A47: Discount factor | B47: =1/(1+$B$10)^B$16 -> 0.96225045 | C47: =1/(1+$B$10)^C$16 -> 0.89097264 | D47: =1/(1+$B$10)^D$16 -> 0.82497466 | E47: =1/(1+$B$10)^E$16 -> 0.76386543 | F47: =1/(1+$B$10)^F$16 -> 0.70728281 | G47: =1/(1+$B$10)^G$16 -> 0.65489149 | H47: =1/(1+$B$10)^H$16 -> 0.60638101 | I47: =1/(1+$B$10)^I$16 -> 0.56146389 | ... K47: =1/(1+$B$10)^K$16 -> 0.48136479
A48: PV of free cash flow | B48: =B46*B47 -> 6.8433616 | C48: =C46*C47 -> 6.6856591 | D48: =D46*D47 -> 6.5283339 | E48: =E46*E47 -> 6.3766432 | F48: =F46*F47 -> 6.2580277 | G48: =G46*G47 -> 6.0277464 | H48: =H46*H47 -> 5.7886427 | I48: =I46*I47 -> 5.542414 | ... K48: =K46*K47 -> 5.0353455
A49: Terminal value | B49: =L46/($B$10-L39) -> 215.48755 | C49: =IF($B$10>L39,"","Discount rate must exceed terminal growth")
A50: PV of terminal value | B50: =B49/(1+$B$10)^$K$16 -> 103.72812
A51: Equity value (PV FCF + PV TV + net cash + other) | B51: =SUM(B48:K48)+B50+$B$7+$B$8 -> 144.93505
A52: Value per share ($) | B52: =B51/$B$6 -> 118.40131
A53: Value vs share price | B53: =B52/$B$4-1 -> 0.24097384
A55: Bull: pulsed field ablation and renal denervation ramp
A56: Revenue | B56: 40.8 | C56: 43.2 | D56: 45.8 | E56: 48.6 | F56: 51.5 | G56: =F56*(1+$F57+($L57-$F57)*G$17/5) -> 54.318936 | H56: =G56*(1+$F57+($L57-$F57)*H$17/5) -> 57.024153 | I56: =H56*(1+$F57+($L57-$F57)*I$17/5) -> 59.582731 | J56: =I56*(1+$F57+($L57-$F57)*J$17/5) -> 61.962117 | K56: =J56*(1+$F57+($L57-$F57)*K$17/5) -> 64.130791 | L56: =K56*(1+L57) -> 66.375369
A57: Revenue growth (terminal column = terminal growth, input) | B57: =B56/$B$12-1 -> 0.046959199 | C57: =C56/B56-1 -> 0.058823529 | D57: =D56/C56-1 -> 0.060185185 | E57: =E56/D56-1 -> 0.061135371 | F57: =F56/E56-1 -> 0.059670782 | G57: =G56/F56-1 -> 0.054736626 | H57: =H56/G56-1 -> 0.049802469 | I57: =I56/H56-1 -> 0.044868313 | J57: =J56/I56-1 -> 0.039934156 | K57: =K56/J56-1 -> 0.035 | L57: 0.035
A58: Operating margin | B58: 0.25 | C58: 0.26 | D58: 0.265 | E58: 0.27 | F58: 0.275 | G58: =$F58+($L58-$F58)*G$17/5 -> 0.273 | H58: =$F58+($L58-$F58)*H$17/5 -> 0.271 | I58: =$F58+($L58-$F58)*I$17/5 -> 0.269 | J58: =$F58+($L58-$F58)*J$17/5 -> 0.267 | K58: =$F58+($L58-$F58)*K$17/5 -> 0.265 | L58: 0.265
A59: Operating income | B59: =B56*B58 -> 10.2 | C59: =C56*C58 -> 11.232 | D59: =D56*D58 -> 12.137 | E59: =E56*E58 -> 13.122 | F59: =F56*F58 -> 14.1625 | G59: =G56*G58 -> 14.82907 | H59: =H56*H58 -> 15.453546 | I59: =I56*I58 -> 16.027755 | ... L59: =L56*L58 -> 17.589473
A60: NOPAT | B60: =B59*(1-$B$9) -> 8.517 | C60: =C59*(1-$B$9) -> 9.37872 | D60: =D59*(1-$B$9) -> 10.134395 | E60: =E59*(1-$B$9) -> 10.95687 | F60: =F59*(1-$B$9) -> 11.825688 | G60: =G59*(1-$B$9) -> 12.382273 | H60: =H59*(1-$B$9) -> 12.903711 | I60: =I59*(1-$B$9) -> 13.383175 | ... L60: =L59*(1-$B$9) -> 14.68721
A61: Net reinvestment, % of revenue | B61: 0.025 | C61: 0.025 | D61: 0.025 | E61: 0.025 | F61: 0.025 | G61: =$F61+($L61-$F61)*G$17/5 -> 0.024 | H61: =$F61+($L61-$F61)*H$17/5 -> 0.023 | I61: =$F61+($L61-$F61)*I$17/5 -> 0.022 | J61: =$F61+($L61-$F61)*J$17/5 -> 0.021 | K61: =$F61+($L61-$F61)*K$17/5 -> 0.02 | L61: 0.02
A62: Net reinvestment | B62: =B56*B61 -> 1.02 | C62: =C56*C61 -> 1.08 | D62: =D56*D61 -> 1.145 | E62: =E56*E61 -> 1.215 | F62: =F56*F61 -> 1.2875 | G62: =G56*G61 -> 1.3036545 | H62: =H56*H61 -> 1.3115555 | I62: =I56*I61 -> 1.3108201 | ... L62: =L56*L61 -> 1.3275074
A63: Change in working capital | B63: =$B$11*(B56-$B$12) -> 0.183 | C63: =$B$11*(C56-B56) -> 0.24 | D63: =$B$11*(D56-C56) -> 0.26 | E63: =$B$11*(E56-D56) -> 0.28 | F63: =$B$11*(F56-E56) -> 0.29 | G63: =$B$11*(G56-F56) -> 0.28189362 | H63: =$B$11*(H56-G56) -> 0.27052171 | I63: =$B$11*(I56-H56) -> 0.25585775 | J63: =$B$11*(J56-I56) -> 0.23793861 | ... L63: =$B$11*(L56-K56) -> 0.22445777
A64: Free cash flow | B64: =B60-B62-B63 -> 7.314 | C64: =C60-C62-C63 -> 8.05872 | D64: =D60-D62-D63 -> 8.729395 | E64: =E60-E62-E63 -> 9.46187 | F64: =F60-F62-F63 -> 10.248188 | G64: =G60-G62-G63 -> 10.796725 | H64: =H60-H62-H63 -> 11.321633 | I64: =I60-I62-I63 -> 11.816497 | ... L64: =L60-L62-L63 -> 13.135245
A65: Discount factor | B65: =1/(1+$B$10)^B$16 -> 0.96225045 | C65: =1/(1+$B$10)^C$16 -> 0.89097264 | D65: =1/(1+$B$10)^D$16 -> 0.82497466 | E65: =1/(1+$B$10)^E$16 -> 0.76386543 | F65: =1/(1+$B$10)^F$16 -> 0.70728281 | G65: =1/(1+$B$10)^G$16 -> 0.65489149 | H65: =1/(1+$B$10)^H$16 -> 0.60638101 | I65: =1/(1+$B$10)^I$16 -> 0.56146389 | ... K65: =1/(1+$B$10)^K$16 -> 0.48136479
A66: PV of free cash flow | B66: =B64*B65 -> 7.0378998 | C66: =C64*C65 -> 7.180099 | D66: =D64*D65 -> 7.2015297 | E66: =E64*E65 -> 7.2275954 | F66: =F64*F65 -> 7.2483668 | G66: =G64*G65 -> 7.0706833 | H66: =H64*H65 -> 6.8652234 | I66: =I64*I65 -> 6.6345366 | ... K66: =K64*K65 -> 6.1090283
A67: Terminal value | B67: =L64/($B$10-L57) -> 291.89432 | C67: =IF($B$10>L57,"","Discount rate must exceed terminal growth")
A68: PV of terminal value | B68: =B67/(1+$B$10)^$K$16 -> 140.50765
A69: Equity value (PV FCF + PV TV + net cash + other) | B69: =SUM(B66:K66)+B68+$B$7+$B$8 -> 190.29407
A70: Value per share ($) | B70: =B69/$B$6 -> 155.45631
A71: Value vs share price | B71: =B70/$B$4-1 -> 0.62935026
A74: Outputs | C74: vs price
A75: Bear value per share | B75: =B34 -> 86.830946 | C75: =B75/$B$4-1 -> -0.089917769
A76: Base value per share | B76: =B52 -> 118.40131 | C76: =B76/$B$4-1 -> 0.24097384
A77: Bull value per share | B77: =B70 -> 155.45631 | C77: =B77/$B$4-1 -> 0.62935026
A78: Selected scenario value per share | B78: =INDEX(B34:B70,1+($B$13-1)*18) -> 118.40131 | C78: =B78/$B$4-1 -> 0.24097384
A79: Share of base value from terminal value | B79: =B50/(SUM(B48:K48)+B50) -> 0.63208365
A81: Base value per share at other discount rates
A82: Discount rate | B82: 0.05 | C82: 0.06 | D82: 0.07 | E82: 0.08 | F82: 0.09 | G82: 0.1 | H82: 0.11 | I82: 0.12 | J82: 0.13 | K82: 0.14
A83: Base value per share | B83: =IF(B82>$L39,(SUMPRODUCT($B46:$K46/(1+B82)^$B$16:$K$16)+$L46/(B82-$L39)/(1+B82)^$K$16+$B$7+$B$8)/$B$6,"n/a") -> 317.72184 | C83: =IF(C82>$L39,(SUMPRODUCT($B46:$K46/(1+C82)^$B$16:$K$16)+$L46/(C82-$L39)/(1+C82)^$K$16+$B$7+$B$8)/$B$6,"n/a") -> 206.96997 | D83: =IF(D82>$L39,(SUMPRODUCT($B46:$K46/(1+D82)^$B$16:$K$16)+$L46/(D82-$L39)/(1+D82)^$K$16+$B$7+$B$8)/$B$6,"n/a") -> 151.608 | E83: =IF(E82>$L39,(SUMPRODUCT($B46:$K46/(1+E82)^$B$16:$K$16)+$L46/(E82-$L39)/(1+E82)^$K$16+$B$7+$B$8)/$B$6,"n/a") -> 118.40131 | F83: =IF(F82>$L39,(SUMPRODUCT($B46:$K46/(1+F82)^$B$16:$K$16)+$L46/(F82-$L39)/(1+F82)^$K$16+$B$7+$B$8)/$B$6,"n/a") -> 96.27173 | G83: =IF(G82>$L39,(SUMPRODUCT($B46:$K46/(1+G82)^$B$16:$K$16)+$L46/(G82-$L39)/(1+G82)^$K$16+$B$7+$B$8)/$B$6,"n/a") -> 80.471489 | H83: =IF(H82>$L39,(SUMPRODUCT($B46:$K46/(1+H82)^$B$16:$K$16)+$L46/(H82-$L39)/(1+H82)^$K$16+$B$7+$B$8)/$B$6,"n/a") -> 68.626735 | I83: =IF(I82>$L39,(SUMPRODUCT($B46:$K46/(1+I82)^$B$16:$K$16)+$L46/(I82-$L39)/(1+I82)^$K$16+$B$7+$B$8)/$B$6,"n/a") -> 59.418679 | ... K83: =IF(K82>$L39,(SUMPRODUCT($B46:$K46/(1+K82)^$B$16:$K$16)+$L46/(K82-$L39)/(1+K82)^$K$16+$B$7+$B$8)/$B$6,"n/a") -> 46.035374
A84: vs share price | B84: =IFERROR(B83/$B$4-1,"n/a") -> 2.3300686 | C84: =IFERROR(C83/$B$4-1,"n/a") -> 1.1692691 | D84: =IFERROR(D83/$B$4-1,"n/a") -> 0.58901584 | E84: =IFERROR(E83/$B$4-1,"n/a") -> 0.24097384 | F84: =IFERROR(F83/$B$4-1,"n/a") -> 0.0090318585 | G84: =IFERROR(G83/$B$4-1,"n/a") -> -0.15657176 | H84: =IFERROR(H83/$B$4-1,"n/a") -> -0.28071759 | I84: =IFERROR(I83/$B$4-1,"n/a") -> -0.37722798 | ... K84: =IFERROR(K83/$B$4-1,"n/a") -> -0.51749948
A86: Implied annual return at today's price, base case | B86: =IFERROR(IF(MATCH($B$4,$B$83:$K$83,-1)=10,"above 14%",INDEX($B$82:$K$82,MATCH($B$4,$B$83:$K$83,-1))+(INDEX($B$83:$K$83,MATCH($B$4,$B$83:$K$83,-1))-$B$4)/(INDEX($B$83:$K$83,MATCH($B$4,$B$83:$K$83,-1))-INDEX($B$83:$K$83,MATCH($B$4,$B$83:$K$83,-1)+1))*(INDEX($B$82:$K$82,MATCH($B$4,$B$83:$K$83,-1)+1)-INDEX($B$82:$K$82,MATCH($B$4,$B$83:$K$83,-1)))),"below 5%") -> 0.09054539 | C86: Discount rate at which base value equals the price (interpolated from the row above)

Sheet MRK
A1: Merck (MRK): 10-year scenario DCF
A2: Units: $ billions unless noted. Blue = input, black = formula, green = link, yellow = key lever. Years 6 to 10 fade growth, margin and reinvestment toward each scenario's terminal levels.
A4: Share price ($) | B4: 144.45 | C4: Stock Analysis, Oct 26, 2026 intraday
A5: Price date | B5: Oct 26, 2026 intraday | C5: Text
A6: Shares outstanding (billions) | B6: 2.4672 | C6: Stock Analysis statistics, Oct 23 to 26, 2026 (market cap / price)
A7: Net cash, negative = net debt | B7: -46.77 | C7: Stock Analysis statistics, Oct 23 to 26, 2026: cash less total debt
A8: Other non-operating assets, less outside claims | B8: 0 | C8: None
A9: Tax rate | B9: 0.15 | C9: Analyst assumption, near the adjusted effective rate
A10: Discount rate (WACC), from WACC tab | B10: =WACC!D29 -> 0.08 | C10: Calculated or assumed, per the switch in WACC!B5
A11: Working capital, % of revenue change | B11: 0.1 | C11: Analyst assumption
A12: Base-year revenue (2026E) | B12: 67.05 | C12: 2026E consensus $67.05B; 2027E $69.94B (Stock Analysis). Keytruda loses US exclusivity in 2028. Reinvestment includes about $3.5B a year of licensing and acquisitions
A13: Selected scenario (1 Bear, 2 Base, 3 Bull) | B13: 2 | C13: Lever
A15: Year | B15: 2027 | C15: 2028 | D15: 2029 | E15: 2030 | F15: 2031 | G15: 2032 | H15: 2033 | I15: 2034 | J15: 2035 | K15: 2036 | L15: Terminal
A16: Discount period (years, mid-year) | B16: 0.5 | C16: =B16+1 -> 1.5 | D16: =C16+1 -> 2.5 | E16: =D16+1 -> 3.5 | F16: =E16+1 -> 4.5 | G16: =F16+1 -> 5.5 | H16: =G16+1 -> 6.5 | I16: =H16+1 -> 7.5 | J16: =I16+1 -> 8.5 | K16: =J16+1 -> 9.5
A17: Fade step (years 6 to 10) | B17: 0 | C17: 0 | D17: 0 | E17: 0 | F17: 0 | G17: 1 | H17: 2 | I17: 3 | J17: 4 | K17: 5
A19: Bear: Keytruda erodes fast, launches disappoint
A20: Revenue | B20: 69 | C20: 65 | D20: 57 | E20: 54 | F20: 55 | G20: =F20*(1+$F21+($L21-$F21)*G$17/5) -> 56.034815 | H20: =G20*(1+$F21+($L21-$F21)*H$17/5) -> 57.105702 | I20: =H20*(1+$F21+($L21-$F21)*I$17/5) -> 58.213976 | J20: =I20*(1+$F21+($L21-$F21)*J$17/5) -> 59.361007 | K20: =J20*(1+$F21+($L21-$F21)*K$17/5) -> 60.548227 | L20: =K20*(1+L21) -> 61.759192
A21: Revenue growth (terminal column = terminal growth, input) | B21: =B20/$B$12-1 -> 0.029082774 | C21: =C20/B20-1 -> -0.057971014 | D21: =D20/C20-1 -> -0.12307692 | E21: =E20/D20-1 -> -0.052631579 | F21: =F20/E20-1 -> 0.018518519 | G21: =G20/F20-1 -> 0.018814815 | H21: =H20/G20-1 -> 0.019111111 | I21: =I20/H20-1 -> 0.019407407 | J21: =J20/I20-1 -> 0.019703704 | K21: =K20/J20-1 -> 0.02 | L21: 0.02
A22: Operating margin | B22: 0.4 | C22: 0.37 | D22: 0.33 | E22: 0.31 | F22: 0.31 | G22: =$F22+($L22-$F22)*G$17/5 -> 0.306 | H22: =$F22+($L22-$F22)*H$17/5 -> 0.302 | I22: =$F22+($L22-$F22)*I$17/5 -> 0.298 | J22: =$F22+($L22-$F22)*J$17/5 -> 0.294 | K22: =$F22+($L22-$F22)*K$17/5 -> 0.29 | L22: 0.29
A23: Operating income | B23: =B20*B22 -> 27.6 | C23: =C20*C22 -> 24.05 | D23: =D20*D22 -> 18.81 | E23: =E20*E22 -> 16.74 | F23: =F20*F22 -> 17.05 | G23: =G20*G22 -> 17.146653 | H23: =H20*H22 -> 17.245922 | I23: =I20*I22 -> 17.347765 | ... L23: =L20*L22 -> 17.910166
A24: NOPAT | B24: =B23*(1-$B$9) -> 23.46 | C24: =C23*(1-$B$9) -> 20.4425 | D24: =D23*(1-$B$9) -> 15.9885 | E24: =E23*(1-$B$9) -> 14.229 | F24: =F23*(1-$B$9) -> 14.4925 | G24: =G23*(1-$B$9) -> 14.574655 | H24: =H23*(1-$B$9) -> 14.659034 | I24: =I23*(1-$B$9) -> 14.7456 | ... L24: =L23*(1-$B$9) -> 15.223641
A25: Net reinvestment, % of revenue | B25: 0.05 | C25: 0.05 | D25: 0.05 | E25: 0.05 | F25: 0.05 | G25: =$F25+($L25-$F25)*G$17/5 -> 0.048 | H25: =$F25+($L25-$F25)*H$17/5 -> 0.046 | I25: =$F25+($L25-$F25)*I$17/5 -> 0.044 | J25: =$F25+($L25-$F25)*J$17/5 -> 0.042 | K25: =$F25+($L25-$F25)*K$17/5 -> 0.04 | L25: 0.04
A26: Net reinvestment | B26: =B20*B25 -> 3.45 | C26: =C20*C25 -> 3.25 | D26: =D20*D25 -> 2.85 | E26: =E20*E25 -> 2.7 | F26: =F20*F25 -> 2.75 | G26: =G20*G25 -> 2.6896711 | H26: =H20*H25 -> 2.6268623 | I26: =I20*I25 -> 2.5614149 | ... L26: =L20*L25 -> 2.4703677
A27: Change in working capital | B27: =$B$11*(B20-$B$12) -> 0.195 | C27: =$B$11*(C20-B20) -> -0.4 | D27: =$B$11*(D20-C20) -> -0.8 | E27: =$B$11*(E20-D20) -> -0.3 | F27: =$B$11*(F20-E20) -> 0.1 | G27: =$B$11*(G20-F20) -> 0.10348148 | H27: =$B$11*(H20-G20) -> 0.10708876 | I27: =$B$11*(I20-H20) -> 0.11082736 | J27: =$B$11*(J20-I20) -> 0.11470309 | ... L27: =$B$11*(L20-K20) -> 0.12109645
A28: Free cash flow | B28: =B24-B26-B27 -> 19.815 | C28: =C24-C26-C27 -> 17.5925 | D28: =D24-D26-D27 -> 13.9385 | E28: =E24-E26-E27 -> 11.829 | F28: =F24-F26-F27 -> 11.6425 | G28: =G24-G26-G27 -> 11.781503 | H28: =H24-H26-H27 -> 11.925083 | I28: =I24-I26-I27 -> 12.073358 | ... L28: =L24-L26-L27 -> 12.632177
A29: Discount factor | B29: =1/(1+$B$10)^B$16 -> 0.96225045 | C29: =1/(1+$B$10)^C$16 -> 0.89097264 | D29: =1/(1+$B$10)^D$16 -> 0.82497466 | E29: =1/(1+$B$10)^E$16 -> 0.76386543 | F29: =1/(1+$B$10)^F$16 -> 0.70728281 | G29: =1/(1+$B$10)^G$16 -> 0.65489149 | H29: =1/(1+$B$10)^H$16 -> 0.60638101 | I29: =1/(1+$B$10)^I$16 -> 0.56146389 | ... K29: =1/(1+$B$10)^K$16 -> 0.48136479
A30: PV of free cash flow | B30: =B28*B29 -> 19.066993 | C30: =C28*C29 -> 15.674436 | D30: =D28*D29 -> 11.498909 | E30: =E28*E29 -> 9.0357642 | F30: =F28*F29 -> 8.2345401 | G30: =G28*G29 -> 7.7156058 | H30: =H28*H29 -> 7.2311437 | I30: =I28*I29 -> 6.7787545 | ... K30: =K28*K29 -> 5.961456
A31: Terminal value | B31: =L28/($B$10-L21) -> 210.53628 | C31: =IF($B$10>L21,"","Discount rate must exceed terminal growth")
A32: PV of terminal value | B32: =B31/(1+$B$10)^$K$16 -> 101.34475
A33: Equity value (PV FCF + PV TV + net cash + other) | B33: =SUM(B30:K30)+B32+$B$7+$B$8 -> 152.12857
A34: Value per share ($) | B34: =B33/$B$6 -> 61.660411
A35: Value vs share price | B35: =B34/$B$4-1 -> -0.57313665
A37: Base: revenue dips about 11% by 2030, then recovers
A38: Revenue | B38: 69.9 | C38: 68 | D38: 63 | E38: 62 | F38: 65 | G38: =F38*(1+$F39+($L39-$F39)*G$17/5) -> 67.841129 | H38: =G38*(1+$F39+($L39-$F39)*H$17/5) -> 70.489121 | I38: =H38*(1+$F39+($L39-$F39)*I$17/5) -> 72.910764 | J38: =I38*(1+$F39+($L39-$F39)*J$17/5) -> 75.074567 | K38: =J38*(1+$F39+($L39-$F39)*K$17/5) -> 76.951431 | L38: =K38*(1+L39) -> 78.875217
A39: Revenue growth (terminal column = terminal growth, input) | B39: =B38/$B$12-1 -> 0.042505593 | C39: =C38/B38-1 -> -0.027181688 | D39: =D38/C38-1 -> -0.073529412 | E39: =E38/D38-1 -> -0.015873016 | F39: =F38/E38-1 -> 0.048387097 | G39: =G38/F38-1 -> 0.043709677 | H39: =H38/G38-1 -> 0.039032258 | I39: =I38/H38-1 -> 0.034354839 | J39: =J38/I38-1 -> 0.029677419 | K39: =K38/J38-1 -> 0.025 | L39: 0.025
A40: Operating margin | B40: 0.405 | C40: 0.39 | D40: 0.36 | E40: 0.35 | F40: 0.355 | G40: =$F40+($L40-$F40)*G$17/5 -> 0.35 | H40: =$F40+($L40-$F40)*H$17/5 -> 0.345 | I40: =$F40+($L40-$F40)*I$17/5 -> 0.34 | J40: =$F40+($L40-$F40)*J$17/5 -> 0.335 | K40: =$F40+($L40-$F40)*K$17/5 -> 0.33 | L40: 0.33
A41: Operating income | B41: =B38*B40 -> 28.3095 | C41: =C38*C40 -> 26.52 | D41: =D38*D40 -> 22.68 | E41: =E38*E40 -> 21.7 | F41: =F38*F40 -> 23.075 | G41: =G38*G40 -> 23.744395 | H41: =H38*H40 -> 24.318747 | I41: =I38*I40 -> 24.78966 | ... L41: =L38*L40 -> 26.028822
A42: NOPAT | B42: =B41*(1-$B$9) -> 24.063075 | C42: =C41*(1-$B$9) -> 22.542 | D42: =D41*(1-$B$9) -> 19.278 | E42: =E41*(1-$B$9) -> 18.445 | F42: =F41*(1-$B$9) -> 19.61375 | G42: =G41*(1-$B$9) -> 20.182736 | H42: =H41*(1-$B$9) -> 20.670935 | I42: =I41*(1-$B$9) -> 21.071211 | ... L42: =L41*(1-$B$9) -> 22.124498
A43: Net reinvestment, % of revenue | B43: 0.05 | C43: 0.05 | D43: 0.05 | E43: 0.05 | F43: 0.05 | G43: =$F43+($L43-$F43)*G$17/5 -> 0.048 | H43: =$F43+($L43-$F43)*H$17/5 -> 0.046 | I43: =$F43+($L43-$F43)*I$17/5 -> 0.044 | J43: =$F43+($L43-$F43)*J$17/5 -> 0.042 | K43: =$F43+($L43-$F43)*K$17/5 -> 0.04 | L43: 0.04
A44: Net reinvestment | B44: =B38*B43 -> 3.495 | C44: =C38*C43 -> 3.4 | D44: =D38*D43 -> 3.15 | E44: =E38*E43 -> 3.1 | F44: =F38*F43 -> 3.25 | G44: =G38*G43 -> 3.2563742 | H44: =H38*H43 -> 3.2424996 | I44: =I38*I43 -> 3.2080736 | ... L44: =L38*L43 -> 3.1550087
A45: Change in working capital | B45: =$B$11*(B38-$B$12) -> 0.285 | C45: =$B$11*(C38-B38) -> -0.19 | D45: =$B$11*(D38-C38) -> -0.5 | E45: =$B$11*(E38-D38) -> -0.1 | F45: =$B$11*(F38-E38) -> 0.3 | G45: =$B$11*(G38-F38) -> 0.2841129 | H45: =$B$11*(H38-G38) -> 0.26479925 | I45: =$B$11*(I38-H38) -> 0.24216424 | J45: =$B$11*(J38-I38) -> 0.21638033 | ... L45: =$B$11*(L38-K38) -> 0.19237858
A46: Free cash flow | B46: =B42-B44-B45 -> 20.283075 | C46: =C42-C44-C45 -> 19.332 | D46: =D42-D44-D45 -> 16.628 | E46: =E42-E44-E45 -> 15.445 | F46: =F42-F44-F45 -> 16.06375 | G46: =G42-G44-G45 -> 16.642249 | H46: =H42-H44-H45 -> 17.163636 | I46: =I42-I44-I45 -> 17.620973 | ... L46: =L42-L44-L45 -> 18.777111
A47: Discount factor | B47: =1/(1+$B$10)^B$16 -> 0.96225045 | C47: =1/(1+$B$10)^C$16 -> 0.89097264 | D47: =1/(1+$B$10)^D$16 -> 0.82497466 | E47: =1/(1+$B$10)^E$16 -> 0.76386543 | F47: =1/(1+$B$10)^F$16 -> 0.70728281 | G47: =1/(1+$B$10)^G$16 -> 0.65489149 | H47: =1/(1+$B$10)^H$16 -> 0.60638101 | I47: =1/(1+$B$10)^I$16 -> 0.56146389 | ... K47: =1/(1+$B$10)^K$16 -> 0.48136479
A48: PV of free cash flow | B48: =B46*B47 -> 19.517398 | C48: =C46*C47 -> 17.224283 | D48: =D46*D47 -> 13.717679 | E48: =E46*E47 -> 11.797902 | F48: =F46*F47 -> 11.361614 | G48: =G46*G47 -> 10.898867 | H48: =H46*H47 -> 10.407703 | I48: =I46*I47 -> 9.8935401 | ... K48: =K46*K47 -> 8.8181856
A49: Terminal value | B49: =L46/($B$10-L39) -> 341.40202 | C49: =IF($B$10>L39,"","Discount rate must exceed terminal growth")
A50: PV of terminal value | B50: =B49/(1+$B$10)^$K$16 -> 164.33891
A51: Equity value (PV FCF + PV TV + net cash + other) | B51: =SUM(B48:K48)+B50+$B$7+$B$8 -> 240.56796
A52: Value per share ($) | B52: =B51/$B$6 -> 97.506469
A53: Value vs share price | B53: =B52/$B$4-1 -> -0.32498118
A55: Bull: Qlex, Winrevair and new launches fill the gap
A56: Revenue | B56: 70.5 | C56: 71 | D56: 69 | E56: 71 | F56: 75 | G56: =F56*(1+$F57+($L57-$F57)*G$17/5) -> 78.830282 | H56: =G56*(1+$F57+($L57-$F57)*H$17/5) -> 82.440931 | I56: =H56*(1+$F57+($L57-$F57)*I$17/5) -> 85.782691 | J56: =I56*(1+$F57+($L57-$F57)*J$17/5) -> 88.808041 | K56: =J56*(1+$F57+($L57-$F57)*K$17/5) -> 91.472283 | L56: =K56*(1+L57) -> 94.216451
A57: Revenue growth (terminal column = terminal growth, input) | B57: =B56/$B$12-1 -> 0.051454139 | C57: =C56/B56-1 -> 0.0070921986 | D57: =D56/C56-1 -> -0.028169014 | E57: =E56/D56-1 -> 0.028985507 | F57: =F56/E56-1 -> 0.056338028 | G57: =G56/F56-1 -> 0.051070423 | H57: =H56/G56-1 -> 0.045802817 | I57: =I56/H56-1 -> 0.040535211 | J57: =J56/I56-1 -> 0.035267606 | K57: =K56/J56-1 -> 0.03 | L57: 0.03
A58: Operating margin | B58: 0.41 | C58: 0.405 | D58: 0.39 | E58: 0.385 | F58: 0.385 | G58: =$F58+($L58-$F58)*G$17/5 -> 0.38 | H58: =$F58+($L58-$F58)*H$17/5 -> 0.375 | I58: =$F58+($L58-$F58)*I$17/5 -> 0.37 | J58: =$F58+($L58-$F58)*J$17/5 -> 0.365 | K58: =$F58+($L58-$F58)*K$17/5 -> 0.36 | L58: 0.36
A59: Operating income | B59: =B56*B58 -> 28.905 | C59: =C56*C58 -> 28.755 | D59: =D56*D58 -> 26.91 | E59: =E56*E58 -> 27.335 | F59: =F56*F58 -> 28.875 | G59: =G56*G58 -> 29.955507 | H59: =H56*H58 -> 30.915349 | I59: =I56*I58 -> 31.739596 | ... L59: =L56*L58 -> 33.917922
A60: NOPAT | B60: =B59*(1-$B$9) -> 24.56925 | C60: =C59*(1-$B$9) -> 24.44175 | D60: =D59*(1-$B$9) -> 22.8735 | E60: =E59*(1-$B$9) -> 23.23475 | F60: =F59*(1-$B$9) -> 24.54375 | G60: =G59*(1-$B$9) -> 25.462181 | H60: =H59*(1-$B$9) -> 26.278047 | I60: =I59*(1-$B$9) -> 26.978656 | ... L60: =L59*(1-$B$9) -> 28.830234
A61: Net reinvestment, % of revenue | B61: 0.05 | C61: 0.05 | D61: 0.05 | E61: 0.05 | F61: 0.05 | G61: =$F61+($L61-$F61)*G$17/5 -> 0.048 | H61: =$F61+($L61-$F61)*H$17/5 -> 0.046 | I61: =$F61+($L61-$F61)*I$17/5 -> 0.044 | J61: =$F61+($L61-$F61)*J$17/5 -> 0.042 | K61: =$F61+($L61-$F61)*K$17/5 -> 0.04 | L61: 0.04
A62: Net reinvestment | B62: =B56*B61 -> 3.525 | C62: =C56*C61 -> 3.55 | D62: =D56*D61 -> 3.45 | E62: =E56*E61 -> 3.55 | F62: =F56*F61 -> 3.75 | G62: =G56*G61 -> 3.7838535 | H62: =H56*H61 -> 3.7922828 | I62: =I56*I61 -> 3.7744384 | ... L62: =L56*L61 -> 3.768658
A63: Change in working capital | B63: =$B$11*(B56-$B$12) -> 0.345 | C63: =$B$11*(C56-B56) -> 0.05 | D63: =$B$11*(D56-C56) -> -0.2 | E63: =$B$11*(E56-D56) -> 0.2 | F63: =$B$11*(F56-E56) -> 0.4 | G63: =$B$11*(G56-F56) -> 0.38302817 | H63: =$B$11*(H56-G56) -> 0.3610649 | I63: =$B$11*(I56-H56) -> 0.33417605 | J63: =$B$11*(J56-I56) -> 0.30253501 | ... L63: =$B$11*(L56-K56) -> 0.27441685
A64: Free cash flow | B64: =B60-B62-B63 -> 20.69925 | C64: =C60-C62-C63 -> 20.84175 | D64: =D60-D62-D63 -> 19.6235 | E64: =E60-E62-E63 -> 19.48475 | F64: =F60-F62-F63 -> 20.39375 | G64: =G60-G62-G63 -> 21.295299 | H64: =H60-H62-H63 -> 22.124699 | I64: =I60-I62-I63 -> 22.870042 | ... L64: =L60-L62-L63 -> 24.787159
A65: Discount factor | B65: =1/(1+$B$10)^B$16 -> 0.96225045 | C65: =1/(1+$B$10)^C$16 -> 0.89097264 | D65: =1/(1+$B$10)^D$16 -> 0.82497466 | E65: =1/(1+$B$10)^E$16 -> 0.76386543 | F65: =1/(1+$B$10)^F$16 -> 0.70728281 | G65: =1/(1+$B$10)^G$16 -> 0.65489149 | H65: =1/(1+$B$10)^H$16 -> 0.60638101 | I65: =1/(1+$B$10)^I$16 -> 0.56146389 | ... K65: =1/(1+$B$10)^K$16 -> 0.48136479
A66: PV of free cash flow | B66: =B64*B65 -> 19.917863 | C66: =C64*C65 -> 18.569429 | D66: =D64*D65 -> 16.18889 | E66: =E64*E65 -> 14.883727 | F66: =F64*F65 -> 14.424149 | G66: =G64*G65 -> 13.94611 | H66: =H64*H65 -> 13.415997 | I66: =I64*I65 -> 12.840703 | ... K66: =K64*K65 -> 11.584141
A67: Terminal value | B67: =L64/($B$10-L57) -> 495.74318 | C67: =IF($B$10>L57,"","Discount rate must exceed terminal growth")
A68: PV of terminal value | B68: =B67/(1+$B$10)^$K$16 -> 238.63331
A69: Equity value (PV FCF + PV TV + net cash + other) | B69: =SUM(B66:K66)+B68+$B$7+$B$8 -> 339.86188
A70: Value per share ($) | B70: =B69/$B$6 -> 137.75206
A71: Value vs share price | B71: =B70/$B$4-1 -> -0.046368591
A74: Outputs | C74: vs price
A75: Bear value per share | B75: =B34 -> 61.660411 | C75: =B75/$B$4-1 -> -0.57313665
A76: Base value per share | B76: =B52 -> 97.506469 | C76: =B76/$B$4-1 -> -0.32498118
A77: Bull value per share | B77: =B70 -> 137.75206 | C77: =B77/$B$4-1 -> -0.046368591
A78: Selected scenario value per share | B78: =INDEX(B34:B70,1+($B$13-1)*18) -> 97.506469 | C78: =B78/$B$4-1 -> -0.32498118
A79: Share of base value from terminal value | B79: =B50/(SUM(B48:K48)+B50) -> 0.57193596
A81: Base value per share at other discount rates
A82: Discount rate | B82: 0.05 | C82: 0.06 | D82: 0.07 | E82: 0.08 | F82: 0.09 | G82: 0.1 | H82: 0.11 | I82: 0.12 | J82: 0.13 | K82: 0.14
A83: Base value per share | B83: =IF(B82>$L39,(SUMPRODUCT($B46:$K46/(1+B82)^$B$16:$K$16)+$L46/(B82-$L39)/(1+B82)^$K$16+$B$7+$B$8)/$B$6,"n/a") -> 228.99653 | C83: =IF(C82>$L39,(SUMPRODUCT($B46:$K46/(1+C82)^$B$16:$K$16)+$L46/(C82-$L39)/(1+C82)^$K$16+$B$7+$B$8)/$B$6,"n/a") -> 160.1496 | D83: =IF(D82>$L39,(SUMPRODUCT($B46:$K46/(1+D82)^$B$16:$K$16)+$L46/(D82-$L39)/(1+D82)^$K$16+$B$7+$B$8)/$B$6,"n/a") -> 121.87858 | E83: =IF(E82>$L39,(SUMPRODUCT($B46:$K46/(1+E82)^$B$16:$K$16)+$L46/(E82-$L39)/(1+E82)^$K$16+$B$7+$B$8)/$B$6,"n/a") -> 97.506469 | F83: =IF(F82>$L39,(SUMPRODUCT($B46:$K46/(1+F82)^$B$16:$K$16)+$L46/(F82-$L39)/(1+F82)^$K$16+$B$7+$B$8)/$B$6,"n/a") -> 80.618996 | G83: =IF(G82>$L39,(SUMPRODUCT($B46:$K46/(1+G82)^$B$16:$K$16)+$L46/(G82-$L39)/(1+G82)^$K$16+$B$7+$B$8)/$B$6,"n/a") -> 68.222796 | H83: =IF(H82>$L39,(SUMPRODUCT($B46:$K46/(1+H82)^$B$16:$K$16)+$L46/(H82-$L39)/(1+H82)^$K$16+$B$7+$B$8)/$B$6,"n/a") -> 58.733115 | I83: =IF(I82>$L39,(SUMPRODUCT($B46:$K46/(1+I82)^$B$16:$K$16)+$L46/(I82-$L39)/(1+I82)^$K$16+$B$7+$B$8)/$B$6,"n/a") -> 51.232443 | ... K83: =IF(K82>$L39,(SUMPRODUCT($B46:$K46/(1+K82)^$B$16:$K$16)+$L46/(K82-$L39)/(1+K82)^$K$16+$B$7+$B$8)/$B$6,"n/a") -> 40.123669
A84: vs share price | B84: =IFERROR(B83/$B$4-1,"n/a") -> 0.58529963 | C84: =IFERROR(C83/$B$4-1,"n/a") -> 0.10868535 | D84: =IFERROR(D83/$B$4-1,"n/a") -> -0.15625769 | E84: =IFERROR(E83/$B$4-1,"n/a") -> -0.32498118 | F84: =IFERROR(F83/$B$4-1,"n/a") -> -0.44188995 | G84: =IFERROR(G83/$B$4-1,"n/a") -> -0.5277065 | H84: =IFERROR(H83/$B$4-1,"n/a") -> -0.59340177 | I84: =IFERROR(I83/$B$4-1,"n/a") -> -0.6453275 | ... K84: =IFERROR(K83/$B$4-1,"n/a") -> -0.72223144
A86: Implied annual return at today's price, base case | B86: =IFERROR(IF(MATCH($B$4,$B$83:$K$83,-1)=10,"above 14%",INDEX($B$82:$K$82,MATCH($B$4,$B$83:$K$83,-1))+(INDEX($B$83:$K$83,MATCH($B$4,$B$83:$K$83,-1))-$B$4)/(INDEX($B$83:$K$83,MATCH($B$4,$B$83:$K$83,-1))-INDEX($B$83:$K$83,MATCH($B$4,$B$83:$K$83,-1)+1))*(INDEX($B$82:$K$82,MATCH($B$4,$B$83:$K$83,-1)+1)-INDEX($B$82:$K$82,MATCH($B$4,$B$83:$K$83,-1)))),"below 5%") -> 0.064102216 | C86: Discount rate at which base value equals the price (interpolated from the row above)

Sheet BDX
A1: Becton Dickinson (BDX): 10-year scenario DCF
A2: Units: $ billions unless noted. Blue = input, black = formula, green = link, yellow = key lever. Years 6 to 10 fade growth, margin and reinvestment toward each scenario's terminal levels.
A4: Share price ($) | B4: 198.91 | C4: Stock Analysis, Oct 23, 2026 close
A5: Price date | B5: Oct 23, 2026 close | C5: Text
A6: Shares outstanding (billions) | B6: 0.27239 | C6: Stock Analysis statistics, Oct 23 to 26, 2026 (market cap / price)
A7: Net cash, negative = net debt | B7: -16.1 | C7: Stock Analysis statistics, Oct 23 to 26, 2026: cash less total debt
A8: Other non-operating assets, less outside claims | B8: 0 | C8: None
A9: Tax rate | B9: 0.14 | C9: Analyst assumption, near the adjusted effective rate
A10: Discount rate (WACC), from WACC tab | B10: =WACC!E29 -> 0.08 | C10: Calculated or assumed, per the switch in WACC!B5
A11: Working capital, % of revenue change | B11: 0.15 | C11: Analyst assumption
A12: Base-year revenue (FY26, ends Sep 2026) | B12: 19.28 | C12: FY26 consensus $19.28B after the Waters separation; FY27 $19.74B (Stock Analysis)
A13: Selected scenario (1 Bear, 2 Base, 3 Bull) | B13: 2 | C13: Lever
A15: Year | B15: FY27 | C15: FY28 | D15: FY29 | E15: FY30 | F15: FY31 | G15: FY32 | H15: FY33 | I15: FY34 | J15: FY35 | K15: FY36 | L15: Terminal
A16: Discount period (years, mid-year) | B16: 0.5 | C16: =B16+1 -> 1.5 | D16: =C16+1 -> 2.5 | E16: =D16+1 -> 3.5 | F16: =E16+1 -> 4.5 | G16: =F16+1 -> 5.5 | H16: =G16+1 -> 6.5 | I16: =H16+1 -> 7.5 | J16: =I16+1 -> 8.5 | K16: =J16+1 -> 9.5
A17: Fade step (years 6 to 10) | B17: 0 | C17: 0 | D17: 0 | E17: 0 | F17: 0 | G17: 1 | H17: 2 | I17: 3 | J17: 4 | K17: 5
A19: Bear: about 2.3% growth, flat margins
A20: Revenue | B20: 19.6 | C20: 20 | D20: 20.5 | E20: 21 | F20: 21.5 | G20: =F20*(1+$F21+($L21-$F21)*G$17/5) -> 22.017024 | H20: =G20*(1+$F21+($L21-$F21)*H$17/5) -> 22.551723 | I20: =H20*(1+$F21+($L21-$F21)*I$17/5) -> 23.104777 | J20: =I20*(1+$F21+($L21-$F21)*J$17/5) -> 23.676895 | K20: =J20*(1+$F21+($L21-$F21)*K$17/5) -> 24.268818 | L20: =K20*(1+L21) -> 24.875538
A21: Revenue growth (terminal column = terminal growth, input) | B21: =B20/$B$12-1 -> 0.01659751 | C21: =C20/B20-1 -> 0.020408163 | D21: =D20/C20-1 -> 0.025 | E21: =E20/D20-1 -> 0.024390244 | F21: =F20/E20-1 -> 0.023809524 | G21: =G20/F20-1 -> 0.024047619 | H21: =H20/G20-1 -> 0.024285714 | I21: =I20/H20-1 -> 0.02452381 | J21: =J20/I20-1 -> 0.024761905 | K21: =K20/J20-1 -> 0.025 | L21: 0.025
A22: Operating margin | B22: 0.235 | C22: 0.235 | D22: 0.235 | E22: 0.235 | F22: 0.235 | G22: =$F22+($L22-$F22)*G$17/5 -> 0.234 | H22: =$F22+($L22-$F22)*H$17/5 -> 0.233 | I22: =$F22+($L22-$F22)*I$17/5 -> 0.232 | J22: =$F22+($L22-$F22)*J$17/5 -> 0.231 | K22: =$F22+($L22-$F22)*K$17/5 -> 0.23 | L22: 0.23
A23: Operating income | B23: =B20*B22 -> 4.606 | C23: =C20*C22 -> 4.7 | D23: =D20*D22 -> 4.8175 | E23: =E20*E22 -> 4.935 | F23: =F20*F22 -> 5.0525 | G23: =G20*G22 -> 5.1519836 | H23: =H20*H22 -> 5.2545514 | I23: =I20*I22 -> 5.3603083 | ... L23: =L20*L22 -> 5.7213738
A24: NOPAT | B24: =B23*(1-$B$9) -> 3.96116 | C24: =C23*(1-$B$9) -> 4.042 | D24: =D23*(1-$B$9) -> 4.14305 | E24: =E23*(1-$B$9) -> 4.2441 | F24: =F23*(1-$B$9) -> 4.34515 | G24: =G23*(1-$B$9) -> 4.4307059 | H24: =H23*(1-$B$9) -> 4.5189142 | I24: =I23*(1-$B$9) -> 4.6098651 | ... L24: =L23*(1-$B$9) -> 4.9203815
A25: Net reinvestment, % of revenue | B25: 0.03 | C25: 0.03 | D25: 0.03 | E25: 0.03 | F25: 0.03 | G25: =$F25+($L25-$F25)*G$17/5 -> 0.029 | H25: =$F25+($L25-$F25)*H$17/5 -> 0.028 | I25: =$F25+($L25-$F25)*I$17/5 -> 0.027 | J25: =$F25+($L25-$F25)*J$17/5 -> 0.026 | K25: =$F25+($L25-$F25)*K$17/5 -> 0.025 | L25: 0.025
A26: Net reinvestment | B26: =B20*B25 -> 0.588 | C26: =C20*C25 -> 0.6 | D26: =D20*D25 -> 0.615 | E26: =E20*E25 -> 0.63 | F26: =F20*F25 -> 0.645 | G26: =G20*G25 -> 0.63849369 | H26: =H20*H25 -> 0.63144824 | I26: =I20*I25 -> 0.62382898 | ... L26: =L20*L25 -> 0.62188846
A27: Change in working capital | B27: =$B$11*(B20-$B$12) -> 0.048 | C27: =$B$11*(C20-B20) -> 0.06 | D27: =$B$11*(D20-C20) -> 0.075 | E27: =$B$11*(E20-D20) -> 0.075 | F27: =$B$11*(F20-E20) -> 0.075 | G27: =$B$11*(G20-F20) -> 0.077553571 | H27: =$B$11*(H20-G20) -> 0.080204872 | I27: =$B$11*(I20-H20) -> 0.082958124 | J27: =$B$11*(J20-I20) -> 0.085817744 | ... L27: =$B$11*(L20-K20) -> 0.091008067
A28: Free cash flow | B28: =B24-B26-B27 -> 3.32516 | C28: =C24-C26-C27 -> 3.382 | D28: =D24-D26-D27 -> 3.45305 | E28: =E24-E26-E27 -> 3.5391 | F28: =F24-F26-F27 -> 3.62515 | G28: =G24-G26-G27 -> 3.7146586 | H28: =H24-H26-H27 -> 3.8072611 | I28: =I24-I26-I27 -> 3.903078 | ... L28: =L24-L26-L27 -> 4.2074849
A29: Discount factor | B29: =1/(1+$B$10)^B$16 -> 0.96225045 | C29: =1/(1+$B$10)^C$16 -> 0.89097264 | D29: =1/(1+$B$10)^D$16 -> 0.82497466 | E29: =1/(1+$B$10)^E$16 -> 0.76386543 | F29: =1/(1+$B$10)^F$16 -> 0.70728281 | G29: =1/(1+$B$10)^G$16 -> 0.65489149 | H29: =1/(1+$B$10)^H$16 -> 0.60638101 | I29: =1/(1+$B$10)^I$16 -> 0.56146389 | ... K29: =1/(1+$B$10)^K$16 -> 0.48136479
A30: PV of free cash flow | B30: =B28*B29 -> 3.1996367 | C30: =C28*C29 -> 3.0132695 | D30: =D28*D29 -> 2.8486788 | E30: =E28*E29 -> 2.7033961 | F30: =F28*F29 -> 2.5640063 | G30: =G28*G29 -> 2.4326983 | H30: =H28*H29 -> 2.3086508 | I30: =I28*I29 -> 2.1914374 | ... K30: =K28*K29 -> 1.9759367
A31: Terminal value | B31: =L28/($B$10-L21) -> 76.499726 | C31: =IF($B$10>L21,"","Discount rate must exceed terminal growth")
A32: PV of terminal value | B32: =B31/(1+$B$10)^$K$16 -> 36.824275
A33: Equity value (PV FCF + PV TV + net cash + other) | B33: =SUM(B30:K30)+B32+$B$7+$B$8 -> 46.042643
A34: Value per share ($) | B34: =B33/$B$6 -> 169.03206
A35: Value vs share price | B35: =B34/$B$4-1 -> -0.15020833
A37: Base: about 4% growth, margins toward 26%
A38: Revenue | B38: 19.74 | C38: 20.5 | D38: 21.3 | E38: 22.2 | F38: 23.1 | G38: =F38*(1+$F39+($L39-$F39)*G$17/5) -> 23.987789 | H38: =G38*(1+$F39+($L39-$F39)*H$17/5) -> 24.859129 | I38: =H38*(1+$F39+($L39-$F39)*I$17/5) -> 25.709715 | J38: =I38*(1+$F39+($L39-$F39)*J$17/5) -> 26.535205 | K38: =J38*(1+$F39+($L39-$F39)*K$17/5) -> 27.331261 | L38: =K38*(1+L39) -> 28.151199
A39: Revenue growth (terminal column = terminal growth, input) | B39: =B38/$B$12-1 -> 0.023858921 | C39: =C38/B38-1 -> 0.038500507 | D39: =D38/C38-1 -> 0.03902439 | E39: =E38/D38-1 -> 0.042253521 | F39: =F38/E38-1 -> 0.040540541 | G39: =G38/F38-1 -> 0.038432432 | H39: =H38/G38-1 -> 0.036324324 | I39: =I38/H38-1 -> 0.034216216 | J39: =J38/I38-1 -> 0.032108108 | K39: =K38/J38-1 -> 0.03 | L39: 0.03
A40: Operating margin | B40: 0.24 | C40: 0.245 | D40: 0.25 | E40: 0.255 | F40: 0.26 | G40: =$F40+($L40-$F40)*G$17/5 -> 0.258 | H40: =$F40+($L40-$F40)*H$17/5 -> 0.256 | I40: =$F40+($L40-$F40)*I$17/5 -> 0.254 | J40: =$F40+($L40-$F40)*J$17/5 -> 0.252 | K40: =$F40+($L40-$F40)*K$17/5 -> 0.25 | L40: 0.25
A41: Operating income | B41: =B38*B40 -> 4.7376 | C41: =C38*C40 -> 5.0225 | D41: =D38*D40 -> 5.325 | E41: =E38*E40 -> 5.661 | F41: =F38*F40 -> 6.006 | G41: =G38*G40 -> 6.1888496 | H41: =H38*H40 -> 6.3639371 | I41: =I38*I40 -> 6.5302676 | ... L41: =L38*L40 -> 7.0377998
A42: NOPAT | B42: =B41*(1-$B$9) -> 4.074336 | C42: =C41*(1-$B$9) -> 4.31935 | D42: =D41*(1-$B$9) -> 4.5795 | E42: =E41*(1-$B$9) -> 4.86846 | F42: =F41*(1-$B$9) -> 5.16516 | G42: =G41*(1-$B$9) -> 5.3224107 | H42: =H41*(1-$B$9) -> 5.4729859 | I42: =I41*(1-$B$9) -> 5.6160301 | ... L42: =L41*(1-$B$9) -> 6.0525078
A43: Net reinvestment, % of revenue | B43: 0.03 | C43: 0.03 | D43: 0.03 | E43: 0.03 | F43: 0.03 | G43: =$F43+($L43-$F43)*G$17/5 -> 0.029 | H43: =$F43+($L43-$F43)*H$17/5 -> 0.028 | I43: =$F43+($L43-$F43)*I$17/5 -> 0.027 | J43: =$F43+($L43-$F43)*J$17/5 -> 0.026 | K43: =$F43+($L43-$F43)*K$17/5 -> 0.025 | L43: 0.025
A44: Net reinvestment | B44: =B38*B43 -> 0.5922 | C44: =C38*C43 -> 0.615 | D44: =D38*D43 -> 0.639 | E44: =E38*E43 -> 0.666 | F44: =F38*F43 -> 0.693 | G44: =G38*G43 -> 0.69564589 | H44: =H38*H43 -> 0.69605562 | I44: =I38*I43 -> 0.6941623 | ... L44: =L38*L43 -> 0.70377998
A45: Change in working capital | B45: =$B$11*(B38-$B$12) -> 0.069 | C45: =$B$11*(C38-B38) -> 0.114 | D45: =$B$11*(D38-C38) -> 0.12 | E45: =$B$11*(E38-D38) -> 0.135 | F45: =$B$11*(F38-E38) -> 0.135 | G45: =$B$11*(G38-F38) -> 0.13316838 | H45: =$B$11*(H38-G38) -> 0.13070104 | I45: =$B$11*(I38-H38) -> 0.1275878 | J45: =$B$11*(J38-I38) -> 0.12382355 | ... L45: =$B$11*(L38-K38) -> 0.12299068
A46: Free cash flow | B46: =B42-B44-B45 -> 3.413136 | C46: =C42-C44-C45 -> 3.59035 | D46: =D42-D44-D45 -> 3.8205 | E46: =E42-E44-E45 -> 4.06746 | F46: =F42-F44-F45 -> 4.33716 | G46: =G42-G44-G45 -> 4.4935964 | H46: =H42-H44-H45 -> 4.6462293 | I46: =I42-I44-I45 -> 4.79428 | ... L46: =L42-L44-L45 -> 5.2257371
A47: Discount factor | B47: =1/(1+$B$10)^B$16 -> 0.96225045 | C47: =1/(1+$B$10)^C$16 -> 0.89097264 | D47: =1/(1+$B$10)^D$16 -> 0.82497466 | E47: =1/(1+$B$10)^E$16 -> 0.76386543 | F47: =1/(1+$B$10)^F$16 -> 0.70728281 | G47: =1/(1+$B$10)^G$16 -> 0.65489149 | H47: =1/(1+$B$10)^H$16 -> 0.60638101 | I47: =1/(1+$B$10)^I$16 -> 0.56146389 | ... K47: =1/(1+$B$10)^K$16 -> 0.48136479
A48: PV of free cash flow | B48: =B46*B47 -> 3.2842916 | C48: =C46*C47 -> 3.1989036 | D48: =D46*D47 -> 3.1518157 | E48: =E46*E47 -> 3.1069921 | F48: =F46*F47 -> 3.0675987 | G48: =G46*G47 -> 2.942818 | H48: =H46*H47 -> 2.8173852 | I48: =I46*I47 -> 2.6918151 | ... K48: =K46*K47 -> 2.4422193
A49: Terminal value | B49: =L46/($B$10-L39) -> 104.51474 | C49: =IF($B$10>L39,"","Discount rate must exceed terminal growth")
A50: PV of terminal value | B50: =B49/(1+$B$10)^$K$16 -> 50.309718
A51: Equity value (PV FCF + PV TV + net cash + other) | B51: =SUM(B48:K48)+B50+$B$7+$B$8 -> 63.48016
A52: Value per share ($) | B52: =B51/$B$6 -> 233.04879
A53: Value vs share price | B53: =B52/$B$4-1 -> 0.17162932
A55: Bull: 5% growth, margins toward 27.5%
A56: Revenue | B56: 20 | C56: 21 | D56: 22.1 | E56: 23.3 | F56: 24.5 | G56: =F56*(1+$F57+($L57-$F57)*G$17/5) -> 25.680942 | H56: =G56*(1+$F57+($L57-$F57)*H$17/5) -> 26.834049 | I56: =H56*(1+$F57+($L57-$F57)*I$17/5) -> 27.950369 | J56: =I56*(1+$F57+($L57-$F57)*J$17/5) -> 29.02088 | K56: =J56*(1+$F57+($L57-$F57)*K$17/5) -> 30.036611 | L56: =K56*(1+L57) -> 31.087892
A57: Revenue growth (terminal column = terminal growth, input) | B57: =B56/$B$12-1 -> 0.037344398 | C57: =C56/B56-1 -> 0.05 | D57: =D56/C56-1 -> 0.052380952 | E57: =E56/D56-1 -> 0.054298643 | F57: =F56/E56-1 -> 0.051502146 | G57: =G56/F56-1 -> 0.048201717 | H57: =H56/G56-1 -> 0.044901288 | I57: =I56/H56-1 -> 0.041600858 | J57: =J56/I56-1 -> 0.038300429 | K57: =K56/J56-1 -> 0.035 | L57: 0.035
A58: Operating margin | B58: 0.245 | C58: 0.255 | D58: 0.265 | E58: 0.27 | F58: 0.275 | G58: =$F58+($L58-$F58)*G$17/5 -> 0.273 | H58: =$F58+($L58-$F58)*H$17/5 -> 0.271 | I58: =$F58+($L58-$F58)*I$17/5 -> 0.269 | J58: =$F58+($L58-$F58)*J$17/5 -> 0.267 | K58: =$F58+($L58-$F58)*K$17/5 -> 0.265 | L58: 0.265
A59: Operating income | B59: =B56*B58 -> 4.9 | C59: =C56*C58 -> 5.355 | D59: =D56*D58 -> 5.8565 | E59: =E56*E58 -> 6.291 | F59: =F56*F58 -> 6.7375 | G59: =G56*G58 -> 7.0108972 | H59: =H56*H58 -> 7.2720274 | I59: =I56*I58 -> 7.5186492 | ... L59: =L56*L58 -> 8.2382914
A60: NOPAT | B60: =B59*(1-$B$9) -> 4.214 | C60: =C59*(1-$B$9) -> 4.6053 | D60: =D59*(1-$B$9) -> 5.03659 | E60: =E59*(1-$B$9) -> 5.41026 | F60: =F59*(1-$B$9) -> 5.79425 | G60: =G59*(1-$B$9) -> 6.0293716 | H60: =H59*(1-$B$9) -> 6.2539436 | I60: =I59*(1-$B$9) -> 6.4660383 | ... L60: =L59*(1-$B$9) -> 7.0849306
A61: Net reinvestment, % of revenue | B61: 0.03 | C61: 0.03 | D61: 0.03 | E61: 0.03 | F61: 0.03 | G61: =$F61+($L61-$F61)*G$17/5 -> 0.029 | H61: =$F61+($L61-$F61)*H$17/5 -> 0.028 | I61: =$F61+($L61-$F61)*I$17/5 -> 0.027 | J61: =$F61+($L61-$F61)*J$17/5 -> 0.026 | K61: =$F61+($L61-$F61)*K$17/5 -> 0.025 | L61: 0.025
A62: Net reinvestment | B62: =B56*B61 -> 0.6 | C62: =C56*C61 -> 0.63 | D62: =D56*D61 -> 0.663 | E62: =E56*E61 -> 0.699 | F62: =F56*F61 -> 0.735 | G62: =G56*G61 -> 0.74474732 | H62: =H56*H61 -> 0.75135338 | I62: =I56*I61 -> 0.75465996 | ... L62: =L56*L61 -> 0.77719731
A63: Change in working capital | B63: =$B$11*(B56-$B$12) -> 0.108 | C63: =$B$11*(C56-B56) -> 0.15 | D63: =$B$11*(D56-C56) -> 0.165 | E63: =$B$11*(E56-D56) -> 0.18 | F63: =$B$11*(F56-E56) -> 0.18 | G63: =$B$11*(G56-F56) -> 0.17714131 | H63: =$B$11*(H56-G56) -> 0.1729661 | I63: =$B$11*(I56-H56) -> 0.16744792 | J63: =$B$11*(J56-I56) -> 0.16057667 | ... L63: =$B$11*(L56-K56) -> 0.15769221
A64: Free cash flow | B64: =B60-B62-B63 -> 3.506 | C64: =C60-C62-C63 -> 3.8253 | D64: =D60-D62-D63 -> 4.20859 | E64: =E60-E62-E63 -> 4.53126 | F64: =F60-F62-F63 -> 4.87925 | G64: =G60-G62-G63 -> 5.1074829 | H64: =H60-H62-H63 -> 5.3296241 | I64: =I60-I62-I63 -> 5.5439305 | ... L64: =L60-L62-L63 -> 6.1500411
A65: Discount factor | B65: =1/(1+$B$10)^B$16 -> 0.96225045 | C65: =1/(1+$B$10)^C$16 -> 0.89097264 | D65: =1/(1+$B$10)^D$16 -> 0.82497466 | E65: =1/(1+$B$10)^E$16 -> 0.76386543 | F65: =1/(1+$B$10)^F$16 -> 0.70728281 | G65: =1/(1+$B$10)^G$16 -> 0.65489149 | H65: =1/(1+$B$10)^H$16 -> 0.60638101 | I65: =1/(1+$B$10)^I$16 -> 0.56146389 | ... K65: =1/(1+$B$10)^K$16 -> 0.48136479
A66: PV of free cash flow | B66: =B64*B65 -> 3.3736501 | C66: =C64*C65 -> 3.4082376 | D66: =D64*D65 -> 3.4719801 | E66: =E64*E65 -> 3.4612729 | F66: =F64*F65 -> 3.4510096 | G66: =G64*G65 -> 3.3448471 | H66: =H64*H65 -> 3.2317828 | I66: =I64*I65 -> 3.1127168 | ... K66: =K64*K65 -> 2.8603027
A67: Terminal value | B67: =L64/($B$10-L57) -> 136.66758 | C67: =IF($B$10>L57,"","Discount rate must exceed terminal growth")
A68: PV of terminal value | B68: =B67/(1+$B$10)^$K$16 -> 65.786962
A69: Equity value (PV FCF + PV TV + net cash + other) | B69: =SUM(B66:K66)+B68+$B$7+$B$8 -> 82.391337
A70: Value per share ($) | B70: =B69/$B$6 -> 302.47563
A71: Value vs share price | B71: =B70/$B$4-1 -> 0.52066579
A74: Outputs | C74: vs price
A75: Bear value per share | B75: =B34 -> 169.03206 | C75: =B75/$B$4-1 -> -0.15020833
A76: Base value per share | B76: =B52 -> 233.04879 | C76: =B76/$B$4-1 -> 0.17162932
A77: Bull value per share | B77: =B70 -> 302.47563 | C77: =B77/$B$4-1 -> 0.52066579
A78: Selected scenario value per share | B78: =INDEX(B34:B70,1+($B$13-1)*18) -> 233.04879 | C78: =B78/$B$4-1 -> 0.17162932
A79: Share of base value from terminal value | B79: =B50/(SUM(B48:K48)+B50) -> 0.6321892
A81: Base value per share at other discount rates
A82: Discount rate | B82: 0.05 | C82: 0.06 | D82: 0.07 | E82: 0.08 | F82: 0.09 | G82: 0.1 | H82: 0.11 | I82: 0.12 | J82: 0.13 | K82: 0.14
A83: Base value per share | B83: =IF(B82>$L39,(SUMPRODUCT($B46:$K46/(1+B82)^$B$16:$K$16)+$L46/(B82-$L39)/(1+B82)^$K$16+$B$7+$B$8)/$B$6,"n/a") -> 667.52371 | C83: =IF(C82>$L39,(SUMPRODUCT($B46:$K46/(1+C82)^$B$16:$K$16)+$L46/(C82-$L39)/(1+C82)^$K$16+$B$7+$B$8)/$B$6,"n/a") -> 426.11523 | D83: =IF(D82>$L39,(SUMPRODUCT($B46:$K46/(1+D82)^$B$16:$K$16)+$L46/(D82-$L39)/(1+D82)^$K$16+$B$7+$B$8)/$B$6,"n/a") -> 305.43659 | E83: =IF(E82>$L39,(SUMPRODUCT($B46:$K46/(1+E82)^$B$16:$K$16)+$L46/(E82-$L39)/(1+E82)^$K$16+$B$7+$B$8)/$B$6,"n/a") -> 233.04879 | F83: =IF(F82>$L39,(SUMPRODUCT($B46:$K46/(1+F82)^$B$16:$K$16)+$L46/(F82-$L39)/(1+F82)^$K$16+$B$7+$B$8)/$B$6,"n/a") -> 184.80556 | G83: =IF(G82>$L39,(SUMPRODUCT($B46:$K46/(1+G82)^$B$16:$K$16)+$L46/(G82-$L39)/(1+G82)^$K$16+$B$7+$B$8)/$B$6,"n/a") -> 150.35854 | H83: =IF(H82>$L39,(SUMPRODUCT($B46:$K46/(1+H82)^$B$16:$K$16)+$L46/(H82-$L39)/(1+H82)^$K$16+$B$7+$B$8)/$B$6,"n/a") -> 124.53357 | I83: =IF(I82>$L39,(SUMPRODUCT($B46:$K46/(1+I82)^$B$16:$K$16)+$L46/(I82-$L39)/(1+I82)^$K$16+$B$7+$B$8)/$B$6,"n/a") -> 104.45614 | ... K83: =IF(K82>$L39,(SUMPRODUCT($B46:$K46/(1+K82)^$B$16:$K$16)+$L46/(K82-$L39)/(1+K82)^$K$16+$B$7+$B$8)/$B$6,"n/a") -> 75.272396
A84: vs share price | B84: =IFERROR(B83/$B$4-1,"n/a") -> 2.3559083 | C84: =IFERROR(C83/$B$4-1,"n/a") -> 1.1422514 | D84: =IFERROR(D83/$B$4-1,"n/a") -> 0.53555168 | E84: =IFERROR(E83/$B$4-1,"n/a") -> 0.17162932 | F84: =IFERROR(F83/$B$4-1,"n/a") -> -0.070908634 | G84: =IFERROR(G83/$B$4-1,"n/a") -> -0.24408757 | H84: =IFERROR(H83/$B$4-1,"n/a") -> -0.37392002 | I84: =IFERROR(I83/$B$4-1,"n/a") -> -0.47485725 | ... K84: =IFERROR(K83/$B$4-1,"n/a") -> -0.6215756
A86: Implied annual return at today's price, base case | B86: =IFERROR(IF(MATCH($B$4,$B$83:$K$83,-1)=10,"above 14%",INDEX($B$82:$K$82,MATCH($B$4,$B$83:$K$83,-1))+(INDEX($B$83:$K$83,MATCH($B$4,$B$83:$K$83,-1))-$B$4)/(INDEX($B$83:$K$83,MATCH($B$4,$B$83:$K$83,-1))-INDEX($B$83:$K$83,MATCH($B$4,$B$83:$K$83,-1)+1))*(INDEX($B$82:$K$82,MATCH($B$4,$B$83:$K$83,-1)+1)-INDEX($B$82:$K$82,MATCH($B$4,$B$83:$K$83,-1)))),"below 5%") -> 0.08707639 | C86: Discount rate at which base value equals the price (interpolated from the row above)
