Workbook

Sheet Summary
A1: Memory and Storage Company Pass: scenario values
A2: Values link to each company sheet (green). Change assumptions on the company sheets.
A4: Company | B4: Share price | C4: Bear value | D4: Base value | E4: Bull value | F4: Base vs price | G4: Bull vs price | H4: Bear vs price | I4: Buy below | J4: Implied terminal margin
A5: Micron Technology (MU) | B5: =MU!B4 -> 909.96 | C5: =MU!B73 -> 350.65053 | D5: =MU!B74 -> 672.04437 | E5: =MU!B75 -> 1091.4646 | F5: =D5/B5-1 -> -0.26145724 | G5: =E5/B5-1 -> 0.19946437 | H5: =C5/B5-1 -> -0.61465281 | I5: =MU!B77 -> 571.23771 | J5: =MU!B79 -> 0.58812746
A6: SK hynix (KRX: 000660) | B6: ='SK hynix'!B4 -> 1239000 | C6: ='SK hynix'!B73 -> 662607.24 | D6: ='SK hynix'!B74 -> 1321578.8 | E6: ='SK hynix'!B75 -> 2197977.2 | F6: =D6/B6-1 -> 0.066649586 | G6: =E6/B6-1 -> 0.77399288 | H6: =C6/B6-1 -> -0.46520804 | I6: ='SK hynix'!B77 -> 1123342 | J6: ='SK hynix'!B79 -> 0.30718532
A7: Seagate Technology (STX) | B7: =STX!B4 -> 688.68 | C7: =STX!B73 -> 154.71667 | D7: =STX!B74 -> 424.8703 | E7: =STX!B75 -> 621.40425 | F7: =D7/B7-1 -> -0.38306572 | G7: =E7/B7-1 -> -0.097687961 | H7: =C7/B7-1 -> -0.77534316 | I7: =STX!B77 -> 361.13976 | J7: =STX!B79 -> 0.70218958
A8: Western Digital (WDC) | B8: =WDC!B4 -> 369.77 | C8: =WDC!B73 -> 79.267289 | D8: =WDC!B74 -> 213.81784 | E8: =WDC!B75 -> 311.24287 | F8: =D8/B8-1 -> -0.42175449 | G8: =E8/B8-1 -> -0.15827981 | H8: =C8/B8-1 -> -0.78563083 | I8: =WDC!B77 -> 181.74517 | J8: =WDC!B79 -> 0.68499521
A11: Notes
A12: Five-year free cash flow DCF with a terminal value; not a full three-statement model.
A13: FCF = EBIT x (1 - tax) - net reinvestment (capex above depreciation) - working capital x revenue change.
A14: Mid-year discounting from October 2026. SK hynix's Q4 2026 cash flow (about KRW 50T) is excluded, which is conservative.
A15: Revenue paths, margins, reinvestment, discount rates and terminal assumptions are analyst judgments, bear-leaning by design.
A16: Discount rate: switch on the WACC tab between a CAPM build and the assumed rates (12%, 13% SK hynix).
A17: Prices: Stock Analysis, Oct 21, 2026 intraday for MU, STX, WDC; SK hynix Oct 19, 2026 KRX close (latest available).
A18: Research for discussion, not investment advice.

Sheet WACC
A1: WACC build: calculated (CAPM) versus assumed
A2: Blue = input, black = formula, green = link. Switches in yellow apply to all four companies.
A5: WACC used in valuations (1 = Calculated, 2 = Assumed) | B5: 2 | C5: Switch. 2 reproduces the journal entry's figures
A6: Beta used (1 = Raw 5-year, 2 = Blume adjusted) | B6: 2 | C6: Blume adjusted = 0.67 x raw + 0.33
A7: Risk-free rate (10-year Treasury) | B7: 0.0531 | C7: FRED via MacroRadar, Oct 6, 2026
A8: Equity risk premium | B8: 0.05 | C8: Analyst assumption
A9: Credit spread over risk-free (pre-tax cost of debt) | B9: 0.012 | C9: Analyst assumption: investment-grade spread
A11: Item | B11: MU | C11: SK hynix | D11: STX | E11: WDC | F11: Source / note
A12: Raw beta (5-year) | B12: 2.23 | C12: 2.39 | D12: 2.08 | E12: 2.17 | F12: Stock Analysis statistics, Oct 2026
A13: Adjusted beta | B13: =0.67*B12+0.33 -> 1.8241 | C13: =0.67*C12+0.33 -> 1.9313 | D13: =0.67*D12+0.33 -> 1.7236 | E13: =0.67*E12+0.33 -> 1.7839 | F13: Blume: 0.67 x raw + 0.33
A14: Beta used | B14: =IF($B$6=1,B12,B13) -> 1.8241 | C14: =IF($B$6=1,C12,C13) -> 1.9313 | D14: =IF($B$6=1,D12,D13) -> 1.7236 | E14: =IF($B$6=1,E12,E13) -> 1.7839 | F14: Per switch in B6
A15: Country risk premium | B15: 0 | C15: 0.01 | D15: 0 | E15: 0 | F15: Analyst assumption (Korea)
A16: Cost of equity | B16: =$B$7+B14*$B$8+B15 -> 0.144305 | C16: =$B$7+C14*$B$8+C15 -> 0.159665 | D16: =$B$7+D14*$B$8+D15 -> 0.13928 | E16: =$B$7+E14*$B$8+E15 -> 0.142295 | F16: Risk-free + beta x ERP + country premium
A17: Pre-tax cost of debt | B17: =$B$7+$B$9+B15 -> 0.0651 | C17: =$B$7+$B$9+C15 -> 0.0751 | D17: =$B$7+$B$9+D15 -> 0.0651 | E17: =$B$7+$B$9+E15 -> 0.0651 | F17: Risk-free + spread
A18: Tax rate | B18: =MU!B8 -> 0.15 | C18: ='SK hynix'!B8 -> 0.22 | D18: =STX!B8 -> 0.1 | E18: =WDC!B8 -> 0.15 | F18: Linked from company sheet
A19: After-tax cost of debt | B19: =B17*(1-B18) -> 0.055335 | C19: =C17*(1-C18) -> 0.058578 | D19: =D17*(1-D18) -> 0.05859 | E19: =E17*(1-E18) -> 0.055335
A20: Market value of equity (company units) | B20: =MU!B4*MU!B6/MU!B13 -> 1028.2548 | C20: ='SK hynix'!B4*'SK hynix'!B6/'SK hynix'!B13 -> 903.06993 | D20: =STX!B4*STX!B6/STX!B13 -> 156.59895 | E20: =WDC!B4*WDC!B6/WDC!B13 -> 138.41231 | F20: Price x shares (KRW sheet: converted to KRW T)
A21: Debt (company units) | B21: 5.18 | C21: 21.11 | D21: 3.9 | E21: 1.19 | F21: Stock Analysis, total debt
A22: Equity weight | B22: =B20/(B20+B21) -> 0.99498759 | C22: =C20/(C20+C21) -> 0.97715813 | D22: =D20/(D20+D21) -> 0.97570077 | E22: =E20/(E20+E21) -> 0.99147579
A23: Debt weight | B23: =B21/(B20+B21) -> 0.005012411 | C23: =C21/(C20+C21) -> 0.022841872 | D23: =D21/(D20+D21) -> 0.024299225 | E23: =E21/(E20+E21) -> 0.0085242145
A24: Calculated WACC (CAPM) | B24: =B22*B16+B23*B19 -> 0.14385905 | C24: =C22*C16+C23*C19 -> 0.15735598 | D24: =D22*D16+D23*D19 -> 0.1373193 | E24: =E22*E16+E23*E19 -> 0.14155373 | F24: Weighted cost of capital
A25: Assumed WACC | B25: 0.12 | C25: 0.13 | D25: 0.12 | E25: 0.12 | F25: Analyst assumption used in the journal entry
A26: WACC used | B26: =IF($B$5=1,B24,B25) -> 0.12 | C26: =IF($B$5=1,C24,C25) -> 0.13 | D26: =IF($B$5=1,D24,D25) -> 0.12 | E26: =IF($B$5=1,E24,E25) -> 0.12 | F26: Per switch in B5; feeds each sheet's B9
A27: Check: WACC above terminal growth | B27: =IF(B26>MU!B10,"OK","WACC must exceed growth") -> OK | C27: =IF(C26>'SK hynix'!B10,"OK","WACC must exceed growth") -> OK | D27: =IF(D26>STX!B10,"OK","WACC must exceed growth") -> OK | E27: =IF(E26>WDC!B10,"OK","WACC must exceed growth") -> OK

Sheet MU
A1: Micron Technology (MU) scenario DCF
A2: Units: $B unless noted. Blue = input, black = formula, yellow = key lever. Change the blue cells; values update.
A4: Share price | B4: 909.96 | C4: Source: Stock Analysis, Oct 21, 2026 10:02 ET
A5: Price date | B5: Oct 21, 2026 10:02 ET | C5: Text
A6: Shares outstanding (billions) | B6: 1.13 | C6: Source: Stock Analysis statistics page, https://stockanalysis.com
A7: Net cash, negative = net debt ($B) | B7: 68.3 | C7: Company: cash and investments $73.5B less $5.2B debt, FQ4 FY26 call (MarketBeat summary, Sep 30, 2026)
A8: Tax rate | B8: 0.15 | C8: Analyst assumption
A9: Discount rate (WACC), from WACC tab | B9: =WACC!B26 -> 0.12 | C9: Selected on the WACC tab: calculated (CAPM) or assumed, per the switch in WACC!B5
A10: Terminal growth | B10: 0.025 | C10: Analyst assumption
A11: Working capital, % of revenue change | B11: 0.08 | C11: Analyst assumption
A12: Base-year revenue ($B) | B12: 133.188 | C12: FY26 (Sep 2026) revenue: sum of four quarters, Stock Analysis quarterly income statement
A13: Per-share multiplier | B13: 1 | C13: Converts equity value per billion shares to per share (1000 for KRW T)
A14: Margin of safety for buy-below | B14: 0.15 | C14: Analyst assumption
A15: Selected scenario (1 Bear, 2 Base, 3 Bull) | B15: 2 | C15: Lever
A17: Year | B17: FY27 | C17: FY28 | D17: FY29 | E17: FY30 | F17: FY31 | G17: Terminal
A18: Discount period (years, mid-year) | B18: 0.5 | C18: =B18+1 -> 1.5 | D18: =C18+1 -> 2.5 | E18: =D18+1 -> 3.5 | F18: =E18+1 -> 4.5
A20: Bear: AI capex slows in 2027, prices roll over late 2027
A21: Revenue | B21: 245 | C21: 150 | D21: 110 | E21: 130 | F21: 150 | G21: =F21*(1+$B$10) -> 153.75
A22: Revenue growth | B22: =B21/$B$12-1 -> 0.83950506 | C22: =C21/B21-1 -> -0.3877551 | D22: =D21/C21-1 -> -0.26666667 | E22: =E21/D21-1 -> 0.18181818 | F22: =F21/E21-1 -> 0.15384615 | G22: =G21/F21-1 -> 0.025
A23: EBIT margin | B23: 0.8 | C23: 0.45 | D23: 0.15 | E23: 0.25 | F23: 0.33 | G23: 0.25
A24: EBIT | B24: =B21*B23 -> 196 | C24: =C21*C23 -> 67.5 | D24: =D21*D23 -> 16.5 | E24: =E21*E23 -> 32.5 | F24: =F21*F23 -> 49.5 | G24: =G21*G23 -> 38.4375
A25: NOPAT (EBIT after tax) | B25: =B24*(1-$B$8) -> 166.6 | C25: =C24*(1-$B$8) -> 57.375 | D25: =D24*(1-$B$8) -> 14.025 | E25: =E24*(1-$B$8) -> 27.625 | F25: =F24*(1-$B$8) -> 42.075 | G25: =G24*(1-$B$8) -> 32.671875
A26: Net reinvestment, % of revenue | B26: 0.15 | C26: 0.15 | D26: 0.12 | E26: 0.08 | F26: 0.07 | G26: 0.06
A27: Net reinvestment (capex above depreciation) | B27: =B21*B26 -> 36.75 | C27: =C21*C26 -> 22.5 | D27: =D21*D26 -> 13.2 | E27: =E21*E26 -> 10.4 | F27: =F21*F26 -> 10.5 | G27: =G21*G26 -> 9.225
A28: Change in working capital | B28: =$B$11*(B21-$B$12) -> 8.94496 | C28: =$B$11*(C21-B21) -> -7.6 | D28: =$B$11*(D21-C21) -> -3.2 | E28: =$B$11*(E21-D21) -> 1.6 | F28: =$B$11*(F21-E21) -> 1.6 | G28: =$B$11*(G21-F21) -> 0.3
A29: Free cash flow | B29: =B25-B27-B28 -> 120.90504 | C29: =C25-C27-C28 -> 42.475 | D29: =D25-D27-D28 -> 4.025 | E29: =E25-E27-E28 -> 15.625 | F29: =F25-F27-F28 -> 29.975 | G29: =G25-G27-G28 -> 23.146875
A30: Discount factor | B30: =1/(1+$B$9)^B$18 -> 0.94491118 | C30: =1/(1+$B$9)^C$18 -> 0.8436707 | D30: =1/(1+$B$9)^D$18 -> 0.75327741 | E30: =1/(1+$B$9)^E$18 -> 0.67256912 | F30: =1/(1+$B$9)^F$18 -> 0.60050814
A31: PV of free cash flow | B31: =B29*B30 -> 114.24452 | C31: =C29*C30 -> 35.834913 | D31: =D29*D30 -> 3.0319416 | E31: =E29*E30 -> 10.508892 | F31: =F29*F30 -> 18.000231
A32: Terminal value | B32: =G29/($B$9-$B$10) -> 243.65132
A33: PV of terminal value | B33: =B32/(1+$B$9)^$F$18 -> 146.3146
A34: Equity value (PV FCF + PV TV + net cash) | B34: =SUM(B31:F31)+B33+$B$7 -> 396.2351
A35: Value per share | B35: =B34/$B$6*$B$13 -> 350.65053
A36: Value vs share price | B36: =B35/$B$4-1 -> -0.61465281
A37: Base: tight through FY28, normal by FY30
A38: Revenue | B38: 260 | C38: 250 | D38: 200 | E38: 190 | F38: 205 | G38: =F38*(1+$B$10) -> 210.125
A39: Revenue growth | B39: =B38/$B$12-1 -> 0.95212782 | C39: =C38/B38-1 -> -0.038461538 | D39: =D38/C38-1 -> -0.2 | E39: =E38/D38-1 -> -0.05 | F39: =F38/E38-1 -> 0.078947368 | G39: =G38/F38-1 -> 0.025
A40: EBIT margin | B40: 0.82 | C40: 0.72 | D40: 0.5 | E40: 0.45 | F40: 0.45 | G40: 0.35
A41: EBIT | B41: =B38*B40 -> 213.2 | C41: =C38*C40 -> 180 | D41: =D38*D40 -> 100 | E41: =E38*E40 -> 85.5 | F41: =F38*F40 -> 92.25 | G41: =G38*G40 -> 73.54375
A42: NOPAT (EBIT after tax) | B42: =B41*(1-$B$8) -> 181.22 | C42: =C41*(1-$B$8) -> 153 | D42: =D41*(1-$B$8) -> 85 | E42: =E41*(1-$B$8) -> 72.675 | F42: =F41*(1-$B$8) -> 78.4125 | G42: =G41*(1-$B$8) -> 62.512188
A43: Net reinvestment, % of revenue | B43: 0.15 | C43: 0.12 | D43: 0.08 | E43: 0.06 | F43: 0.06 | G43: 0.05
A44: Net reinvestment (capex above depreciation) | B44: =B38*B43 -> 39 | C44: =C38*C43 -> 30 | D44: =D38*D43 -> 16 | E44: =E38*E43 -> 11.4 | F44: =F38*F43 -> 12.3 | G44: =G38*G43 -> 10.50625
A45: Change in working capital | B45: =$B$11*(B38-$B$12) -> 10.14496 | C45: =$B$11*(C38-B38) -> -0.8 | D45: =$B$11*(D38-C38) -> -4 | E45: =$B$11*(E38-D38) -> -0.8 | F45: =$B$11*(F38-E38) -> 1.2 | G45: =$B$11*(G38-F38) -> 0.41
A46: Free cash flow | B46: =B42-B44-B45 -> 132.07504 | C46: =C42-C44-C45 -> 123.8 | D46: =D42-D44-D45 -> 73 | E46: =E42-E44-E45 -> 62.075 | F46: =F42-F44-F45 -> 64.9125 | G46: =G42-G44-G45 -> 51.595937
A47: Discount factor | B47: =1/(1+$B$9)^B$18 -> 0.94491118 | C47: =1/(1+$B$9)^C$18 -> 0.8436707 | D47: =1/(1+$B$9)^D$18 -> 0.75327741 | E47: =1/(1+$B$9)^E$18 -> 0.67256912 | F47: =1/(1+$B$9)^F$18 -> 0.60050814
A48: PV of free cash flow | B48: =B46*B47 -> 124.79918 | C48: =C46*C47 -> 104.44643 | D48: =D46*D47 -> 54.989251 | E48: =E46*E47 -> 41.749728 | F48: =F46*F47 -> 38.980485
A49: Terminal value | B49: =G46/($B$9-$B$10) -> 543.11513
A50: PV of terminal value | B50: =B49/(1+$B$9)^$F$18 -> 326.14506
A51: Equity value (PV FCF + PV TV + net cash) | B51: =SUM(B48:F48)+B50+$B$7 -> 759.41013
A52: Value per share | B52: =B51/$B$6*$B$13 -> 672.04437
A53: Value vs share price | B53: =B52/$B$4-1 -> -0.26145724
A54: Bull: shortage lasts through 2029
A55: Revenue | B55: 270 | C55: 320 | D55: 330 | E55: 290 | F55: 280 | G55: =F55*(1+$B$10) -> 287
A56: Revenue growth | B56: =B55/$B$12-1 -> 1.0272097 | C56: =C55/B55-1 -> 0.18518519 | D56: =D55/C55-1 -> 0.03125 | E56: =E55/D55-1 -> -0.12121212 | F56: =F55/E55-1 -> -0.034482759 | G56: =G55/F55-1 -> 0.025
A57: EBIT margin | B57: 0.83 | C57: 0.8 | D57: 0.72 | E57: 0.6 | F57: 0.55 | G57: 0.45
A58: EBIT | B58: =B55*B57 -> 224.1 | C58: =C55*C57 -> 256 | D58: =D55*D57 -> 237.6 | E58: =E55*E57 -> 174 | F58: =F55*F57 -> 154 | G58: =G55*G57 -> 129.15
A59: NOPAT (EBIT after tax) | B59: =B58*(1-$B$8) -> 190.485 | C59: =C58*(1-$B$8) -> 217.6 | D59: =D58*(1-$B$8) -> 201.96 | E59: =E58*(1-$B$8) -> 147.9 | F59: =F58*(1-$B$8) -> 130.9 | G59: =G58*(1-$B$8) -> 109.7775
A60: Net reinvestment, % of revenue | B60: 0.14 | C60: 0.12 | D60: 0.1 | E60: 0.07 | F60: 0.06 | G60: 0.05
A61: Net reinvestment (capex above depreciation) | B61: =B55*B60 -> 37.8 | C61: =C55*C60 -> 38.4 | D61: =D55*D60 -> 33 | E61: =E55*E60 -> 20.3 | F61: =F55*F60 -> 16.8 | G61: =G55*G60 -> 14.35
A62: Change in working capital | B62: =$B$11*(B55-$B$12) -> 10.94496 | C62: =$B$11*(C55-B55) -> 4 | D62: =$B$11*(D55-C55) -> 0.8 | E62: =$B$11*(E55-D55) -> -3.2 | F62: =$B$11*(F55-E55) -> -0.8 | G62: =$B$11*(G55-F55) -> 0.56
A63: Free cash flow | B63: =B59-B61-B62 -> 141.74004 | C63: =C59-C61-C62 -> 175.2 | D63: =D59-D61-D62 -> 168.16 | E63: =E59-E61-E62 -> 130.8 | F63: =F59-F61-F62 -> 114.9 | G63: =G59-G61-G62 -> 94.8675
A64: Discount factor | B64: =1/(1+$B$9)^B$18 -> 0.94491118 | C64: =1/(1+$B$9)^C$18 -> 0.8436707 | D64: =1/(1+$B$9)^D$18 -> 0.75327741 | E64: =1/(1+$B$9)^E$18 -> 0.67256912 | F64: =1/(1+$B$9)^F$18 -> 0.60050814
A65: PV of free cash flow | B65: =B63*B64 -> 133.93175 | C65: =C63*C64 -> 147.81111 | D65: =D63*D64 -> 126.67113 | E65: =E63*E64 -> 87.97204 | F65: =F63*F64 -> 68.998385
A66: Terminal value | B66: =G63/($B$9-$B$10) -> 998.60526
A67: PV of terminal value | B67: =B66/(1+$B$9)^$F$18 -> 599.67059
A68: Equity value (PV FCF + PV TV + net cash) | B68: =SUM(B65:F65)+B67+$B$7 -> 1233.355
A69: Value per share | B69: =B68/$B$6*$B$13 -> 1091.4646
A70: Value vs share price | B70: =B69/$B$4-1 -> 0.19946437
A72: Outputs | C72: vs price
A73: Bear value per share | B73: =B35 -> 350.65053 | C73: =B73/$B$4-1 -> -0.61465281
A74: Base value per share | B74: =B52 -> 672.04437 | C74: =B74/$B$4-1 -> -0.26145724
A75: Bull value per share | B75: =B69 -> 1091.4646 | C75: =B75/$B$4-1 -> 0.19946437
A76: Selected scenario value per share | B76: =INDEX(B35:B69,1+($B$15-1)*17) -> 672.04437 | C76: =B76/$B$4-1 -> -0.26145724
A77: Buy below (base value less margin of safety) | B77: =B74*(1-$B$14) -> 571.23771
A79: Terminal EBIT margin implied by today's price (base path) | B79: =(($B$4*$B$6/$B$13-$B$7-SUM(B48:F48))*(1+$B$9)^$F$18*($B$9-$B$10)+G38*G43+$B$11*(G38-F38))/(G38*(1-$B$8)) -> 0.58812746 | C79: Compare with the base terminal margin input in G40
A81: Base value per share at other discount rates
A82: Discount rate | B82: 0.1 | C82: 0.11 | D82: 0.12 | E82: 0.13 | F82: 0.14
A83: Base value per share | B83: =(SUMPRODUCT(B46:F46/(1+B82)^$B$18:$F$18)+G46/(B82-$B$10)/(1+B82)^$F$18+$B$7)/$B$6*$B$13 -> 790.98156 | C83: =(SUMPRODUCT(B46:F46/(1+C82)^$B$18:$F$18)+G46/(C82-$B$10)/(1+C82)^$F$18+$B$7)/$B$6*$B$13 -> 724.73595 | D83: =(SUMPRODUCT(B46:F46/(1+D82)^$B$18:$F$18)+G46/(D82-$B$10)/(1+D82)^$F$18+$B$7)/$B$6*$B$13 -> 672.04437 | E83: =(SUMPRODUCT(B46:F46/(1+E82)^$B$18:$F$18)+G46/(E82-$B$10)/(1+E82)^$F$18+$B$7)/$B$6*$B$13 -> 629.04916 | F83: =(SUMPRODUCT(B46:F46/(1+F82)^$B$18:$F$18)+G46/(F82-$B$10)/(1+F82)^$F$18+$B$7)/$B$6*$B$13 -> 593.2337

Sheet SK hynix
A1: SK hynix (KRX: 000660) scenario DCF
A2: Units: KRW T unless noted. Blue = input, black = formula, yellow = key lever. Change the blue cells; values update.
A4: Share price | B4: 1239000 | C4: Source: Stock Analysis, Oct 19, 2026 KRX (latest available)
A5: Price date | B5: Oct 19, 2026 KRX (latest available) | C5: Text
A6: Shares outstanding (billions) | B6: 0.72887 | C6: Source: Stock Analysis statistics page, https://stockanalysis.com
A7: Net cash, negative = net debt (KRW T) | B7: 66.87 | C7: Stock Analysis: cash KRW 87.98T less debt KRW 21.11T (stats updated Oct 18, 2026)
A8: Tax rate | B8: 0.22 | C8: Analyst assumption
A9: Discount rate (WACC), from WACC tab | B9: =WACC!C26 -> 0.13 | C9: Selected on the WACC tab: calculated (CAPM) or assumed, per the switch in WACC!B5
A10: Terminal growth | B10: 0.025 | C10: Analyst assumption
A11: Working capital, % of revenue change | B11: 0.08 | C11: Analyst assumption
A12: Base-year revenue (KRW T) | B12: 339 | C12: 2026E revenue, analyst estimate: Q1 52.9T + Q2 79.3T (reported) + Q3E 97T + Q4E 110T
A13: Per-share multiplier | B13: 1000 | C13: Converts equity value per billion shares to per share (1000 for KRW T)
A14: Margin of safety for buy-below | B14: 0.15 | C14: Analyst assumption
A15: Selected scenario (1 Bear, 2 Base, 3 Bull) | B15: 2 | C15: Lever
A17: Year | B17: 2027 | C17: 2028 | D17: 2029 | E17: 2030 | F17: 2031 | G17: Terminal
A18: Discount period (years, mid-year) | B18: 0.5 | C18: =B18+1 -> 1.5 | D18: =C18+1 -> 2.5 | E18: =D18+1 -> 3.5 | F18: =E18+1 -> 4.5
A20: Bear: AI capex slows in 2027
A21: Revenue | B21: 400 | C21: 250 | D21: 180 | E21: 200 | F21: 230 | G21: =F21*(1+$B$10) -> 235.75
A22: Revenue growth | B22: =B21/$B$12-1 -> 0.179941 | C22: =C21/B21-1 -> -0.375 | D22: =D21/C21-1 -> -0.28 | E22: =E21/D21-1 -> 0.11111111 | F22: =F21/E21-1 -> 0.15 | G22: =G21/F21-1 -> 0.025
A23: EBIT margin | B23: 0.72 | C23: 0.4 | D23: 0.15 | E23: 0.25 | F23: 0.32 | G23: 0.25
A24: EBIT | B24: =B21*B23 -> 288 | C24: =C21*C23 -> 100 | D24: =D21*D23 -> 27 | E24: =E21*E23 -> 50 | F24: =F21*F23 -> 73.6 | G24: =G21*G23 -> 58.9375
A25: NOPAT (EBIT after tax) | B25: =B24*(1-$B$8) -> 224.64 | C25: =C24*(1-$B$8) -> 78 | D25: =D24*(1-$B$8) -> 21.06 | E25: =E24*(1-$B$8) -> 39 | F25: =F24*(1-$B$8) -> 57.408 | G25: =G24*(1-$B$8) -> 45.97125
A26: Net reinvestment, % of revenue | B26: 0.13 | C26: 0.14 | D26: 0.12 | E26: 0.08 | F26: 0.07 | G26: 0.06
A27: Net reinvestment (capex above depreciation) | B27: =B21*B26 -> 52 | C27: =C21*C26 -> 35 | D27: =D21*D26 -> 21.6 | E27: =E21*E26 -> 16 | F27: =F21*F26 -> 16.1 | G27: =G21*G26 -> 14.145
A28: Change in working capital | B28: =$B$11*(B21-$B$12) -> 4.88 | C28: =$B$11*(C21-B21) -> -12 | D28: =$B$11*(D21-C21) -> -5.6 | E28: =$B$11*(E21-D21) -> 1.6 | F28: =$B$11*(F21-E21) -> 2.4 | G28: =$B$11*(G21-F21) -> 0.46
A29: Free cash flow | B29: =B25-B27-B28 -> 167.76 | C29: =C25-C27-C28 -> 55 | D29: =D25-D27-D28 -> 5.06 | E29: =E25-E27-E28 -> 21.4 | F29: =F25-F27-F28 -> 38.908 | G29: =G25-G27-G28 -> 31.36625
A30: Discount factor | B30: =1/(1+$B$9)^B$18 -> 0.94072087 | C30: =1/(1+$B$9)^C$18 -> 0.83249634 | D30: =1/(1+$B$9)^D$18 -> 0.73672243 | E30: =1/(1+$B$9)^E$18 -> 0.65196675 | F30: =1/(1+$B$9)^F$18 -> 0.57696173
A31: PV of free cash flow | B31: =B29*B30 -> 157.81533 | C31: =C29*C30 -> 45.787299 | D31: =D29*D30 -> 3.7278155 | E31: =E29*E30 -> 13.952088 | F31: =F29*F30 -> 22.448427
A32: Terminal value | B32: =G29/($B$9-$B$10) -> 298.72619
A33: PV of terminal value | B33: =B32/(1+$B$9)^$F$18 -> 172.35358
A34: Equity value (PV FCF + PV TV + net cash) | B34: =SUM(B31:F31)+B33+$B$7 -> 482.95454
A35: Value per share | B35: =B34/$B$6*$B$13 -> 662607.24
A36: Value vs share price | B36: =B35/$B$4-1 -> -0.46520804
A37: Base: tight through 2028
A38: Revenue | B38: 450 | C38: 410 | D38: 320 | E38: 300 | F38: 320 | G38: =F38*(1+$B$10) -> 328
A39: Revenue growth | B39: =B38/$B$12-1 -> 0.32743363 | C39: =C38/B38-1 -> -0.088888889 | D39: =D38/C38-1 -> -0.2195122 | E39: =E38/D38-1 -> -0.0625 | F39: =F38/E38-1 -> 0.066666667 | G39: =G38/F38-1 -> 0.025
A40: EBIT margin | B40: 0.75 | C40: 0.66 | D40: 0.46 | E40: 0.42 | F40: 0.42 | G40: 0.35
A41: EBIT | B41: =B38*B40 -> 337.5 | C41: =C38*C40 -> 270.6 | D41: =D38*D40 -> 147.2 | E41: =E38*E40 -> 126 | F41: =F38*F40 -> 134.4 | G41: =G38*G40 -> 114.8
A42: NOPAT (EBIT after tax) | B42: =B41*(1-$B$8) -> 263.25 | C42: =C41*(1-$B$8) -> 211.068 | D42: =D41*(1-$B$8) -> 114.816 | E42: =E41*(1-$B$8) -> 98.28 | F42: =F41*(1-$B$8) -> 104.832 | G42: =G41*(1-$B$8) -> 89.544
A43: Net reinvestment, % of revenue | B43: 0.13 | C43: 0.11 | D43: 0.08 | E43: 0.06 | F43: 0.06 | G43: 0.05
A44: Net reinvestment (capex above depreciation) | B44: =B38*B43 -> 58.5 | C44: =C38*C43 -> 45.1 | D44: =D38*D43 -> 25.6 | E44: =E38*E43 -> 18 | F44: =F38*F43 -> 19.2 | G44: =G38*G43 -> 16.4
A45: Change in working capital | B45: =$B$11*(B38-$B$12) -> 8.88 | C45: =$B$11*(C38-B38) -> -3.2 | D45: =$B$11*(D38-C38) -> -7.2 | E45: =$B$11*(E38-D38) -> -1.6 | F45: =$B$11*(F38-E38) -> 1.6 | G45: =$B$11*(G38-F38) -> 0.64
A46: Free cash flow | B46: =B42-B44-B45 -> 195.87 | C46: =C42-C44-C45 -> 169.168 | D46: =D42-D44-D45 -> 96.416 | E46: =E42-E44-E45 -> 81.88 | F46: =F42-F44-F45 -> 84.032 | G46: =G42-G44-G45 -> 72.504
A47: Discount factor | B47: =1/(1+$B$9)^B$18 -> 0.94072087 | C47: =1/(1+$B$9)^C$18 -> 0.83249634 | D47: =1/(1+$B$9)^D$18 -> 0.73672243 | E47: =1/(1+$B$9)^E$18 -> 0.65196675 | F47: =1/(1+$B$9)^F$18 -> 0.57696173
A48: PV of free cash flow | B48: =B46*B47 -> 184.259 | C48: =C46*C47 -> 140.83174 | D48: =D46*D47 -> 71.03183 | E48: =E46*E47 -> 53.383038 | F48: =F46*F47 -> 48.483248
A49: Terminal value | B49: =G46/($B$9-$B$10) -> 690.51429
A50: PV of terminal value | B50: =B49/(1+$B$9)^$F$18 -> 398.40031
A51: Equity value (PV FCF + PV TV + net cash) | B51: =SUM(B48:F48)+B50+$B$7 -> 963.25917
A52: Value per share | B52: =B51/$B$6*$B$13 -> 1321578.8
A53: Value vs share price | B53: =B52/$B$4-1 -> 0.066649586
A54: Bull: shortage through 2029
A55: Revenue | B55: 470 | C55: 520 | D55: 520 | E55: 460 | F55: 450 | G55: =F55*(1+$B$10) -> 461.25
A56: Revenue growth | B56: =B55/$B$12-1 -> 0.38643068 | C56: =C55/B55-1 -> 0.10638298 | D56: =D55/C55-1 -> 0 | E56: =E55/D55-1 -> -0.11538462 | F56: =F55/E55-1 -> -0.02173913 | G56: =G55/F55-1 -> 0.025
A57: EBIT margin | B57: 0.77 | C57: 0.75 | D57: 0.68 | E57: 0.58 | F57: 0.52 | G57: 0.45
A58: EBIT | B58: =B55*B57 -> 361.9 | C58: =C55*C57 -> 390 | D58: =D55*D57 -> 353.6 | E58: =E55*E57 -> 266.8 | F58: =F55*F57 -> 234 | G58: =G55*G57 -> 207.5625
A59: NOPAT (EBIT after tax) | B59: =B58*(1-$B$8) -> 282.282 | C59: =C58*(1-$B$8) -> 304.2 | D59: =D58*(1-$B$8) -> 275.808 | E59: =E58*(1-$B$8) -> 208.104 | F59: =F58*(1-$B$8) -> 182.52 | G59: =G58*(1-$B$8) -> 161.89875
A60: Net reinvestment, % of revenue | B60: 0.13 | C60: 0.11 | D60: 0.09 | E60: 0.07 | F60: 0.06 | G60: 0.05
A61: Net reinvestment (capex above depreciation) | B61: =B55*B60 -> 61.1 | C61: =C55*C60 -> 57.2 | D61: =D55*D60 -> 46.8 | E61: =E55*E60 -> 32.2 | F61: =F55*F60 -> 27 | G61: =G55*G60 -> 23.0625
A62: Change in working capital | B62: =$B$11*(B55-$B$12) -> 10.48 | C62: =$B$11*(C55-B55) -> 4 | D62: =$B$11*(D55-C55) -> 0 | E62: =$B$11*(E55-D55) -> -4.8 | F62: =$B$11*(F55-E55) -> -0.8 | G62: =$B$11*(G55-F55) -> 0.9
A63: Free cash flow | B63: =B59-B61-B62 -> 210.702 | C63: =C59-C61-C62 -> 243 | D63: =D59-D61-D62 -> 229.008 | E63: =E59-E61-E62 -> 180.704 | F63: =F59-F61-F62 -> 156.32 | G63: =G59-G61-G62 -> 137.93625
A64: Discount factor | B64: =1/(1+$B$9)^B$18 -> 0.94072087 | C64: =1/(1+$B$9)^C$18 -> 0.83249634 | D64: =1/(1+$B$9)^D$18 -> 0.73672243 | E64: =1/(1+$B$9)^E$18 -> 0.65196675 | F64: =1/(1+$B$9)^F$18 -> 0.57696173
A65: PV of free cash flow | B65: =B63*B64 -> 198.21177 | C65: =C63*C64 -> 202.29661 | D65: =D63*D64 -> 168.71533 | E65: =E63*E64 -> 117.813 | F65: =F63*F64 -> 90.190657
A66: Terminal value | B66: =G63/($B$9-$B$10) -> 1313.6786
A67: PV of terminal value | B67: =B66/(1+$B$9)^$F$18 -> 757.94226
A68: Equity value (PV FCF + PV TV + net cash) | B68: =SUM(B65:F65)+B67+$B$7 -> 1602.0396
A69: Value per share | B69: =B68/$B$6*$B$13 -> 2197977.2
A70: Value vs share price | B70: =B69/$B$4-1 -> 0.77399288
A72: Outputs | C72: vs price
A73: Bear value per share | B73: =B35 -> 662607.24 | C73: =B73/$B$4-1 -> -0.46520804
A74: Base value per share | B74: =B52 -> 1321578.8 | C74: =B74/$B$4-1 -> 0.066649586
A75: Bull value per share | B75: =B69 -> 2197977.2 | C75: =B75/$B$4-1 -> 0.77399288
A76: Selected scenario value per share | B76: =INDEX(B35:B69,1+($B$15-1)*17) -> 1321578.8 | C76: =B76/$B$4-1 -> 0.066649586
A77: Buy below (base value less margin of safety) | B77: =B74*(1-$B$14) -> 1123342
A79: Terminal EBIT margin implied by today's price (base path) | B79: =(($B$4*$B$6/$B$13-$B$7-SUM(B48:F48))*(1+$B$9)^$F$18*($B$9-$B$10)+G38*G43+$B$11*(G38-F38))/(G38*(1-$B$8)) -> 0.30718532 | C79: Compare with the base terminal margin input in G40
A81: Base value per share at other discount rates
A82: Discount rate | B82: 0.1 | C82: 0.11 | D82: 0.12 | E82: 0.13 | F82: 0.14
A83: Base value per share | B83: =(SUMPRODUCT(B46:F46/(1+B82)^$B$18:$F$18)+G46/(B82-$B$10)/(1+B82)^$F$18+$B$7)/$B$6*$B$13 -> 1672678.2 | C83: =(SUMPRODUCT(B46:F46/(1+C82)^$B$18:$F$18)+G46/(C82-$B$10)/(1+C82)^$F$18+$B$7)/$B$6*$B$13 -> 1528941.9 | D83: =(SUMPRODUCT(B46:F46/(1+D82)^$B$18:$F$18)+G46/(D82-$B$10)/(1+D82)^$F$18+$B$7)/$B$6*$B$13 -> 1414709.8 | E83: =(SUMPRODUCT(B46:F46/(1+E82)^$B$18:$F$18)+G46/(E82-$B$10)/(1+E82)^$F$18+$B$7)/$B$6*$B$13 -> 1321578.8 | F83: =(SUMPRODUCT(B46:F46/(1+F82)^$B$18:$F$18)+G46/(F82-$B$10)/(1+F82)^$F$18+$B$7)/$B$6*$B$13 -> 1244067.6

Sheet STX
A1: Seagate Technology (STX) scenario DCF
A2: Units: $B unless noted. Blue = input, black = formula, yellow = key lever. Change the blue cells; values update.
A4: Share price | B4: 688.68 | C4: Source: Stock Analysis, Oct 21, 2026 9:50 ET
A5: Price date | B5: Oct 21, 2026 9:50 ET | C5: Text
A6: Shares outstanding (billions) | B6: 0.22739 | C6: Source: Stock Analysis statistics page, https://stockanalysis.com
A7: Net cash, negative = net debt ($B) | B7: -2.2 | C7: Stock Analysis: cash $1.70B less debt $3.90B. Exchangeable notes due 2028 may dilute; not modeled
A8: Tax rate | B8: 0.1 | C8: Analyst assumption
A9: Discount rate (WACC), from WACC tab | B9: =WACC!D26 -> 0.12 | C9: Selected on the WACC tab: calculated (CAPM) or assumed, per the switch in WACC!B5
A10: Terminal growth | B10: 0.04 | C10: Analyst assumption
A11: Working capital, % of revenue change | B11: 0.1 | C11: Analyst assumption
A12: Base-year revenue ($B) | B12: 12.195 | C12: FY26 (Jul 2026) revenue, Stock Analysis annual income statement
A13: Per-share multiplier | B13: 1 | C13: Converts equity value per billion shares to per share (1000 for KRW T)
A14: Margin of safety for buy-below | B14: 0.15 | C14: Analyst assumption
A15: Selected scenario (1 Bear, 2 Base, 3 Bull) | B15: 2 | C15: Lever
A17: Year | B17: FY27 | C17: FY28 | D17: FY29 | E17: FY30 | F17: FY31 | G17: Terminal
A18: Discount period (years, mid-year) | B18: 0.5 | C18: =B18+1 -> 1.5 | D18: =C18+1 -> 2.5 | E18: =D18+1 -> 3.5 | F18: =E18+1 -> 4.5
A20: Bear: AI capex slows, Toshiba adds supply
A21: Revenue | B21: 17 | C21: 15.5 | D21: 14 | E21: 14.5 | F21: 15 | G21: =F21*(1+$B$10) -> 15.6
A22: Revenue growth | B22: =B21/$B$12-1 -> 0.39401394 | C22: =C21/B21-1 -> -0.088235294 | D22: =D21/C21-1 -> -0.096774194 | E22: =E21/D21-1 -> 0.035714286 | F22: =F21/E21-1 -> 0.034482759 | G22: =G21/F21-1 -> 0.04
A23: EBIT margin | B23: 0.49 | C23: 0.38 | D23: 0.28 | E23: 0.25 | F23: 0.25 | G23: 0.22
A24: EBIT | B24: =B21*B23 -> 8.33 | C24: =C21*C23 -> 5.89 | D24: =D21*D23 -> 3.92 | E24: =E21*E23 -> 3.625 | F24: =F21*F23 -> 3.75 | G24: =G21*G23 -> 3.432
A25: NOPAT (EBIT after tax) | B25: =B24*(1-$B$8) -> 7.497 | C25: =C24*(1-$B$8) -> 5.301 | D25: =D24*(1-$B$8) -> 3.528 | E25: =E24*(1-$B$8) -> 3.2625 | F25: =F24*(1-$B$8) -> 3.375 | G25: =G24*(1-$B$8) -> 3.0888
A26: Net reinvestment, % of revenue | B26: 0.02 | C26: 0.02 | D26: 0.02 | E26: 0.02 | F26: 0.02 | G26: 0.02
A27: Net reinvestment (capex above depreciation) | B27: =B21*B26 -> 0.34 | C27: =C21*C26 -> 0.31 | D27: =D21*D26 -> 0.28 | E27: =E21*E26 -> 0.29 | F27: =F21*F26 -> 0.3 | G27: =G21*G26 -> 0.312
A28: Change in working capital | B28: =$B$11*(B21-$B$12) -> 0.4805 | C28: =$B$11*(C21-B21) -> -0.15 | D28: =$B$11*(D21-C21) -> -0.15 | E28: =$B$11*(E21-D21) -> 0.05 | F28: =$B$11*(F21-E21) -> 0.05 | G28: =$B$11*(G21-F21) -> 0.06
A29: Free cash flow | B29: =B25-B27-B28 -> 6.6765 | C29: =C25-C27-C28 -> 5.141 | D29: =D25-D27-D28 -> 3.398 | E29: =E25-E27-E28 -> 2.9225 | F29: =F25-F27-F28 -> 3.025 | G29: =G25-G27-G28 -> 2.7168
A30: Discount factor | B30: =1/(1+$B$9)^B$18 -> 0.94491118 | C30: =1/(1+$B$9)^C$18 -> 0.8436707 | D30: =1/(1+$B$9)^D$18 -> 0.75327741 | E30: =1/(1+$B$9)^E$18 -> 0.67256912 | F30: =1/(1+$B$9)^F$18 -> 0.60050814
A31: PV of free cash flow | B31: =B29*B30 -> 6.3086995 | C31: =C29*C30 -> 4.3373111 | D31: =D29*D30 -> 2.5596366 | E31: =E29*E30 -> 1.9655832 | F31: =F29*F30 -> 1.8165371
A32: Terminal value | B32: =G29/($B$9-$B$10) -> 33.96
A33: PV of terminal value | B33: =B32/(1+$B$9)^$F$18 -> 20.393256
A34: Equity value (PV FCF + PV TV + net cash) | B34: =SUM(B31:F31)+B33+$B$7 -> 35.181024
A35: Value per share | B35: =B34/$B$6*$B$13 -> 154.71667
A36: Value vs share price | B36: =B35/$B$4-1 -> -0.77534316
A37: Base: exabytes grow, price per TB eases
A38: Revenue | B38: 17.5 | C38: 20.5 | D38: 23 | E38: 25 | F38: 26.5 | G38: =F38*(1+$B$10) -> 27.56
A39: Revenue growth | B39: =B38/$B$12-1 -> 0.43501435 | C39: =C38/B38-1 -> 0.17142857 | D39: =D38/C38-1 -> 0.12195122 | E39: =E38/D38-1 -> 0.086956522 | F39: =F38/E38-1 -> 0.06 | G39: =G38/F38-1 -> 0.04
A40: EBIT margin | B40: 0.51 | C40: 0.51 | D40: 0.48 | E40: 0.45 | F40: 0.42 | G40: 0.38
A41: EBIT | B41: =B38*B40 -> 8.925 | C41: =C38*C40 -> 10.455 | D41: =D38*D40 -> 11.04 | E41: =E38*E40 -> 11.25 | F41: =F38*F40 -> 11.13 | G41: =G38*G40 -> 10.4728
A42: NOPAT (EBIT after tax) | B42: =B41*(1-$B$8) -> 8.0325 | C42: =C41*(1-$B$8) -> 9.4095 | D42: =D41*(1-$B$8) -> 9.936 | E42: =E41*(1-$B$8) -> 10.125 | F42: =F41*(1-$B$8) -> 10.017 | G42: =G41*(1-$B$8) -> 9.42552
A43: Net reinvestment, % of revenue | B43: 0.02 | C43: 0.02 | D43: 0.02 | E43: 0.02 | F43: 0.02 | G43: 0.02
A44: Net reinvestment (capex above depreciation) | B44: =B38*B43 -> 0.35 | C44: =C38*C43 -> 0.41 | D44: =D38*D43 -> 0.46 | E44: =E38*E43 -> 0.5 | F44: =F38*F43 -> 0.53 | G44: =G38*G43 -> 0.5512
A45: Change in working capital | B45: =$B$11*(B38-$B$12) -> 0.5305 | C45: =$B$11*(C38-B38) -> 0.3 | D45: =$B$11*(D38-C38) -> 0.25 | E45: =$B$11*(E38-D38) -> 0.2 | F45: =$B$11*(F38-E38) -> 0.15 | G45: =$B$11*(G38-F38) -> 0.106
A46: Free cash flow | B46: =B42-B44-B45 -> 7.152 | C46: =C42-C44-C45 -> 8.6995 | D46: =D42-D44-D45 -> 9.226 | E46: =E42-E44-E45 -> 9.425 | F46: =F42-F44-F45 -> 9.337 | G46: =G42-G44-G45 -> 8.76832
A47: Discount factor | B47: =1/(1+$B$9)^B$18 -> 0.94491118 | C47: =1/(1+$B$9)^C$18 -> 0.8436707 | D47: =1/(1+$B$9)^D$18 -> 0.75327741 | E47: =1/(1+$B$9)^E$18 -> 0.67256912 | F47: =1/(1+$B$9)^F$18 -> 0.60050814
A48: PV of free cash flow | B48: =B46*B47 -> 6.7580048 | C48: =C46*C47 -> 7.3395132 | D48: =D46*D47 -> 6.9497374 | E48: =E46*E47 -> 6.3389639 | F48: =F46*F47 -> 5.6069445
A49: Terminal value | B49: =G46/($B$9-$B$10) -> 109.604
A50: PV of terminal value | B50: =B49/(1+$B$9)^$F$18 -> 65.818094
A51: Equity value (PV FCF + PV TV + net cash) | B51: =SUM(B48:F48)+B50+$B$7 -> 96.611258
A52: Value per share | B52: =B51/$B$6*$B$13 -> 424.8703
A53: Value vs share price | B53: =B52/$B$4-1 -> -0.38306572
A54: Bull: shortage and HAMR lead persist
A55: Revenue | B55: 18 | C55: 22.5 | D55: 27 | E55: 31 | F55: 34 | G55: =F55*(1+$B$10) -> 35.36
A56: Revenue growth | B56: =B55/$B$12-1 -> 0.47601476 | C56: =C55/B55-1 -> 0.25 | D56: =D55/C55-1 -> 0.2 | E56: =E55/D55-1 -> 0.14814815 | F56: =F55/E55-1 -> 0.096774194 | G56: =G55/F55-1 -> 0.04
A57: EBIT margin | B57: 0.52 | C57: 0.55 | D57: 0.55 | E57: 0.52 | F57: 0.48 | G57: 0.45
A58: EBIT | B58: =B55*B57 -> 9.36 | C58: =C55*C57 -> 12.375 | D58: =D55*D57 -> 14.85 | E58: =E55*E57 -> 16.12 | F58: =F55*F57 -> 16.32 | G58: =G55*G57 -> 15.912
A59: NOPAT (EBIT after tax) | B59: =B58*(1-$B$8) -> 8.424 | C59: =C58*(1-$B$8) -> 11.1375 | D59: =D58*(1-$B$8) -> 13.365 | E59: =E58*(1-$B$8) -> 14.508 | F59: =F58*(1-$B$8) -> 14.688 | G59: =G58*(1-$B$8) -> 14.3208
A60: Net reinvestment, % of revenue | B60: 0.02 | C60: 0.02 | D60: 0.02 | E60: 0.02 | F60: 0.02 | G60: 0.02
A61: Net reinvestment (capex above depreciation) | B61: =B55*B60 -> 0.36 | C61: =C55*C60 -> 0.45 | D61: =D55*D60 -> 0.54 | E61: =E55*E60 -> 0.62 | F61: =F55*F60 -> 0.68 | G61: =G55*G60 -> 0.7072
A62: Change in working capital | B62: =$B$11*(B55-$B$12) -> 0.5805 | C62: =$B$11*(C55-B55) -> 0.45 | D62: =$B$11*(D55-C55) -> 0.45 | E62: =$B$11*(E55-D55) -> 0.4 | F62: =$B$11*(F55-E55) -> 0.3 | G62: =$B$11*(G55-F55) -> 0.136
A63: Free cash flow | B63: =B59-B61-B62 -> 7.4835 | C63: =C59-C61-C62 -> 10.2375 | D63: =D59-D61-D62 -> 12.375 | E63: =E59-E61-E62 -> 13.488 | F63: =F59-F61-F62 -> 13.708 | G63: =G59-G61-G62 -> 13.4776
A64: Discount factor | B64: =1/(1+$B$9)^B$18 -> 0.94491118 | C64: =1/(1+$B$9)^C$18 -> 0.8436707 | D64: =1/(1+$B$9)^D$18 -> 0.75327741 | E64: =1/(1+$B$9)^E$18 -> 0.67256912 | F64: =1/(1+$B$9)^F$18 -> 0.60050814
A65: PV of free cash flow | B65: =B63*B64 -> 7.0712428 | C65: =C63*C64 -> 8.6370788 | D65: =D63*D64 -> 9.3218079 | E65: =E63*E64 -> 9.0716122 | F65: =F63*F64 -> 8.2317656
A66: Terminal value | B66: =G63/($B$9-$B$10) -> 168.47
A67: PV of terminal value | B67: =B66/(1+$B$9)^$F$18 -> 101.16761
A68: Equity value (PV FCF + PV TV + net cash) | B68: =SUM(B65:F65)+B67+$B$7 -> 141.30111
A69: Value per share | B69: =B68/$B$6*$B$13 -> 621.40425
A70: Value vs share price | B70: =B69/$B$4-1 -> -0.097687961
A72: Outputs | C72: vs price
A73: Bear value per share | B73: =B35 -> 154.71667 | C73: =B73/$B$4-1 -> -0.77534316
A74: Base value per share | B74: =B52 -> 424.8703 | C74: =B74/$B$4-1 -> -0.38306572
A75: Bull value per share | B75: =B69 -> 621.40425 | C75: =B75/$B$4-1 -> -0.097687961
A76: Selected scenario value per share | B76: =INDEX(B35:B69,1+($B$15-1)*17) -> 424.8703 | C76: =B76/$B$4-1 -> -0.38306572
A77: Buy below (base value less margin of safety) | B77: =B74*(1-$B$14) -> 361.13976
A79: Terminal EBIT margin implied by today's price (base path) | B79: =(($B$4*$B$6/$B$13-$B$7-SUM(B48:F48))*(1+$B$9)^$F$18*($B$9-$B$10)+G38*G43+$B$11*(G38-F38))/(G38*(1-$B$8)) -> 0.70218958 | C79: Compare with the base terminal margin input in G40
A81: Base value per share at other discount rates
A82: Discount rate | B82: 0.1 | C82: 0.11 | D82: 0.12 | E82: 0.13 | F82: 0.14
A83: Base value per share | B83: =(SUMPRODUCT(B46:F46/(1+B82)^$B$18:$F$18)+G46/(B82-$B$10)/(1+B82)^$F$18+$B$7)/$B$6*$B$13 -> 560.40892 | C83: =(SUMPRODUCT(B46:F46/(1+C82)^$B$18:$F$18)+G46/(C82-$B$10)/(1+C82)^$F$18+$B$7)/$B$6*$B$13 -> 483.0124 | D83: =(SUMPRODUCT(B46:F46/(1+D82)^$B$18:$F$18)+G46/(D82-$B$10)/(1+D82)^$F$18+$B$7)/$B$6*$B$13 -> 424.8703 | E83: =(SUMPRODUCT(B46:F46/(1+E82)^$B$18:$F$18)+G46/(E82-$B$10)/(1+E82)^$F$18+$B$7)/$B$6*$B$13 -> 379.56885 | F83: =(SUMPRODUCT(B46:F46/(1+F82)^$B$18:$F$18)+G46/(F82-$B$10)/(1+F82)^$F$18+$B$7)/$B$6*$B$13 -> 343.25956

Sheet WDC
A1: Western Digital (WDC) scenario DCF
A2: Units: $B unless noted. Blue = input, black = formula, yellow = key lever. Change the blue cells; values update.
A4: Share price | B4: 369.77 | C4: Source: Stock Analysis, Oct 21, 2026 9:51 ET
A5: Price date | B5: Oct 21, 2026 9:51 ET | C5: Text
A6: Shares outstanding (billions) | B6: 0.37432 | C6: Source: Stock Analysis statistics page, https://stockanalysis.com
A7: Net cash, negative = net debt ($B) | B7: 0.39 | C7: Stock Analysis: cash $1.58B less debt $1.19B
A8: Tax rate | B8: 0.15 | C8: Analyst assumption
A9: Discount rate (WACC), from WACC tab | B9: =WACC!E26 -> 0.12 | C9: Selected on the WACC tab: calculated (CAPM) or assumed, per the switch in WACC!B5
A10: Terminal growth | B10: 0.04 | C10: Analyst assumption
A11: Working capital, % of revenue change | B11: 0.1 | C11: Analyst assumption
A12: Base-year revenue ($B) | B12: 12.919 | C12: FY26 (Jul 2026) revenue: sum of four quarters, Stock Analysis quarterly income statement
A13: Per-share multiplier | B13: 1 | C13: Converts equity value per billion shares to per share (1000 for KRW T)
A14: Margin of safety for buy-below | B14: 0.15 | C14: Analyst assumption
A15: Selected scenario (1 Bear, 2 Base, 3 Bull) | B15: 2 | C15: Lever
A17: Year | B17: FY27 | C17: FY28 | D17: FY29 | E17: FY30 | F17: FY31 | G17: Terminal
A18: Discount period (years, mid-year) | B18: 0.5 | C18: =B18+1 -> 1.5 | D18: =C18+1 -> 2.5 | E18: =D18+1 -> 3.5 | F18: =E18+1 -> 4.5
A20: Bear: AI capex slows, Toshiba adds supply
A21: Revenue | B21: 16.5 | C21: 14.5 | D21: 13 | E21: 13.5 | F21: 14 | G21: =F21*(1+$B$10) -> 14.56
A22: Revenue growth | B22: =B21/$B$12-1 -> 0.27718864 | C22: =C21/B21-1 -> -0.12121212 | D22: =D21/C21-1 -> -0.10344828 | E22: =E21/D21-1 -> 0.038461538 | F22: =F21/E21-1 -> 0.037037037 | G22: =G21/F21-1 -> 0.04
A23: EBIT margin | B23: 0.44 | C23: 0.33 | D23: 0.24 | E23: 0.22 | F23: 0.22 | G23: 0.2
A24: EBIT | B24: =B21*B23 -> 7.26 | C24: =C21*C23 -> 4.785 | D24: =D21*D23 -> 3.12 | E24: =E21*E23 -> 2.97 | F24: =F21*F23 -> 3.08 | G24: =G21*G23 -> 2.912
A25: NOPAT (EBIT after tax) | B25: =B24*(1-$B$8) -> 6.171 | C25: =C24*(1-$B$8) -> 4.06725 | D25: =D24*(1-$B$8) -> 2.652 | E25: =E24*(1-$B$8) -> 2.5245 | F25: =F24*(1-$B$8) -> 2.618 | G25: =G24*(1-$B$8) -> 2.4752
A26: Net reinvestment, % of revenue | B26: 0.02 | C26: 0.02 | D26: 0.02 | E26: 0.02 | F26: 0.02 | G26: 0.02
A27: Net reinvestment (capex above depreciation) | B27: =B21*B26 -> 0.33 | C27: =C21*C26 -> 0.29 | D27: =D21*D26 -> 0.26 | E27: =E21*E26 -> 0.27 | F27: =F21*F26 -> 0.28 | G27: =G21*G26 -> 0.2912
A28: Change in working capital | B28: =$B$11*(B21-$B$12) -> 0.3581 | C28: =$B$11*(C21-B21) -> -0.2 | D28: =$B$11*(D21-C21) -> -0.15 | E28: =$B$11*(E21-D21) -> 0.05 | F28: =$B$11*(F21-E21) -> 0.05 | G28: =$B$11*(G21-F21) -> 0.056
A29: Free cash flow | B29: =B25-B27-B28 -> 5.4829 | C29: =C25-C27-C28 -> 3.97725 | D29: =D25-D27-D28 -> 2.542 | E29: =E25-E27-E28 -> 2.2045 | F29: =F25-F27-F28 -> 2.288 | G29: =G25-G27-G28 -> 2.128
A30: Discount factor | B30: =1/(1+$B$9)^B$18 -> 0.94491118 | C30: =1/(1+$B$9)^C$18 -> 0.8436707 | D30: =1/(1+$B$9)^D$18 -> 0.75327741 | E30: =1/(1+$B$9)^E$18 -> 0.67256912 | F30: =1/(1+$B$9)^F$18 -> 0.60050814
A31: PV of free cash flow | B31: =B29*B30 -> 5.1808535 | C31: =C29*C30 -> 3.3554893 | D31: =D29*D30 -> 1.9148312 | E31: =E29*E30 -> 1.4826786 | F31: =F29*F30 -> 1.3739626
A32: Terminal value | B32: =G29/($B$9-$B$10) -> 26.6
A33: PV of terminal value | B33: =B32/(1+$B$9)^$F$18 -> 15.973516
A34: Equity value (PV FCF + PV TV + net cash) | B34: =SUM(B31:F31)+B33+$B$7 -> 29.671332
A35: Value per share | B35: =B34/$B$6*$B$13 -> 79.267289
A36: Value vs share price | B36: =B35/$B$4-1 -> -0.78563083
A37: Base: exabytes grow, price per TB eases
A38: Revenue | B38: 17 | C38: 19.5 | D38: 22 | E38: 24 | F38: 25.5 | G38: =F38*(1+$B$10) -> 26.52
A39: Revenue growth | B39: =B38/$B$12-1 -> 0.31589132 | C39: =C38/B38-1 -> 0.14705882 | D39: =D38/C38-1 -> 0.12820513 | E39: =E38/D38-1 -> 0.090909091 | F39: =F38/E38-1 -> 0.0625 | G39: =G38/F38-1 -> 0.04
A40: EBIT margin | B40: 0.46 | C40: 0.46 | D40: 0.44 | E40: 0.41 | F40: 0.38 | G40: 0.34
A41: EBIT | B41: =B38*B40 -> 7.82 | C41: =C38*C40 -> 8.97 | D41: =D38*D40 -> 9.68 | E41: =E38*E40 -> 9.84 | F41: =F38*F40 -> 9.69 | G41: =G38*G40 -> 9.0168
A42: NOPAT (EBIT after tax) | B42: =B41*(1-$B$8) -> 6.647 | C42: =C41*(1-$B$8) -> 7.6245 | D42: =D41*(1-$B$8) -> 8.228 | E42: =E41*(1-$B$8) -> 8.364 | F42: =F41*(1-$B$8) -> 8.2365 | G42: =G41*(1-$B$8) -> 7.66428
A43: Net reinvestment, % of revenue | B43: 0.02 | C43: 0.02 | D43: 0.02 | E43: 0.02 | F43: 0.02 | G43: 0.02
A44: Net reinvestment (capex above depreciation) | B44: =B38*B43 -> 0.34 | C44: =C38*C43 -> 0.39 | D44: =D38*D43 -> 0.44 | E44: =E38*E43 -> 0.48 | F44: =F38*F43 -> 0.51 | G44: =G38*G43 -> 0.5304
A45: Change in working capital | B45: =$B$11*(B38-$B$12) -> 0.4081 | C45: =$B$11*(C38-B38) -> 0.25 | D45: =$B$11*(D38-C38) -> 0.25 | E45: =$B$11*(E38-D38) -> 0.2 | F45: =$B$11*(F38-E38) -> 0.15 | G45: =$B$11*(G38-F38) -> 0.102
A46: Free cash flow | B46: =B42-B44-B45 -> 5.8989 | C46: =C42-C44-C45 -> 6.9845 | D46: =D42-D44-D45 -> 7.538 | E46: =E42-E44-E45 -> 7.684 | F46: =F42-F44-F45 -> 7.5765 | G46: =G42-G44-G45 -> 7.03188
A47: Discount factor | B47: =1/(1+$B$9)^B$18 -> 0.94491118 | C47: =1/(1+$B$9)^C$18 -> 0.8436707 | D47: =1/(1+$B$9)^D$18 -> 0.75327741 | E47: =1/(1+$B$9)^E$18 -> 0.67256912 | F47: =1/(1+$B$9)^F$18 -> 0.60050814
A48: PV of free cash flow | B48: =B46*B47 -> 5.5739366 | C48: =C46*C47 -> 5.892618 | D48: =D46*D47 -> 5.6782051 | E48: =E46*E47 -> 5.1680211 | F48: =F46*F47 -> 4.5497499
A49: Terminal value | B49: =G46/($B$9-$B$10) -> 87.8985
A50: PV of terminal value | B50: =B49/(1+$B$9)^$F$18 -> 52.783765
A51: Equity value (PV FCF + PV TV + net cash) | B51: =SUM(B48:F48)+B50+$B$7 -> 80.036295
A52: Value per share | B52: =B51/$B$6*$B$13 -> 213.81784
A53: Value vs share price | B53: =B52/$B$4-1 -> -0.42175449
A54: Bull: shortage persists, HAMR lands on time
A55: Revenue | B55: 17.5 | C55: 21.5 | D55: 26 | E55: 30 | F55: 33 | G55: =F55*(1+$B$10) -> 34.32
A56: Revenue growth | B56: =B55/$B$12-1 -> 0.35459401 | C56: =C55/B55-1 -> 0.22857143 | D56: =D55/C55-1 -> 0.20930233 | E56: =E55/D55-1 -> 0.15384615 | F56: =F55/E55-1 -> 0.1 | G56: =G55/F55-1 -> 0.04
A57: EBIT margin | B57: 0.47 | C57: 0.5 | D57: 0.5 | E57: 0.47 | F57: 0.44 | G57: 0.4
A58: EBIT | B58: =B55*B57 -> 8.225 | C58: =C55*C57 -> 10.75 | D58: =D55*D57 -> 13 | E58: =E55*E57 -> 14.1 | F58: =F55*F57 -> 14.52 | G58: =G55*G57 -> 13.728
A59: NOPAT (EBIT after tax) | B59: =B58*(1-$B$8) -> 6.99125 | C59: =C58*(1-$B$8) -> 9.1375 | D59: =D58*(1-$B$8) -> 11.05 | E59: =E58*(1-$B$8) -> 11.985 | F59: =F58*(1-$B$8) -> 12.342 | G59: =G58*(1-$B$8) -> 11.6688
A60: Net reinvestment, % of revenue | B60: 0.02 | C60: 0.02 | D60: 0.02 | E60: 0.02 | F60: 0.02 | G60: 0.02
A61: Net reinvestment (capex above depreciation) | B61: =B55*B60 -> 0.35 | C61: =C55*C60 -> 0.43 | D61: =D55*D60 -> 0.52 | E61: =E55*E60 -> 0.6 | F61: =F55*F60 -> 0.66 | G61: =G55*G60 -> 0.6864
A62: Change in working capital | B62: =$B$11*(B55-$B$12) -> 0.4581 | C62: =$B$11*(C55-B55) -> 0.4 | D62: =$B$11*(D55-C55) -> 0.45 | E62: =$B$11*(E55-D55) -> 0.4 | F62: =$B$11*(F55-E55) -> 0.3 | G62: =$B$11*(G55-F55) -> 0.132
A63: Free cash flow | B63: =B59-B61-B62 -> 6.18315 | C63: =C59-C61-C62 -> 8.3075 | D63: =D59-D61-D62 -> 10.08 | E63: =E59-E61-E62 -> 10.985 | F63: =F59-F61-F62 -> 11.382 | G63: =G59-G61-G62 -> 10.8504
A64: Discount factor | B64: =1/(1+$B$9)^B$18 -> 0.94491118 | C64: =1/(1+$B$9)^C$18 -> 0.8436707 | D64: =1/(1+$B$9)^D$18 -> 0.75327741 | E64: =1/(1+$B$9)^E$18 -> 0.67256912 | F64: =1/(1+$B$9)^F$18 -> 0.60050814
A65: PV of free cash flow | B65: =B63*B64 -> 5.8425276 | C65: =C63*C64 -> 7.0087943 | D65: =D63*D64 -> 7.5930363 | E65: =E63*E64 -> 7.3881717 | F65: =F63*F64 -> 6.8349836
A66: Terminal value | B66: =G63/($B$9-$B$10) -> 135.63
A67: PV of terminal value | B67: =B66/(1+$B$9)^$F$18 -> 81.446919
A68: Equity value (PV FCF + PV TV + net cash) | B68: =SUM(B65:F65)+B67+$B$7 -> 116.50443
A69: Value per share | B69: =B68/$B$6*$B$13 -> 311.24287
A70: Value vs share price | B70: =B69/$B$4-1 -> -0.15827981
A72: Outputs | C72: vs price
A73: Bear value per share | B73: =B35 -> 79.267289 | C73: =B73/$B$4-1 -> -0.78563083
A74: Base value per share | B74: =B52 -> 213.81784 | C74: =B74/$B$4-1 -> -0.42175449
A75: Bull value per share | B75: =B69 -> 311.24287 | C75: =B75/$B$4-1 -> -0.15827981
A76: Selected scenario value per share | B76: =INDEX(B35:B69,1+($B$15-1)*17) -> 213.81784 | C76: =B76/$B$4-1 -> -0.42175449
A77: Buy below (base value less margin of safety) | B77: =B74*(1-$B$14) -> 181.74517
A79: Terminal EBIT margin implied by today's price (base path) | B79: =(($B$4*$B$6/$B$13-$B$7-SUM(B48:F48))*(1+$B$9)^$F$18*($B$9-$B$10)+G38*G43+$B$11*(G38-F38))/(G38*(1-$B$8)) -> 0.68499521 | C79: Compare with the base terminal margin input in G40
A81: Base value per share at other discount rates
A82: Discount rate | B82: 0.1 | C82: 0.11 | D82: 0.12 | E82: 0.13 | F82: 0.14
A83: Base value per share | B83: =(SUMPRODUCT(B46:F46/(1+B82)^$B$18:$F$18)+G46/(B82-$B$10)/(1+B82)^$F$18+$B$7)/$B$6*$B$13 -> 279.89241 | C83: =(SUMPRODUCT(B46:F46/(1+C82)^$B$18:$F$18)+G46/(C82-$B$10)/(1+C82)^$F$18+$B$7)/$B$6*$B$13 -> 242.1646 | D83: =(SUMPRODUCT(B46:F46/(1+D82)^$B$18:$F$18)+G46/(D82-$B$10)/(1+D82)^$F$18+$B$7)/$B$6*$B$13 -> 213.81784 | E83: =(SUMPRODUCT(B46:F46/(1+E82)^$B$18:$F$18)+G46/(E82-$B$10)/(1+E82)^$F$18+$B$7)/$B$6*$B$13 -> 191.7275 | F83: =(SUMPRODUCT(B46:F46/(1+F82)^$B$18:$F$18)+G46/(F82-$B$10)/(1+F82)^$F$18+$B$7)/$B$6*$B$13 -> 174.01865
