Workbook

Sheet Summary
A1: Optical Networking Company Pass: scenario values
A2: Values link to each company sheet (green). Switch the discount rate on the WACC tab.
A4: Company | B4: Share price | C4: Discount rate used | D4: Bear value | E4: Base value | F4: Bull value | G4: Bear vs price | H4: Base vs price | I4: Bull vs price | J4: Buy below
A5: Coherent (COHR) | B5: =COHR!B4 -> 234.86 | C5: =COHR!B9 -> 0.115 | D5: =COHR!B77 -> 38.400215 | E5: =COHR!B78 -> 111.67202 | F5: =COHR!B79 -> 182.04673 | G5: =D5/B5-1 -> -0.83649742 | H5: =E5/B5-1 -> -0.52451664 | I5: =F5/B5-1 -> -0.22487128 | J5: =COHR!B81 -> 111.67202
A6: Fabrinet (FN) | B6: =FN!B4 -> 355.48 | C6: =FN!B9 -> 0.1 | D6: =FN!B77 -> 169.40052 | E6: =FN!B78 -> 279.13684 | F6: =FN!B79 -> 387.98926 | G6: =D6/B6-1 -> -0.52345978 | H6: =E6/B6-1 -> -0.21476077 | I6: =F6/B6-1 -> 0.091451713 | J6: =FN!B81 -> 279.13684
A13: Notes
A14: Ten-year free cash flow DCF: five explicit years, then five years fading growth, margin and reinvestment toward terminal levels; not a three-statement model.
A15: FCF = operating income x (1 - tax) - net reinvestment (capex above depreciation) - working capital x revenue change. Mid-year discounting from October 2026.
A16: Scenario paths, margins, reinvestment, discount rates and terminal assumptions are analyst judgments. Bear cases assume an AI capex slowdown in 2027 to 2028.
A17: Implied returns quoted in the journal entry were solved outside the workbook; the rate sensitivity row on each sheet shows where base value crosses the price.
A18: Prices: Stock Analysis, Coherent Oct 21, 2026; Fabrinet Oct 20 close. Research for discussion, not investment advice.

Sheet WACC
A1: WACC build: calculated (CAPM) versus assumed
A2: Blue = input, black = formula, green = link. The yellow switches apply to both companies.
A5: WACC used in valuations (1 = Calculated, 2 = Assumed) | B5: 2 | C5: Switch. 2 reproduces the journal entry's figures
A6: Beta used (1 = Raw 5-year, 2 = Blume adjusted) | B6: 2 | C6: Blume adjusted = 0.67 x raw + 0.33
A7: Risk-free rate (10-year Treasury) | B7: 0.0531 | C7: FRED via MacroRadar, Oct 6, 2026
A8: Equity risk premium | B8: 0.05 | C8: Analyst assumption
A9: Credit spread over risk-free (pre-tax cost of debt) | B9: 0.012 | C9: Analyst assumption: investment-grade spread
A11: Item | B11: COHR | C11: FN | D11: Source / note
A12: Raw beta (5-year) | B12: 2.11 | C12: 1.22 | D12: Stock Analysis statistics, Oct 2026
A13: Adjusted beta | B13: =0.67*B12+0.33 -> 1.7437 | C13: =0.67*C12+0.33 -> 1.1474 | D13: Blume: 0.67 x raw + 0.33
A14: Beta used | B14: =IF($B$6=1,B12,B13) -> 1.7437 | C14: =IF($B$6=1,C12,C13) -> 1.1474 | D14: Per switch in B6
A15: Country risk premium | B15: 0 | C15: 0 | D15: Analyst assumption
A16: Cost of equity | B16: =$B$7+B14*$B$8+B15 -> 0.140285 | C16: =$B$7+C14*$B$8+C15 -> 0.11047 | D16: Risk-free + beta x ERP + country premium
A17: Pre-tax cost of debt | B17: =$B$7+$B$9+B15 -> 0.0651 | C17: =$B$7+$B$9+C15 -> 0.0651 | D17: Risk-free + spread + country premium
A18: Tax rate | B18: =COHR!B8 -> 0.15 | C18: =FN!B8 -> 0.08 | D18: Linked from company sheet
A19: After-tax cost of debt | B19: =B17*(1-B18) -> 0.055335 | C19: =C17*(1-C18) -> 0.059892
A20: Market value of equity (company units) | B20: =COHR!B4*COHR!B6/COHR!B13 -> 46.25098 | C20: =FN!B4*FN!B6/FN!B13 -> 12.903924 | D20: Price x shares
A21: Debt (company units) | B21: 3.55 | C21: 0.004 | D21: Stock Analysis, total debt
A22: Equity weight | B22: =B20/(B20+B21) -> 0.92871626 | C22: =C20/(C20+C21) -> 0.99969011
A23: Debt weight | B23: =B21/(B20+B21) -> 0.071283738 | C23: =C21/(C20+C21) -> 0.00030988717
A24: Calculated WACC (CAPM) | B24: =B22*B16+B23*B19 -> 0.13422945 | C24: =C22*C16+C23*C19 -> 0.11045433 | D24: Weighted cost of capital
A25: Assumed WACC | B25: 0.115 | C25: 0.1 | D25: Analyst assumption used in the journal entry
A26: WACC used | B26: =IF($B$5=1,B24,B25) -> 0.115 | C26: =IF($B$5=1,C24,C25) -> 0.1 | D26: Per switch in B5; feeds each sheet's B9
A27: Check: WACC above terminal growth | B27: =IF(B26>COHR!B10,"OK","WACC must exceed growth") -> OK | C27: =IF(C26>FN!B10,"OK","WACC must exceed growth") -> OK

Sheet COHR
A1: Coherent (COHR): 10-year scenario DCF
A2: Units: $B unless noted. Blue = input, black = formula, green = link, yellow = key lever. Years 6 to 10 fade growth, margin and reinvestment toward terminal levels.
A4: Share price | B4: 234.86 | C4: Source: Stock Analysis, Oct 21, 2026 11:34 ET
A5: Price date | B5: Oct 21, 2026 11:34 ET | C5: Text
A6: Shares outstanding (billions) | B6: 0.19693 | C6: Source: Stock Analysis, https://stockanalysis.com
A7: Net cash, negative = net debt ($B) | B7: -1.56 | C7: Stock Analysis: cash $1.99B less debt $3.55B
A8: Tax rate | B8: 0.15 | C8: Analyst assumption
A9: Discount rate (WACC), from WACC tab | B9: =WACC!B26 -> 0.115 | C9: Calculated or assumed, per switch in WACC!B5
A10: Terminal growth | B10: 0.04 | C10: Analyst assumption
A11: Working capital, % of revenue change | B11: 0.15 | C11: Analyst assumption
A12: Base-year revenue ($B) | B12: 7.118 | C12: FY26 (Jun 2026) revenue, Stock Analysis annual income statement. Margins about 2 pts below non-GAAP
A13: Per-share multiplier | B13: 1 | C13: Units conversion (1 here)
A14: Selected scenario (1 Bear, 2 Base, 3 Bull) | B14: 2 | C14: Lever
A16: Year | B16: FY27 | C16: FY28 | D16: FY29 | E16: FY30 | F16: FY31 | G16: FY32 | H16: FY33 | I16: FY34 | J16: FY35 | K16: FY36 | L16: Terminal
A17: Discount period (years, mid-year) | B17: 0.5 | C17: =B17+1 -> 1.5 | D17: =C17+1 -> 2.5 | E17: =D17+1 -> 3.5 | F17: =E17+1 -> 4.5 | G17: =F17+1 -> 5.5 | H17: =G17+1 -> 6.5 | I17: =H17+1 -> 7.5 | J17: =I17+1 -> 8.5 | K17: =J17+1 -> 9.5
A18: Fade step (years 6 to 10) | B18: 0 | C18: 0 | D18: 0 | E18: 0 | F18: 0 | G18: 1 | H18: 2 | I18: 3 | J18: 4 | K18: 5
A20: Bear: AI optics orders fall in FY28
A21: Revenue | B21: 9.2 | C21: 8 | D21: 8.3 | E21: 9 | F21: 9.8 | G21: =F21*(1+$F22+($B$10-$F22)*G$18/5) -> 10.575289 | H21: =G21*(1+$F22+($B$10-$F22)*H$18/5) -> 11.308509 | I21: =H21*(1+$F22+($B$10-$F22)*I$18/5) -> 11.981993 | J21: =I21*(1+$F22+($B$10-$F22)*J$18/5) -> 12.57843 | K21: =J21*(1+$F22+($B$10-$F22)*K$18/5) -> 13.081568 | L21: =K21*(1+$B$10) -> 13.60483
A22: Revenue growth | B22: =B21/$B$12-1 -> 0.29249789 | C22: =C21/B21-1 -> -0.13043478 | D22: =D21/C21-1 -> 0.0375 | E22: =E21/D21-1 -> 0.084337349 | F22: =F21/E21-1 -> 0.088888889 | G22: =G21/F21-1 -> 0.079111111 | H22: =H21/G21-1 -> 0.069333333 | I22: =I21/H21-1 -> 0.059555556 | J22: =J21/I21-1 -> 0.049777778 | ... L22: =L21/K21-1 -> 0.04
A23: Operating margin | B23: 0.18 | C23: 0.12 | D23: 0.12 | E23: 0.14 | F23: 0.15 | G23: =$F23+($L23-$F23)*G$18/5 -> 0.148 | H23: =$F23+($L23-$F23)*H$18/5 -> 0.146 | I23: =$F23+($L23-$F23)*I$18/5 -> 0.144 | J23: =$F23+($L23-$F23)*J$18/5 -> 0.142 | K23: =$F23+($L23-$F23)*K$18/5 -> 0.14 | L23: 0.14
A24: Operating income | B24: =B21*B23 -> 1.656 | C24: =C21*C23 -> 0.96 | D24: =D21*D23 -> 0.996 | E24: =E21*E23 -> 1.26 | F24: =F21*F23 -> 1.47 | G24: =G21*G23 -> 1.5651428 | H24: =H21*H23 -> 1.6510423 | I24: =I21*I23 -> 1.7254071 | ... L24: =L21*L23 -> 1.9046763
A25: NOPAT | B25: =B24*(1-$B$8) -> 1.4076 | C25: =C24*(1-$B$8) -> 0.816 | D25: =D24*(1-$B$8) -> 0.8466 | E25: =E24*(1-$B$8) -> 1.071 | F25: =F24*(1-$B$8) -> 1.2495 | G25: =G24*(1-$B$8) -> 1.3303713 | H25: =H24*(1-$B$8) -> 1.403386 | I25: =I24*(1-$B$8) -> 1.466596 | ... L25: =L24*(1-$B$8) -> 1.6189748
A26: Net reinvestment, % of revenue | B26: 0.12 | C26: 0.06 | D26: 0.04 | E26: 0.04 | F26: 0.04 | G26: =$F26+($L26-$F26)*G$18/5 -> 0.038 | H26: =$F26+($L26-$F26)*H$18/5 -> 0.036 | I26: =$F26+($L26-$F26)*I$18/5 -> 0.034 | J26: =$F26+($L26-$F26)*J$18/5 -> 0.032 | K26: =$F26+($L26-$F26)*K$18/5 -> 0.03 | L26: 0.03
A27: Net reinvestment | B27: =B21*B26 -> 1.104 | C27: =C21*C26 -> 0.48 | D27: =D21*D26 -> 0.332 | E27: =E21*E26 -> 0.36 | F27: =F21*F26 -> 0.392 | G27: =G21*G26 -> 0.40186098 | H27: =H21*H26 -> 0.40710632 | I27: =I21*I26 -> 0.40738778 | ... L27: =L21*L26 -> 0.40814491
A28: Change in working capital | B28: =$B$11*(B21-$B$12) -> 0.3123 | C28: =$B$11*(C21-B21) -> -0.18 | D28: =$B$11*(D21-C21) -> 0.045 | E28: =$B$11*(E21-D21) -> 0.105 | F28: =$B$11*(F21-E21) -> 0.12 | G28: =$B$11*(G21-F21) -> 0.11629333 | H28: =$B$11*(H21-G21) -> 0.109983 | I28: =$B$11*(I21-H21) -> 0.10102268 | J28: =$B$11*(J21-I21) -> 0.089465551 | ... L28: =$B$11*(L21-K21) -> 0.078489406
A29: Free cash flow | B29: =B25-B27-B28 -> -0.0087 | C29: =C25-C27-C28 -> 0.516 | D29: =D25-D27-D28 -> 0.4696 | E29: =E25-E27-E28 -> 0.606 | F29: =F25-F27-F28 -> 0.7375 | G29: =G25-G27-G28 -> 0.81221703 | H29: =H25-H27-H28 -> 0.88629663 | I29: =I25-I27-I28 -> 0.95818554 | ... L29: =L25-L27-L28 -> 1.1323405
A30: Discount factor | B30: =1/(1+$B$9)^B$17 -> 0.94702745 | C30: =1/(1+$B$9)^C$17 -> 0.84935197 | D30: =1/(1+$B$9)^D$17 -> 0.76175065 | E30: =1/(1+$B$9)^E$17 -> 0.68318444 | F30: =1/(1+$B$9)^F$17 -> 0.61272147 | G30: =1/(1+$B$9)^G$17 -> 0.54952598 | H30: =1/(1+$B$9)^H$17 -> 0.49284841 | I30: =1/(1+$B$9)^I$17 -> 0.44201651 | ... K30: =1/(1+$B$9)^K$17 -> 0.35554024
A31: PV of free cash flow | B31: =B29*B30 -> -0.0082391388 | C31: =C29*C30 -> 0.43826562 | D31: =D29*D30 -> 0.3577181 | E31: =E29*E30 -> 0.41400977 | F31: =F29*F30 -> 0.45188208 | G31: =G29*G30 -> 0.44633436 | H31: =H29*H30 -> 0.43680989 | I31: =I29*I30 -> 0.42353383 | ... K31: =K29*K30 -> 0.38710828
A32: Terminal value | B32: =L29/($B$9-$B$10) -> 15.097873
A33: PV of terminal value | B33: =B32/(1+$B$9)^$K$17 -> 5.3679015
A34: Equity value (PV FCF + PV TV + net cash) | B34: =SUM(B31:K31)+B33+$B$7 -> 7.5621544
A35: Value per share | B35: =B34/$B$6*$B$13 -> 38.400215
A36: Value vs share price | B36: =B35/$B$4-1 -> -0.83649742
A38: Base: near the $3B quarterly target, then slower
A39: Revenue | B39: 10.2 | C39: 12.5 | D39: 13 | E39: 14.5 | F39: 16 | G39: =F39*(1+$F40+($B$10-$F40)*G$18/5) -> 17.452138 | H39: =G39*(1+$F40+($B$10-$F40)*H$18/5) -> 18.814608 | I39: =H39*(1+$F40+($B$10-$F40)*I$18/5) -> 20.044694 | J39: =I39*(1+$F40+($B$10-$F40)*J$18/5) -> 21.100842 | K39: =J39*(1+$F40+($B$10-$F40)*K$18/5) -> 21.944876 | L39: =K39*(1+$B$10) -> 22.822671
A40: Revenue growth | B40: =B39/$B$12-1 -> 0.43298679 | C40: =C39/B39-1 -> 0.2254902 | D40: =D39/C39-1 -> 0.04 | E40: =E39/D39-1 -> 0.11538462 | F40: =F39/E39-1 -> 0.10344828 | G40: =G39/F39-1 -> 0.090758621 | H40: =H39/G39-1 -> 0.078068966 | I40: =I39/H39-1 -> 0.06537931 | J40: =J39/I39-1 -> 0.052689655 | ... L40: =L39/K39-1 -> 0.04
A41: Operating margin | B41: 0.2 | C41: 0.22 | D41: 0.2 | E41: 0.21 | F41: 0.21 | G41: =$F41+($L41-$F41)*G$18/5 -> 0.206 | H41: =$F41+($L41-$F41)*H$18/5 -> 0.202 | I41: =$F41+($L41-$F41)*I$18/5 -> 0.198 | J41: =$F41+($L41-$F41)*J$18/5 -> 0.194 | K41: =$F41+($L41-$F41)*K$18/5 -> 0.19 | L41: 0.19
A42: Operating income | B42: =B39*B41 -> 2.04 | C42: =C39*C41 -> 2.75 | D42: =D39*D41 -> 2.6 | E42: =E39*E41 -> 3.045 | F42: =F39*F41 -> 3.36 | G42: =G39*G41 -> 3.5951404 | H42: =H39*H41 -> 3.8005509 | I42: =I39*I41 -> 3.9688495 | ... L42: =L39*L41 -> 4.3363075
A43: NOPAT | B43: =B42*(1-$B$8) -> 1.734 | C43: =C42*(1-$B$8) -> 2.3375 | D43: =D42*(1-$B$8) -> 2.21 | E43: =E42*(1-$B$8) -> 2.58825 | F43: =F42*(1-$B$8) -> 2.856 | G43: =G42*(1-$B$8) -> 3.0558694 | H43: =H42*(1-$B$8) -> 3.2304682 | I43: =I42*(1-$B$8) -> 3.3735221 | ... L43: =L42*(1-$B$8) -> 3.6858614
A44: Net reinvestment, % of revenue | B44: 0.12 | C44: 0.08 | D44: 0.05 | E44: 0.04 | F44: 0.04 | G44: =$F44+($L44-$F44)*G$18/5 -> 0.038 | H44: =$F44+($L44-$F44)*H$18/5 -> 0.036 | I44: =$F44+($L44-$F44)*I$18/5 -> 0.034 | J44: =$F44+($L44-$F44)*J$18/5 -> 0.032 | K44: =$F44+($L44-$F44)*K$18/5 -> 0.03 | L44: 0.03
A45: Net reinvestment | B45: =B39*B44 -> 1.224 | C45: =C39*C44 -> 1 | D45: =D39*D44 -> 0.65 | E45: =E39*E44 -> 0.58 | F45: =F39*F44 -> 0.64 | G45: =G39*G44 -> 0.66318124 | H45: =H39*H44 -> 0.6773259 | I45: =I39*I44 -> 0.68151961 | ... L45: =L39*L44 -> 0.68468014
A46: Change in working capital | B46: =$B$11*(B39-$B$12) -> 0.4623 | C46: =$B$11*(C39-B39) -> 0.345 | D46: =$B$11*(D39-C39) -> 0.075 | E46: =$B$11*(E39-D39) -> 0.225 | F46: =$B$11*(F39-E39) -> 0.225 | G46: =$B$11*(G39-F39) -> 0.21782069 | H46: =$B$11*(H39-G39) -> 0.20437055 | I46: =$B$11*(I39-H39) -> 0.18451292 | J46: =$B$11*(J39-I39) -> 0.15842221 | ... L46: =$B$11*(L39-K39) -> 0.13166926
A47: Free cash flow | B47: =B43-B45-B46 -> 0.0477 | C47: =C43-C45-C46 -> 0.9925 | D47: =D43-D45-D46 -> 1.485 | E47: =E43-E45-E46 -> 1.78325 | F47: =F43-F45-F46 -> 1.991 | G47: =G43-G45-G46 -> 2.1748674 | H47: =H43-H45-H46 -> 2.3487718 | I47: =I43-I45-I46 -> 2.5074895 | ... L47: =L43-L45-L46 -> 2.869512
A48: Discount factor | B48: =1/(1+$B$9)^B$17 -> 0.94702745 | C48: =1/(1+$B$9)^C$17 -> 0.84935197 | D48: =1/(1+$B$9)^D$17 -> 0.76175065 | E48: =1/(1+$B$9)^E$17 -> 0.68318444 | F48: =1/(1+$B$9)^F$17 -> 0.61272147 | G48: =1/(1+$B$9)^G$17 -> 0.54952598 | H48: =1/(1+$B$9)^H$17 -> 0.49284841 | I48: =1/(1+$B$9)^I$17 -> 0.44201651 | ... K48: =1/(1+$B$9)^K$17 -> 0.35554024
A49: PV of free cash flow | B49: =B47*B48 -> 0.045173209 | C49: =C47*C48 -> 0.84298183 | D49: =D47*D48 -> 1.1311997 | E49: =E47*E48 -> 1.2182886 | F49: =F47*F48 -> 1.2199284 | G49: =G47*G48 -> 1.1951462 | H49: =H47*H48 -> 1.1575884 | I49: =I47*I48 -> 1.1083518 | ... K49: =K47*K48 -> 0.98098748
A50: Terminal value | B50: =L47/($B$9-$B$10) -> 38.26016
A51: PV of terminal value | B51: =B50/(1+$B$9)^$K$17 -> 13.603026
A52: Equity value (PV FCF + PV TV + net cash) | B52: =SUM(B49:K49)+B51+$B$7 -> 21.991571
A53: Value per share | B53: =B52/$B$6*$B$13 -> 111.67202
A54: Value vs share price | B54: =B53/$B$4-1 -> -0.52451664
A56: Bull: target beaten, co-packaged optics ramps
A57: Revenue | B57: 11 | C57: 14.5 | D57: 17 | E57: 19.5 | F57: 22 | G57: =F57*(1+$F58+($B$10-$F58)*G$18/5) -> 24.43241 | H57: =G57*(1+$F58+($B$10-$F58)*H$18/5) -> 26.702745 | I57: =H57*(1+$F58+($B$10-$F58)*I$18/5) -> 28.712982 | J57: =I57*(1+$F58+($B$10-$F58)*J$18/5) -> 30.368028 | K57: =J57*(1+$F58+($B$10-$F58)*K$18/5) -> 31.582749 | L57: =K57*(1+$B$10) -> 32.846059
A58: Revenue growth | B58: =B57/$B$12-1 -> 0.54537792 | C58: =C57/B57-1 -> 0.31818182 | D58: =D57/C57-1 -> 0.17241379 | E58: =E57/D57-1 -> 0.14705882 | F58: =F57/E57-1 -> 0.12820513 | G58: =G57/F57-1 -> 0.1105641 | H58: =H57/G57-1 -> 0.092923077 | I58: =I57/H57-1 -> 0.075282051 | J58: =J57/I57-1 -> 0.057641026 | ... L58: =L57/K57-1 -> 0.04
A59: Operating margin | B59: 0.21 | C59: 0.24 | D59: 0.24 | E59: 0.24 | F59: 0.23 | G59: =$F59+($L59-$F59)*G$18/5 -> 0.226 | H59: =$F59+($L59-$F59)*H$18/5 -> 0.222 | I59: =$F59+($L59-$F59)*I$18/5 -> 0.218 | J59: =$F59+($L59-$F59)*J$18/5 -> 0.214 | K59: =$F59+($L59-$F59)*K$18/5 -> 0.21 | L59: 0.21
A60: Operating income | B60: =B57*B59 -> 2.31 | C60: =C57*C59 -> 3.48 | D60: =D57*D59 -> 4.08 | E60: =E57*E59 -> 4.68 | F60: =F57*F59 -> 5.06 | G60: =G57*G59 -> 5.5217247 | H60: =H57*H59 -> 5.9280094 | I60: =I57*I59 -> 6.2594302 | ... L60: =L57*L59 -> 6.8976724
A61: NOPAT | B61: =B60*(1-$B$8) -> 1.9635 | C61: =C60*(1-$B$8) -> 2.958 | D61: =D60*(1-$B$8) -> 3.468 | E61: =E60*(1-$B$8) -> 3.978 | F61: =F60*(1-$B$8) -> 4.301 | G61: =G60*(1-$B$8) -> 4.693466 | H61: =H60*(1-$B$8) -> 5.038808 | I61: =I60*(1-$B$8) -> 5.3205156 | ... L61: =L60*(1-$B$8) -> 5.8630216
A62: Net reinvestment, % of revenue | B62: 0.12 | C62: 0.08 | D62: 0.06 | E62: 0.05 | F62: 0.04 | G62: =$F62+($L62-$F62)*G$18/5 -> 0.038 | H62: =$F62+($L62-$F62)*H$18/5 -> 0.036 | I62: =$F62+($L62-$F62)*I$18/5 -> 0.034 | J62: =$F62+($L62-$F62)*J$18/5 -> 0.032 | K62: =$F62+($L62-$F62)*K$18/5 -> 0.03 | L62: 0.03
A63: Net reinvestment | B63: =B57*B62 -> 1.32 | C63: =C57*C62 -> 1.16 | D63: =D57*D62 -> 1.02 | E63: =E57*E62 -> 0.975 | F63: =F57*F62 -> 0.88 | G63: =G57*G62 -> 0.92843159 | H63: =H57*H62 -> 0.96129882 | I63: =I57*I62 -> 0.9762414 | ... L63: =L57*L62 -> 0.98538178
A64: Change in working capital | B64: =$B$11*(B57-$B$12) -> 0.5823 | C64: =$B$11*(C57-B57) -> 0.525 | D64: =$B$11*(D57-C57) -> 0.375 | E64: =$B$11*(E57-D57) -> 0.375 | F64: =$B$11*(F57-E57) -> 0.375 | G64: =$B$11*(G57-F57) -> 0.36486154 | H64: =$B$11*(H57-G57) -> 0.34055021 | I64: =$B$11*(I57-H57) -> 0.30153561 | J64: =$B$11*(J57-I57) -> 0.24825686 | ... L64: =$B$11*(L57-K57) -> 0.1894965
A65: Free cash flow | B65: =B61-B63-B64 -> 0.0612 | C65: =C61-C63-C64 -> 1.273 | D65: =D61-D63-D64 -> 2.073 | E65: =E61-E63-E64 -> 2.628 | F65: =F61-F63-F64 -> 3.046 | G65: =G61-G63-G64 -> 3.4001729 | H65: =H61-H63-H64 -> 3.7369589 | I65: =I61-I63-I64 -> 4.0427386 | ... L65: =L61-L63-L64 -> 4.6881433
A66: Discount factor | B66: =1/(1+$B$9)^B$17 -> 0.94702745 | C66: =1/(1+$B$9)^C$17 -> 0.84935197 | D66: =1/(1+$B$9)^D$17 -> 0.76175065 | E66: =1/(1+$B$9)^E$17 -> 0.68318444 | F66: =1/(1+$B$9)^F$17 -> 0.61272147 | G66: =1/(1+$B$9)^G$17 -> 0.54952598 | H66: =1/(1+$B$9)^H$17 -> 0.49284841 | I66: =1/(1+$B$9)^I$17 -> 0.44201651 | ... K66: =1/(1+$B$9)^K$17 -> 0.35554024
A67: PV of free cash flow | B67: =B65*B66 -> 0.05795808 | C67: =C65*C66 -> 1.0812251 | D67: =D65*D66 -> 1.5791091 | E67: =E65*E66 -> 1.7954087 | F67: =F65*F66 -> 1.8663496 | G67: =G65*G66 -> 1.8684833 | H67: =H65*H66 -> 1.8417543 | I67: =I65*I66 -> 1.7869572 | ... K67: =K65*K66 -> 1.602715
A68: Terminal value | B68: =L65/($B$9-$B$10) -> 62.508577
A69: PV of terminal value | B69: =B68/(1+$B$9)^$K$17 -> 22.224315
A70: Equity value (PV FCF + PV TV + net cash) | B70: =SUM(B67:K67)+B69+$B$7 -> 35.850463
A71: Value per share | B71: =B70/$B$6*$B$13 -> 182.04673
A72: Value vs share price | B72: =B71/$B$4-1 -> -0.22487128
A76: Outputs | C76: vs price
A77: Bear value per share | B77: =B35 -> 38.400215 | C77: =B77/$B$4-1 -> -0.83649742
A78: Base value per share | B78: =B53 -> 111.67202 | C78: =B78/$B$4-1 -> -0.52451664
A79: Bull value per share | B79: =B71 -> 182.04673 | C79: =B79/$B$4-1 -> -0.22487128
A80: Selected scenario value per share | B80: =INDEX(B35:B71,1+($B$14-1)*18) -> 111.67202 | C80: =B80/$B$4-1 -> -0.52451664
A81: Buy below: base value (earns the discount rate if the base case plays out) | B81: =B78 -> 111.67202
A83: Base value per share at other discount rates (where it crosses the price is roughly the implied return)
A84: Discount rate | B84: 0.08 | C84: 0.09 | D84: 0.1 | E84: 0.11 | F84: 0.12 | G84: 0.13
A85: Base value per share | B85: =(SUMPRODUCT(B47:K47/(1+B84)^$B$17:$K$17)+L47/(B84-$B$10)/(1+B84)^$K$17+$B$7)/$B$6*$B$13 -> 227.78545 | C85: =(SUMPRODUCT(B47:K47/(1+C84)^$B$17:$K$17)+L47/(C84-$B$10)/(1+C84)^$K$17+$B$7)/$B$6*$B$13 -> 177.89289 | D85: =(SUMPRODUCT(B47:K47/(1+D84)^$B$17:$K$17)+L47/(D84-$B$10)/(1+D84)^$K$17+$B$7)/$B$6*$B$13 -> 144.72011 | E85: =(SUMPRODUCT(B47:K47/(1+E84)^$B$17:$K$17)+L47/(E84-$B$10)/(1+E84)^$K$17+$B$7)/$B$6*$B$13 -> 121.09719 | F85: =(SUMPRODUCT(B47:K47/(1+F84)^$B$17:$K$17)+L47/(F84-$B$10)/(1+F84)^$K$17+$B$7)/$B$6*$B$13 -> 103.43944 | G85: =(SUMPRODUCT(B47:K47/(1+G84)^$B$17:$K$17)+L47/(G84-$B$10)/(1+G84)^$K$17+$B$7)/$B$6*$B$13 -> 89.755589
A86: vs share price | B86: =B85/$B$4-1 -> -0.030122408 | C86: =C85/$B$4-1 -> -0.24255775 | D86: =D85/$B$4-1 -> -0.38380267 | E86: =E85/$B$4-1 -> -0.48438564 | F86: =F85/$B$4-1 -> -0.55956977 | G86: =G85/$B$4-1 -> -0.61783365

Sheet FN
A1: Fabrinet (FN): 10-year scenario DCF
A2: Units: $B unless noted. Blue = input, black = formula, green = link, yellow = key lever. Years 6 to 10 fade growth, margin and reinvestment toward terminal levels.
A4: Share price | B4: 355.48 | C4: Source: Stock Analysis, Oct 20, 2026 close
A5: Price date | B5: Oct 20, 2026 close | C5: Text
A6: Shares outstanding (billions) | B6: 0.0363 | C6: Diluted shares guided for FQ1 FY27 (Fabrinet 8-K, Aug 2026)
A7: Net cash, negative = net debt ($B) | B7: 0.871 | C7: Fabrinet 8-K: cash and short-term investments $875M; debt $4M (Stock Analysis)
A8: Tax rate | B8: 0.08 | C8: Analyst assumption
A9: Discount rate (WACC), from WACC tab | B9: =WACC!C26 -> 0.1 | C9: Calculated or assumed, per switch in WACC!B5
A10: Terminal growth | B10: 0.04 | C10: Analyst assumption
A11: Working capital, % of revenue change | B11: 0.15 | C11: Analyst assumption
A12: Base-year revenue ($B) | B12: 4.641 | C12: FY26 (Jun 2026) revenue, Stock Analysis annual income statement
A13: Per-share multiplier | B13: 1 | C13: Units conversion (1 here)
A14: Selected scenario (1 Bear, 2 Base, 3 Bull) | B14: 2 | C14: Lever
A16: Year | B16: FY27 | C16: FY28 | D16: FY29 | E16: FY30 | F16: FY31 | G16: FY32 | H16: FY33 | I16: FY34 | J16: FY35 | K16: FY36 | L16: Terminal
A17: Discount period (years, mid-year) | B17: 0.5 | C17: =B17+1 -> 1.5 | D17: =C17+1 -> 2.5 | E17: =D17+1 -> 3.5 | F17: =E17+1 -> 4.5 | G17: =F17+1 -> 5.5 | H17: =G17+1 -> 6.5 | I17: =H17+1 -> 7.5 | J17: =I17+1 -> 8.5 | K17: =J17+1 -> 9.5
A18: Fade step (years 6 to 10) | B18: 0 | C18: 0 | D18: 0 | E18: 0 | F18: 0 | G18: 1 | H18: 2 | I18: 3 | J18: 4 | K18: 5
A20: Bear: a top customer program lost plus AI slowdown
A21: Revenue | B21: 5.6 | C21: 4.8 | D21: 5 | E21: 5.5 | F21: 6 | G21: =F21*(1+$F22+($B$10-$F22)*G$18/5) -> 6.4843636 | H21: =G21*(1+$F22+($B$10-$F22)*H$18/5) -> 6.941806 | I21: =H21*(1+$F22+($B$10-$F22)*I$18/5) -> 7.3608387 | J21: =I21*(1+$F22+($B$10-$F22)*J$18/5) -> 7.7302189 | K21: =J21*(1+$F22+($B$10-$F22)*K$18/5) -> 8.0394277 | L21: =K21*(1+$B$10) -> 8.3610048
A22: Revenue growth | B22: =B21/$B$12-1 -> 0.2066365 | C22: =C21/B21-1 -> -0.14285714 | D22: =D21/C21-1 -> 0.041666667 | E22: =E21/D21-1 -> 0.1 | F22: =F21/E21-1 -> 0.090909091 | G22: =G21/F21-1 -> 0.080727273 | H22: =H21/G21-1 -> 0.070545455 | I22: =I21/H21-1 -> 0.060363636 | J22: =J21/I21-1 -> 0.050181818 | ... L22: =L21/K21-1 -> 0.04
A23: Operating margin | B23: 0.1 | C23: 0.085 | D23: 0.09 | E23: 0.095 | F23: 0.095 | G23: =$F23+($L23-$F23)*G$18/5 -> 0.094 | H23: =$F23+($L23-$F23)*H$18/5 -> 0.093 | I23: =$F23+($L23-$F23)*I$18/5 -> 0.092 | J23: =$F23+($L23-$F23)*J$18/5 -> 0.091 | K23: =$F23+($L23-$F23)*K$18/5 -> 0.09 | L23: 0.09
A24: Operating income | B24: =B21*B23 -> 0.56 | C24: =C21*C23 -> 0.408 | D24: =D21*D23 -> 0.45 | E24: =E21*E23 -> 0.5225 | F24: =F21*F23 -> 0.57 | G24: =G21*G23 -> 0.60953018 | H24: =H21*H23 -> 0.64558796 | I24: =I21*I23 -> 0.67719716 | ... L24: =L21*L23 -> 0.75249043
A25: NOPAT | B25: =B24*(1-$B$8) -> 0.5152 | C25: =C24*(1-$B$8) -> 0.37536 | D25: =D24*(1-$B$8) -> 0.414 | E25: =E24*(1-$B$8) -> 0.4807 | F25: =F24*(1-$B$8) -> 0.5244 | G25: =G24*(1-$B$8) -> 0.56076777 | H25: =H24*(1-$B$8) -> 0.59394092 | I25: =I24*(1-$B$8) -> 0.62302139 | ... L25: =L24*(1-$B$8) -> 0.6922912
A26: Net reinvestment, % of revenue | B26: 0.05 | C26: 0.025 | D26: 0.02 | E26: 0.02 | F26: 0.02 | G26: =$F26+($L26-$F26)*G$18/5 -> 0.02 | H26: =$F26+($L26-$F26)*H$18/5 -> 0.02 | I26: =$F26+($L26-$F26)*I$18/5 -> 0.02 | J26: =$F26+($L26-$F26)*J$18/5 -> 0.02 | K26: =$F26+($L26-$F26)*K$18/5 -> 0.02 | L26: 0.02
A27: Net reinvestment | B27: =B21*B26 -> 0.28 | C27: =C21*C26 -> 0.12 | D27: =D21*D26 -> 0.1 | E27: =E21*E26 -> 0.11 | F27: =F21*F26 -> 0.12 | G27: =G21*G26 -> 0.12968727 | H27: =H21*H26 -> 0.13883612 | I27: =I21*I26 -> 0.14721677 | ... L27: =L21*L26 -> 0.1672201
A28: Change in working capital | B28: =$B$11*(B21-$B$12) -> 0.14385 | C28: =$B$11*(C21-B21) -> -0.12 | D28: =$B$11*(D21-C21) -> 0.03 | E28: =$B$11*(E21-D21) -> 0.075 | F28: =$B$11*(F21-E21) -> 0.075 | G28: =$B$11*(G21-F21) -> 0.072654545 | H28: =$B$11*(H21-G21) -> 0.068616357 | I28: =$B$11*(I21-H21) -> 0.062854898 | J28: =$B$11*(J21-I21) -> 0.05540704 | ... L28: =$B$11*(L21-K21) -> 0.048236566
A29: Free cash flow | B29: =B25-B27-B28 -> 0.09135 | C29: =C25-C27-C28 -> 0.37536 | D29: =D25-D27-D28 -> 0.284 | E29: =E25-E27-E28 -> 0.2957 | F29: =F25-F27-F28 -> 0.3294 | G29: =G25-G27-G28 -> 0.35842595 | H29: =H25-H27-H28 -> 0.38648845 | I29: =I25-I27-I28 -> 0.41294971 | ... L29: =L25-L27-L28 -> 0.47683454
A30: Discount factor | B30: =1/(1+$B$9)^B$17 -> 0.95346259 | C30: =1/(1+$B$9)^C$17 -> 0.86678417 | D30: =1/(1+$B$9)^D$17 -> 0.78798561 | E30: =1/(1+$B$9)^E$17 -> 0.71635056 | F30: =1/(1+$B$9)^F$17 -> 0.65122778 | G30: =1/(1+$B$9)^G$17 -> 0.59202525 | H30: =1/(1+$B$9)^H$17 -> 0.53820477 | I30: =1/(1+$B$9)^I$17 -> 0.48927707 | ... K30: =1/(1+$B$9)^K$17 -> 0.40436121
A31: PV of free cash flow | B31: =B29*B30 -> 0.087098808 | C31: =C29*C30 -> 0.32535611 | D31: =D29*D30 -> 0.22378791 | E31: =E29*E30 -> 0.21182486 | F31: =F29*F30 -> 0.21451443 | G31: =G29*G30 -> 0.21219721 | H31: =H29*H30 -> 0.20800993 | I31: =I29*I30 -> 0.20204683 | ... K31: =K29*K30 -> 0.18539749
A32: Terminal value | B32: =L29/($B$9-$B$10) -> 7.9472423
A33: PV of terminal value | B33: =B32/(1+$B$9)^$K$17 -> 3.2135565
A34: Equity value (PV FCF + PV TV + net cash) | B34: =SUM(B31:K31)+B33+$B$7 -> 6.1492388
A35: Value per share | B35: =B34/$B$6*$B$13 -> 169.40052
A36: Value vs share price | B36: =B35/$B$4-1 -> -0.52345978
A38: Base: Building 10 fills, growth slows after FY28
A39: Revenue | B39: 6.2 | C39: 7.8 | D39: 8.2 | E39: 9.2 | F39: 10.2 | G39: =F39*(1+$F40+($B$10-$F40)*G$18/5) -> 11.168557 | H39: =G39*(1+$F40+($B$10-$F40)*H$18/5) -> 12.075638 | I39: =H39*(1+$F40+($B$10-$F40)*I$18/5) -> 12.890481 | J39: =I39*(1+$F40+($B$10-$F40)*J$18/5) -> 13.583204 | K39: =J39*(1+$F40+($B$10-$F40)*K$18/5) -> 14.126532 | L39: =K39*(1+$B$10) -> 14.691593
A40: Revenue growth | B40: =B39/$B$12-1 -> 0.33591898 | C40: =C39/B39-1 -> 0.25806452 | D40: =D39/C39-1 -> 0.051282051 | E40: =E39/D39-1 -> 0.12195122 | F40: =F39/E39-1 -> 0.10869565 | G40: =G39/F39-1 -> 0.094956522 | H40: =H39/G39-1 -> 0.081217391 | I40: =I39/H39-1 -> 0.067478261 | J40: =J39/I39-1 -> 0.05373913 | ... L40: =L39/K39-1 -> 0.04
A41: Operating margin | B41: 0.105 | C41: 0.105 | D41: 0.1 | E41: 0.1 | F41: 0.1 | G41: =$F41+($L41-$F41)*G$18/5 -> 0.099 | H41: =$F41+($L41-$F41)*H$18/5 -> 0.098 | I41: =$F41+($L41-$F41)*I$18/5 -> 0.097 | J41: =$F41+($L41-$F41)*J$18/5 -> 0.096 | K41: =$F41+($L41-$F41)*K$18/5 -> 0.095 | L41: 0.095
A42: Operating income | B42: =B39*B41 -> 0.651 | C42: =C39*C41 -> 0.819 | D42: =D39*D41 -> 0.82 | E42: =E39*E41 -> 0.92 | F42: =F39*F41 -> 1.02 | G42: =G39*G41 -> 1.1056871 | H42: =H39*H41 -> 1.1834125 | I42: =I39*I41 -> 1.2503766 | ... L42: =L39*L41 -> 1.3957014
A43: NOPAT | B43: =B42*(1-$B$8) -> 0.59892 | C43: =C42*(1-$B$8) -> 0.75348 | D43: =D42*(1-$B$8) -> 0.7544 | E43: =E42*(1-$B$8) -> 0.8464 | F43: =F42*(1-$B$8) -> 0.9384 | G43: =G42*(1-$B$8) -> 1.0172321 | H43: =H42*(1-$B$8) -> 1.0887395 | I43: =I42*(1-$B$8) -> 1.1503465 | ... L43: =L42*(1-$B$8) -> 1.2840452
A44: Net reinvestment, % of revenue | B44: 0.05 | C44: 0.03 | D44: 0.025 | E44: 0.025 | F44: 0.025 | G44: =$F44+($L44-$F44)*G$18/5 -> 0.024 | H44: =$F44+($L44-$F44)*H$18/5 -> 0.023 | I44: =$F44+($L44-$F44)*I$18/5 -> 0.022 | J44: =$F44+($L44-$F44)*J$18/5 -> 0.021 | K44: =$F44+($L44-$F44)*K$18/5 -> 0.02 | L44: 0.02
A45: Net reinvestment | B45: =B39*B44 -> 0.31 | C45: =C39*C44 -> 0.234 | D45: =D39*D44 -> 0.205 | E45: =E39*E44 -> 0.23 | F45: =F39*F44 -> 0.255 | G45: =G39*G44 -> 0.26804536 | H45: =H39*H44 -> 0.27773966 | I45: =I39*I44 -> 0.28359057 | ... L45: =L39*L44 -> 0.29383186
A46: Change in working capital | B46: =$B$11*(B39-$B$12) -> 0.23385 | C46: =$B$11*(C39-B39) -> 0.24 | D46: =$B$11*(D39-C39) -> 0.06 | E46: =$B$11*(E39-D39) -> 0.15 | F46: =$B$11*(F39-E39) -> 0.15 | G46: =$B$11*(G39-F39) -> 0.14528348 | H46: =$B$11*(H39-G39) -> 0.13606215 | I46: =$B$11*(I39-H39) -> 0.12222645 | J46: =$B$11*(J39-I39) -> 0.10390848 | ... L46: =$B$11*(L39-K39) -> 0.084759192
A47: Free cash flow | B47: =B43-B45-B46 -> 0.05507 | C47: =C43-C45-C46 -> 0.27948 | D47: =D43-D45-D46 -> 0.4894 | E47: =E43-E45-E46 -> 0.4664 | F47: =F43-F45-F46 -> 0.5334 | G47: =G43-G45-G46 -> 0.60390329 | H47: =H43-H45-H46 -> 0.67493766 | I47: =I43-I45-I46 -> 0.74452946 | ... L47: =L43-L45-L46 -> 0.90545419
A48: Discount factor | B48: =1/(1+$B$9)^B$17 -> 0.95346259 | C48: =1/(1+$B$9)^C$17 -> 0.86678417 | D48: =1/(1+$B$9)^D$17 -> 0.78798561 | E48: =1/(1+$B$9)^E$17 -> 0.71635056 | F48: =1/(1+$B$9)^F$17 -> 0.65122778 | G48: =1/(1+$B$9)^G$17 -> 0.59202525 | H48: =1/(1+$B$9)^H$17 -> 0.53820477 | I48: =1/(1+$B$9)^I$17 -> 0.48927707 | ... K48: =1/(1+$B$9)^K$17 -> 0.40436121
A49: PV of free cash flow | B49: =B47*B48 -> 0.052507185 | C49: =C47*C48 -> 0.24224884 | D49: =D47*D48 -> 0.38564016 | E49: =E47*E48 -> 0.3341059 | F49: =F47*F48 -> 0.3473649 | G49: =G47*G48 -> 0.357526 | H49: =H47*H48 -> 0.36325467 | I49: =I47*I48 -> 0.36428119 | ... K49: =K47*K48 -> 0.35204861
A50: Terminal value | B50: =L47/($B$9-$B$10) -> 15.090903
A51: PV of terminal value | B51: =B50/(1+$B$9)^$K$17 -> 6.1021759
A52: Equity value (PV FCF + PV TV + net cash) | B52: =SUM(B49:K49)+B51+$B$7 -> 10.132667
A53: Value per share | B53: =B52/$B$6*$B$13 -> 279.13684
A54: Value vs share price | B54: =B53/$B$4-1 -> -0.21476077
A56: Bull: capacity fills toward $12B+
A57: Revenue | B57: 6.6 | C57: 9 | D57: 11 | E57: 12.5 | F57: 13.5 | G57: =F57*(1+$F58+($B$10-$F58)*G$18/5) -> 14.472 | H57: =G57*(1+$F58+($B$10-$F58)*H$18/5) -> 15.398208 | I57: =H57*(1+$F58+($B$10-$F58)*I$18/5) -> 16.260508 | J57: =I57*(1+$F58+($B$10-$F58)*J$18/5) -> 17.041012 | K57: =J57*(1+$F58+($B$10-$F58)*K$18/5) -> 17.722652 | L57: =K57*(1+$B$10) -> 18.431559
A58: Revenue growth | B58: =B57/$B$12-1 -> 0.4221073 | C58: =C57/B57-1 -> 0.36363636 | D58: =D57/C57-1 -> 0.22222222 | E58: =E57/D57-1 -> 0.13636364 | F58: =F57/E57-1 -> 0.08 | G58: =G57/F57-1 -> 0.072 | H58: =H57/G57-1 -> 0.064 | I58: =I57/H57-1 -> 0.056 | J58: =J57/I57-1 -> 0.048 | ... L58: =L57/K57-1 -> 0.04
A59: Operating margin | B59: 0.108 | C59: 0.11 | D59: 0.11 | E59: 0.11 | F59: 0.11 | G59: =$F59+($L59-$F59)*G$18/5 -> 0.109 | H59: =$F59+($L59-$F59)*H$18/5 -> 0.108 | I59: =$F59+($L59-$F59)*I$18/5 -> 0.107 | J59: =$F59+($L59-$F59)*J$18/5 -> 0.106 | K59: =$F59+($L59-$F59)*K$18/5 -> 0.105 | L59: 0.105
A60: Operating income | B60: =B57*B59 -> 0.7128 | C60: =C57*C59 -> 0.99 | D60: =D57*D59 -> 1.21 | E60: =E57*E59 -> 1.375 | F60: =F57*F59 -> 1.485 | G60: =G57*G59 -> 1.577448 | H60: =H57*H59 -> 1.6630065 | I60: =I57*I59 -> 1.7398743 | ... L60: =L57*L59 -> 1.9353137
A61: NOPAT | B61: =B60*(1-$B$8) -> 0.655776 | C61: =C60*(1-$B$8) -> 0.9108 | D61: =D60*(1-$B$8) -> 1.1132 | E61: =E60*(1-$B$8) -> 1.265 | F61: =F60*(1-$B$8) -> 1.3662 | G61: =G60*(1-$B$8) -> 1.4512522 | H61: =H60*(1-$B$8) -> 1.5299659 | I61: =I60*(1-$B$8) -> 1.6006844 | ... L61: =L60*(1-$B$8) -> 1.7804886
A62: Net reinvestment, % of revenue | B62: 0.05 | C62: 0.035 | D62: 0.03 | E62: 0.025 | F62: 0.025 | G62: =$F62+($L62-$F62)*G$18/5 -> 0.024 | H62: =$F62+($L62-$F62)*H$18/5 -> 0.023 | I62: =$F62+($L62-$F62)*I$18/5 -> 0.022 | J62: =$F62+($L62-$F62)*J$18/5 -> 0.021 | K62: =$F62+($L62-$F62)*K$18/5 -> 0.02 | L62: 0.02
A63: Net reinvestment | B63: =B57*B62 -> 0.33 | C63: =C57*C62 -> 0.315 | D63: =D57*D62 -> 0.33 | E63: =E57*E62 -> 0.3125 | F63: =F57*F62 -> 0.3375 | G63: =G57*G62 -> 0.347328 | H63: =H57*H62 -> 0.35415878 | I63: =I57*I62 -> 0.35773117 | ... L63: =L57*L62 -> 0.36863117
A64: Change in working capital | B64: =$B$11*(B57-$B$12) -> 0.29385 | C64: =$B$11*(C57-B57) -> 0.36 | D64: =$B$11*(D57-C57) -> 0.3 | E64: =$B$11*(E57-D57) -> 0.225 | F64: =$B$11*(F57-E57) -> 0.15 | G64: =$B$11*(G57-F57) -> 0.1458 | H64: =$B$11*(H57-G57) -> 0.1389312 | I64: =$B$11*(I57-H57) -> 0.12934495 | J64: =$B$11*(J57-I57) -> 0.11707566 | ... L64: =$B$11*(L57-K57) -> 0.10633591
A65: Free cash flow | B65: =B61-B63-B64 -> 0.031926 | C65: =C61-C63-C64 -> 0.2358 | D65: =D61-D63-D64 -> 0.4832 | E65: =E61-E63-E64 -> 0.7275 | F65: =F61-F63-F64 -> 0.8787 | G65: =G61-G63-G64 -> 0.95812416 | H65: =H61-H63-H64 -> 1.036876 | I65: =I61-I63-I64 -> 1.1136083 | ... L65: =L61-L63-L64 -> 1.3055215
A66: Discount factor | B66: =1/(1+$B$9)^B$17 -> 0.95346259 | C66: =1/(1+$B$9)^C$17 -> 0.86678417 | D66: =1/(1+$B$9)^D$17 -> 0.78798561 | E66: =1/(1+$B$9)^E$17 -> 0.71635056 | F66: =1/(1+$B$9)^F$17 -> 0.65122778 | G66: =1/(1+$B$9)^G$17 -> 0.59202525 | H66: =1/(1+$B$9)^H$17 -> 0.53820477 | I66: =1/(1+$B$9)^I$17 -> 0.48927707 | ... K66: =1/(1+$B$9)^K$17 -> 0.40436121
A67: PV of free cash flow | B67: =B65*B66 -> 0.030440247 | C67: =C65*C66 -> 0.20438771 | D67: =D65*D66 -> 0.38075465 | E67: =E65*E66 -> 0.52114503 | F67: =F65*F66 -> 0.57223385 | G67: =G65*G66 -> 0.5672337 | H67: =H65*H66 -> 0.55805159 | I67: =I65*I66 -> 0.54486298 | ... K67: =K65*K66 -> 0.50759831
A68: Terminal value | B68: =L65/($B$9-$B$10) -> 21.758691
A69: PV of terminal value | B69: =B68/(1+$B$9)^$K$17 -> 8.7983708
A70: Equity value (PV FCF + PV TV + net cash) | B70: =SUM(B67:K67)+B69+$B$7 -> 14.08401
A71: Value per share | B71: =B70/$B$6*$B$13 -> 387.98926
A72: Value vs share price | B72: =B71/$B$4-1 -> 0.091451713
A76: Outputs | C76: vs price
A77: Bear value per share | B77: =B35 -> 169.40052 | C77: =B77/$B$4-1 -> -0.52345978
A78: Base value per share | B78: =B53 -> 279.13684 | C78: =B78/$B$4-1 -> -0.21476077
A79: Bull value per share | B79: =B71 -> 387.98926 | C79: =B79/$B$4-1 -> 0.091451713
A80: Selected scenario value per share | B80: =INDEX(B35:B71,1+($B$14-1)*18) -> 279.13684 | C80: =B80/$B$4-1 -> -0.21476077
A81: Buy below: base value (earns the discount rate if the base case plays out) | B81: =B78 -> 279.13684
A83: Base value per share at other discount rates (where it crosses the price is roughly the implied return)
A84: Discount rate | B84: 0.08 | C84: 0.09 | D84: 0.1 | E84: 0.11 | F84: 0.12 | G84: 0.13
A85: Base value per share | B85: =(SUMPRODUCT(B47:K47/(1+B84)^$B$17:$K$17)+L47/(B84-$B$10)/(1+B84)^$K$17+$B$7)/$B$6*$B$13 -> 420.6573 | C85: =(SUMPRODUCT(B47:K47/(1+C84)^$B$17:$K$17)+L47/(C84-$B$10)/(1+C84)^$K$17+$B$7)/$B$6*$B$13 -> 335.5965 | D85: =(SUMPRODUCT(B47:K47/(1+D84)^$B$17:$K$17)+L47/(D84-$B$10)/(1+D84)^$K$17+$B$7)/$B$6*$B$13 -> 279.13684 | E85: =(SUMPRODUCT(B47:K47/(1+E84)^$B$17:$K$17)+L47/(E84-$B$10)/(1+E84)^$K$17+$B$7)/$B$6*$B$13 -> 239.00599 | F85: =(SUMPRODUCT(B47:K47/(1+F84)^$B$17:$K$17)+L47/(F84-$B$10)/(1+F84)^$K$17+$B$7)/$B$6*$B$13 -> 209.06883 | G85: =(SUMPRODUCT(B47:K47/(1+G84)^$B$17:$K$17)+L47/(G84-$B$10)/(1+G84)^$K$17+$B$7)/$B$6*$B$13 -> 185.91783
A86: vs share price | B86: =B85/$B$4-1 -> 0.18335012 | C86: =C85/$B$4-1 -> -0.055934227 | D86: =D85/$B$4-1 -> -0.21476077 | E86: =E85/$B$4-1 -> -0.32765279 | F86: =F85/$B$4-1 -> -0.41186894 | G86: =G85/$B$4-1 -> -0.47699496
